Workbook
Name Company_Name: 'Returns-Summary'!$D$7
Name Hist_Yr: 'Returns-Summary'!$D$8

Sheet Returns-Summary
B2: =Company_Name&" - Operating Model" -> Beacon Staffing Group Limited - Operating Model
B3: (all figures £m unless noted)
B5: BRIEF & INPUTS:
C7: Entity Name: | D7: Beacon Staffing Group Limited | H7: Equity Invested at Entry: | K7: 28.6166
C8: Final Actual Year: | D8: 42338 | H8: Ownership Acquired (%): | K8: 0.239925
C10: Prepare a fully integrated three-statement projection spanning five forecast years for Beacon Staffing Group, a specialist IT recruitment
C11: business based in the United Kingdom. Its purpose is to help a private-equity or growth-equity sponsor gauge the internal rate of return and cash-on-cash returns achievable
C12: on a minority growth-equity position.
E14: Actuals | H14: Forecast
B15: Investment Summary & Returns: | D15: Reporting Units: | E15: =EOMONTH(F15,-12) -> 41608 | F15: =EOMONTH(G15,-12) -> 41973 | G15: =Hist_Yr -> 42338 | H15: =EOMONTH(G15,12) -> 42704 | I15: =EOMONTH(H15,12) -> 43069 | J15: =EOMONTH(I15,12) -> 43434 | K15: =EOMONTH(J15,12) -> 43799 | L15: =EOMONTH(K15,12) -> 44165
B16: Leverage & Coverage Metrics:
C18: Revenue (Turnover): | D18: £ M | E18: ='Model-Build'!E83 -> 39.4 | F18: ='Model-Build'!F83 -> 62.472 | G18: ='Model-Build'!G83 -> 94.983 | H18: ='Model-Build'!H83 -> 146.60761 | I18: ='Model-Build'!I83 -> 202.15825 | J18: ='Model-Build'!J83 -> 279.17751 | K18: ='Model-Build'!K83 -> 353.96798 | L18: ='Model-Build'!L83 -> 423.07609
C19: Rate of Growth: | D19: % | E19: ='Model-Build'!E84 -> N/A | F19: ='Model-Build'!F84 -> 0.58558376 | G19: ='Model-Build'!G84 -> 0.52040914 | H19: ='Model-Build'!H84 -> 0.54351426 | I19: ='Model-Build'!I84 -> 0.37890688 | J19: ='Model-Build'!J84 -> 0.38098499 | K19: ='Model-Build'!K84 -> 0.26789576 | L19: ='Model-Build'!L84 -> 0.19523833
C21: EBITDA — | D21: £ M | E21: ='Model-Build'!E93 -> 5.3 | F21: ='Model-Build'!F93 -> 8.359 | G21: ='Model-Build'!G93 -> 14.775 | H21: ='Model-Build'!H93 -> 25.77206 | I21: ='Model-Build'!I93 -> 51.895812 | J21: ='Model-Build'!J93 -> 28.002143 | K21: ='Model-Build'!K93 -> 72.544353 | L21: ='Model-Build'!L93 -> 81.307159
C22: Rate of Growth: | D22: % | E22: =IFERROR(E21/D21-1,"N/A") -> N/A | F22: =IFERROR(F21/E21-1,"N/A") -> 0.57716981 | G22: =IFERROR(G21/F21-1,"N/A") -> 0.76755593 | H22: =IFERROR(H21/G21-1,"N/A") -> 0.74430188 | I22: =IFERROR(I21/H21-1,"N/A") -> 1.0136462 | J22: =IFERROR(J21/I21-1,"N/A") -> -0.46041613 | K22: =IFERROR(K21/J21-1,"N/A") -> 1.5906715 | L22: =IFERROR(L21/K21-1,"N/A") -> 0.1207924
C23: Margin (%): | D23: % | E23: =E21/E18 -> 0.13451777 | F23: =F21/F18 -> 0.13380394 | G23: =G21/G18 -> 0.15555415 | H23: =H21/H18 -> 0.17578937 | I23: =I21/I18 -> 0.25670885 | J23: =J21/J18 -> 0.10030229 | K23: =K21/K18 -> 0.20494609 | L23: =L21/L18 -> 0.19218093
C25: Interest Cost: | D25: £ M | E25: =-'Model-Build'!E95 -> 1.180592 | F25: =-'Model-Build'!F95 -> 3.101 | G25: =-'Model-Build'!G95 -> 3.36 | H25: =-'Model-Build'!H95 -> 2.1648983 | I25: =-'Model-Build'!I95 -> 2.1211706 | J25: =-'Model-Build'!J95 -> 2.123551 | K25: =-'Model-Build'!K95 -> 2.2003245 | L25: =-'Model-Build'!L95 -> 2.3755873
C26: Interest Paid in Cash: | D26: £ M | E26: =E25 -> 1.180592 | F26: =F25 -> 3.101 | G26: =G25 -> 3.36 | H26: ='Model-Build'!H41+'Model-Build'!H47 -> 1.6079955 | I26: ='Model-Build'!I41+'Model-Build'!I47 -> 1.5040755 | J26: ='Model-Build'!J41+'Model-Build'!J47 -> 1.4397578 | K26: ='Model-Build'!K41+'Model-Build'!K47 -> 1.4426242 | L26: ='Model-Build'!L41+'Model-Build'!L47 -> 1.5359917
C28: Debt — Total | D28: £ M | E28: ='Model-Build'!E124 -> 32.826583 | F28: ='Model-Build'!F124 -> 34.557 | G28: ='Model-Build'!G124 -> 33.953 | H28: ='Model-Build'!H124 -> 0 | I28: ='Model-Build'!I124 -> 0 | J28: ='Model-Build'!J124 -> 0 | K28: ='Model-Build'!K124 -> 0 | L28: ='Model-Build'!L124 -> 0
C29: Debt, Net: | D29: £ M | E29: ='Model-Build'!E124-'Model-Build'!E104 -> 30.002971 | F29: ='Model-Build'!F124-'Model-Build'!F104 -> 32.152 | G29: ='Model-Build'!G124-'Model-Build'!G104 -> 21.804 | H29: ='Model-Build'!H124-'Model-Build'!H104 -> 0 | I29: ='Model-Build'!I124-'Model-Build'!I104 -> 0 | J29: ='Model-Build'!J124-'Model-Build'!J104 -> 0 | K29: ='Model-Build'!K124-'Model-Build'!K104 -> 0 | L29: ='Model-Build'!L124-'Model-Build'!L104 -> 0
C31: EBITDA-to-Interest: | D31: x | E31: =E21/E25 -> 4.4892732 | F31: =F21/F25 -> 2.6955821 | G31: =G21/G25 -> 4.3973214 | H31: =H21/H25 -> 11.904513 | I31: =I21/I25 -> 24.465648 | J31: =J21/J25 -> 13.186471 | K31: =K21/K25 -> 32.969843 | L31: =L21/L25 -> 34.22613
C32: EBITDA-to-Cash-Interest: | D32: x | E32: =E21/E26 -> 4.4892732 | F32: =F21/F26 -> 2.6955821 | G32: =G21/G26 -> 4.3973214 | H32: =H21/H26 -> 16.027446 | I32: =I21/I26 -> 34.503463 | J32: =J21/J26 -> 19.449204 | K32: =K21/K26 -> 50.286384 | L32: =L21/L26 -> 52.934634
C33: Total-Debt-to-EBITDA: | D33: x | E33: =E28/E21 -> 6.1936949 | F33: =F28/F21 -> 4.134107 | G33: =G28/G21 -> 2.2980034 | H33: =H28/H21 -> 0 | I33: =I28/I21 -> 0 | J33: =J28/J21 -> 0 | K33: =K28/K21 -> 0 | L33: =L28/L21 -> 0
C34: Net-Debt-to-EBITDA: | D34: x | E34: =E29/E21 -> 5.6609379 | F34: =F29/F21 -> 3.8463931 | G34: =G29/G21 -> 1.475736 | H34: =H29/H21 -> 0 | I34: =I29/I21 -> 0 | J34: =J29/J21 -> 0 | K34: =K29/K21 -> 0 | L34: =L29/L21 -> 0
B36: Returns — Money Multiple & IRR:
C38: EBITDA in Exit Year: | D38: £ M | J38: =J21 -> 28.002143 | K38: =K21 -> 72.544353 | L38: =L21 -> 81.307159
C39: Times: Assumed Exit Multiple | D39: x | J39: 8.8896 | K39: 7.7414 | L39: 8.1905
C40: Enterprise Value at Exit: | D40: £ M | J40: =J38*J39 -> 248.92785 | K40: =K38*K39 -> 561.59485 | L40: =L38*L39 -> 665.94629
C41: Less: Net Debt | D41: £ M | J41: =-J29 -> 0 | K41: =-K29 -> 0 | L41: =-L29 -> 0
C42: Equity Value at Exit: | D42: £ M | J42: =J40+J41 -> 248.92785 | K42: =K40+K41 -> 561.59485 | L42: =L40+L41 -> 665.94629
C44: Investor Exit Proceeds: | D44: x | J44: =J42*$K$8 -> 59.724015 | K44: =K42*$K$8 -> 134.74065 | L44: =L42*$K$8 -> 159.77716
C45: Money-on-Money Multiple: | D45: x | J45: =J44/$K$7 -> 2.0870409 | K45: =K44/$K$7 -> 4.7084785 | L45: =L44/$K$7 -> 5.5833734
C46: IRR (Internal Rate of Return): | D46: % | J46: =POWER(J44/$K$7,1/3)-1 -> 0.27793958 | K46: =POWER(K44/$K$7,1/4)-1 -> 0.47305902 | L46: =POWER(L44/$K$7,1/5)-1 -> 0.41052028

Sheet Model-Build
E2: ='Returns-Summary'!$E$14 -> Actuals | H2: ='Returns-Summary'!$H$14 -> Forecast
B3: Operating & Financing Drivers: | D3: ='Returns-Summary'!$D$15 -> Reporting Units: | E3: ='Returns-Summary'!$E$15 -> 41608 | F3: ='Returns-Summary'!$F$15 -> 41973 | G3: ='Returns-Summary'!$G$15 -> 42338 | H3: ='Returns-Summary'!$H$15 -> 42704 | I3: ='Returns-Summary'!$I$15 -> 43069 | J3: ='Returns-Summary'!$J$15 -> 43434 | K3: ='Returns-Summary'!$K$15 -> 43799 | L3: ='Returns-Summary'!$L$15 -> 44165
B4: Revenue & Cost Drivers:
C6: Selling Staff: | D6: Headcount (#) | E6: 192 | F6: 271 | G6: 417 | H6: =G6*(1+H7) -> 627.32312 | I6: =H6*(1+I7) -> 839.60613 | J6: =I6*(1+J7) -> 1133.7286 | K6: =J6*(1+K7) -> 1411.0794 | L6: =K6*(1+L7) -> 1651.1604
C7: Growth (%): | D7: % | F7: =F6/E6-1 -> 0.41145833 | G7: =G6/F6-1 -> 0.53874539 | H7: 0.504372 | I7: 0.338395 | J7: 0.35031 | K7: 0.244636 | L7: 0.17014
C9: Productivity per Sales Rep: | D9: £ M | E9: =E83/E6 -> 0.20520833 | F9: =F83/F6 -> 0.23052399 | G9: =G83/G6 -> 0.22777698 | H9: =G9*(1+H10) -> 0.23370351 | I9: =H9*(1+I10) -> 0.24077748 | J9: =I9*(1+J10) -> 0.24624722 | K9: =J9*(1+K10) -> 0.25084909 | L9: =K9*(1+L10) -> 0.25622955
C10: Growth (%): | D10: % | F10: =F9/E9-1 -> 0.12336561 | G10: =G9/F9-1 -> -0.01191636 | H10: 0.026019 | I10: 0.030269 | J10: 0.022717 | K10: 0.018688 | L10: 0.021449
C12: Non-Selling Staff: | D12: Headcount (#) | E12: 53 | F12: 66 | G12: 88 | H12: =H13*H6 -> 135.8876 | I12: =I13*I6 -> 139.65337 | J12: =J13*J6 -> 183.68443 | K12: =K13*K6 -> 235.31724 | L12: =L13*L6 -> 277.12086
C13: Other Staff as % of Sales Reps: | D13: % | E13: =E12/E6 -> 0.27604167 | F13: =F12/F6 -> 0.24354244 | G13: =G12/G6 -> 0.21103118 | H13: 0.216615 | I13: 0.166332 | J13: 0.162018 | K13: 0.166764 | L13: 0.167834
C15: NFI Margin (%): | D15: % | E15: =E86/E83 -> 0.51269036 | F15: =F86/F83 -> 0.47949481 | G15: =G86/G83 -> 0.48428666 | H15: 0.493802 | I15: 0.556668 | J15: 0.39428 | K15: 0.501311 | L15: 0.489702
C17: Payroll Cost per Head: | D17: £ M | E17: =E89/(E6+E12) -> 0.040816327 | F17: =F89/(F6+F12) -> 0.048652819 | G17: =G89/(G6+G12) -> 0.050740594 | H17: =G17*(1+H18) -> 0.053366471 | I17: =H17*(1+I18) -> 0.055603059 | J17: =I17*(1+J18) -> 0.057404209 | K17: =J17*(1+K18) -> 0.059606866 | L17: =K17*(1+L18) -> 0.061626168
C18: Growth (%): | D18: % | F18: =F17/E17-1 -> 0.19199407 | G18: =G17/F17-1 -> 0.042911698 | H18: 0.051751 | I18: 0.04191 | J18: 0.032393 | K18: 0.038371 | L18: 0.033877
C20: Sundry SG&A: | D20: £ M | E20: =E90 -> 4.9 | F20: =F90 -> 5.2 | G20: =G90 -> 5.6 | H20: =G20*(1+H21) -> 5.8932104 | I20: =H20*(1+I21) -> 6.1893914 | J20: =I20*(1+J21) -> 6.4469134 | K20: =J20*(1+K21) -> 6.7671445 | L20: =K20*(1+L21) -> 7.0414642
C21: Growth (%): | D21: % | F21: =F20/E20-1 -> 0.06122449 | G21: =G20/F20-1 -> 0.076923077 | H21: 0.052359 | I21: 0.050258 | J21: 0.041607 | K21: 0.049672 | L21: 0.040537
C23: UK Corporation Tax Rate: | D23: % | H23: 0.232767 | I23: 0.162604 | J23: 0.166824 | K23: 0.209089 | L23: 0.168549
B25: Debt & Interest Schedule: | D25: Opening Balance: | E25: Spread (bps) / PIK %: | F25: Amortisation (% of Balance): | G25: PIK Flag?
C26: Bank Facility A: | D26: 11.4987 | E26: 378.076 | F26: 0.096761 | G26: 0
C27: Bank Facility B: | D27: 19.9396 | E27: 403.761 | F27: 0 | G27: 0
C28: Shareholder PIK Loan: | D28: 5.1525 | E28: 0.108084 | F28: 0 | G28: 1
C29: Cash Balance: | D29: =G104 -> 12.149 | E29: 51.3748
C31: Benchmark Rate (LIBOR): | D31: % | H31: 0.011711 | I31: 0.010101 | J31: 0.009724 | K31: 0.011708 | L31: 0.017209
C32: Bank Facility A — Interest | D32: % | H32: =H31+$E$26/10000 -> 0.0495186 | I32: =I31+$E$26/10000 -> 0.0479086 | J32: =J31+$E$26/10000 -> 0.0475316 | K32: =K31+$E$26/10000 -> 0.0495156 | L32: =L31+$E$26/10000 -> 0.0550166
C33: Bank Facility B — Interest | D33: % | H33: =H31+$E$27/10000 -> 0.0520871 | I33: =I31+$E$27/10000 -> 0.0504771 | J33: =J31+$E$27/10000 -> 0.0501001 | K33: =K31+$E$27/10000 -> 0.0520841 | L33: =L31+$E$27/10000 -> 0.0575851
C34: Shareholder PIK Loan — Interest | D34: % | H34: =$E$28 -> 0.108084 | I34: =$E$28 -> 0.108084 | J34: =$E$28 -> 0.108084 | K34: =$E$28 -> 0.108084 | L34: =$E$28 -> 0.108084
C35: Cash — Interest | D35: % | H35: =H31+$E$29/10000 -> 0.01684848 | I35: =I31+$E$29/10000 -> 0.01523848 | J35: =J31+$E$29/10000 -> 0.01486148 | K35: =K31+$E$29/10000 -> 0.01684548 | L35: =L31+$E$29/10000 -> 0.02234648
C37: Bank Facility A — Opening | D37: £ M | H37: =D26 -> 11.4987 | I37: =H39 -> 10.386074 | J37: =I39 -> 9.2734486 | K37: =J39 -> 8.1608229 | L37: =K39 -> 7.0481972
C38: Less: Amortisation | D38: £ M | H38: =-$D$26*$F$26 -> -1.1126257 | I38: =-$D$26*$F$26 -> -1.1126257 | J38: =-$D$26*$F$26 -> -1.1126257 | K38: =-$D$26*$F$26 -> -1.1126257 | L38: =-$D$26*$F$26 -> -1.1126257
C39: Bank Facility A — Closing | D39: £ M | H39: =SUM(H37:H38) -> 10.386074 | I39: =SUM(I37:I38) -> 9.2734486 | J39: =SUM(J37:J38) -> 8.1608229 | K39: =SUM(K37:K38) -> 7.0481972 | L39: =SUM(L37:L38) -> 5.9355714
C41: Bank Facility A — Interest | D41: £ M | H41: =H37*H32 -> 0.56939953 | I41: =I37*I32 -> 0.49758228 | J41: =J37*J32 -> 0.44078185 | K41: =K37*K32 -> 0.40408804 | L41: =L37*L32 -> 0.38776784
C43: Bank Facility B — Opening | D43: £ M | H43: =D27 -> 19.9396 | I43: =H45 -> 19.9396 | J43: =I45 -> 19.9396 | K43: =J45 -> 19.9396 | L43: =K45 -> 19.9396
C44: Less: Amortisation | D44: £ M | H44: =-$D$27*$F$27 -> 0 | I44: =-$D$27*$F$27 -> 0 | J44: =-$D$27*$F$27 -> 0 | K44: =-$D$27*$F$27 -> 0 | L44: =-$D$27*$F$27 -> 0
C45: Bank Facility B — Closing | D45: £ M | H45: =SUM(H43:H44) -> 19.9396 | I45: =SUM(I43:I44) -> 19.9396 | J45: =SUM(J43:J44) -> 19.9396 | K45: =SUM(K43:K44) -> 19.9396 | L45: =SUM(L43:L44) -> 19.9396
C47: Bank Facility B — Interest | D47: £ M | H47: =H43*H33 -> 1.0385959 | I47: =I43*I33 -> 1.0064932 | J47: =J43*J33 -> 0.99897595 | K47: =K43*K33 -> 1.0385361 | L47: =L43*L33 -> 1.1482239
C49: Shareholder Loan — Opening | D49: £ M | H49: =D28 -> 5.1525 | I49: =H52 -> 5.7094028 | J49: =I52 -> 6.3264979 | K49: =J52 -> 7.0102911 | L49: =K52 -> 7.7679914
C50: Less: Amortisation | D50: £ M | H50: =-$D$28*$F$28 -> 0 | I50: =-$D$28*$F$28 -> 0 | J50: =-$D$28*$F$28 -> 0 | K50: =-$D$28*$F$28 -> 0 | L50: =-$D$28*$F$28 -> 0
C51: Add: PIK Interest | D51: £ M | H51: =H49*H34 -> 0.55690281 | I51: =I49*I34 -> 0.61709509 | J51: =J49*J34 -> 0.6837932 | K51: =K49*K34 -> 0.7577003 | L51: =L49*L34 -> 0.83959558
C52: Shareholder Loan — Closing | D52: £ M | H52: =SUM(H49:H51) -> 5.7094028 | I52: =SUM(I49:I51) -> 6.3264979 | J52: =SUM(J49:J51) -> 7.0102911 | K52: =SUM(K49:K51) -> 7.7679914 | L52: =SUM(L49:L51) -> 8.607587
C54: Cash — Interest Income | D54: £ M | H54: =H35*G104 -> 0.20469218 | I54: =I35*H104 -> 0 | J54: =J35*I104 -> 0 | K54: =K35*J104 -> 0 | L54: =L35*K104 -> 0
B56: Balance-Sheet Assumptions:
C57: Receivables as % of Turnover: | D57: % | E57: =E105/E83 -> 0.13379406 | F57: =F105/F83 -> 0.19536752 | G57: =G105/G83 -> 0.13209732 | H57: 0.153214 | I57: 0.116453 | J57: 0.097187 | K57: 0.137171 | L57: 0.130161
C58: Prepayments as % of OpEx: | D58: % | E58: =E106/E91 -> 0.13585208 | F58: =F106/F91 -> 0.18072791 | G58: =G106/G91 -> 0.11869075 | H58: 0.117565 | I58: 0.116913 | J58: 0.116106 | K58: 0.116061 | L58: 0.094074
C60: Payables as % of OpEx: | D60: % | E60: =E118/E$91 -> 0.048680201 | F60: =F118/F$91 -> 0.031718837 | G60: =G118/G$91 -> 0.044196772 | H60: =AVERAGE(E60:G60) -> 0.041531937 | I60: =H60 -> 0.041531937 | J60: =I60 -> 0.041531937 | K60: =J60 -> 0.041531937 | L60: =K60 -> 0.041531937
C61: Accruals as % of OpEx: | D61: % | E61: =E119/E$91 -> 0.12765403 | F61: =F119/F$91 -> 0.24476755 | G61: =G119/G$91 -> 0.20019857 | H61: 0.195737 | I61: 0.186404 | J61: 0.152415 | K61: 0.188716 | L61: 0.176244
C62: Other Current Liabilities as % of OpEx: | D62: % | E62: =E120/E$91 -> 0.15758584 | F62: =F120/F$91 -> 0.103584 | G62: =G120/G$91 -> 0.08394184 | H62: 0.094914 | I62: 0.066014 | J62: 0.062217 | K62: 0.072203 | L62: 0.05905
B64: Cash-Flow Assumptions:
C65: CapEx as % of Turnover: | D65: £ M | E65: 0.009 | F65: 0.011973364 | G65: 0.0065695967 | H65: 0.011577 | I65: 0.013395 | J65: 0.015239 | K65: 0.013973 | L65: 0.018639
C66: Depreciation as % of Turnover: | D66: % | E66: 0.005 | F66: 0.0056025099 | G66: 0.0062326943 | H66: 0.007417 | I66: 0.011478 | J66: 0.009929 | K66: 0.015188 | L66: 0.014608
C68: Intangible Asset Additions: | D68: £ M | H68: 5.2531 | I68: 5.5022 | J68: 11.1065 | K68: 8.8491 | L68: 14.942
C69: Existing-Intangible Amortisation: | H69: 0.08363
C70: New-Intangible Amortisation: | D70: % | H70: 0.202029
C72: Amortisation — Existing Intangibles | D72: £ M | H72: =$G$111*$H$69 -> 1.9451502 | I72: =$G$111*$H$69 -> 1.9451502 | J72: =$G$111*$H$69 -> 1.9451502 | K72: =$G$111*$H$69 -> 1.9451502 | L72: =$G$111*$H$69 -> 1.9451502
C73: Amortisation — Yr 1 Additions | D73: £ M | H73: =$H68*$H$70/2 -> 0.53063927 | I73: =$H68*$H$70 -> 1.0612785 | J73: =$H68*$H$70 -> 1.0612785 | K73: =$H68*$H$70 -> 1.0612785 | L73: =$H68*$H$70 -> 1.0612785
C74: Amortisation — Yr 2 Additions | D74: £ M | I74: =$I68*$H$70/2 -> 0.55580198 | J74: =$I68*$H$70 -> 1.111604 | K74: =$I68*$H$70 -> 1.111604 | L74: =$I68*$H$70 -> 1.111604
C75: Amortisation — Yr 3 Additions | D75: £ M | J75: =$J68*$H$70/2 -> 1.1219175 | K75: =$J68*$H$70 -> 2.2438351 | L75: =$J68*$H$70 -> 2.2438351
C76: Amortisation — Yr 4 Additions | D76: £ M | K76: =$K68*$H$70/2 -> 0.89388741 | L76: =$K68*$H$70 -> 1.7877748
C77: Amortisation — Yr 5 Additions | D77: £ M | L77: =$L68*$H$70/2 -> 1.5093587
C78: Amortisation — Total | D78: £ M | H78: =SUM(H72:H77) -> 2.4757894 | I78: =SUM(I72:I77) -> 3.5622307 | J78: =SUM(J72:J77) -> 5.2399502 | K78: =SUM(K72:K77) -> 7.2557552 | L78: =SUM(L72:L77) -> 9.6590012
E80: =$E$2 -> Actuals | H80: =$H$2 -> Forecast
B81: Consolidated Income Statement: | D81: =$D$3 -> Reporting Units: | E81: =$E$3 -> 41608 | F81: =$F$3 -> 41973 | G81: =$G$3 -> 42338 | H81: =$H$3 -> 42704 | I81: =$I$3 -> 43069 | J81: =$J$3 -> 43434 | K81: =$K$3 -> 43799 | L81: =$L$3 -> 44165
C83: Revenue (Turnover): | D83: £ M | E83: 39.4 | F83: 62.472 | G83: 94.983 | H83: =H6*H9 -> 146.60761 | I83: =I6*I9 -> 202.15825 | J83: =J6*J9 -> 279.17751 | K83: =K6*K9 -> 353.96798 | L83: =L6*L9 -> 423.07609
C84: Growth Rate (%): | D84: % | E84: =IFERROR(+E83/D83-1,"N/A") -> N/A | F84: =IFERROR(+F83/E83-1,"N/A") -> 0.58558376 | G84: =IFERROR(+G83/F83-1,"N/A") -> 0.52040914 | H84: =IFERROR(+H83/G83-1,"N/A") -> 0.54351426 | I84: =IFERROR(+I83/H83-1,"N/A") -> 0.37890688 | J84: =IFERROR(+J83/I83-1,"N/A") -> 0.38098499 | K84: =IFERROR(+K83/J83-1,"N/A") -> 0.26789576 | L84: =IFERROR(+L83/K83-1,"N/A") -> 0.19523833
C86: NFI (Net Fee Income): | D86: £ M | E86: 20.2 | F86: 29.955 | G86: 45.999 | H86: =H83*H15 -> 72.395133 | I86: =I83*I15 -> 112.53503 | J86: =J83*J15 -> 110.07411 | K86: =K83*K15 -> 177.44804 | L86: =L83*L15 -> 207.18121
C88: Operating Costs:
C89: Add: Payroll Costs | D89: £ M | E89: 10 | F89: 16.396 | G89: 25.624 | H89: =H17*(H12+H6) -> 40.729863 | I89: =I17*(I12+I6) -> 54.449824 | J89: =J17*(J12+J6) -> 75.625051 | K89: =K17*(K12+K6) -> 98.136543 | L89: =L17*(L12+L6) -> 118.83259
C90: Add: Other SG&A | D90: £ M | E90: 4.9 | F90: 5.2 | G90: 5.6 | H90: =H20 -> 5.8932104 | I90: =I20 -> 6.1893914 | J90: =J20 -> 6.4469134 | K90: =K20 -> 6.7671445 | L90: =L20 -> 7.0414642
C91: Operating Costs — Total | D91: £ M | E91: =SUM(E89:E90) -> 14.9 | F91: =SUM(F89:F90) -> 21.596 | G91: =SUM(G89:G90) -> 31.224 | H91: =SUM(H89:H90) -> 46.623073 | I91: =SUM(I89:I90) -> 60.639215 | J91: =SUM(J89:J90) -> 82.071964 | K91: =SUM(K89:K90) -> 104.90369 | L91: =SUM(L89:L90) -> 125.87405
C93: EBITDA — | D93: £ M | E93: =E86-E91 -> 5.3 | F93: =F86-F91 -> 8.359 | G93: =G86-G91 -> 14.775 | H93: =H86-H91 -> 25.77206 | I93: =I86-I91 -> 51.895812 | J93: =J86-J91 -> 28.002143 | K93: =K86-K91 -> 72.544353 | L93: =L86-L91 -> 81.307159
C94: Less: Depreciation & Amortisation | D94: £ M | E94: -0.710208 | F94: -1.982 | G94: -1.933 | H94: =-H66*H83-H78 -> -3.5631781 | I94: =-I66*I83-I78 -> -5.8826031 | J94: =-J66*J83-J78 -> -8.0119037 | K94: =-K66*K83-K78 -> -12.631821 | L94: =-L66*L83-L78 -> -15.839297
C95: Less: Interest Expense | D95: £ M | E95: -1.180592 | F95: -3.101 | G95: -3.36 | H95: =-H51-H47-H41 -> -2.1648983 | I95: =-I51-I47-I41 -> -2.1211706 | J95: =-J51-J47-J41 -> -2.123551 | K95: =-K51-K47-K41 -> -2.2003245 | L95: =-L51-L47-L41 -> -2.3755873
C96: Add: Interest & Other Income | D96: £ M | E96: 0.000359 | F96: 0.001 | G96: - | H96: =H54 -> 0.20469218 | I96: =I54 -> 0 | J96: =J54 -> 0 | K96: =K54 -> 0 | L96: =L54 -> 0
C97: Less: Income Tax Provision | D97: £ M | E97: -0.605386 | F97: -1.164 | G97: -2.822 | H97: =-SUM(H93:H96)*H23 -> -4.7132236 | I97: =-SUM(I93:I96)*I23 -> -7.137021 | J97: =-SUM(J93:J96)*J23 -> -2.9805924 | K97: =-SUM(K93:K96)*K23 -> -12.066988 | L97: =-SUM(L93:L96)*L23 -> -10.63414
C98: Net Profit for the Period: | D98: £ M | E98: =SUM(E93:E97) -> 2.804173 | F98: =SUM(F93:F97) -> 2.113 | G98: =SUM(G93:G97) -> 6.66 | H98: =SUM(H93:H97) -> 15.535453 | I98: =SUM(I93:I97) -> 36.755018 | J98: =SUM(J93:J97) -> 14.886096 | K98: =SUM(K93:K97) -> 45.64522 | L98: =SUM(L93:L97) -> 52.458135
E100: =$E$2 -> Actuals | H100: =$H$2 -> Forecast
B101: Balance Sheet: | D101: =$D$3 -> Reporting Units: | E101: =$E$3 -> 41608 | F101: =$F$3 -> 41973 | G101: =$G$3 -> 42338 | H101: =$H$3 -> 42704 | I101: =$I$3 -> 43069 | J101: =$J$3 -> 43434 | K101: =$K$3 -> 43799 | L101: =$L$3 -> 44165
B102: Assets —
C103: Assets, Current:
C104: Cash and Cash Equivalents: | D104: £ M | E104: 2.823612 | F104: 2.405 | G104: 12.149
C105: Trade Receivables: | D105: £ M | E105: 5.271486 | F105: 12.205 | G105: 12.547
C106: Prepayments: | D106: £ M | E106: 2.024196 | F106: 3.903 | G106: 3.706
C107: Current Assets — Total | D107: £ M | E107: =SUM(E104:E106) -> 10.119294 | F107: =SUM(F104:F106) -> 18.513 | G107: =SUM(G104:G106) -> 28.402
C109: Assets, Non-Current:
C110: Property, Plant & Equipment, Net: | D110: £ M | E110: 0.466522 | F110: 0.863 | G110: 0.861
C111: Sundry Intangible Assets: | D111: £ M | E111: 26.198047 | F111: 24.566 | G111: 23.259
C112: Non-Current Assets — Total | D112: £ M | E112: =SUM(E110:E111) -> 26.664569 | F112: =SUM(F110:F111) -> 25.429 | G112: =SUM(G110:G111) -> 24.12
C114: Assets — Total | D114: £ M | E114: =E107+E112 -> 36.783863 | F114: =F107+F112 -> 43.942 | G114: =G107+G112 -> 52.522
B116: Liabilities & Equity —
C117: Liabilities, Current:
C118: Trade Payables: | D118: £ M | E118: 0.725335 | F118: 0.685 | G118: 1.38
C119: Accruals: | D119: £ M | E119: 1.902045 | F119: 5.286 | G119: 6.251
C120: Sundry Current Liabilities: | D120: £ M | E120: 2.348029 | F120: 2.237 | G120: 2.621
C121: Current Liabilities — Total | D121: £ M | E121: =SUM(E118:E120) -> 4.975409 | F121: =SUM(F118:F120) -> 8.208 | G121: =SUM(G118:G120) -> 10.252
C123: Liabilities, Non-Current:
C124: Debt, Long-Term: | D124: £ M | E124: 32.826583 | F124: 34.557 | G124: 33.953
C125: Sundry Long-Term Liabilities: | D125: £ M | E125: 0.055376 | F125: 0.043 | G125: 0.037
C126: Non-Current Liabilities — Total | D126: £ M | E126: =SUM(E124:E125) -> 32.881959 | F126: =SUM(F124:F125) -> 34.6 | G126: =SUM(G124:G125) -> 33.99
C128: Liabilities — Total | D128: £ M | E128: =E121+E126 -> 37.857368 | F128: =F121+F126 -> 42.808 | G128: =G121+G126 -> 44.242
C130: Shareholders' Equity: | D130: £ M | E130: -1.073505 | F130: 1.134 | G130: 8.28
C132: Liabilities & Equity — Total | D132: £ M | E132: =E128+E130 -> 36.783863 | F132: =F128+F130 -> 43.942 | G132: =G128+G130 -> 52.522
C134: Balance Tie-Out: | E134: =E114-E132 -> 0 | F134: =F114-F132 -> 0 | G134: =G114-G132 -> 0
E136: =$E$2 -> Actuals | H136: =$H$2 -> Forecast
...
