Workbook

Sheet Drivers
A2: Projection Inputs
B6: Operating Model Assumptions | C6: 40908 | D6: =EOMONTH(C6,13) -> 41305 | E6: =EOMONTH(D6,12) -> 41670 | F6: =EOMONTH(E6,12) -> 42035 | G6: =EOMONTH(F6,12) -> 42400 | H6: =EOMONTH(G6,12) -> 42766 | I6: =EOMONTH(H6,12) -> 43131 | J6: =EOMONTH(I6,12) -> 43496
B7: Top-Line Growth (YoY %) | E7: ='P&L'!E102 -> 0.96688702 | F7: 1 | G7: 0.772078 | H7: 0.932974 | I7: 0.946124 | J7: 0.767217
B8: Delivery Cost Ratio (% of Sales) | D8: ='P&L'!D105 -> -0.225728 | E8: ='P&L'!E105 -> -0.232448 | F8: -0.191609 | G8: -0.21867 | H8: -0.238979 | I8: -0.238706 | J8: -0.196203
B9: Product Engineering (% of Sales) | D9: ='P&L'!D107 -> -0.533345 | E9: ='P&L'!E107 -> -0.343535 | F9: -0.257327 | G9: -0.29594 | H9: -0.226937 | I9: -0.125974 | J9: -0.086575
B10: Commercial Spend (% of Sales) | D10: ='P&L'!D109 -> -1.374587 | E10: ='P&L'!E109 -> -1.620786 | F10: -1.259474 | G10: -1.245412 | H10: -1 | I10: -0.806052 | J10: -0.804721
B11: G&A Load (% of Sales) | D11: ='P&L'!D111 -> -0.431271 | E11: ='P&L'!E111 -> -0.347697 | F11: -0.269781 | G11: -0.326593 | H11: -0.301588 | I11: -0.212493 | J11: -0.263047
B12: Capital Spend (% of Sales) | D12: ='Debt-Capex-Amort'!D52 -> 0.27890972 | E12: ='Debt-Capex-Amort'!E52 -> 0.18379859 | F12: 0.042093 | G12: 0.047855 | H12: 0.058757 | I12: 0.059184 | J12: 0.053319
B13: Minimum Cash Buffer | C13: 85530

Sheet P&L
A2: Quarterly Income Statement
C4: Period Ending
C5: Apr. 30,2012 | D5: Jul. 31,2012 | E5: Oct. 31,2012 | F5: Jan. 31,2013 | G5: Apr. 30,2013 | H5: Jul. 31,2013 | I5: Oct. 31,2013 | J5: Jan. 31,2014
B6: (USD millions, except per-share figures) | C6: 1932 | D6: 2133 | E6: 2275 | F6: 2234 | G6: 2261 | H6: 2249 | I6: 1870 | J6: 2181
B8: Total Revenue | C8: 11618 | D8: 13858 | E8: 18502 | F8: 22280 | G8: 23639 | H8: 28365 | I8: 37389 | J8: 40929
B9: Cost of delivery | C9: -2545 | D9: -3494 | E9: -3614 | F9: -4087 | G9: -5229 | H9: -6642 | I9: -8535 | J9: -8789
B10: Gross margin ($) | C10: =SUM(C8:C9) -> 9073 | D10: =SUM(D8:D9) -> 10364 | E10: =SUM(E8:E9) -> 14888 | F10: =SUM(F8:F9) -> 18193 | G10: =SUM(G8:G9) -> 18410 | H10: =SUM(H8:H9) -> 21723 | I10: =SUM(I8:I9) -> 28854 | J10: =SUM(J8:J9) -> 32140
B12: Operating cost lines:
B13: Product engineering | C13: -6956 | D13: -6702 | E13: -8464 | F13: -9141 | G13: -9125 | H13: -9340 | I13: -11816 | J13: -14504
B14: Go-to-market | C14: -18687 | D14: -19422 | E14: -22701 | F14: -32462 | G14: -40477 | H14: -40765 | I14: -53103 | J14: -45133
B15: Corporate & administrative | C15: -4419 | D15: -5990 | E15: -9618 | F15: -7245 | G15: -6950 | H15: -9873 | I15: -11133 | J15: -11263
B16: Aggregate operating costs | C16: =SUM(C13:C15) -> -30062 | D16: =SUM(D13:D15) -> -32114 | E16: =SUM(E13:E15) -> -40783 | F16: =SUM(F13:F15) -> -48848 | G16: =SUM(G13:G15) -> -56552 | H16: =SUM(H13:H15) -> -59978 | I16: =SUM(I13:I15) -> -76052 | J16: =SUM(J13:J15) -> -70900
B18: Operating income/(loss) — EBIT | C18: =C10+C16 -> -20989 | D18: =D10+D16 -> -21750 | E18: =E10+E16 -> -25895 | F18: =F10+F16 -> -30655 | G18: =G10+G16 -> -38142 | H18: =H10+H16 -> -38255 | I18: =I10+I16 -> -47198 | J18: =J10+J16 -> -38760
B20: Fair-value change on preferred warrant obligation | C20: 0 | D20: -1617 | E20: -81 | F20: -96 | G20: -800 | H20: -1473 | I20: -3765 | J20: -2817
B21: Net interest, income/(expense) | C21: -261 | D21: -404 | E21: -551 | F21: -653 | G21: -629 | H21: -585 | I21: -2327 | J21: -531
B22: Net other, income/(expense) | C22: 9.388387 | D22: 5.734957 | E22: 0 | F22: 111 | G22: -9.29612 | H22: -79 | I22: 94 | J22: -45
B24: Pre-tax income/(loss) | C24: =SUM(C18:C22) -> -21240.612 | D24: =SUM(D18:D22) -> -23765.265 | E24: =SUM(E18:E22) -> -26527 | F24: =SUM(F18:F22) -> -31293 | G24: =SUM(G18:G22) -> -39580.296 | H24: =SUM(H18:H22) -> -40392 | I24: =SUM(I18:I22) -> -53196 | J24: =SUM(J18:J22) -> -42153
B25: Income tax charge/(credit) | C25: 3.505081 | D25: 0 | E25: 7.044941 | F25: 44 | G25: 5.202842 | H25: -2218 | I25: 62 | J25: 85
B27: Net income/(loss) | C27: =C24-C25 -> -21244.117 | D27: =D24-D25 -> -23765.265 | E27: =E24-E25 -> -26534.045 | F27: =F24-F25 -> -31337 | G27: =G24-G25 -> -39585.499 | H27: =H24-H25 -> -38174 | I27: =I24-I25 -> -53258 | J27: =J24-J25 -> -42238
B28: Preferred-stock accretion charge
B30: Earnings/(loss) to common holders | C30: =SUM(C27:C28) -> -21244.117 | D30: =SUM(D27:D28) -> -23765.265 | E30: =SUM(E27:E28) -> -26534.045 | F30: =SUM(F27:F28) -> -31337 | G30: =SUM(G27:G28) -> -39585.499 | H30: =SUM(H27:H28) -> -38174 | I30: =SUM(I27:I28) -> -53258 | J30: =SUM(J27:J28) -> -42238
B32: EPS to common — basic & diluted | C32: =C30/C34 -> -4.0204611 | D32: =D30/D34 -> -3.8965839 | F32: =F30/F34 -> -4.0782145 | G32: =G30/G34 -> -3.4904769
B34: Weighted-average common shares — basic & diluted | C34: 5284 | D34: 6099 | F34: 7684 | G34: 11341
B36: Pro-forma EPS to common — basic & diluted (unaudited) | G36: -1.978028
B38: Diluted weighted-average shares | G38: 7671
B40: Operating cash earnings (EBITDA) | H40: =H18+'BS-CF-WC'!F59 -> -8961.565 | I40: =I18+'BS-CF-WC'!G59 -> -10816.779 | J40: =J18+'BS-CF-WC'!H59 -> 12902.723
B42: Total Revenue | C42: =C8 -> 11618 | D42: =D8 -> 13858 | E42: =E8 -> 18502 | F42: =F8 -> 22280 | G42: =G8 -> 23639 | H42: =H8 -> 28365 | I42: =I8 -> 37389 | J42: =J8 -> 40929
B43: (YoY %) | F43: =F42/E42-1 -> 0.20419414 | G43: =G42/F42-1 -> 0.060996409 | H43: =H42/G42-1 -> 0.19992385 | I43: =I42/H42-1 -> 0.31813855 | J43: =J42/I42-1 -> 0.094680254
B45: Cost of delivery | C45: =C9 -> -2545 | D45: =D9 -> -3494 | E45: =E9 -> -3614 | F45: =F9 -> -4087 | G45: =G9 -> -5229 | H45: =H9 -> -6642 | I45: =I9 -> -8535 | J45: =J9 -> -8789
B46: % of sales | C46: =C45/C42 -> -0.21905664 | D46: =D45/D42 -> -0.25212873 | E46: =E45/E42 -> -0.19533023 | F46: =F45/F42 -> -0.18343806 | G46: =G45/G42 -> -0.22120225 | H46: =H45/H42 -> -0.23416182 | I46: =I45/I42 -> -0.2282757 | J46: =J45/J42 -> -0.21473772
B47: Product engineering | C47: =C13 -> -6956 | D47: =D13 -> -6702 | E47: =E13 -> -8464 | F47: =F13 -> -9141 | G47: =G13 -> -9125 | H47: =H13 -> -9340 | I47: =I13 -> -11816 | J47: =J13 -> -14504
B48: % of sales | C48: =C47/C42 -> -0.59872611 | D48: =D47/D42 -> -0.48361957 | E48: =E47/E42 -> -0.45746406 | F48: =F47/F42 -> -0.41027828 | G48: =G47/G42 -> -0.38601464 | H48: =H47/H42 -> -0.32927904 | I48: =I47/I42 -> -0.31602878 | J48: =J47/J42 -> -0.35436976
B49: Go-to-market | C49: =C14 -> -18687 | D49: =D14 -> -19422 | E49: =E14 -> -22701 | F49: =F14 -> -32462 | G49: =G14 -> -40477 | H49: =H14 -> -40765 | I49: =I14 -> -53103 | J49: =J14 -> -45133
B50: % of sales | C50: =C49/C42 -> -1.6084524 | D50: =D49/D42 -> -1.4015009 | E50: =E49/E42 -> -1.2269484 | F50: =F49/F42 -> -1.4570018 | G50: =G49/G42 -> -1.7122975 | H50: =H49/H42 -> -1.4371585 | I50: =I49/I42 -> -1.420284 | J50: =J49/J42 -> -1.1027145
B51: Corporate & administrative | C51: =C15 -> -4419 | D51: =D15 -> -5990 | E51: =E15 -> -9618 | F51: =F15 -> -7245 | G51: =G15 -> -6950 | H51: =H15 -> -9873 | I51: =I15 -> -11133 | J51: =J15 -> -11263
B52: % of sales | C52: =C51/C42 -> -0.38035807 | D52: =D51/D42 -> -0.4322413 | E52: =E51/E42 -> -0.51983569 | F52: =F51/F42 -> -0.32517953 | G52: =G51/G42 -> -0.29400567 | H52: =H51/H42 -> -0.3480698 | I52: =I51/I42 -> -0.29776137 | J52: =J51/J42 -> -0.27518385
B54: Aggregate operating costs | C54: =C51+C49+C47+C45 -> -32607 | D54: =D51+D49+D47+D45 -> -35608 | E54: =E51+E49+E47+E45 -> -44397 | F54: =F51+F49+F47+F45 -> -52935 | G54: =G51+G49+G47+G45 -> -61781 | H54: =H51+H49+H47+H45 -> -66620 | I54: =I51+I49+I47+I45 -> -84587 | J54: =J51+J49+J47+J45 -> -79689
B55: % of sales | C55: =C54/C42 -> -2.8065932 | D55: =D54/D42 -> -2.5694905 | E55: =E54/E42 -> -2.3995784 | F55: =F54/F42 -> -2.3758977 | G55: =G54/G42 -> -2.61352 | H55: =H54/H42 -> -2.3486691 | I55: =I54/I42 -> -2.2623499 | J55: =J54/J42 -> -1.9470058
B57: Operating income/(loss) | C57: =C42+C54 -> -20989 | D57: =D42+D54 -> -21750 | E57: =E42+E54 -> -25895 | F57: =F42+F54 -> -30655 | G57: =G42+G54 -> -38142 | H57: =H42+H54 -> -38255 | I57: =I42+I54 -> -47198 | J57: =J42+J54 -> -38760
C58: =C57/C42 -> -1.8065932 | D58: =D57/D42 -> -1.5694905 | E58: =E57/E42 -> -1.3995784 | F58: =F57/F42 -> -1.3758977 | G58: =G57/G42 -> -1.61352 | H58: =H57/H42 -> -1.3486691 | I58: =I57/I42 -> -1.2623499 | J58: =J57/J42 -> -0.94700579
B60: Effective tax rate | G60: =G25/G24 -> -0.00013145031 | H60: =H25/H24 -> 0.054911864 | I60: =I25/I24 -> -0.0011655012 | J60: =J25/J24 -> -0.0020164638
B62: Operating cash earnings (EBITDA)
A65: Annual Income Statement
C67: Reported history | F67: Projected periods
B68: (USD millions, except per-share figures) | C68: 40908 | D68: =EOMONTH(C68,13) -> 41305 | E68: =EOMONTH(D68,12) -> 41670 | F68: =EOMONTH(E68,12) -> 42035 | G68: =EOMONTH(F68,12) -> 42400 | H68: =EOMONTH(G68,12) -> 42766 | I68: =EOMONTH(H68,12) -> 43131 | J68: =EOMONTH(I68,12) -> 43496
B70: Total Revenue | C70: 23669 | D70: =SUM(C8:F8) -> 66258 | E70: =SUM(G8:J8) -> 130322 | F70: =F101 -> 260644 | G70: =G101 -> 461881.5 | H70: =H101 -> 892804.93 | I70: =I101 -> 1737509.1 | J70: =J101 -> 3070555.6
B71: Cost of delivery | C71: -6697 | D71: =SUM(C9:F9) -> -13740 | E71: =SUM(G9:J9) -> -29195 | F71: =F104 -> -49941.736 | G71: =G104 -> -100999.63 | H71: =H104 -> -213361.63 | I71: =I104 -> -414753.85 | J71: =J104 -> -602452.22
B72: Gross margin ($) | C72: =SUM(C70:C71) -> 16972 | D72: =SUM(D70:D71) -> 52518 | E72: =SUM(E70:E71) -> 101127 | F72: =SUM(F70:F71) -> 210702.26 | G72: =SUM(G70:G71) -> 360881.87 | H72: =SUM(H70:H71) -> 679443.3 | I72: =SUM(I70:I71) -> 1322755.2 | J72: =SUM(J70:J71) -> 2468103.4
B74: Operating cost lines:
B75: Product engineering | C75: -12696 | D75: =SUM(C13:F13) -> -31263 | E75: =SUM(G13:J13) -> -44785 | F75: =F106 -> -67070.739 | G75: =G106 -> -136689.21 | H75: =H106 -> -202610.47 | I75: =I106 -> -218880.97 | J75: =J106 -> -265833.35
B76: Go-to-market | C76: -38092 | D76: =SUM(C14:F14) -> -93272 | E76: =SUM(G14:J14) -> -179478 | F76: =F108 -> -328274.34 | G76: =G108 -> -575232.76 | H76: =H108 -> -892804.93 | I76: =I108 -> -1400522.7 | J76: =J108 -> -2470940.6
B77: Corporate & administrative | C77: -13066 | D77: =SUM(C15:F15) -> -27272 | E77: =SUM(G15:J15) -> -39219 | F77: =F110 -> -70316.799 | G77: =G110 -> -150847.26 | H77: =H110 -> -269259.25 | I77: =I110 -> -369208.52 | J77: =J110 -> -807700.44
B78: Aggregate operating costs | C78: =SUM(C75:C77) -> -63854 | D78: =SUM(D75:D77) -> -151807 | E78: =SUM(E75:E77) -> -263482 | F78: =SUM(F75:F77) -> -465661.88 | G78: =SUM(G75:G77) -> -862769.24 | H78: =SUM(H75:H77) -> -1364674.7 | I78: =SUM(I75:I77) -> -1988612.2 | J78: =SUM(J75:J77) -> -3544474.4
B80: Monthly operating spend | C80: =C78/12 -> -5321.1667 | D80: =D78/12 -> -12650.583 | E80: =E78/12 -> -21956.833 | F80: =F78/12 -> -38805.157 | G80: =G78/12 -> -71897.436 | H80: =H78/12 -> -113722.89 | I80: =I78/12 -> -165717.68 | J80: =J78/12 -> -295372.86
B81: Monthly operating spend (excl. engineering) | C81: =(C76+C77)/12 -> -4263.1667 | D81: =(D76+D77)/12 -> -10045.333 | E81: =(E76+E77)/12 -> -18224.75 | F81: =(F76+F77)/12 -> -33215.928 | G81: =(G76+G77)/12 -> -60506.669 | H81: =(H76+H77)/12 -> -96838.682 | I81: =(I76+I77)/12 -> -147477.6 | J81: =(J76+J77)/12 -> -273220.09
B84: Operating income/(loss) — EBIT | C84: =C72+C78 -> -46882 | D84: =D72+D78 -> -99289 | E84: =E72+E78 -> -162355 | F84: =F72+F78 -> -254959.62 | G84: =G72+G78 -> -501887.36 | H84: =H72+H78 -> -685231.35 | I84: =I72+I78 -> -665856.92 | J84: =J72+J78 -> -1076371
B86: Fair-value change on preferred warrant obligation | C86: -423 | D86: =SUM(C20:F20) -> -1794 | E86: =SUM(G20:J20) -> -8855
B87: Net interest, income/(expense) | C87: -127 | D87: =SUM(C21:F21) -> -1869 | E87: =SUM(G21:J21) -> -4072 | F87: -1985.6993 | G87: 1351.6542 | H87: 10765.989 | I87: 23512.066 | J87: 35448.097
B88: Net other, income/(expense) | C88: 41 | D88: =SUM(C22:F22) -> 126.12334 | E88: =SUM(G22:J22) -> -39.29612
B90: Pre-tax income/(loss) | C90: =SUM(C84:C88) -> -47391 | D90: =SUM(D84:D88) -> -102825.88 | E90: =SUM(E84:E88) -> -175321.3 | F90: =SUM(F84:F88) -> -256945.31 | G90: =SUM(G84:G88) -> -500535.71 | H90: =SUM(H84:H88) -> -674465.36 | I90: =SUM(I84:I88) -> -642344.86 | J90: =SUM(J84:J88) -> -1040922.9
B91: Income tax charge/(credit) | C91: 1 | D91: =SUM(C25:F25) -> 54.550022 | E91: =SUM(G25:J25) -> -2065.7972 | F91: 0 | G91: 0 | H91: 0 | I91: 0 | J91: 0
B92: Net income/(loss) | C92: =C90-C91 -> -47392 | D92: =D90-D91 -> -102880.43 | E92: =E90-E91 -> -173255.5 | F92: -250369.7 | G92: -390349.91 | H92: -565460.05 | I92: -746535.46 | J92: -844606.22
B93: Preferred-stock accretion charge | C93: -90 | D93: -186 | E93: -380
B95: Earnings/(loss) to common holders | C95: =SUM(C92:C93) -> -47482 | D95: =SUM(D92:D93) -> -103066.43 | E95: =SUM(E92:E93) -> -173635.5 | F95: =SUM(F92:F93) -> -250369.7 | G95: =SUM(G92:G93) -> -390349.91 | H95: =SUM(H92:H93) -> -565460.05 | I95: =SUM(I92:I93) -> -746535.46 | J95: =SUM(J92:J93) -> -844606.22
B97: Operating cash earnings (EBITDA) | F97: =F84+'BS-CF-WC'!F59 -> -225666.18 | G97: =G84+'BS-CF-WC'!G59 -> -465506.14 | H97: =H84+'BS-CF-WC'!H59 -> -633568.63 | I97: =I84+'BS-CF-WC'!I59 -> -581537.63 | J97: =J84+'BS-CF-WC'!J59 -> -992051.69
B99: Operating Driver Buildup
B101: Total Revenue | C101: =C70 -> 23669 | D101: =D70 -> 66258 | E101: =E70 -> 130322 | F101: =E101*(1+F102) -> 260644 | G101: =F101*(1+G102) -> 461881.5 | H101: =G101*(1+H102) -> 892804.93 | I101: =H101*(1+I102) -> 1737509.1 | J101: =I101*(1+J102) -> 3070555.6
B102: (YoY %) | D102: =D101/C101-1 -> 1.7993578 | E102: =E101/D101-1 -> 0.96688702 | F102: =Drivers!F7 -> 1 | G102: =Drivers!G7 -> 0.772078 | H102: =Drivers!H7 -> 0.932974 | I102: =Drivers!I7 -> 0.946124 | J102: =Drivers!J7 -> 0.767217
B104: Cost of delivery | C104: -5747 | D104: -15130 | E104: -25528 | F104: =F101*F105 -> -49941.736 | G104: =G101*G105 -> -100999.63 | H104: =H101*H105 -> -213361.63 | I104: =I101*I105 -> -414753.85 | J104: =J101*J105 -> -602452.22
B105: % of sales | C105: -0.302539 | D105: -0.225728 | E105: -0.232448 | F105: =Drivers!F8 -> -0.191609 | G105: =Drivers!G8 -> -0.21867 | H105: =Drivers!H8 -> -0.238979 | I105: =Drivers!I8 -> -0.238706 | J105: =Drivers!J8 -> -0.196203
B106: Product engineering | C106: -15084 | D106: -25873 | E106: -39781 | F106: =F107*F101 -> -67070.739 | G106: =G107*G101 -> -136689.21 | H106: =H107*H101 -> -202610.47 | I106: =I107*I101 -> -218880.97 | J106: =J107*J101 -> -265833.35
B107: % of sales | C107: -0.652053 | D107: -0.533345 | E107: -0.343535 | F107: =Drivers!F9 -> -0.257327 | G107: =Drivers!G9 -> -0.29594 | H107: =Drivers!H9 -> -0.226937 | I107: =Drivers!I9 -> -0.125974 | J107: =Drivers!J9 -> -0.086575
B108: Go-to-market | C108: -34912 | D108: -100511 | E108: -140371 | F108: =F109*F101 -> -328274.34 | G108: =G109*G101 -> -575232.76 | H108: =H109*H101 -> -892804.93 | I108: =I109*I101 -> -1400522.7 | J108: =J109*J101 -> -2470940.6
B109: % of sales | C109: -1.867094 | D109: -1.374587 | E109: -1.620786 | F109: =Drivers!F10 -> -1.259474 | G109: =Drivers!G10 -> -1.245412 | H109: =Drivers!H10 -> -1 | I109: =Drivers!I10 -> -0.806052 | J109: =Drivers!J10 -> -0.804721
B110: Corporate & administrative | C110: -15652 | D110: -27263 | E110: -33359 | F110: =F111*F101 -> -70316.799 | G110: =G111*G101 -> -150847.26 | H110: =H111*H101 -> -269259.25 | I110: =I111*I101 -> -369208.52 | J110: =J111*J101 -> -807700.44
B111: % of sales | C111: -0.739249 | D111: -0.431271 | E111: -0.347697 | F111: =Drivers!F11 -> -0.269781 | G111: =Drivers!G11 -> -0.326593 | H111: =Drivers!H11 -> -0.301588 | I111: =Drivers!I11 -> -0.212493 | J111: =Drivers!J11 -> -0.263047
B113: Aggregate operating costs | C113: -67860 | D113: -198196 | E113: -292062 | F113: =F110+F108+F106+F104 -> -515603.62 | G113: =G110+G108+G106+G104 -> -963768.86 | H113: =H110+H108+H106+H104 -> -1578036.3 | I113: =I110+I108+I106+I104 -> -2403366 | J113: =J110+J108+J106+J104 -> -4146926.6
B114: % of sales | C114: -2.96292 | D114: -2.661121 | E114: -2.260601 | F114: =F113/F101 -> -1.978191 | G114: =G113/G101 -> -2.086615 | H114: =H113/H101 -> -1.767504 | I114: =I113/I101 -> -1.383225 | J114: =J113/J101 -> -1.350546
B116: Operating income/(loss) | C116: -40123 | D116: -96740 | E116: -149567 | F116: =F101+F113 -> -254959.62 | G116: =G101+G113 -> -501887.36 | H116: =H101+H113 -> -685231.35 | I116: =I101+I113 -> -665856.92 | J116: =J101+J113 -> -1076371
B117: % of sales | C117: -2.667716 | D117: -1.688065 | E117: -1.447737 | F117: =F116/F101 -> -0.978191 | G117: =G116/G101 -> -1.086615 | H117: =H116/H101 -> -0.767504 | I117: =I116/I101 -> -0.383225 | J117: =J116/J101 -> -0.350546
B119: Effective tax rate | E119: 0.014827 | F119: 0.3 | G119: 0.3 | H119: 0.3 | I119: 0.3 | J119: 0.3
B122: Billings & Unearned Revenue
B124: Total Revenue | C124: =C70 -> 23669 | D124: =D70 -> 66258 | E124: =E70 -> 130322 | F124: =F70 -> 260644 | G124: =G70 -> 461881.5 | H124: =H70 -> 892804.93 | I124: =I70 -> 1737509.1 | J124: =J70 -> 3070555.6
B125: Unearned revenue, period close | C125: 14185 | D125: 35537 | E125: 106751 | F125: 193492.44 | G125: 340312.08 | H125: 651148.28 | I125: 1124905.6 | J125: 1986434
B126: Less: unearned revenue, period open | C126: -3198 | D126: -11845 | E126: -41394 | F126: =-E125 -> -106751 | G126: =-F125 -> -193492.44 | H126: =-G125 -> -340312.08 | I126: =-H125 -> -651148.28 | J126: =-I125 -> -1124905.6
B127: Invoiced billings | C127: =SUM(C124:C126) -> 34656 | D127: =SUM(D124:D126) -> 89950 | E127: =SUM(E124:E126) -> 195679 | F127: =SUM(F124:F126) -> 347385.44 | G127: =SUM(G124:G126) -> 608701.13 | H127: =SUM(H124:H126) -> 1203641.1 | I127: =SUM(I124:I126) -> 2211266.4 | J127: =SUM(J124:J126) -> 3932084
B128: Billings growth | C128: 1.612328 | D128: =D127/C127-1 -> 1.5955102 | E128: =E127/D127-1 -> 1.1754197 | F128: =F127/E127-1 -> 0.77528219 | G128: =G127/F127-1 -> 0.75223557 | H128: =H127/G127-1 -> 0.97739262 | I128: =I127/H127-1 -> 0.83714759 | J128: =J127/I127-1 -> 0.77820457
B130: Unearned revenue as % of billings | C130: =C125/C127 -> 0.40930863 | D130: =D125/D127 -> 0.39507504 | E130: =E125/E127 -> 0.54554142 | F130: 0.55 | G130: 0.55 | H130: 0.55 | I130: 0.55 | J130: 0.55

Sheet BS-CF-WC
A2: Projected Balance Sheet
C4: ='P&L'!C68 -> 40908 | D4: ='P&L'!D68 -> 41305 | E4: ='P&L'!E68 -> 41670 | F4: ='P&L'!F68 -> 42035 | G4: ='P&L'!G68 -> 42400 | H4: ='P&L'!H68 -> 42766 | I4: ='P&L'!I68 -> 43131 | J4: ='P&L'!J68 -> 43496
B6: ASSET BASE
B7: Short-term assets:
B8: Cash & equivalents | D8: 102958 | E8: 101561 | F8: =F99 -> 206118.43 | G8: =G99 -> 100000 | H8: =H99 -> 100000 | I8: =I99 -> 100000 | J8: =J99 -> 100000
B9: Trade receivables | D9: 17352 | E9: 49977 | F9: =F110 -> 0 | G9: =G110 -> 0 | H9: =H110 -> 0 | I9: =I110 -> 0 | J9: =J110 -> 0
B10: Prepaids & other short-term assets | D10: 8379 | E10: 8437 | F10: =F111 -> 0 | G10: =G111 -> 0 | H10: =H111 -> 0 | I10: =I111 -> 0 | J10: =J111 -> 0
B11: Capitalized commissions | D11: 8246 | E11: 7071 | F11: =F112 -> 0 | G11: =G112 -> 0 | H11: =H112 -> 0 | I11: =I112 -> 0 | J11: =J112 -> 0
B12: Short-term assets — total | D12: =SUM(D8:D11) -> 136935 | E12: =SUM(E8:E11) -> 167046 | F12: =SUM(F8:F11) -> 206118.43 | G12: =SUM(G8:G11) -> 100000 | H12: =SUM(H8:H11) -> 100000 | I12: =SUM(I8:I11) -> 100000 | J12: =SUM(J8:J11) -> 100000
B14: Net fixed assets | D14: 32513 | E14: 35981 | F14: ='Debt-Capex-Amort'!F58 -> 20441.853 | G14: ='Debt-Capex-Amort'!G58 -> 8850.971 | H14: ='Debt-Capex-Amort'!H58 -> 10565.787 | I14: ='Debt-Capex-Amort'!I58 -> 29233.228 | J14: ='Debt-Capex-Amort'!J58 -> 108786.88
B15: Net intangible assets | D15: 715 | E15: 7419 | F15: ='Debt-Capex-Amort'!F148 -> 7242.44 | G15: ='Debt-Capex-Amort'!G148 -> 6864.8475 | H15: ='Debt-Capex-Amort'!H148 -> 10409.872 | I15: ='Debt-Capex-Amort'!I148 -> 18943.418 | J15: ='Debt-Capex-Amort'!J148 -> 34142.196
B16: Acquired goodwill | D16: 0 | E16: 8669 | F16: =E16 -> 8669 | G16: =F16 -> 8669 | H16: =G16 -> 8669 | I16: =H16 -> 8669 | J16: =I16 -> 8669
B17: Other non-current assets | D17: 3318 | E17: 11450 | F17: =E17 -> 11450 | G17: =F17 -> 11450 | H17: =G17 -> 11450 | I17: =H17 -> 11450 | J17: =I17 -> 11450
B19: Asset base — total | D19: =SUM(D12:D17) -> 173481 | E19: =SUM(E12:E17) -> 230565 | F19: =SUM(F12:F17) -> 253921.73 | G19: =SUM(G12:G17) -> 135834.82 | H19: =SUM(H12:H17) -> 141094.66 | I19: =SUM(I12:I17) -> 168295.65 | J19: =SUM(J12:J17) -> 263048.08
B21: OBLIGATIONS
B22: Short-term obligations:
B23: Trade payables | D23: 13726 | E23: 14208 | F23: =F115 -> 0 | G23: =G115 -> 0 | H23: =H115 -> 0 | I23: =I115 -> 0 | J23: =J115 -> 0
B24: Accrued payroll & benefits | D24: 3572 | E24: 18132 | F24: =F116 -> 0 | G24: =G116 -> 0 | H24: =H116 -> 0 | I24: =I116 -> 0 | J24: =J116 -> 0
B25: Accruals & other short-term obligations | D25: 1599 | E25: 16988 | F25: =F117 -> 0 | G25: =G117 -> 0 | H25: =H117 -> 0 | I25: =I117 -> 0 | J25: =J117 -> 0
B26: Unearned revenue | D26: 31625 | E26: 85653 | F26: =F118 -> 0 | G26: =G118 -> 0 | H26: =H118 -> 0 | I26: =I118 -> 0 | J26: =J118 -> 0
B27: Deferred lease cost | D27: 590 | E27: 1222 | F27: =F119 -> 0 | G27: =G119 -> 0 | H27: =H119 -> 0 | I27: =I119 -> 0 | J27: =J119 -> 0
B28: Borrowings | D28: 1132 | F28: ='Debt-Capex-Amort'!F17 -> 0 | G28: ='Debt-Capex-Amort'!G17 -> 165307.84 | H28: ='Debt-Capex-Amort'!H17 -> 489408.45 | I28: ='Debt-Capex-Amort'!I17 -> 885227.88 | J28: ='Debt-Capex-Amort'!J17 -> 1142527.4
B29: Short-term obligations — total | D29: =SUM(D23:D28) -> 52244 | E29: =SUM(E23:E28) -> 136203 | F29: =SUM(F23:F28) -> 0 | G29: =SUM(G23:G28) -> 165307.84 | H29: =SUM(H23:H28) -> 489408.45 | I29: =SUM(I23:I28) -> 885227.88 | J29: =SUM(J23:J28) -> 1142527.4
B31: Non-current borrowings (revolver) | D31: 25423 | E31: 28577 | F31: ='Debt-Capex-Amort'!F23 -> 27091 | G31: ='Debt-Capex-Amort'!G23 -> 13545.5 | H31: ='Debt-Capex-Amort'!H23 -> 0 | I31: ='Debt-Capex-Amort'!I23 -> 0 | J31: ='Debt-Capex-Amort'!J23 -> 0
B32: Unearned revenue, non-current | D32: 1584 | E32: 12747 | F32: =E32 -> 12747 | G32: =F32 -> 12747 | H32: =G32 -> 12747 | I32: =H32 -> 12747 | J32: =I32 -> 12747
B33: Preferred warrant obligation, non-current | D33: 3154 | E33: 0 | F33: =E33 -> 0 | G33: =F33 -> 0 | H33: =G33 -> 0 | I33: =H33 -> 0 | J33: =I33 -> 0
B34: Deferred lease cost, non-current | D34: 5849 | E34: 3465 | F34: =E34 -> 3465 | G34: =F34 -> 3465 | H34: =G34 -> 3465 | I34: =H34 -> 3465 | J34: =I34 -> 3465
B35: Other non-current obligations | D35: 574 | E35: 1478 | F35: =E35 -> 1478 | G35: =F35 -> 1478 | H35: =G35 -> 1478 | I35: =H35 -> 1478 | J35: =I35 -> 1478
B37: Obligations — total | D37: =SUM(D29:D35) -> 88828 | E37: =SUM(E29:E35) -> 182470 | F37: =SUM(F29:F35) -> 44781 | G37: =SUM(G29:G35) -> 196543.34 | H37: =SUM(H29:H35) -> 507098.45 | I37: =SUM(I29:I35) -> 902917.88 | J37: =SUM(J29:J35) -> 1160217.4
B39: Redeemable preferred equity: | D39: 250523 | E39: 0
B40: Common equity/(deficit):
B41: Class A & Class B common shares | D41: 1 | E41: 9
B42: Paid-in capital surplus | D42: 8582 | E42: 340603
B43: Treasury shares (refer Note 10) | D43: -1142 | E43: -1292
B44: Cumulative other comprehensive income | D44: 0 | E44: 16
B45: Retained deficit | D45: -205805 | E45: -322829
B46: Common equity/(deficit) — total | D46: =SUM(D41:D45) -> -198364 | E46: =SUM(E41:E45) -> 16507 | F46: ='Equity-Shares'!F8 -> 16137.301 | G46: ='Equity-Shares'!G8 -> -374212.61 | H46: ='Equity-Shares'!H8 -> -939672.67 | I46: ='Equity-Shares'!I8 -> -1686208.1 | J46: ='Equity-Shares'!J8 -> -2530814.3
B47: Obligations + equity — total | D47: =D46+D39+D37 -> 140987 | E47: =E46+E39+E37 -> 198977 | F47: =F46+F39+F37 -> 60918.301 | G47: =G46+G39+G37 -> -177669.27 | H47: =H46+H39+H37 -> -432574.21 | I47: =I46+I39+I37 -> -783290.25 | J47: =J46+J39+J37 -> -1370597
B49: Balance check | D49: =D47-D19 -> -32494 | E49: =E47-E19 -> -31588 | F49: =F47-F19 -> -193003.43 | G49: =G47-G19 -> -313504.09 | H49: =H47-H19 -> -573668.87 | I49: =I47-I19 -> -951585.9 | J49: =J47-J19 -> -1633645.1
A52: Projected Cash Flow Statement
C55: =C4 -> 40908 | D55: =D4 -> 41305 | E55: =E4 -> 41670 | F55: =F4 -> 42035 | G55: =G4 -> 42400 | H55: =H4 -> 42766 | I55: =I4 -> 43131 | J55: =J4 -> 43496
B56: OPERATING CASH FLOWS:
B57: Net income/(loss) | C57: -51724 | D57: -105541 | E57: -181071 | F57: ='P&L'!F95 -> -250369.7 | G57: ='P&L'!G95 -> -390349.91 | H57: ='P&L'!H95 -> -565460.05 | I57: ='P&L'!I95 -> -746535.46 | J57: ='P&L'!J95 -> -844606.22
B58: Reconciling items from net result to operating cash:
B59: Depreciation & amortization charge | C59: 3338 | D59: 8616 | E59: 15964 | F59: =-'Debt-Capex-Amort'!F56-'Debt-Capex-Amort'!F146 -> 29293.435 | G59: =-'Debt-Capex-Amort'!G56-'Debt-Capex-Amort'!G146 -> 36381.221 | H59: =-'Debt-Capex-Amort'!H56-'Debt-Capex-Amort'!H146 -> 51662.723 | I59: =-'Debt-Capex-Amort'!I56-'Debt-Capex-Amort'!I146 -> 84319.298 | J59: =-'Debt-Capex-Amort'!J56-'Debt-Capex-Amort'!J146 -> 84319.298
B60: Share-based pay expense | C60: 5281 | D60: 6207 | E60: 11679
B61: Amortization of capitalized commissions | C61: 1916 | D61: 7983 | E61: 11310
B62: Fair-value change on preferred warrant obligation | C62: 378 | D62: 1398 | E62: 8433
B63: Reversal of deferred-tax valuation allowance | E63: -2519
B64: Other adjustments | C64: 246 | D64: 657 | E64: 182
B65: Working-capital movements, net of acquisition effects:
B66: Trade receivables | C66: -4659 | D66: -10762 | E66: -29402 | F66: =E110-F110 -> 0 | G66: =F110-G110 -> 0 | H66: =G110-H110 -> 0 | I66: =H110-I110 -> 0 | J66: =I110-J110 -> 0
B67: Capitalized commissions | C67: -3602 | D67: -11664 | E67: -12962 | F67: =E112-F112 -> 0 | G67: =F112-G112 -> 0 | H67: =G112-H112 -> 0 | I67: =H112-I112 -> 0 | J67: =I112-J112 -> 0
B68: Prepaids & other assets | C68: -8817 | D68: -1929 | E68: -3437 | F68: =E111-F111 -> 0 | G68: =F111-G111 -> 0 | H68: =G111-H111 -> 0 | I68: =H111-I111 -> 0 | J68: =I111-J111 -> 0
B69: Trade payables | C69: 3565 | D69: 1678 | E69: -2707 | F69: =F115-E115 -> 0 | G69: =G115-F115 -> 0 | H69: =H115-G115 -> 0 | I69: =I115-H115 -> 0 | J69: =J115-I115 -> 0
B70: Accruals & other obligations | C70: 3282 | D70: 1856 | E70: 27390 | F70: =F117-E117+F116-E116 -> 0 | G70: =G117-F117+G116-F116 -> 0 | H70: =H117-G117+H116-G116 -> 0 | I70: =I117-H117+I116-H116 -> 0 | J70: =J117-I117+J116-I116 -> 0
B71: Deferred lease cost | C71: 2950 | D71: 1642 | E71: -358 | F71: =F119-E119 -> 0 | G71: =G119-F119 -> 0 | H71: =H119-G119 -> 0 | I71: =I119-H119 -> 0 | J71: =J119-I119 -> 0
B72: Unearned revenue | C72: 8135 | D72: 29455 | E72: 47316 | F72: =F118-E118 -> 0 | G72: =G118-F118 -> 0 | H72: =H118-G118 -> 0 | I72: =I118-H118 -> 0 | J72: =J118-I118 -> 0
B73: Operating cash flow, net | C73: =SUM(C57:C72) -> -39711 | D73: =SUM(D57:D72) -> -70404 | E73: =SUM(E57:E72) -> -110182 | F73: =SUM(F57:F72) -> -221076.26 | G73: =SUM(G57:G72) -> -353968.69 | H73: =SUM(H57:H72) -> -513797.33 | I73: =SUM(I57:I72) -> -662216.16 | J73: =SUM(J57:J72) -> -760286.92
B75: INVESTING CASH FLOWS:
B76: Marketable securities purchased | C76: -32693 | D76: 0 | E76: 0
B77: Marketable securities matured | C77: 13029 | D77: 20340 | E77: 0
B78: Fixed-asset additions | C78: -14876 | D78: -18480 | E78: -23953 | F78: =-'Debt-Capex-Amort'!F51 -> -10971.288 | G78: =-'Debt-Capex-Amort'!G51 -> -22103.339 | H78: =-'Debt-Capex-Amort'!H51 -> -52458.539 | I78: =-'Debt-Capex-Amort'!I51 -> -102832.74 | J78: =-'Debt-Capex-Amort'!J51 -> -163718.95
B79: Investments in private equity holdings | C79: 0 | D79: -103 | E79: 0
B80: Acquisitions (net of cash) & intangible purchases | C80: -990 | D80: -53 | E80: -8768 | F80: =-'Debt-Capex-Amort'!F141 -> -2606.44 | G80: =-'Debt-Capex-Amort'!G141 -> -2309.4075 | H80: =-'Debt-Capex-Amort'!H141 -> -4464.0246 | I80: =-'Debt-Capex-Amort'!I141 -> -8687.5455 | J80: =-'Debt-Capex-Amort'!J141 -> -15352.778
B81: Investing cash flow, net | C81: =SUM(C76:C80) -> -35530 | D81: =SUM(D76:D80) -> 1704 | E81: =SUM(E76:E80) -> -32721 | F81: =SUM(F76:F80) -> -13577.728 | G81: =SUM(G76:G80) -> -24412.747 | H81: =SUM(H76:H80) -> -56922.564 | I81: =SUM(I76:I80) -> -111520.28 | J81: =SUM(J76:J80) -> -179071.73
B83: Cash available before financing | D83: =D81+D73 -> -68700 | E83: =E81+E73 -> -142903 | F83: -151246.57 | G83: -272350.78 | H83: -325025.11 | I83: -410289.42 | J83: -271769.48
D84: =D83/12 -> -5725 | E84: =E83/12 -> -11908.583
B85: FINANCING CASH FLOWS:
B86: Borrowing proceeds, net of costs | C86: 12252 | D86: 22468 | E86: 33802 | F86: ='Debt-Capex-Amort'!F16 -> 0 | G86: ='Debt-Capex-Amort'!G16 -> 165307.84 | H86: ='Debt-Capex-Amort'!H16 -> 324100.61 | I86: ='Debt-Capex-Amort'!I16 -> 395819.42 | J86: ='Debt-Capex-Amort'!J16 -> 257299.48
B87: Debt principal repaid | C87: -289 | D87: -658 | E87: -36352 | F87: ='Debt-Capex-Amort'!F22 -> -1486 | G87: ='Debt-Capex-Amort'!G22 -> -13545.5 | H87: ='Debt-Capex-Amort'!H22 -> -13545.5 | I87: ='Debt-Capex-Amort'!I22 -> 0 | J87: ='Debt-Capex-Amort'!J22 -> 0
B88: Preferred-stock issuance proceeds, net of costs | C88: 96444 | D88: 169238 | E88: 94427
B89: Preferred warrant exercise proceeds | C89: 0 | D89: 0 | E89: 1097
B90: Offering proceeds | F90: ='Equity-Shares'!F7 -> 250000
B91: Option exercise proceeds | C91: 298 | D91: 2204 | E91: 2949
B92: Deferred offering costs paid | C92: 0 | D92: 0 | E92: -650
B93: Financing cash flow, net | C93: =SUM(C86:C92) -> 108705 | D93: =SUM(D86:D92) -> 193252 | E93: =SUM(E86:E92) -> 95273 | F93: =SUM(F86:F92) -> 248514 | G93: =SUM(G86:G92) -> 151762.34 | H93: =SUM(H86:H92) -> 310555.11 | I93: =SUM(I86:I92) -> 395819.42 | J93: =SUM(J86:J92) -> 257299.48
B94: FX impact on cash | C94: 0 | D94: 0 | E94: 13
B96: Net movement in cash | C96: =C93+C81+C73 -> 33464 | D96: =D93+D81+D73 -> 124552 | E96: =E93+E81+E73+E94 -> -47617 | F96: 97267.435 | G96: -106118.43 | H96: -5.8207661e-11 | I96: 5.8207661e-11 | J96: -2.910383e-11
B98: Cash, period open | C98: 7298 | D98: 30539 | E98: =D99 -> 155091 | F98: =E99 -> 107474 | G98: =F99 -> 206118.43 | H98: =G99 -> 100000 | I98: =H99 -> 100000 | J98: =I99 -> 100000
B99: Cash, period close | C99: =C96+C98 -> 40762 | D99: =D96+D98 -> 155091 | E99: =E96+E98 -> 107474 | F99: 206118.43 | G99: 100000 | H99: 100000 | I99: 100000 | J99: 100000
A102: Working Capital Schedule
D105: =D4 -> 41305 | E105: =E4 -> 41670 | F105: =F4 -> 42035 | G105: =G4 -> 42400 | H105: =H4 -> 42766 | I105: =I4 -> 43131 | J105: =J4 -> 43496
B106: Net revenue
B107: Cost of delivery
B109: Short-term asset & obligation balances
B110: Trade receivables | L110: Assumed days outstanding | M110: 365
B111: Prepaids & other short-term assets
B112: Capitalized commissions
B113: Non-cash short-term assets — total
B115: Trade payables
B116: Accrued payroll & benefits
B117: Accruals & other short-term obligations
B118: Unearned revenue
B119: Deferred lease cost
B120: Non-debt short-term obligations — total
B122: Working capital/(deficit)
B124: (Increase)/decrease in working capital
B128: Efficiency Ratios & Drivers
B129: Trade receivables (days to collect) | D129: =365/(D106/D110) -> #DIV/0! | E129: =365/(E106/E110) -> #DIV/0! | F129: 126 | G129: 140 | H129: 117 | I129: 147 | J129: 102
...

Sheet Debt-Capex-Amort
A2: Borrowings Roll-Forward
C4: ='BS-CF-WC'!C4 -> 40908 | D4: ='BS-CF-WC'!D4 -> 41305 | E4: ='BS-CF-WC'!E4 -> 41670 | F4: ='BS-CF-WC'!F4 -> 42035 | G4: ='BS-CF-WC'!G4 -> 42400 | H4: ='BS-CF-WC'!H4 -> 42766 | I4: ='BS-CF-WC'!I4 -> 43131 | J4: ='BS-CF-WC'!J4 -> 43496
B5: Cash available before financing | F5: ='BS-CF-WC'!F83 -> -151246.57 | G5: ='BS-CF-WC'!G83 -> -272350.78 | H5: ='BS-CF-WC'!H83 -> -325025.11 | I5: ='BS-CF-WC'!I83 -> -410289.42 | J5: ='BS-CF-WC'!J83 -> -271769.48
B6: Equity issued/(repurchased) | F6: ='Equity-Shares'!F7 -> 250000 | G6: ='Equity-Shares'!G7 -> 0 | H6: ='Equity-Shares'!H7 -> 0 | I6: ='Equity-Shares'!I7 -> 0 | J6: ='Equity-Shares'!J7 -> 0
B7: + Opening cash | F7: 108851 | G7: 206118.43 | H7: 100000 | I7: 100000 | J7: 100000
B8: - Minimum cash buffer | F8: =-Drivers!$C$13 -> -85530 | G8: =-Drivers!$C$13 -> -85530 | H8: =-Drivers!$C$13 -> -85530 | I8: =-Drivers!$C$13 -> -85530 | J8: =-Drivers!$C$13 -> -85530
B9: Cash free for debt service | F9: =SUM(F5:F8) -> 122074.43 | G9: =SUM(G5:G8) -> -151762.34 | H9: =SUM(H5:H8) -> -310555.11 | I9: =SUM(I5:I8) -> -395819.42 | J9: =SUM(J5:J8) -> -257299.48
B10: Term-debt drawdowns
B11: Term-debt repayments | F11: =F22 -> -1486 | G11: =G22 -> -13545.5 | H11: =H22 -> -13545.5 | I11: =I22 -> 0 | J11: =J22 -> 0
B12: Cash free for revolver | F12: =F9+F10+F11 -> 120588.43 | G12: =G9+G10+G11 -> -165307.84 | H12: =H9+H10+H11 -> -324100.61 | I12: =I9+I10+I11 -> -395819.42 | J12: =J9+J10+J11 -> -257299.48
B14: Incremental revolver draw
B15: Opening balance | F15: =E17 -> 0 | G15: =F17 -> 0 | H15: =G17 -> 165307.84 | I15: =H17 -> 489408.45 | J15: =I17 -> 885227.88
B16: Discretionary (paydown)/draw | F16: =IF(F12<0,-F12,-MIN(F15,F12)) -> 0 | G16: =IF(G12<0,-G12,-MIN(G15,G12)) -> 165307.84 | H16: =IF(H12<0,-H12,-MIN(H15,H12)) -> 324100.61 | I16: =IF(I12<0,-I12,-MIN(I15,I12)) -> 395819.42 | J16: =IF(J12<0,-J12,-MIN(J15,J12)) -> 257299.48
B17: Closing balance | E17: 0 | F17: =SUM(F15:F16) -> 0 | G17: =SUM(G15:G16) -> 165307.84 | H17: =SUM(H15:H16) -> 489408.45 | I17: =SUM(I15:I16) -> 885227.88 | J17: =SUM(J15:J16) -> 1142527.4
B19: Revolver (committed repayments)
B20: Opening balance | F20: =E23 -> 28577 | G20: =F23 -> 27091 | H20: =G23 -> 13545.5 | I20: =H23 -> 0 | J20: =I23 -> 0
B21: Draws
B22: (Repayment/amortization) | F22: -1486 | G22: =-(E23+F22)/2 -> -13545.5 | H22: =G22 -> -13545.5 | I22: 0 | J22: 0
B23: Closing balance | E23: ='BS-CF-WC'!E31 -> 28577 | F23: =SUM(F20:F22) -> 27091 | G23: =SUM(G20:G22) -> 13545.5 | H23: =SUM(H20:H22) -> 0 | I23: =SUM(I20:I22) -> 0 | J23: =SUM(J20:J22) -> 0
B25: Interest Cost Build
B27: 1) Revolver | F27: 0 | G27: 91244.672 | H27: 353130.4 | I27: 728916.16 | J27: 1069945.6
F28: 0.035 | G28: 0.035 | H28: 0.035 | I28: 0.035 | J28: 0.035
B29: Revolver interest cost | F29: =F28*F27 -> 0 | G29: =G28*G27 -> 3193.5635 | H29: =H28*H27 -> 12359.564 | I29: =I28*I27 -> 25512.066 | J29: =J28*J27 -> 37448.097
B31: 2) Revolver (committed) | F31: 33257 | G31: 24385.5 | H31: 8128.5 | I31: 0 | J31: 0
F32: 0.035 | G32: 0.05 | H32: 0.05 | I32: 0.05 | J32: 0.05
B33: Interest cost | F33: =F32*F31 -> 1163.995 | G33: =G32*G31 -> 1219.275 | H33: =H32*H31 -> 406.425 | I33: =I32*I31 -> 0 | J33: =J32*J31 -> 0
B35: (1) + (2): Total interest cost | F35: =F33+F29 -> 1163.995 | G35: =G33+G29 -> 4412.8385 | H35: =H33+H29 -> 12765.989 | I35: =I33+I29 -> 25512.066 | J35: =J33+J29 -> 37448.097
B38: Cash Balance Roll-Forward Schedule
B40: Cash on hand | E40: 108851 | F40: 206118.43 | G40: 100000 | H40: 100000 | I40: 100000 | J40: 100000
B41: Average cash on hand | F41: 157484.72 | G41: 153059.22 | H41: 100000 | I41: 100000 | J41: 100000
B43: Interest income earned | D43: 0.02 | F43: 3149.6943 | G43: 3061.1843 | H43: 2000 | I43: 2000 | J43: 2000
A46: Fixed-Asset & Depreciation Schedule
C49: ='BS-CF-WC'!C4 -> 40908 | D49: ='BS-CF-WC'!D4 -> 41305 | E49: ='BS-CF-WC'!E4 -> 41670 | F49: ='BS-CF-WC'!F4 -> 42035 | G49: ='BS-CF-WC'!G4 -> 42400 | H49: ='BS-CF-WC'!H4 -> 42766 | I49: ='BS-CF-WC'!I4 -> 43131 | J49: ='BS-CF-WC'!J4 -> 43496
B50: Net revenue | D50: ='P&L'!D70 -> 66258 | E50: ='P&L'!E70 -> 130322 | F50: ='P&L'!F70 -> 260644 | G50: ='P&L'!G70 -> 461881.5 | H50: ='P&L'!H70 -> 892804.93 | I50: ='P&L'!I70 -> 1737509.1 | J50: ='P&L'!J70 -> 3070555.6
B51: Capital spend | D51: =-'BS-CF-WC'!D78 -> 18480 | E51: =-'BS-CF-WC'!E78 -> 23953 | F51: =F52*F50 -> 10971.288 | G51: =G52*G50 -> 22103.339 | H51: =H52*H50 -> 52458.539 | I51: =I52*I50 -> 102832.74 | J51: =J52*J50 -> 163718.95
B52: Capital spend as % of net revenue | D52: =D51/D50 -> 0.27890972 | E52: =E51/E50 -> 0.18379859 | F52: =Drivers!F12 -> 0.042093 | G52: =Drivers!G12 -> 0.047855 | H52: =Drivers!H12 -> 0.058757 | I52: =Drivers!I12 -> 0.059184 | J52: =Drivers!J12 -> 0.053319
B54: Opening net fixed assets | F54: =E58 -> 35981 | G54: =F58 -> 20441.853 | H54: =G58 -> 8850.971 | I54: =H58 -> 10565.787 | J54: =I58 -> 29233.228
B55: Capital spend | F55: =F51 -> 10971.288 | G55: =G51 -> 22103.339 | H55: =H51 -> 52458.539 | I55: =I51 -> 102832.74 | J55: =J51 -> 163718.95
B56: (Depreciation charge) | F56: =-F131 -> -26510.435 | G56: =-G131 -> -33694.221 | H56: =-H131 -> -50743.723 | I56: =-I131 -> -84165.298 | J56: =-J131 -> -84165.298
B57: (Asset disposals)
B58: Closing net fixed assets | E58: ='BS-CF-WC'!E14 -> 35981 | F58: =SUM(F54:F57) -> 20441.853 | G58: =SUM(G54:G57) -> 8850.971 | H58: =SUM(H54:H57) -> 10565.787 | I58: =SUM(I54:I57) -> 29233.228 | J58: =SUM(J54:J57) -> 108786.88
E60: figures below stated gross
B61: Fixed assets (opening breakdown) | E61: Value | F61: Value | G61: Service life | H61: Asset mix share
B62: Server hardware | E62: 22254 | F62: 49168 | G62: 3 | H62: =F62/$F$67 -> 0.69646019
B63: Computing hardware & software | E63: 3086 | F63: 5792 | G63: 3 | H63: =F63/$F$67 -> 0.082043146
B64: Furniture & fixtures | E64: 3427 | F64: 4388 | G64: 3 | H64: =F64/$F$67 -> 0.062155616 | I64: Straight-line depreciation basis
B65: Leasehold build-outs | E65: 7483 | F65: 9486 | G65: 3 | H65: =F65/$F$67 -> 0.13436832 | I65: Straight-line depreciation basis
B66: Assets under construction | E66: 7031 | F66: 1763 | G66: NA | H66: =F66/$F$67 -> 0.024972733 | I66: Straight-line depreciation basis
B67: Total | E67: =SUM(E62:E66) -> 43281 | F67: =SUM(F62:F66) -> 70597
B70: Total capital spend
B71: Breakdown
B72: Server hardware | F72: =F$51*$H62 -> 7641.0652 | G72: =G$51*$H62 -> 15394.096 | H72: =H$51*$H62 -> 36535.284 | I72: =I$51*$H62 -> 71618.908 | J72: =J$51*$H62 -> 114023.73
B73: Computing hardware & software | F73: =F$51*$H63 -> 900.11898 | G73: =G$51*$H63 -> 1813.4275 | H73: =H$51*$H63 -> 4303.8636 | I73: =I$51*$H63 -> 8436.7214 | J73: =J$51*$H63 -> 13432.018
B74: Furniture & fixtures | F74: =F$51*$H64 -> 681.92715 | G74: =G$51*$H64 -> 1373.8467 | H74: =H$51*$H64 -> 3260.5928 | I74: =I$51*$H64 -> 6391.6322 | J74: =J$51*$H64 -> 10176.052
B75: Leasehold build-outs | F75: =F$51*$H65 -> 1474.1935 | G75: =G$51*$H65 -> 2969.9885 | H75: =H$51*$H65 -> 7048.7656 | I75: =I$51*$H65 -> 13817.462 | J75: =J$51*$H65 -> 21998.64
B76: Assets under construction | F76: =F$51*$H66 -> 273.98304 | G76: =G$51*$H66 -> 551.98078 | H76: =H$51*$H66 -> 1310.0331 | I76: =I$51*$H66 -> 2568.0145 | J76: =J$51*$H66 -> 4088.5097
B79: Server hardware — straight-line
B80: Service life | C80: =G62 -> 3
B81: Server hardware | C81: =F62 -> 49168
B82: Depreciation on legacy assets | F82: =$C81/$C80 -> 16389.333 | G82: =$C81/$C80 -> 16389.333 | H82: =$C81/$C80 -> 16389.333 | I82: =$C81/$C80 -> 16389.333 | J82: =$C81/$C80 -> 16389.333
B84: Year | C84: Capital spend | D84: Service life
B85: 2015 | C85: {=TRANSPOSE(F72:I72)} -> 7641.0652 | D85: 3 | F85: =$C85/$D85 -> 2547.0217 | G85: =$C85/$D85 -> 2547.0217 | H85: =$C85/$D85 -> 2547.0217 | I85: =$C85/$D85 -> 2547.0217 | J85: =$C85/$D85 -> 2547.0217
B86: =B85+1 -> 2016 | C86: 15394.096 | D86: 3 | G86: =$C86/$D86 -> 5131.3652 | H86: =$C86/$D86 -> 5131.3652 | I86: =$C86/$D86 -> 5131.3652 | J86: =$C86/$D86 -> 5131.3652
B87: =B86+1 -> 2017 | C87: 36535.284 | D87: 3 | H87: =$C87/$D87 -> 12178.428 | I87: =$C87/$D87 -> 12178.428 | J87: =$C87/$D87 -> 12178.428
B88: =B87+1 -> 2018 | C88: 71618.908 | D88: 3 | I88: =$C88/$D88 -> 23872.969 | J88: =$C88/$D88 -> 23872.969
B90: Depreciation — server hardware | F90: =SUM(F82:F88) -> 18936.355 | G90: =SUM(G82:G88) -> 24067.72 | H90: =SUM(H82:H88) -> 36246.148 | I90: =SUM(I82:I88) -> 60119.118 | J90: =SUM(J82:J88) -> 60119.118
B92: Computing hardware & software
B93: Service life | C93: =G63 -> 3
B94: Computing hardware & software | C94: =F63 -> 5792
B95: Depreciation on legacy assets | F95: =$C94/$C93 -> 1930.6667 | G95: =$C94/$C93 -> 1930.6667 | H95: =$C94/$C93 -> 1930.6667 | I95: =$C94/$C93 -> 1930.6667 | J95: =$C94/$C93 -> 1930.6667
B97: Year | C97: Capital spend | D97: Service life
B98: 2015 | C98: {=TRANSPOSE(F73:I73)} -> 900.11898 | D98: 3 | F98: =$C98/$D98 -> 300.03966 | G98: =$C98/$D98 -> 300.03966 | H98: =$C98/$D98 -> 300.03966 | I98: =$C98/$D98 -> 300.03966 | J98: =$C98/$D98 -> 300.03966
B99: =B98+1 -> 2016 | C99: 1813.4275 | D99: 3 | G99: =$C99/$D99 -> 604.47583 | H99: =$C99/$D99 -> 604.47583 | I99: =$C99/$D99 -> 604.47583 | J99: =$C99/$D99 -> 604.47583
B100: =B99+1 -> 2017 | C100: 4303.8636 | D100: 3 | H100: =$C100/$D100 -> 1434.6212 | I100: =$C100/$D100 -> 1434.6212 | J100: =$C100/$D100 -> 1434.6212
B101: =B100+1 -> 2018 | C101: 8436.7214 | D101: 3 | I101: =$C101/$D101 -> 2812.2405 | J101: =$C101/$D101 -> 2812.2405
B103: Depreciation — computing hardware & software | F103: =SUM(F95:F101) -> 2230.7063 | G103: =SUM(G95:G101) -> 2835.1822 | H103: =SUM(H95:H101) -> 4269.8034 | I103: =SUM(I95:I101) -> 7082.0438 | J103: =SUM(J95:J101) -> 7082.0438
B105: Furniture & fixtures
B106: Service life | C106: =G64 -> 3
B107: Furniture & fixtures | C107: =F64 -> 4388
B108: Depreciation on legacy assets | F108: =$C107/$C106 -> 1462.6667 | G108: =$C107/$C106 -> 1462.6667 | H108: =$C107/$C106 -> 1462.6667 | I108: =$C107/$C106 -> 1462.6667 | J108: =$C107/$C106 -> 1462.6667
B110: Year | C110: Capital spend | D110: Service life
B111: 2015 | C111: {=TRANSPOSE(F74:I74)} -> 681.92715 | D111: 3 | F111: =$C111/$D111 -> 227.30905 | G111: =$C111/$D111 -> 227.30905 | H111: =$C111/$D111 -> 227.30905 | I111: =$C111/$D111 -> 227.30905 | J111: =$C111/$D111 -> 227.30905
B112: =B111+1 -> 2016 | C112: 1373.8467 | D112: 3 | G112: =$C112/$D112 -> 457.94888 | H112: =$C112/$D112 -> 457.94888 | I112: =$C112/$D112 -> 457.94888 | J112: =$C112/$D112 -> 457.94888
B113: =B112+1 -> 2017 | C113: 3260.5928 | D113: 3 | H113: =$C113/$D113 -> 1086.8643 | I113: =$C113/$D113 -> 1086.8643 | J113: =$C113/$D113 -> 1086.8643
B114: =B113+1 -> 2018 | C114: 6391.6322 | D114: 3 | I114: =$C114/$D114 -> 2130.5441 | J114: =$C114/$D114 -> 2130.5441
B116: Depreciation — furniture & fixtures | F116: =SUM(F108:F114) -> 1689.9757 | G116: =SUM(G108:G114) -> 2147.9246 | H116: =SUM(H108:H114) -> 3234.7889 | I116: =SUM(I108:I114) -> 5365.3329 | J116: =SUM(J108:J114) -> 5365.3329
B118: Leasehold build-outs
B119: Service life | C119: =G65 -> 3
B120: Leasehold build-outs | C120: =F65 -> 9486
B121: Depreciation on legacy assets | F121: =$C120/$C119 -> 3162 | G121: =$C120/$C119 -> 3162 | H121: =$C120/$C119 -> 3162 | I121: =$C120/$C119 -> 3162 | J121: =$C120/$C119 -> 3162
B123: Year | C123: Capital spend | D123: Service life
B124: 2015 | C124: {=TRANSPOSE(F75:I75)} -> 1474.1935 | D124: 3 | F124: =$C124/$D124 -> 491.39783 | G124: =$C124/$D124 -> 491.39783 | H124: =$C124/$D124 -> 491.39783 | I124: =$C124/$D124 -> 491.39783 | J124: =$C124/$D124 -> 491.39783
B125: =B124+1 -> 2016 | C125: 2969.9885 | D125: 3 | G125: =$C125/$D125 -> 989.99615 | H125: =$C125/$D125 -> 989.99615 | I125: =$C125/$D125 -> 989.99615 | J125: =$C125/$D125 -> 989.99615
B126: =B125+1 -> 2017 | C126: 7048.7656 | D126: 3 | H126: =$C126/$D126 -> 2349.5885 | I126: =$C126/$D126 -> 2349.5885 | J126: =$C126/$D126 -> 2349.5885
B127: =B126+1 -> 2018 | C127: 13817.462 | D127: 3 | I127: =$C127/$D127 -> 4605.8206 | J127: =$C127/$D127 -> 4605.8206
B129: Depreciation — leasehold build-outs | F129: =SUM(F121:F127) -> 3653.3978 | G129: =SUM(G121:G127) -> 4643.394 | H129: =SUM(H121:H127) -> 6992.9825 | I129: =SUM(I121:I127) -> 11598.803 | J129: =SUM(J121:J127) -> 11598.803
B131: Total depreciation charge | F131: =F129+F116+F103+F90 -> 26510.435 | G131: =G129+G116+G103+G90 -> 33694.221 | H131: =H129+H116+H103+H90 -> 50743.723 | I131: =I129+I116+I103+I90 -> 84165.298 | J131: =J129+J116+J103+J90 -> 84165.298
A134: Reconciliation check | B134: =SUM(D50:J51,D52:E52,F54:J56,E58:J58) -> 7406231.9
A137: Intangibles & Amortization Schedule
C139: ='BS-CF-WC'!C4 -> 40908 | D139: ='BS-CF-WC'!D4 -> 41305 | E139: ='BS-CF-WC'!E4 -> 41670 | F139: ='BS-CF-WC'!F4 -> 42035 | G139: ='BS-CF-WC'!G4 -> 42400 | H139: ='BS-CF-WC'!H4 -> 42766 | I139: ='BS-CF-WC'!I4 -> 43131 | J139: ='BS-CF-WC'!J4 -> 43496
...

Sheet Equity-Shares
A2: Common Equity Roll-Forward
C4: ='BS-CF-WC'!C4 -> 40908 | D4: ='BS-CF-WC'!D4 -> 41305 | E4: ='BS-CF-WC'!E4 -> 41670 | F4: ='BS-CF-WC'!F4 -> 42035 | G4: ='BS-CF-WC'!G4 -> 42400 | H4: ='BS-CF-WC'!H4 -> 42766 | I4: ='BS-CF-WC'!I4 -> 43131 | J4: ='BS-CF-WC'!J4 -> 43496
B5: Opening equity | F5: =E8 -> 16507 | G5: =F8 -> 16137.301 | H5: =G8 -> -374212.61 | I5: =H8 -> -939672.67 | J5: =I8 -> -1686208.1
B6: Net result | F6: ='P&L'!F92 -> -250369.7 | G6: ='P&L'!G92 -> -390349.91 | H6: ='P&L'!H92 -> -565460.05 | I6: ='P&L'!I92 -> -746535.46 | J6: ='P&L'!J92 -> -844606.22
B7: Equity issued/(repurchased) | F7: =250000 -> 250000 | G7: ='BS-CF-WC'!G90 -> 0 | H7: ='BS-CF-WC'!H90 -> 0 | I7: ='BS-CF-WC'!I90 -> 0 | J7: ='BS-CF-WC'!J90 -> 0
B8: Closing equity | E8: ='BS-CF-WC'!E46 -> 16507 | F8: =SUM(F5:F7) -> 16137.301 | G8: =SUM(G5:G7) -> -374212.61 | H8: =SUM(H5:H7) -> -939672.67 | I8: =SUM(I5:I7) -> -1686208.1 | J8: =SUM(J5:J7) -> -2530814.3
A14: Reconciliation check | B14: =SUM(F5:J8,E8) -> -11013034
A17: Option Valuation Model
A19: Projection Inputs
A21: Black-Scholes model inputs
A22: Current share price = | B22: 17
A23: Option strike price = | B23: =E78 -> 3.65
A24: Option expiry = | B24: =F78/2 -> 4.225
A25: Share-price volatility = | B25: 0.450592
A26: Annualized dividend yield = | B26: 0
A27: Risk-free treasury rate = | B27: 0.023242
A28: Warrants/options outstanding = | B28: =D78/10^3 -> 18427.075
A29: Shares outstanding = | B29: =C67/10^3 -> 91460.679
A31: Option value calculation
A33: Share price = | B33: =B22 -> 17
A34: Strike = | B34: =B23 -> 3.65
A35: Adjusted S = | B35: 19.357064
A36: Adjusted K = | B36: =B34 -> 3.65
A37: Expiry (years) = | B37: =B24 -> 4.225
A39: Options granted | B39: =B28 -> 18427.075
A40: Shares outstanding — total | B40: =B29 -> 91460.679
A41: Treasury rate | B41: =B27 -> 0.023242
A42: Return variance | B42: =B25^2 -> 0.20303315
A43: Annualized dividend yield | B43: =B26 -> 0
A44: Discount rate | B44: =B41-B43 -> 0.023242
A46: d1 = | B46: =(LN(B35/B36)+(B44+(B42/2))*B37)/(((B42)^(0.5))*(B37^0.5)) -> 2.3704118
A47: N (d1) = | B47: =NORMSDIST(B46) -> 0.99111586
A49: d2 = | B49: =B46-((B42^0.5)*(B37^(0.5))) -> 1.4442287
A50: N (d2) = | B50: =NORMSDIST(B49) -> 0.92566267
A52: Value per option = | B52: =((EXP((0-B43)*B37))*B35*B47-B36*(EXP((0-B41)*B37))*B50) -> 16.122431
A54: Aggregate option value = | B54: =B52*B28 -> 297089.25
A57: Share Count Buildup
B59: Common shares
B61: Existing structure
B62: Class A | C62: 0
B63: Class B | C63: 90193539
B64: Class B | C64: 225300 | D64: issuable on vesting
B65: Class B | C65: 41840 | D65: future issuance
B66: New Class B shares from offering | C66: 1000000 | D66: (input)
C67: =SUM(C62:C66) -> 91460679 | D67: =1.2*10^9/C67 -> 13.120392
B70: Option grant data
D72: Shares under outstanding options | E72: Weighted-average strike | F72: Weighted-average remaining term (years) | G72: Aggregate intrinsic value (000s)
B73: Balance as of January 31, 2013 | D73: 13992407 | E73: 1.84 | F73: 8.69 | G73: 38954
B74: Options granted | D74: 7847410 | E74: 6.16
B75: Options exercised | D75: -2267540 | E75: 1.32
B76: Options forfeited/cancelled — Plan A | D76: -189936 | E76: 0.73
B77: Options forfeited/cancelled — Plan B | D77: -955266 | E77: 3.77
B78: Balance as of January 31, 2014 | D78: =SUM(D73:D77) -> 18427075 | E78: 3.65 | F78: 8.45 | G78: 191809
B79: Vested & expected to vest at period close | D79: 17863613 | E79: 3.62 | F79: 8.44 | G79: 186436
B80: Exercisable at period close | D80: 5438985 | E80: 1.57 | F80: 7.49 | G80: 67947

Sheet Valuation
A2: Discounted Cash Flow Valuation
B4: Projected free cash flow | C4: Reported history | F4: Projected periods
B5: (USD millions, except per-share figures) | C5: 40908 | D5: =EOMONTH(C5,13) -> 41305 | E5: =EOMONTH(D5,12) -> 41670 | F5: =EOMONTH(E5,12) -> 42035 | G5: =EOMONTH(F5,12) -> 42400 | H5: =EOMONTH(G5,12) -> 42766 | I5: =EOMONTH(H5,12) -> 43131 | J5: =EOMONTH(I5,12) -> 43496
B7: Operating income (EBIT) | C7: ='P&L'!C84 -> -46882 | D7: ='P&L'!D84 -> -99289 | E7: ='P&L'!E84 -> -162355 | F7: ='P&L'!F84 -> -254959.62 | G7: ='P&L'!G84 -> -501887.36 | H7: ='P&L'!H84 -> -685231.35 | I7: ='P&L'!I84 -> -665856.92 | J7: ='P&L'!J84 -> -1076371
B9: Unlevered free cash flow
B10: EBIT after tax | C10: =C7*(1-'P&L'!C119) -> -46882 | D10: =D7*(1-'P&L'!D119) -> -99289 | E10: =E7*(1-'P&L'!E119) -> -159947.76 | F10: =IF(F7>0,IF(F7<E16,F7,F7-(F7-E16)*'P&L'!F119),F7) -> -254959.62 | G10: =IF(G7>0,IF(G7<F16,G7,G7-(G7-F16)*'P&L'!G119),G7) -> -501887.36 | H10: =IF(H7>0,IF(H7<G16,H7,H7-(H7-G16)*'P&L'!H119),H7) -> -685231.35 | I10: =IF(I7>0,IF(I7<H16,I7,I7-(I7-H16)*'P&L'!I119),I7) -> -665856.92 | J10: =IF(J7>0,IF(J7<I16,J7,J7-(J7-I16)*'P&L'!J119),J7) -> -1076371
B11: Add: depreciation & amortization | C11: ='BS-CF-WC'!C59 -> 3338 | D11: ='BS-CF-WC'!D59 -> 8616 | E11: ='BS-CF-WC'!E59 -> 15964 | F11: ='BS-CF-WC'!F59 -> 29293.435 | G11: ='BS-CF-WC'!G59 -> 36381.221 | H11: ='BS-CF-WC'!H59 -> 51662.723 | I11: ='BS-CF-WC'!I59 -> 84319.298 | J11: ='BS-CF-WC'!J59 -> 84319.298
B12: Less: capital spend | C12: ='BS-CF-WC'!C78+'BS-CF-WC'!C80 -> -15866 | D12: ='BS-CF-WC'!D78+'BS-CF-WC'!D80 -> -18533 | E12: ='BS-CF-WC'!E78+'BS-CF-WC'!E80 -> -32721 | F12: ='BS-CF-WC'!F78+'BS-CF-WC'!F80 -> -13577.728 | G12: ='BS-CF-WC'!G78+'BS-CF-WC'!G80 -> -24412.747 | H12: ='BS-CF-WC'!H78+'BS-CF-WC'!H80 -> -56922.564 | I12: ='BS-CF-WC'!I78+'BS-CF-WC'!I80 -> -111520.28 | J12: ='BS-CF-WC'!J78+'BS-CF-WC'!J80 -> -179071.73
B13: Add: working-capital movement | E13: ='BS-CF-WC'!E124 -> 0 | F13: ='BS-CF-WC'!F124 -> 0 | G13: ='BS-CF-WC'!G124 -> 0 | H13: ='BS-CF-WC'!H124 -> 0 | I13: ='BS-CF-WC'!I124 -> 0 | J13: ='BS-CF-WC'!J124 -> 0
B14: Unlevered FCF | C14: =SUM(C10:C13) -> -59410 | D14: =SUM(D10:D13) -> -109206 | E14: =SUM(E10:E13) -> -176704.76 | F14: =SUM(F10:F13) -> -239243.91 | G14: =SUM(G10:G13) -> -489918.89 | H14: =SUM(H10:H13) -> -690491.19 | I14: =SUM(I10:I13) -> -693057.91 | J14: =SUM(J10:J13) -> -1171123.4
B16: Loss carryforwards | E16: 251543 | F16: =IF(F7<0,E16-F7,IF(E16>0,E16-F7,0)) -> 506502.62 | G16: =IF(G7<0,F16-G7,IF(F16>0,F16-G7,0)) -> 1008390 | H16: =IF(H7<0,G16-H7,IF(G16>0,G16-H7,0)) -> 1693621.3 | I16: =IF(I7<0,H16-I7,IF(H16>0,H16-I7,0)) -> 2359478.3 | J16: =IF(J7<0,I16-J7,IF(I16>0,I16-J7,0)) -> 3435849.2
B18: Discount rate (WACC) | C18: 0.137179
B19: Perpetual growth rate | C19: 0.042337
B21: Unlevered FCF over explicit horizon (2015P-2019P)
C22: =C5 -> 40908 | D22: =D5 -> 41305 | E22: =E5 -> 41670 | F22: =F5 -> 42035 | G22: =G5 -> 42400 | H22: =H5 -> 42766 | I22: =I5 -> 43131 | J22: =J5 -> 43496
B23: Cash flow stream | F23: =F14 -> -239243.91 | G23: =G14 -> -489918.89 | H23: =H14 -> -690491.19 | I23: =I14 -> -693057.91 | J23: =J14 -> -1171123.4
B24: PV of explicit horizon | C24: {=NPV(C18,F23:J23)} -> -2089031.6
B27: Continuing value at perpetual growth (2019) | C27: =C5 -> 40908 | D27: =D5 -> 41305 | E27: =E5 -> 41670 | F27: =F5 -> 42035 | G27: =G5 -> 42400 | H27: =H5 -> 42766 | I27: =I5 -> 43131 | J27: =J5 -> 43496
B28: Continuing value as of 2019 | F28: 0 | G28: 0 | H28: 0 | I28: 0 | J28: =J14*(1+C19)/(C18-C19) -> -12870936
B29: PV of continuing value | C29: {=NPV(C18,F28:J28)} -> -6768087.5
B31: DCF valuation summary
B33: Valuation date | C33: 2014
B34: PV of explicit horizon | C34: =C24 -> -2089031.6 | D34: =C34/$C$36 -> 0.23585904
B35: PV of continuing value | C35: =C29 -> -6768087.5 | D35: =C35/$C$36 -> 0.76414096
B36: Total firm value | C36: =SUM(C34:C35) -> -8857119
B37: Net borrowings | C37: ='Debt-Capex-Amort'!E23-'BS-CF-WC'!E8 -> -72984
B38: Equity value | C38: =C36-C37 -> -8784135
B39: Option value | C39: ='Equity-Shares'!B54 -> 297089.25
B40: Adjusted equity value | C40: =C38-C39 -> -9081224.3
B41: Value per share | C41: =C40/('Equity-Shares'!C67/10^3) -> -99.291022 | D41: not meaningful — unlevered FCF is negative
D43: Sensitivity Grid
E44: WACC
D45: =C41 -> -99.291022 | E45: 0.12 | F45: 0.14 | G45: 0.15 | H45: 0.2 | I45: 0.25
C46: perpetual growth | D46: 0.1 | E46: -118.65164 | F46: -61.186401 | G46: -49.663982 | H46: -26.494771 | I46: -18.66135
D47: 0.08 | E47: -65.283808 | F47: -44.613025 | G47: -38.689545 | H47: -23.794947 | I47: -17.582251
D48: 0.06 | E48: -47.494531 | F48: -36.326337 | G48: -32.592636 | H48: -21.866501 | I48: -16.730331
D49: 0.05 | E49: -42.41188 | F49: -33.564107 | G49: -30.458718 | H49: -21.095123 | I49: -16.368264
D50: 0.03 | E50: -35.635013 | F50: -29.546319 | G50: -27.25784 | H50: -19.824618 | I50: -15.742877
D51: 0.01 | E51: -31.322461 | F51: -26.764773 | G51: -24.971499 | H51: -18.821587 | I51: -15.221722
A54: Comparable Companies
I55: Valuation multiples | P55: Operating KPIs
I56: EV / Revenue | L56: Price / FCF | N56: EV / EBITDA | P56: Total Revenue | Q56: Revenue growth % | T56: Margin % | Y56: Gross % | AE56: Revenue | AJ56: Gross margin | AL56: Free cash flow | AO56: Operating cash earnings (EBITDA) | AR56: Gross
B57: Company | C57: Ticker | E57: Share price | F57: Market cap | G57: Enterprise value | I57: 2014 | J57: 2015 | L57: 2014 | N57: 2014 | P57: 2013 | Q57: '13-'14 | R57: 14-'15 | T57: Gross | U57: GTM % | V57: Eng % | W57: Free cash flow | Y57: Net retention | AE57: 2012 | AF57: 2013 | AG57: 2014 | AH57: 2015 | AJ57: 2013 | AL57: 2013 | AM57: 2014 | AO57: 2013 | AP57: 2014 | AR57: Net retention | AT57: GTM % | AU57: Eng %
B58: Athenahealth | C58: ATHN | E58: 191.51 | F58: 7022.52 | G58: 6342.87 | I58: =$G58/AG58 -> 7.73483 | J58: =$G58/AH58 -> 6.543291 | L58: =IF(($F58/AM58)<0,"NM",IF(($F58/AM58)>75,"NM",($F58/AM58))) -> NM | N58: =IF(($F58/AP58)<0,"NM",IF(($F58/AP58)>75,"NM",($F58/AP58))) -> 46.779376 | P58: =AF58 -> 515.59 | Q58: =AG58/AF58-1 -> 0.59048857 | R58: =AH58/AG58-1 -> 0.18210087 | T58: =AJ58 -> 0.725689 | U58: =AT58 -> 0.24699778 | V58: =AU58 -> 0.080024439 | W58: =AL58/AF58 -> 0.10452934 | Y58: =IF(ISNUMBER(AR58),AR58,"NA") -> NA | AE58: 458.38 | AF58: 515.59 | AG58: 820.04 | AH58: 969.37 | AJ58: 0.725689 | AL58: 53.894283 | AM58: 59.095574 | AO58: 119.91 | AP58: 150.12 | AT58: 0.24699778 | AU58: 0.080024439
B59: Bazaarvoice | C59: BV | E59: 6.86194 | F59: 709.21 | G59: 636.94 | I59: =$G59/AG59 -> 3.6715472 | J59: =$G59/AH59 -> 3.4455263 | L59: =IF(($F59/AM59)<0,"NM",IF(($F59/AM59)>75,"NM",($F59/AM59))) -> NM | N59: =IF(($F59/AP59)<0,"NM",IF(($F59/AP59)>75,"NM",($F59/AP59))) -> NM | P59: =AF59 -> 168.64 | Q59: =AG59/AF59-1 -> 0.02870019 | R59: =AH59/AG59-1 -> 0.06559834 | T59: =AJ59 -> 0.67815 | U59: =AT59 -> 0.46968604 | V59: =AU59 -> 0.21335337 | W59: =AL59/AF59 -> -0.27711069 | Y59: =IF(ISNUMBER(AR59),AR59,"NA") -> 1.005675 | AE59: 135.2 | AF59: 168.64 | AG59: 173.48 | AH59: 184.86 | AJ59: 0.67815 | AL59: -46.731947 | AM59: -16.050426 | AO59: -18.102556 | AP59: -12.798149 | AR59: 1.005675 | AT59: 0.46968604 | AU59: 0.21335337
B60: Benefitfocus | C60: BNFT | E60: 49.562414 | F60: 1488.4 | G60: 1698.96 | I60: =$G60/AG60 -> 14.4114 | J60: =$G60/AH60 -> 11.282773 | L60: =IF(($F60/AM60)<0,"NM",IF(($F60/AM60)>75,"NM",($F60/AM60))) -> NM | N60: =IF(($F60/AP60)<0,"NM",IF(($F60/AP60)>75,"NM",($F60/AP60))) -> NM | P60: =AF60 -> 100.67 | Q60: =AG60/AF60-1 -> 0.17105394 | R60: =AH60/AG60-1 -> 0.27729239 | T60: =AJ60 -> 0.367926 | U60: =AT60 -> 0.34583247 | V60: =AU60 -> 0.13683798 | W60: =AL60/AF60 -> -0.08274776 | Y60: =IF(ISNUMBER(AR60),AR60,"NA") -> NA | AE60: 90.705054 | AF60: 100.67 | AG60: 117.89 | AH60: 150.58 | AJ60: 0.367926 | AL60: -8.330217 | AM60: -21.041456 | AO60: -17.297502 | AP60: -26.258278 | AT60: 0.34583247 | AU60: 0.13683798
B61: BroadSoft | C61: BSFT | E61: 25.702065 | F61: 815.34 | G61: 722.42 | I61: =$G61/AG61 -> 3.780918 | J61: =$G61/AH61 -> 3.0070763 | L61: =IF(($F61/AM61)<0,"NM",IF(($F61/AM61)>75,"NM",($F61/AM61))) -> 17.074368 | N61: =IF(($F61/AP61)<0,"NM",IF(($F61/AP61)>75,"NM",($F61/AP61))) -> 13.037501 | P61: =AF61 -> 146.71 | Q61: =AG61/AF61-1 -> 0.30236521 | R61: =AH61/AG61-1 -> 0.25734024 | T61: =AJ61 -> 0.960067 | U61: =AT61 -> 1.1529343 | V61: =AU61 -> 0.21947077 | W61: =AL61/AF61 -> 0.20898301 | Y61: =IF(ISNUMBER(AR61),AR61,"NA") -> NA | AE61: 134.6 | AF61: 146.71 | AG61: 191.07 | AH61: 240.24 | AJ61: 0.960067 | AL61: 30.659897 | AM61: 47.752281 | AO61: 40.668679 | AP61: 62.538057 | AT61: 1.1529343 | AU61: 0.21947077
B62: Concur Technologies | C62: CNQR | E62: 107.37 | F62: 7112.48 | G62: 6470.44 | I62: =$G62/AG62 -> 8.5382281 | J62: =$G62/AH62 -> 8.3450784 | L62: =IF(($F62/AM62)<0,"NM",IF(($F62/AM62)>75,"NM",($F62/AM62))) -> NM | N62: =IF(($F62/AP62)<0,"NM",IF(($F62/AP62)>75,"NM",($F62/AP62))) -> 52.420991 | P62: =AF62 -> 661.13 | Q62: =AG62/AF62-1 -> 0.1462496 | R62: =AH62/AG62-1 -> 0.023145338 | T62: =AJ62 -> 0.69103 | U62: =AT62 -> 0.41125822 | V62: =AU62 -> 0.10448685 | W62: =AL62/AF62 -> 0.042784912 | Y62: =IF(ISNUMBER(AR62),AR62,"NA") -> 1.027998 | AE62: 385.1 | AF62: 661.13 | AG62: 757.82 | AH62: 775.36 | AJ62: 0.69103 | AL62: 28.286389 | AM62: 22.199737 | AO62: 91.47 | AP62: 135.68 | AR62: 1.027998 | AT62: 0.41125822 | AU62: 0.10448685
B63: Constant Contact | C63: CTCT | E63: 23.385084 | F63: 904.14 | G63: 798.32 | I63: =$G63/AG63 -> 2.5325804 | J63: =$G63/AH63 -> 1.8980504 | L63: =IF(($F63/AM63)<0,"NM",IF(($F63/AM63)>75,"NM",($F63/AM63))) -> 26.579321 | N63: =IF(($F63/AP63)<0,"NM",IF(($F63/AP63)>75,"NM",($F63/AP63))) -> 15.767549 | P63: =AF63 -> 237.82 | Q63: =AG63/AF63-1 -> 0.32545623 | R63: =AH63/AG63-1 -> 0.3343062 | T63: =AJ63 -> 0.746095 | U63: =AT63 -> 0.41442928 | V63: =AU63 -> 0.15382266 | W63: =AL63/AF63 -> 0.10190781 | Y63: =IF(ISNUMBER(AR63),AR63,"NA") -> 0.672066 | AE63: 220.22 | AF63: 237.82 | AG63: 315.22 | AH63: 420.6 | AJ63: 0.746095 | AL63: 24.235716 | AM63: 34.01667 | AO63: 51.588766 | AP63: 57.341823 | AR63: 0.672066 | AT63: 0.41442928 | AU63: 0.15382266
B64: Cornerstone OnDemand | C64: CSOD | E64: 65.73405 | F64: 3278.42 | G64: 3580.31 | I64: =$G64/AG64 -> 12.302203 | J64: =$G64/AH64 -> 10.028318 | L64: =IF(($F64/AM64)<0,"NM",IF(($F64/AM64)>75,"NM",($F64/AM64))) -> NM | N64: =IF(($F64/AP64)<0,"NM",IF(($F64/AP64)>75,"NM",($F64/AP64))) -> NM | P64: =AF64 -> 168.55 | Q64: =AG64/AF64-1 -> 0.72666864 | R64: =AH64/AG64-1 -> 0.22674638 | T64: =AJ64 -> 0.62515 | U64: =AT64 -> 0.62333565 | V64: =AU64 -> 0.12624455 | W64: =AL64/AF64 -> 0.051493658 | Y64: =IF(ISNUMBER(AR64),AR64,"NA") -> 1.099656 | AE64: 112.35 | AF64: 168.55 | AG64: 291.03 | AH64: 357.02 | AJ64: 0.62515 | AL64: 8.679256 | AM64: 26.063125 | AO64: 1.13798 | AP64: 13.106855 | AR64: 1.099656 | AT64: 0.62333565 | AU64: 0.12624455
B65: Cvent | C65: CVT | E65: 43.535358 | F65: 1916.99 | G65: 1883.75 | I65: =$G65/AG65 -> 13.008425 | J65: =$G65/AH65 -> 13.067985 | L65: NA | N65: NA | P65: =AF65 -> 124.11 | Q65: =AG65/AF65-1 -> 0.16678753 | R65: =AH65/AG65-1 -> -0.0045576963 | T65: =AJ65 -> 0.673644 | U65: =AT65 -> 0.42987038 | V65: =AU65 -> 0.091106213 | W65: NA | Y65: =IF(ISNUMBER(AR65),AR65,"NA") -> NA | AE65: 69.116685 | AF65: 124.11 | AG65: 144.81 | AH65: 144.15 | AJ65: 0.673644 | AL65: 18.416844 | AM65: 16.755659 | AO65: 11.075544 | AP65: 12.404668 | AT65: 0.42987038 | AU65: 0.091106213
B66: Dealertrack Technologies | C66: TRAK | E66: 54.165939 | F66: 2692.68 | G66: 3244.47 | I66: =$G66/AG66 -> 6.634908 | J66: =$G66/AH66 -> 4.4993344 | L66: =IF(($F66/AM66)<0,"NM",IF(($F66/AM66)>75,"NM",($F66/AM66))) -> 38.157069 | N66: =IF(($F66/AP66)<0,"NM",IF(($F66/AP66)>75,"NM",($F66/AP66))) -> 23.862815 | P66: =AF66 -> 569.61 | Q66: =AG66/AF66-1 -> -0.14151788 | R66: =AH66/AG66-1 -> 0.47464213 | T66: =AJ66 -> 0.375517 | U66: =AT66 -> 0.35332963 | V66: =AU66 -> 0.03016931 | W66: =AL66/AF66 -> 0.10814465 | Y66: =IF(ISNUMBER(AR66),AR66,"NA") -> 0.704759 | AE66: 368.09 | AF66: 569.61 | AG66: 489 | AH66: 721.1 | AJ66: 0.375517 | AL66: 61.600272 | AM66: 70.568313 | AO66: 128.43 | AP66: 112.84 | AR66: 0.704759 | AT66: 0.35332963 | AU66: 0.03016931
B67: Demandware | C67: DWRE | E67: 79.87652 | F67: 3208.45 | G67: 2895.58 | I67: =$G67/AG67 -> 17.636618 | J67: =$G67/AH67 -> 15.568471 | L67: =IF(($F67/AM67)<0,"NM",IF(($F67/AM67)>75,"NM",($F67/AM67))) -> NM | N67: =IF(($F67/AP67)<0,"NM",IF(($F67/AP67)>75,"NM",($F67/AP67))) -> NM | P67: =AF67 -> 113.47 | Q67: =AG67/AF67-1 -> 0.44690226 | R67: =AH67/AG67-1 -> 0.132842 | T67: =AJ67 -> 0.816647 | U67: =AT67 -> 0.4214407 | V67: =AU67 -> 0.18980812 | W67: =AL67/AF67 -> 0.014656755 | Y67: =IF(ISNUMBER(AR67),AR67,"NA") -> 0.992631 | AE67: 74.643735 | AF67: 113.47 | AG67: 164.18 | AH67: 185.99 | AJ67: 0.816647 | AL67: 1.663102 | AM67: -0.519256 | AO67: -2.263854 | AP67: 5.618687 | AR67: 0.992631 | AT67: 0.4214407 | AU67: 0.18980812
B68: E2open | C68: EOPN | E68: 22.0509 | F68: 869.35 | G68: 821.82 | I68: =$G68/AG68 -> 4.2849992 | J68: =$G68/AH68 -> 2.6316767 | L68: =IF(($F68/AM68)<0,"NM",IF(($F68/AM68)>75,"NM",($F68/AM68))) -> 36.336638 | N68: =IF(($F68/AP68)<0,"NM",IF(($F68/AP68)>75,"NM",($F68/AP68))) -> 11.681791 | P68: =AF68 -> 173.29 | Q68: =AG68/AF68-1 -> 0.10675746 | R68: =AH68/AG68-1 -> 0.62823922 | T68: =AJ68 -> 0.832942 | U68: =AT68 -> 0.32277503 | V68: =AU68 -> 0.05789676 | W68: =AL68/AF68 -> 0.11075351 | Y68: =IF(ISNUMBER(AR68),AR68,"NA") -> 0.982641 | AE68: 129.97 | AF68: 173.29 | AG68: 191.79 | AH68: 312.28 | AJ68: 0.832942 | AL68: 19.192476 | AM68: 23.924888 | AO68: 58.485443 | AP68: 74.419241 | AR68: 0.982641 | AT68: 0.32277503 | AU68: 0.05789676
B69: Fleetmatics Group | C69: FLTX | E69: 35.843139 | F69: 1240.3 | G69: 1496.37 | I69: =$G69/AG69 -> 8.0354957 | J69: =$G69/AH69 -> 6.0347233 | L69: =IF(($F69/AM69)<0,"NM",IF(($F69/AM69)>75,"NM",($F69/AM69))) -> 44.152713 | N69: =IF(($F69/AP69)<0,"NM",IF(($F69/AP69)>75,"NM",($F69/AP69))) -> 16.612139 | P69: =AF69 -> 208.56 | Q69: =AG69/AF69-1 -> -0.10711546 | R69: =AH69/AG69-1 -> 0.33154334 | T69: =AJ69 -> 0.711538 | U69: =AT69 -> 0.32277503 | V69: =AU69 -> 0.05789676 | W69: =AL69/AF69 -> 0.087826314 | Y69: =IF(ISNUMBER(AR69),AR69,"NA") -> NA | AE69: 149.31 | AF69: 208.56 | AG69: 186.22 | AH69: 247.96 | AJ69: 0.711538 | AL69: 18.317056 | AM69: 28.091139 | AO69: 44.906149 | AP69: 74.66227 | AT69: 0.32277503 | AU69: 0.05789676
B70: IntraLinks | C70: IL | E70: 10.998462 | F70: 685.94 | G70: 644.72 | I70: =$G70/AG70 -> 2.4469409 | J70: =$G70/AH70 -> 3.0106 | L70: =IF(($F70/AM70)<0,"NM",IF(($F70/AM70)>75,"NM",($F70/AM70))) -> 16.427918 | N70: =IF(($F70/AP70)<0,"NM",IF(($F70/AP70)>75,"NM",($F70/AP70))) -> 15.649732 | P70: =AF70 -> 246.08 | Q70: =AG70/AF70-1 -> 0.070708713 | R70: =AH70/AG70-1 -> -0.18722484 | T70: =AJ70 -> 0.612293 | U70: =AT70 -> 0.62399904 | V70: =AU70 -> 0.097347543 | W70: =AL70/AF70 -> 0.11145638 | Y70: =IF(ISNUMBER(AR70),AR70,"NA") -> 0.71855 | AE70: 216.24 | AF70: 246.08 | AG70: 263.48 | AH70: 214.15 | AJ70: 0.612293 | AL70: 27.427186 | AM70: 41.75453 | AO70: 40.309789 | AP70: 43.830783 | AR70: 0.71855 | AT70: 0.62399904 | AU70: 0.097347543
B71: Jive Software | C71: JIVE | E71: 8.614422 | F71: 815.13 | G71: 577.75 | I71: =$G71/AG71 -> 3.1409699 | J71: =$G71/AH71 -> 2.3495323 | L71: =IF(($F71/AM71)<0,"NM",IF(($F71/AM71)>75,"NM",($F71/AM71))) -> NM | N71: =IF(($F71/AP71)<0,"NM",IF(($F71/AP71)>75,"NM",($F71/AP71))) -> NM | P71: =AF71 -> 131.08 | Q71: =AG71/AF71-1 -> 0.40326518 | R71: =AH71/AG71-1 -> 0.33684897 | T71: =AJ71 -> 0.789966 | U71: =AT71 -> 0.53048405 | V71: =AU71 -> 0.34478208 | W71: =AL71/AF71 -> -0.077956233 | Y71: =IF(ISNUMBER(AR71),AR71,"NA") -> 0.882449 | AE71: 126.14 | AF71: 131.08 | AG71: 183.94 | AH71: 245.9 | AJ71: 0.789966 | AL71: -10.218503 | AM71: 10.289377 | AO71: -22.115521 | AP71: -11.19776 | AR71: 0.882449 | AT71: 0.53048405 | AU71: 0.34478208
B72: LifeLock | C72: LOCK | E72: 18.884289 | F72: 1899.57 | G72: 1879.85 | I72: =$G72/AG72 -> 5.1191384 | J72: =$G72/AH72 -> 3.8560235 | L72: =IF(($F72/AM72)<0,"NM",IF(($F72/AM72)>75,"NM",($F72/AM72))) -> 31.776412 | N72: =IF(($F72/AP72)<0,"NM",IF(($F72/AP72)>75,"NM",($F72/AP72))) -> 37.564084 | P72: =AF72 -> 357.28 | Q72: =AG72/AF72-1 -> 0.027821317 | R72: =AH72/AG72-1 -> 0.3275693 | T72: =AJ72 -> 0.827311 | U72: =AT72 -> 0.44481022 | V72: =AU72 -> 0.10687412 | W72: =AL72/AF72 -> 0.16290032 | Y72: =IF(ISNUMBER(AR72),AR72,"NA") -> NA | AE72: 304.55 | AF72: 357.28 | AG72: 367.22 | AH72: 487.51 | AJ72: 0.827311 | AL72: 58.201027 | AM72: 59.779247 | AO72: 35.795049 | AP72: 50.568782 | AT72: 0.44481022 | AU72: 0.10687412
B73: LinkedIn | C73: LNKD | E73: 225.74 | F73: 27680.19 | G73: 21158.83 | I73: =$G73/AG73 -> 11.655574 | J73: =$G73/AH73 -> 7.7743227 | L73: =IF(($F73/AM73)<0,"NM",IF(($F73/AM73)>75,"NM",($F73/AM73))) -> NM | N73: =IF(($F73/AP73)<0,"NM",IF(($F73/AP73)>75,"NM",($F73/AP73))) -> 40.501273 | P73: =AF73 -> 1596.95 | Q73: =AG73/AF73-1 -> 0.13675444 | R73: =AH73/AG73-1 -> 0.49923981 | T73: =AJ73 -> 0.704891 | U73: =AT73 -> 0.33415715 | V73: =AU73 -> 0.26450336 | W73: =AL73/AF73 -> 0.12879552 | Y73: =IF(ISNUMBER(AR73),AR73,"NA") -> NA | AE73: 788.51 | AF73: 1596.95 | AG73: 1815.34 | AH73: 2721.63 | AJ73: 0.704891 | AL73: 205.68 | AM73: 279.23 | AO73: 302.27 | AP73: 683.44 | AT73: 0.33415715 | AU73: 0.26450336
B74: LivePerson | C74: LPSN | E74: 11.32423 | F74: 663.73 | G74: 604.21 | I74: =$G74/AG74 -> 3.6070085 | J74: =$G74/AH74 -> 3.1402214 | L74: =IF(($F74/AM74)<0,"NM",IF(($F74/AM74)>75,"NM",($F74/AM74))) -> NM | N74: =IF(($F74/AP74)<0,"NM",IF(($F74/AP74)>75,"NM",($F74/AP74))) -> 26.070322 | P74: =AF74 -> 154.62 | Q74: =AG74/AF74-1 -> 0.083365671 | R74: =AH74/AG74-1 -> 0.14864784 | T74: =AJ74 -> 0.83272 | U74: =AT74 -> 0.31507093 | V74: =AU74 -> 0.1909103 | W74: =AL74/AF74 -> 0.04171428 | Y74: =IF(ISNUMBER(AR74),AR74,"NA") -> 0.839091 | AE74: 156.8 | AF74: 154.62 | AG74: 167.51 | AH74: 192.41 | AJ74: 0.83272 | AL74: 6.449862 | AM74: 7.534684 | AO74: 20.271028 | AP74: 25.459218 | AR74: 0.839091 | AT74: 0.31507093 | AU74: 0.1909103
B75: LogMeIn | C75: LOGM | E75: 52.443236 | F75: 1359.2 | G75: 915.66 | I75: =$G75/AG75 -> 5.0041535 | J75: =$G75/AH75 -> 3.4298236 | L75: =IF(($F75/AM75)<0,"NM",IF(($F75/AM75)>75,"NM",($F75/AM75))) -> 40.768565 | N75: =IF(($F75/AP75)<0,"NM",IF(($F75/AP75)>75,"NM",($F75/AP75))) -> 36.944903 | P75: =AF75 -> 178.2 | Q75: =AG75/AF75-1 -> 0.026823793 | R75: =AH75/AG75-1 -> 0.45901191 | T75: =AJ75 -> 1.034575 | U75: =AT75 -> 0.50418789 | V75: =AU75 -> 0.17906824 | W75: =AL75/AF75 -> 0.1029585 | Y75: =IF(ISNUMBER(AR75),AR75,"NA") -> 0.80163 | AE75: 122.64 | AF75: 178.2 | AG75: 182.98 | AH75: 266.97 | AJ75: 1.034575 | AL75: 18.347204 | AM75: 33.339412 | AO75: 26.474209 | AP75: 36.789919 | AR75: 0.80163 | AT75: 0.50418789 | AU75: 0.17906824
B76: Marin Software | C76: MRIN | E76: 10.914718 | F76: 431.59 | G76: 221.28 | I76: =$G76/AG76 -> 2.5400744 | J76: =$G76/AH76 -> 1.9357886 | L76: =IF(($F76/AM76)<0,"NM",IF(($F76/AM76)>75,"NM",($F76/AM76))) -> NM | N76: =IF(($F76/AP76)<0,"NM",IF(($F76/AP76)>75,"NM",($F76/AP76))) -> NM | P76: =AF76 -> 88.50695 | Q76: =AG76/AF76-1 -> -0.015720686 | R76: =AH76/AG76-1 -> 0.31216513 | T76: =AJ76 -> 0.659475 | U76: =AT76 -> 0.54791967 | V76: =AU76 -> 0.23530004 | W76: =AL76/AF76 -> -0.29701026 | Y76: =IF(ISNUMBER(AR76),AR76,"NA") -> 0.707238 | AE76: 62.997251 | AF76: 88.50695 | AG76: 87.11556 | AH76: 114.31 | AJ76: 0.659475 | AL76: -26.287472 | AM76: -29.663128 | AO76: -28.703171 | AP76: -26.380951 | AR76: 0.707238 | AT76: 0.54791967 | AU76: 0.23530004
B77: Marketo | C77: MKTO | E77: 30.02437 | F77: 1949.21 | G77: 1399.07 | I77: =$G77/AG77 -> 11.218587 | J77: =$G77/AH77 -> 7.9542328 | L77: =IF(($F77/AM77)<0,"NM",IF(($F77/AM77)>75,"NM",($F77/AM77))) -> NM | N77: =IF(($F77/AP77)<0,"NM",IF(($F77/AP77)>75,"NM",($F77/AP77))) -> NM | P77: =AF77 -> 111.07914 | Q77: =AG77/AF77-1 -> 0.12271309 | R77: =AH77/AG77-1 -> 0.41039211 | T77: =AJ77 -> 0.583376 | U77: =AT77 -> 0.64670536 | V77: =AU77 -> 0.32182904 | W77: =AL77/AF77 -> -0.23637374 | Y77: =IF(ISNUMBER(AR77),AR77,"NA") -> 0.812815 | AE77: 62.905684 | AF77: 111.07914 | AG77: 124.71 | AH77: 175.89 | AJ77: 0.583376 | AL77: -26.256191 | AM77: -16.095707 | AO77: -31.357564 | AP77: -28.174705 | AR77: 0.812815 | AT77: 0.64670536 | AU77: 0.32182904
B78: Medidata Solutions | C78: MDSO | E78: 63.195285 | F78: 3786.32 | G78: 3742.7 | I78: =$G78/AG78 -> 10.237144 | J78: =$G78/AH78 -> 8.0560937 | L78: NM | N78: =IF(($F78/AP78)<0,"NM",IF(($F78/AP78)>75,"NM",($F78/AP78))) -> 39.62451 | P78: =AF78 -> 298.42 | Q78: =AG78/AF78-1 -> 0.22511896 | R78: =AH78/AG78-1 -> 0.27073304 | T78: =AJ78 -> 0.600325 | U78: =AT78 -> 0.21867028 | V78: =AU78 -> 0.19361841 | W78: =AL78/AF78 -> 0.12448649 | Y78: =IF(ISNUMBER(AR78),AR78,"NA") -> NA | AE78: 222.12 | AF78: 298.42 | AG78: 365.6 | AH78: 464.58 | AJ78: 0.600325 | AL78: 37.149258 | AM78: 56.188284 | AO78: 67.601476 | AP78: 95.554998 | AT78: 0.21867028 | AU78: 0.19361841
B79: NetSuite | C79: N | E79: 101.58 | F79: 8812.91 | G79: 9602.67 | I79: =$G79/AG79 -> 16.134331 | J79: =$G79/AH79 -> 12.004388 | L79: =IF(($F79/AM79)<0,"NM",IF(($F79/AM79)>75,"NM",($F79/AM79))) -> NM | N79: =IF(($F79/AP79)<0,"NM",IF(($F79/AP79)>75,"NM",($F79/AP79))) -> NM | P79: =AF79 -> 378.95 | Q79: =AG79/AF79-1 -> 0.57057659 | R79: =AH79/AG79-1 -> 0.34403616 | T79: =AJ79 -> 0.802956 | U79: =AT79 -> 0.49995952 | V79: =AU79 -> 0.17077309 | W79: =AL79/AF79 -> 0.10440882 | Y79: =IF(ISNUMBER(AR79),AR79,"NA") -> 0.760819 | AE79: 280.6 | AF79: 378.95 | AG79: 595.17 | AH79: 799.93 | AJ79: 0.802956 | AL79: 39.565723 | AM79: 56.606478 | AO79: 48.428538 | AP79: 47.329384 | AR79: 0.760819 | AT79: 0.49995952 | AU79: 0.17077309
B80: Proofpoint | C80: PFPT | E80: 50.271372 | F80: 1590.13 | G80: 1637.77 | I80: =$G80/AG80 -> 9.1296616 | J80: =$G80/AH80 -> 7.8175179 | L80: =IF(($F80/AM80)<0,"NM",IF(($F80/AM80)>75,"NM",($F80/AM80))) -> NM | N80: =IF(($F80/AP80)<0,"NM",IF(($F80/AP80)>75,"NM",($F80/AP80))) -> NM | P80: =AF80 -> 143.63 | Q80: =AG80/AF80-1 -> 0.24897306 | R80: =AH80/AG80-1 -> 0.16784659 | T80: =AJ80 -> 0.719467 | U80: =AT80 -> 0.51978927 | V80: =AU80 -> 0.21926713 | W80: =AL80/AF80 -> 0.039435828 | Y80: =IF(ISNUMBER(AR80),AR80,"NA") -> 0.755368 | AE80: 119.98 | AF80: 143.63 | AG80: 179.39 | AH80: 209.5 | AJ80: 0.719467 | AL80: 5.664168 | AM80: 12.645133 | AO80: -6.607231 | AP80: -2.818268 | AR80: 0.755368 | AT80: 0.51978927 | AU80: 0.21926713
B81: Qualys | C81: QLYS | E81: 27.278102 | F81: 1023.44 | G81: 1068.07 | I81: =$G81/AG81 -> 7.1596058 | J81: =$G81/AH81 -> 6.4136792 | L81: =IF(($F81/AM81)<0,"NM",IF(($F81/AM81)>75,"NM",($F81/AM81))) -> 50.917646 | N81: =IF(($F81/AP81)<0,"NM",IF(($F81/AP81)>75,"NM",($F81/AP81))) -> 50.128655 | P81: =AF81 -> 120.69 | Q81: =AG81/AF81-1 -> 0.23605933 | R81: =AH81/AG81-1 -> 0.11630245 | T81: =AJ81 -> 0.683763 | U81: =AT81 -> 0.41250273 | V81: =AU81 -> 0.22090352 | W81: =AL81/AF81 -> 0.10086145 | Y81: =IF(ISNUMBER(AR81),AR81,"NA") -> NA | AE81: 86.667174 | AF81: 120.69 | AG81: 149.18 | AH81: 166.53 | AJ81: 0.683763 | AL81: 12.172968 | AM81: 20.099908 | AO81: 20.999361 | AP81: 20.416267 | AT81: 0.41250273 | AU81: 0.22090352
B82: Rally Software | C82: RALY | E82: 21.232345 | F82: 426.29 | G82: 295.35 | I82: =$G82/AG82 -> 2.9578389 | J82: =$G82/AH82 -> 2.9312227 | L82: =IF(($F82/AM82)<0,"NM",IF(($F82/AM82)>75,"NM",($F82/AM82))) -> NM | N82: =IF(($F82/AP82)<0,"NM",IF(($F82/AP82)>75,"NM",($F82/AP82))) -> NM | P82: =AF82 -> 66.784633 | Q82: =AG82/AF82-1 -> 0.49515395 | R82: =AH82/AG82-1 -> 0.00908024 | T82: =AJ82 -> 0.705347 | U82: =AT82 -> 0.51796081 | V82: =AU82 -> 0.26599937 | W82: =AL82/AF82 -> -0.28905981 | Y82: =IF(ISNUMBER(AR82),AR82,"NA") -> 1.012784 | AE82: 46.746828 | AF82: 66.784633 | AG82: 99.853308 | AH82: 100.76 | AJ82: 0.705347 | AL82: -19.304753 | AM82: -16.982423 | AO82: -14.356285 | AP82: -11.781056 | AR82: 1.012784 | AT82: 0.51796081 | AU82: 0.26599937
B83: RealPage | C83: RP | E83: 18.516262 | F83: 1778.63 | G83: 1405.89 | I83: =$G83/AG83 -> 2.6997926 | J83: =$G83/AH83 -> 2.3431109 | L83: =IF(($F83/AM83)<0,"NM",IF(($F83/AM83)>75,"NM",($F83/AM83))) -> 28.38279 | N83: =IF(($F83/AP83)<0,"NM",IF(($F83/AP83)>75,"NM",($F83/AP83))) -> 14.584912 | P83: =AF83 -> 332.51 | Q83: =AG83/AF83-1 -> 0.56608824 | R83: =AH83/AG83-1 -> 0.15222568 | T83: =AJ83 -> 0.547981 | U83: =AT83 -> 0.23900277 | V83: =AU83 -> 0.14953813 | W83: =AL83/AF83 -> 0.16499536 | Y83: =IF(ISNUMBER(AR83),AR83,"NA") -> NA | AE83: 345.58 | AF83: 332.51 | AG83: 520.74 | AH83: 600.01 | AJ83: 0.547981 | AL83: 54.862606 | AM83: 62.665791 | AO83: 75 | AP83: 121.95 | AR83: NA | AT83: 0.23900277 | AU83: 0.14953813
B84: RingCentral | C84: RNG | E84: 22.643345 | F84: 1759.36 | G84: 1378.82 | I84: =$G84/AG84 -> 7.542779 | J84: =$G84/AH84 -> 5.0356817 | L84: =IF(($F84/AM84)<0,"NM",IF(($F84/AM84)>75,"NM",($F84/AM84))) -> NM | N84: =IF(($F84/AP84)<0,"NM",IF(($F84/AP84)>75,"NM",($F84/AP84))) -> NM | P84: =AF84 -> 128.69 | Q84: =AG84/AF84-1 -> 0.42046779 | R84: =AH84/AG84-1 -> 0.49786652 | T84: =AJ84 -> 0.57653 | U84: =AT84 -> NA | V84: =AU84 -> NA | W84: =AL84/AF84 -> -0.28462505 | Y84: =IF(ISNUMBER(AR84),AR84,"NA") -> NA | AE84: 114.91 | AF84: 128.69 | AG84: 182.8 | AH84: 273.81 | AJ84: 0.57653 | AL84: -36.628398 | AM84: -27.562926 | AO84: -25.260328 | AP84: -19.032978 | AT84: NA | AU84: NA
B85: Salesforce | C85: CRM | E85: 65.602642 | F85: 40969.58 | G85: 40040.33 | I85: =$G85/AG85 -> 9.1523265 | J85: =$G85/AH85 -> 5.5131239 | L85: =IF(($F85/AM85)<0,"NM",IF(($F85/AM85)>75,"NM",($F85/AM85))) -> 53.266739 | N85: =IF(($F85/AP85)<0,"NM",IF(($F85/AP85)>75,"NM",($F85/AP85))) -> 48.71995 | P85: =AF85 -> 4277.26 | Q85: =AG85/AF85-1 -> 0.022823022 | R85: =AH85/AG85-1 -> 0.66009811 | T85: =AJ85 -> 0.695976 | U85: =AT85 -> 0.52917928 | V85: =AU85 -> 0.14080378 | W85: =AL85/AF85 -> 0.10529638 | Y85: =IF(ISNUMBER(AR85),AR85,"NA") -> 0.786303 | AE85: 3443.55 | AF85: 4277.26 | AG85: 4374.88 | AH85: 7262.73 | AJ85: 0.695976 | AL85: 450.38 | AM85: 769.14 | AO85: 759.97 | AP85: 840.92 | AR85: 0.786303 | AT85: 0.52917928 | AU85: 0.14080378
B86: ServiceNow | C86: NOW | E86: 79.061202 | F86: 11763.9 | G86: 9124.42 | I86: =$G86/AG86 -> 12.594614 | J86: =$G86/AH86 -> 8.8000502 | L86: =IF(($F86/AM86)<0,"NM",IF(($F86/AM86)>75,"NM",($F86/AM86))) -> NM | N86: =IF(($F86/AP86)<0,"NM",IF(($F86/AP86)>75,"NM",($F86/AP86))) -> NM | P86: =AF86 -> 358.89 | Q86: =AG86/AF86-1 -> 1.0186408 | R86: =AH86/AG86-1 -> 0.43119798 | T86: =AJ86 -> 0.774283 | U86: =AT86 -> 0.39760045 | V86: =AU86 -> 0.16139131 | W86: =AL86/AF86 -> 0.027547809 | Y86: =IF(ISNUMBER(AR86),AR86,"NA") -> 1.144914 | AE86: 256.37 | AF86: 358.89 | AG86: 724.47 | AH86: 1036.86 | AJ86: 0.774283 | AL86: 9.886633 | AM86: 53.513737 | AO86: 25.33 | AP86: 63.63872 | AR86: 1.144914 | AT86: 0.39760045 | AU86: 0.16139131
B87: SPS Commerce | C87: SPSC | E87: 69.635857 | F87: 1273.36 | G87: 814.36 | I87: =$G87/AG87 -> 5.9594585 | J87: =$G87/AH87 -> 5.1830448 | L87: =IF(($F87/AM87)<0,"NM",IF(($F87/AM87)>75,"NM",($F87/AM87))) -> NM | N87: =IF(($F87/AP87)<0,"NM",IF(($F87/AP87)>75,"NM",($F87/AP87))) -> 70.813772 | P87: =AF87 -> 97.98 | Q87: =AG87/AF87-1 -> 0.39467238 | R87: =AH87/AG87-1 -> 0.14979876 | T87: =AJ87 -> 0.60262 | U87: =AT87 -> NA | V87: =AU87 -> NA | W87: =AL87/AF87 -> 0.11631396 | Y87: =IF(ISNUMBER(AR87),AR87,"NA") -> NA | AE87: 79.540182 | AF87: 97.98 | AG87: 136.65 | AH87: 157.12 | AJ87: 0.60262 | AL87: 11.396442 | AM87: 13.244283 | AO87: 13.822858 | AP87: 17.981813 | AT87: NA | AU87: NA
B88: Textura | C88: TXTR | E88: 26.679441 | F88: 878.92 | G88: 783.23 | I88: =$G88/AG88 -> 14.054759 | J88: =$G88/AH88 -> 7.2387246 | L88: =IF(($F88/AM88)<0,"NM",IF(($F88/AM88)>75,"NM",($F88/AM88))) -> NM | N88: =IF(($F88/AP88)<0,"NM",IF(($F88/AP88)>75,"NM",($F88/AP88))) -> NM | P88: =AF88 -> 43.631211 | Q88: =AG88/AF88-1 -> 0.27722866 | R88: =AH88/AG88-1 -> 0.94160705 | T88: =AJ88 -> 0 | U88: =AT88 -> NA | V88: =AU88 -> NA | W88: =AL88/AF88 -> -0.23131162 | Y88: =IF(ISNUMBER(AR88),AR88,"NA") -> NA | AE88: 21.728974 | AF88: 43.631211 | AG88: 55.727033 | AH88: 108.2 | AJ88: 0 | AL88: -10.092406 | AM88: -4.510688 | AO88: -12.990874 | AP88: -5.564894 | AT88: NA | AU88: NA
B89: The Ultimate Software Group | C89: ULTI | E89: 131.1 | F89: 4520.66 | G89: 3708.82 | I89: =$G89/AG89 -> 6.2505393 | J89: =$G89/AH89 -> 7.4918089 | L89: =IF(($F89/AM89)<0,"NM",IF(($F89/AM89)>75,"NM",($F89/AM89))) -> NM | N89: =IF(($F89/AP89)<0,"NM",IF(($F89/AP89)>75,"NM",($F89/AP89))) -> 46.356235 | P89: =AF89 -> 356.95 | Q89: =AG89/AF89-1 -> 0.66230565 | R89: =AH89/AG89-1 -> -0.16568356 | T89: =AJ89 -> 0.523665 | U89: =AT89 -> 0.21819736 | V89: =AU89 -> 0.18266279 | W89: =AL89/AF89 -> 0.11502133 | Y89: =IF(ISNUMBER(AR89),AR89,"NA") -> 1.10858 | AE89: 293.54 | AF89: 356.95 | AG89: 593.36 | AH89: 495.05 | AJ89: 0.523665 | AL89: 41.056862 | AM89: 45.558434 | AO89: 84.807797 | AP89: 97.52 | AR89: 1.10858 | AT89: 0.21819736 | AU89: 0.18266279
B90: Veeva | C90: VEEV | E90: 38.641983 | F90: 4748.63 | G90: 5060.59 | I90: =$G90/AG90 -> 23.296 | J90: =$G90/AH90 -> 17.785787 | L90: =IF(($F90/AM90)<0,"NM",IF(($F90/AM90)>75,"NM",($F90/AM90))) -> NM | N90: =IF(($F90/AP90)<0,"NM",IF(($F90/AP90)>75,"NM",($F90/AP90))) -> NM | P90: =AF90 -> 205.78 | Q90: =AG90/AF90-1 -> 0.055641948 | R90: =AH90/AG90-1 -> 0.30980988 | T90: =AJ90 -> 0.59021 | U90: =AT90 -> NA | V90: =AU90 -> NA | W90: =AL90/AF90 -> 0.1425784 | Y90: =IF(ISNUMBER(AR90),AR90,"NA") -> NA | AE90: 141.97 | AF90: 205.78 | AG90: 217.23 | AH90: 284.53 | AJ90: 0.59021 | AL90: 29.339783 | AM90: 48.12101 | AO90: 37.098178 | AP90: 55.72883 | AT90: NA | AU90: NA
B91: Vocus | C91: VOCS | E91: 16.077816 | F91: 268.03 | G91: 421.55 | I91: =$G91/AG91 -> 2.3281052 | J91: =$G91/AH91 -> 2.590169 | L91: =IF(($F91/AM91)<0,"NM",IF(($F91/AM91)>75,"NM",($F91/AM91))) -> 46.814818 | N91: =IF(($F91/AP91)<0,"NM",IF(($F91/AP91)>75,"NM",($F91/AP91))) -> 11.983782 | P91: =AF91 -> 207.54 | Q91: =AG91/AF91-1 -> -0.12754168 | R91: =AH91/AG91-1 -> -0.10117634 | T91: =AJ91 -> 0.775051 | U91: =AT91 -> 0.57258612 | V91: =AU91 -> 0.073973677 | W91: =AL91/AF91 -> 0.013746728 | Y91: =IF(ISNUMBER(AR91),AR91,"NA") -> 0.805696 | AE91: 163.07 | AF91: 207.54 | AG91: 181.07 | AH91: 162.75 | AJ91: 0.775051 | AL91: 2.852996 | AM91: 5.725324 | AO91: 25.067197 | AP91: 22.366061 | AR91: 0.805696 | AT91: 0.57258612 | AU91: 0.073973677
B92: Wix | C92: WIX | E92: 28.84624 | F92: 1067.84 | G92: 937.16 | I92: =$G92/AG92 -> 6.9947753 | J92: =$G92/AH92 -> 5.2696806 | L92: =IF(($F92/AM92)<0,"NM",IF(($F92/AM92)>75,"NM",($F92/AM92))) -> NM | N92: =IF(($F92/AP92)<0,"NM",IF(($F92/AP92)>75,"NM",($F92/AP92))) -> NM | P92: =AF92 -> 73.900165 | Q92: =AG92/AF92-1 -> 0.81298648 | R92: =AH92/AG92-1 -> 0.32736229 | T92: =AJ92 -> 0.729967 | U92: =AT92 -> NA | V92: =AU92 -> NA | W92: =AL92/AF92 -> -0.056575963 | Y92: =IF(ISNUMBER(AR92),AR92,"NA") -> NA | AE92: 46.547504 | AF92: 73.900165 | AG92: 133.98 | AH92: 177.84 | AJ92: 0.729967 | AL92: -4.180973 | AM92: -8.849784 | AO92: -19.765259 | AP92: -25.03057 | AT92: NA | AU92: NA
B93: Workday | C93: WDAY | E93: 112.44 | F93: 22301.92 | G93: 22433.3 | I93: =$G93/AG93 -> 32.726411 | J93: =$G93/AH93 -> 22.205911 | L93: =IF(($F93/AM93)<0,"NM",IF(($F93/AM93)>75,"NM",($F93/AM93))) -> NM | N93: =IF(($F93/AP93)<0,"NM",IF(($F93/AP93)>75,"NM",($F93/AP93))) -> NM | P93: =AF93 -> 383.62 | Q93: =AG93/AF93-1 -> 0.78687243 | R93: =AH93/AG93-1 -> 0.4737702 | T93: =AJ93 -> 0.558124 | U93: =AT93 -> 0.45107562 | V93: =AU93 -> 0.37515941 | W93: =AL93/AF93 -> -0.14562998 | Y93: =IF(ISNUMBER(AR93),AR93,"NA") -> 0.912175 | AE93: 253.41 | AF93: 383.62 | AG93: 685.48 | AH93: 1010.24 | AJ93: 0.558124 | AL93: -55.866572 | AM93: -38.705407 | AO93: -70.356557 | AP93: -55.266915 | AR93: 0.912175 | AT93: 0.45107562 | AU93: 0.37515941
B94: Xero | C94: XRO | E94: 42.66607 | F94: 4300.8 | G94: 5105.97 | I94: =$G94/AG94 -> 46.878167 | J94: =$G94/AH94 -> 28.798477 | L94: =IF(($F94/AM94)<0,"NM",IF(($F94/AM94)>75,"NM",($F94/AM94))) -> NM | N94: =IF(($F94/AP94)<0,"NM",IF(($F94/AP94)>75,"NM",($F94/AP94))) -> NM | P94: =AF94 -> 61.306304 | Q94: =AG94/AF94-1 -> 0.77665253 | R94: =AH94/AG94-1 -> 0.62780022 | T94: =AJ94 -> NA | U94: =AT94 -> NA | V94: =AU94 -> NA | W94: =AL94/AF94 -> -0.32088946 | Y94: =IF(ISNUMBER(AR94),AR94,"NA") -> NA | AE94: 23.063749 | AF94: 61.306304 | AG94: 108.92 | AH94: 177.3 | AJ94: NA | AL94: -19.672547 | AM94: -51.452504 | AO94: -25.514946 | AP94: -33.908535 | AT94: NA | AU94: NA
B96: Median | F96: =MEDIAN(F58:F94) -> 1759.36 | G96: =MEDIAN(G58:G94) -> 1496.37 | I96: =MEDIAN(I58:I94) -> 7.542779 | J96: =MEDIAN(J58:J94) -> 6.0347233 | L96: =MEDIAN(L58:L94) -> 37.246854 | N96: =MEDIAN(N58:N94) -> 36.944903 | P96: =MEDIAN(P58:P94) -> 173.29 | Q96: =MEDIAN(Q58:Q94) -> 0.23605933 | R96: =MEDIAN(R58:R94) -> 0.30980988 | T96: =MEDIAN(T58:T94) -> 0.693503 | U96: =MEDIAN(U58:U94) -> 0.42987038 | V96: =MEDIAN(V58:V94) -> 0.17077309 | W96: =MEDIAN(W58:W94) -> 0.069659986 | Y96: =MEDIAN(Y58:Y94) -> 0.839091
B97: Average | F97: =AVERAGE(F58:F94) -> 4811.1773 | G97: =AVERAGE(G58:G94) -> 4474.4492 | I97: =AVERAGE(I58:I94) -> 9.8216462 | J97: =AVERAGE(J58:J94) -> 7.4400357 | L97: =AVERAGE(L58:L94) -> 35.887917 | N97: =AVERAGE(N58:N94) -> 32.584436 | P97: =AVERAGE(P58:P94) -> 367.25617 | Q97: =AVERAGE(Q58:Q94) -> 0.29895265 | R97: =AVERAGE(R58:R94) -> 0.28239363 | T97: =AVERAGE(T58:T94) -> 0.67042408 | U97: =AVERAGE(U58:U94) -> 0.45285558 | V97: =AVERAGE(V58:V94) -> 0.17276849 | W97: =AVERAGE(W58:W94) -> 0.0037307482 | Y97: =AVERAGE(Y58:Y94) -> 0.88256371
B98: Minimum | F98: =MIN(F58:F94) -> 268.03 | G98: =MIN(G58:G94) -> 221.28 | I98: =MIN(I58:I94) -> 2.3281052 | J98: =MIN(J58:J94) -> 1.8980504 | L98: =MIN(L58:L94) -> 16.427918 | N98: =MIN(N58:N94) -> 11.681791 | P98: =MIN(P58:P94) -> 43.631211 | Q98: =MIN(Q58:Q94) -> -0.14151788 | R98: =MIN(R58:R94) -> -0.18722484 | T98: =MIN(T58:T94) -> 0 | U98: =MIN(U58:U94) -> 0.21819736 | V98: =MIN(V58:V94) -> 0.03016931 | W98: =MIN(W58:W94) -> -0.32088946 | Y98: =MIN(Y58:Y94) -> 0.672066
B99: Maximum | F99: =MAX(F58:F94) -> 40969.58 | G99: =MAX(G58:G94) -> 40040.33 | I99: =MAX(I58:I94) -> 46.878167 | J99: =MAX(J58:J94) -> 28.798477 | L99: =MAX(L58:L94) -> 53.266739 | N99: =MAX(N58:N94) -> 70.813772 | P99: =MAX(P58:P94) -> 4277.26 | Q99: =MAX(Q58:Q94) -> 1.0186408 | R99: =MAX(R58:R94) -> 0.94160705 | T99: =MAX(T58:T94) -> 1.034575 | U99: =MAX(U58:U94) -> 1.1529343 | V99: =MAX(V58:V94) -> 0.37515941 | W99: =MAX(W58:W94) -> 0.20898301 | Y99: =MAX(Y58:Y94) -> 1.144914
B101: valuation output | D101: 2015
C102: Downside case | D102: Base case | E102: Upside case
B103: Implied EV / Revenue | C103: 5 | D103: =J97 -> 7.4400357 | E103: 10
B104: revenue | C104: ='P&L'!F70 -> 260644 | D104: ='P&L'!F70 -> 260644 | E104: ='P&L'!F70 -> 260644
B105: Enterprise value | C105: =C104*C103 -> 1303220 | D105: =D104*D103 -> 1939200.7 | E105: =E104*E103 -> 2606440
B107: Borrowings | C107: ='BS-CF-WC'!F31+'BS-CF-WC'!F28 -> 27091 | D107: ='BS-CF-WC'!F31+'BS-CF-WC'!F28 -> 27091 | E107: ='BS-CF-WC'!F31+'BS-CF-WC'!F28 -> 27091
B108: Cash | C108: ='BS-CF-WC'!F8 -> 206118.43 | D108: ='BS-CF-WC'!F8 -> 206118.43 | E108: ='BS-CF-WC'!F8 -> 206118.43
B109: Equity value | C109: =C105+C107-C108 -> 1124192.6 | D109: =D105+D107-D108 -> 1760173.2 | E109: =E105+E107-E108 -> 2427412.6
B111: Value per share | C111: =C109/('Equity-Shares'!C67/10^3) -> 12.29154 | D111: =D109/('Equity-Shares'!C67/10^3) -> 19.245136 | E111: =E109/('Equity-Shares'!C67/10^3) -> 26.540505
