Workbook

Sheet Assumptions
B2: Transaction Scenario Assumptions
B4: Capital and Ownership Inputs | H4: Fees and Forward Metrics
B6: Reference Share Price | F6: 456.03296 | H6: Regulatory Filing Fees | J6: 0.163386
B7: Diluted Shares | F7: 56.721032 | H7: Document Production Fees | J7: 0.086736
B8: Diluted Equity Value | F8: =F6*F7 -> 25866.66 | H8: Accounting and Legal Fees | J8: 0.114488
H9: Other Transaction Fees | J9: 0.111437
B10: Base Offering Proceeds | F10: 1453 | H10: Total Transaction Fees | J10: =SUM(J6:J9) -> 0.476047
B11: Underwriting Fee Rate | F11: 0.02331
H12: Pre-Transaction Forward EPS | J12: 5.140629
B13: Primary Share Mix | F13: 0.949167
B14: Secondary Share Mix | F14: =1-F13 -> 0.050833 | H14: Forward Revenue | J14: 5914.5882
H15: Forward EBITDA | J15: 690.23351
B16: Overallotment Rate | F16: 0.143216 | H16: Forward Net Income | J16: 283.30691
B17: Primary Overallotment Mix | F17: 0.782447 | H17: Debt and Convertible Costs | J17: Scenario-specific

Sheet Scenario Engine
B2: Scenario Calculation Engine
B5: Scenario | D5: Pricing Step | E5: Scenario Offer Price | F5: Base Shares in Transaction | G5: Overallotment Shares | H5: Primary Shares — Overallotment | I5: Diluted Shares Before Transaction | J5: Base Transaction Value | K5: Total Transaction Fees | L5: Less: Cash and Equivalents | M5: Less: Equity Investments | N5: Less: Non-Core Assets | O5: Less: Tax Attributes | P5: Add: Debt | Q5: Add: Noncontrolling Interests | R5: Secondary Shares — Overallotment | S5: After-Tax Debt Cost | T5: After-Tax Convertible Cost
B6: Pricing Discount | D6: % | E6: $ | F6: M shares | G6: M shares | H6: M shares | I6: M shares | J6: $M | K6: $M | L6: $M | M6: $M | N6: $M | O6: $M | P6: $M | Q6: $M | R6: M shares | S6: % | T6: %
B7: Scenario 1 | D7: -0.282191 | E7: =Assumptions!F6*(1+D7) -> 327.34456 | F7: =Assumptions!F10/E7 -> 4.4387479 | G7: =F7*Assumptions!F16 -> 0.63569972 | H7: =G7*Assumptions!F17 -> 0.49740134 | I7: =Assumptions!F7 -> 56.721032 | J7: =F7*E7 -> 1453 | K7: =-Assumptions!J10 -> -0.476047 | L7: -1641.0471 | M7: 0 | N7: 0 | O7: 0 | P7: 914.69783 | Q7: 0 | R7: =G7-H7 -> 0.13829838 | S7: 0.030909 | T7: 0.008054
B8: Scenario 2 | D8: -0.232191 | E8: =Assumptions!F6*(1+D8) -> 350.14621 | F8: =Assumptions!F10/E8 -> 4.149695 | G8: =F8*Assumptions!F16 -> 0.59430272 | H8: =G8*Assumptions!F17 -> 0.46501038 | I8: =Assumptions!F7 -> 56.721032 | J8: =F8*E8 -> 1453 | K8: =-Assumptions!J10 -> -0.476047 | L8: -1395.8204 | M8: 0 | N8: 0 | O8: 0 | P8: 821.41272 | Q8: 0 | R8: =G8-H8 -> 0.12929234 | S8: 0.041825 | T8: 0.008623
B9: Scenario 3 | D9: -0.182191 | E9: =Assumptions!F6*(1+D9) -> 372.94786 | F9: =Assumptions!F10/E9 -> 3.895987 | G9: =F9*Assumptions!F16 -> 0.55796767 | H9: =G9*Assumptions!F17 -> 0.43658013 | I9: =Assumptions!F7 -> 56.721032 | J9: =F9*E9 -> 1453 | K9: =-Assumptions!J10 -> -0.476047 | L9: -1778.0757 | M9: 0 | N9: 0 | O9: 0 | P9: 810.06477 | Q9: 0 | R9: =G9-H9 -> 0.12138754 | S9: 0.034759 | T9: 0.009477
B10: Scenario 4 | D10: -0.132191 | E10: =Assumptions!F6*(1+D10) -> 395.74951 | F10: =Assumptions!F10/E10 -> 3.6715143 | G10: =F10*Assumptions!F16 -> 0.5258196 | H10: =G10*Assumptions!F17 -> 0.41142597 | I10: =Assumptions!F7 -> 56.721032 | J10: =F10*E10 -> 1453 | K10: =-Assumptions!J10 -> -0.476047 | L10: -1633.9267 | M10: 0 | N10: 0 | O10: 0 | P10: 815.65032 | Q10: 0 | R10: =G10-H10 -> 0.11439363 | S10: 0.032319 | T10: 0.011279
B11: Scenario 5 | D11: -0.082191 | E11: =Assumptions!F6*(1+D11) -> 418.55116 | F11: =Assumptions!F10/E11 -> 3.4714992 | G11: =F11*Assumptions!F16 -> 0.49717423 | H11: =G11*Assumptions!F17 -> 0.38901248 | I11: =Assumptions!F7 -> 56.721032 | J11: =F11*E11 -> 1453 | K11: =-Assumptions!J10 -> -0.476047 | L11: -1720.5347 | M11: 0 | N11: 0 | O11: 0 | P11: 777.93471 | Q11: 0 | R11: =G11-H11 -> 0.10816174 | S11: 0.035771 | T11: 0.009761
B12: Scenario 6 | D12: -0.032191 | E12: =Assumptions!F6*(1+D12) -> 441.3528 | F12: =Assumptions!F10/E12 -> 3.2921508 | G12: =F12*Assumptions!F16 -> 0.47148867 | H12: =G12*Assumptions!F17 -> 0.3689149 | I12: =Assumptions!F7 -> 56.721032 | J12: =F12*E12 -> 1453 | K12: =-Assumptions!J10 -> -0.476047 | L12: -1388.898 | M12: 0 | N12: 0 | O12: 0 | P12: 872.78779 | Q12: 0 | R12: =G12-H12 -> 0.10257378 | S12: 0.033781 | T12: 0.008276

Sheet Valuation Output
B2: Scenario Valuation and Dilution Outputs
B5: Scenario | D5: Primary Shares — Base | E5: Secondary Shares — Base | F5: Total Primary Shares | G5: Diluted Shares After Transaction | H5: Equity Value at Offer Price | I5: Offer-Price Discount | J5: Equity Value Discount | K5: Equity Value at Market Price | L5: Overallotment Value | M5: Total Transaction Value | N5: Gross Primary Capital | O5: Underwriting Fees | P5: Net Primary Capital | Q5: Ownership Sold | R5: Equity Value at Market Price | S5: Less: Net Primary Capital | T5: Enterprise Value at Market Price | U5: Equity Value at Offer Price | V5: Forward P/E at Offer Price | W5: Forward P/E at Market Price | X5: Forward EV / EBITDA at Market Price | Y5: Forward EV / Revenue at Market Price | Z5: Forward EPS After Transaction | AA5: Forward EPS Change per Share | AB5: Forward EPS Change | AC5: Cost of Equity After Taxes | AD5: Enterprise Value at Offer Price | AE5: Forward EV / EBITDA at Offer Price | AF5: Forward EV / Revenue at Offer Price
B6: Pricing Discount | D6: M shares | E6: M shares | F6: M shares | G6: M shares | H6: $M | I6: % | J6: $M | K6: $M | L6: $M | M6: $M | N6: $M | O6: $M | P6: $M | Q6: % | R6: $M | S6: $M | T6: $M | U6: $M | V6: x | W6: x | X6: x | Y6: x | Z6: $ | AA6: $ | AB6: % | AC6: % | AD6: $M | AE6: x | AF6: x
B7: Scenario 1 | D7: ='Scenario Engine'!F7*Assumptions!F13 -> 4.213113 | E7: ='Scenario Engine'!F7-'Valuation Output'!D7 -> 0.22563487 | F7: ='Valuation Output'!D7+'Scenario Engine'!H7 -> 4.7105144 | G7: =SUM('Scenario Engine'!I7,'Valuation Output'!F7) -> 61.431546 | H7: ='Valuation Output'!G7*'Scenario Engine'!E7 -> 20109.283 | I7: ='Valuation Output'!J7/'Valuation Output'!K7 -> 0.282191 | J7: ='Valuation Output'!K7-'Valuation Output'!H7 -> 7905.5273 | K7: ='Valuation Output'!G7*Assumptions!F6 -> 28014.81 | L7: ='Scenario Engine'!G7*'Scenario Engine'!E7 -> 208.09285 | M7: =SUM('Scenario Engine'!J7,'Valuation Output'!L7) -> 1661.0928 | N7: ='Valuation Output'!F7*'Scenario Engine'!E7 -> 1541.9613 | O7: =-'Valuation Output'!F7*'Scenario Engine'!E7*Assumptions!F11 -> -35.943117 | P7: =SUM('Valuation Output'!N7,'Valuation Output'!O7,'Scenario Engine'!K7) -> 1505.5421 | Q7: ='Valuation Output'!F7/'Valuation Output'!G7 -> 0.076679079 | R7: ='Valuation Output'!K7 -> 28014.81 | S7: =-'Valuation Output'!P7 -> -1505.5421 | T7: =SUM('Valuation Output'!R7,'Valuation Output'!S7,'Scenario Engine'!L7:'Scenario Engine'!Q7) -> 25782.919 | U7: ='Valuation Output'!H7 -> 20109.283 | V7: ='Valuation Output'!U7/Assumptions!J16 -> 70.98056 | W7: ='Valuation Output'!R7/Assumptions!J16 -> 98.885023 | X7: ='Valuation Output'!T7/Assumptions!J15 -> 37.353907 | Y7: ='Valuation Output'!T7/Assumptions!J14 -> 4.3592077 | Z7: =Assumptions!J16/'Valuation Output'!G7 -> 4.6117496 | AA7: ='Valuation Output'!Z7-Assumptions!J12 -> -0.52887944 | AB7: ='Valuation Output'!AA7/Assumptions!J12 -> -0.10288224 | AC7: =Assumptions!J16/'Valuation Output'!H7 -> 0.014088365 | AD7: ='Valuation Output'!U7+SUM('Valuation Output'!S7,'Scenario Engine'!L7:'Scenario Engine'!Q7) -> 17877.391 | AE7: ='Valuation Output'!AD7/Assumptions!J15 -> 25.900498 | AF7: ='Valuation Output'!AD7/Assumptions!J14 -> 3.0225927
B8: Scenario 2 | D8: ='Scenario Engine'!F8*Assumptions!F13 -> 3.9387536 | E8: ='Scenario Engine'!F8-'Valuation Output'!D8 -> 0.21094145 | F8: ='Valuation Output'!D8+'Scenario Engine'!H8 -> 4.403764 | G8: =SUM('Scenario Engine'!I8,'Valuation Output'!F8) -> 61.124796 | H8: ='Valuation Output'!G8*'Scenario Engine'!E8 -> 21402.616 | I8: ='Valuation Output'!J8/'Valuation Output'!K8 -> 0.232191 | J8: ='Valuation Output'!K8-'Valuation Output'!H8 -> 6472.306 | K8: ='Valuation Output'!G8*Assumptions!F6 -> 27874.922 | L8: ='Scenario Engine'!G8*'Scenario Engine'!E8 -> 208.09285 | M8: =SUM('Scenario Engine'!J8,'Valuation Output'!L8) -> 1661.0928 | N8: ='Valuation Output'!F8*'Scenario Engine'!E8 -> 1541.9613 | O8: =-'Valuation Output'!F8*'Scenario Engine'!E8*Assumptions!F11 -> -35.943117 | P8: =SUM('Valuation Output'!N8,'Valuation Output'!O8,'Scenario Engine'!K8) -> 1505.5421 | Q8: ='Valuation Output'!F8/'Valuation Output'!G8 -> 0.072045459 | R8: ='Valuation Output'!K8 -> 27874.922 | S8: =-'Valuation Output'!P8 -> -1505.5421 | T8: =SUM('Valuation Output'!R8,'Valuation Output'!S8,'Scenario Engine'!L8:'Scenario Engine'!Q8) -> 25794.972 | U8: ='Valuation Output'!H8 -> 21402.616 | V8: ='Valuation Output'!U8/Assumptions!J16 -> 75.54569 | W8: ='Valuation Output'!R8/Assumptions!J16 -> 98.391254 | X8: ='Valuation Output'!T8/Assumptions!J15 -> 37.37137 | Y8: ='Valuation Output'!T8/Assumptions!J14 -> 4.3612456 | Z8: =Assumptions!J16/'Valuation Output'!G8 -> 4.6348933 | AA8: ='Valuation Output'!Z8-Assumptions!J12 -> -0.50573571 | AB8: ='Valuation Output'!AA8/Assumptions!J12 -> -0.098380121 | AC8: =Assumptions!J16/'Valuation Output'!H8 -> 0.013237023 | AD8: ='Valuation Output'!U8+SUM('Valuation Output'!S8,'Scenario Engine'!L8:'Scenario Engine'!Q8) -> 19322.666 | AE8: ='Valuation Output'!AD8/Assumptions!J15 -> 27.99439 | AF8: ='Valuation Output'!AD8/Assumptions!J14 -> 3.2669503
B9: Scenario 3 | D9: ='Scenario Engine'!F9*Assumptions!F13 -> 3.6979423 | E9: ='Scenario Engine'!F9-'Valuation Output'!D9 -> 0.1980447 | F9: ='Valuation Output'!D9+'Scenario Engine'!H9 -> 4.1345224 | G9: =SUM('Scenario Engine'!I9,'Valuation Output'!F9) -> 60.855554 | H9: ='Valuation Output'!G9*'Scenario Engine'!E9 -> 22695.949 | I9: ='Valuation Output'!J9/'Valuation Output'!K9 -> 0.182191 | J9: ='Valuation Output'!K9-'Valuation Output'!H9 -> 5056.1899 | K9: ='Valuation Output'!G9*Assumptions!F6 -> 27752.139 | L9: ='Scenario Engine'!G9*'Scenario Engine'!E9 -> 208.09285 | M9: =SUM('Scenario Engine'!J9,'Valuation Output'!L9) -> 1661.0928 | N9: ='Valuation Output'!F9*'Scenario Engine'!E9 -> 1541.9613 | O9: =-'Valuation Output'!F9*'Scenario Engine'!E9*Assumptions!F11 -> -35.943117 | P9: =SUM('Valuation Output'!N9,'Valuation Output'!O9,'Scenario Engine'!K9) -> 1505.5421 | Q9: ='Valuation Output'!F9/'Valuation Output'!G9 -> 0.067939934 | R9: ='Valuation Output'!K9 -> 27752.139 | S9: =-'Valuation Output'!P9 -> -1505.5421 | T9: =SUM('Valuation Output'!R9,'Valuation Output'!S9,'Scenario Engine'!L9:'Scenario Engine'!Q9) -> 25278.586 | U9: ='Valuation Output'!H9 -> 22695.949 | V9: ='Valuation Output'!U9/Assumptions!J16 -> 80.110821 | W9: ='Valuation Output'!R9/Assumptions!J16 -> 97.957861 | X9: ='Valuation Output'!T9/Assumptions!J15 -> 36.623237 | Y9: ='Valuation Output'!T9/Assumptions!J14 -> 4.2739384 | Z9: =Assumptions!J16/'Valuation Output'!G9 -> 4.6553993 | AA9: ='Valuation Output'!Z9-Assumptions!J12 -> -0.48522967 | AB9: ='Valuation Output'!AA9/Assumptions!J12 -> -0.094391109 | AC9: =Assumptions!J16/'Valuation Output'!H9 -> 0.012482708 | AD9: ='Valuation Output'!U9+SUM('Valuation Output'!S9,'Scenario Engine'!L9:'Scenario Engine'!Q9) -> 20222.396 | AE9: ='Valuation Output'!AD9/Assumptions!J15 -> 29.297905 | AF9: ='Valuation Output'!AD9/Assumptions!J14 -> 3.4190708
B10: Scenario 4 | D10: ='Scenario Engine'!F10*Assumptions!F13 -> 3.4848803 | E10: ='Scenario Engine'!F10-'Valuation Output'!D10 -> 0.18663409 | F10: ='Valuation Output'!D10+'Scenario Engine'!H10 -> 3.8963062 | G10: =SUM('Scenario Engine'!I10,'Valuation Output'!F10) -> 60.617338 | H10: ='Valuation Output'!G10*'Scenario Engine'!E10 -> 23989.282 | I10: ='Valuation Output'!J10/'Valuation Output'!K10 -> 0.132191 | J10: ='Valuation Output'!K10-'Valuation Output'!H10 -> 3654.2225 | K10: ='Valuation Output'!G10*Assumptions!F6 -> 27643.504 | L10: ='Scenario Engine'!G10*'Scenario Engine'!E10 -> 208.09285 | M10: =SUM('Scenario Engine'!J10,'Valuation Output'!L10) -> 1661.0928 | N10: ='Valuation Output'!F10*'Scenario Engine'!E10 -> 1541.9613 | O10: =-'Valuation Output'!F10*'Scenario Engine'!E10*Assumptions!F11 -> -35.943117 | P10: =SUM('Valuation Output'!N10,'Valuation Output'!O10,'Scenario Engine'!K10) -> 1505.5421 | Q10: ='Valuation Output'!F10/'Valuation Output'!G10 -> 0.064277092 | R10: ='Valuation Output'!K10 -> 27643.504 | S10: =-'Valuation Output'!P10 -> -1505.5421 | T10: =SUM('Valuation Output'!R10,'Valuation Output'!S10,'Scenario Engine'!L10:'Scenario Engine'!Q10) -> 25319.686 | U10: ='Valuation Output'!H10 -> 23989.282 | V10: ='Valuation Output'!U10/Assumptions!J16 -> 84.675951 | W10: ='Valuation Output'!R10/Assumptions!J16 -> 97.57441 | X10: ='Valuation Output'!T10/Assumptions!J15 -> 36.682783 | Y10: ='Valuation Output'!T10/Assumptions!J14 -> 4.2808873 | Z10: =Assumptions!J16/'Valuation Output'!G10 -> 4.6736943 | AA10: ='Valuation Output'!Z10-Assumptions!J12 -> -0.46693472 | AB10: ='Valuation Output'!AA10/Assumptions!J12 -> -0.090832215 | AC10: =Assumptions!J16/'Valuation Output'!H10 -> 0.011809729 | AD10: ='Valuation Output'!U10+SUM('Valuation Output'!S10,'Scenario Engine'!L10:'Scenario Engine'!Q10) -> 21665.463 | AE10: ='Valuation Output'!AD10/Assumptions!J15 -> 31.3886 | AF10: ='Valuation Output'!AD10/Assumptions!J14 -> 3.6630552
B11: Scenario 5 | D11: ='Scenario Engine'!F11*Assumptions!F13 -> 3.2950325 | E11: ='Scenario Engine'!F11-'Valuation Output'!D11 -> 0.17646672 | F11: ='Valuation Output'!D11+'Scenario Engine'!H11 -> 3.684045 | G11: =SUM('Scenario Engine'!I11,'Valuation Output'!F11) -> 60.405077 | H11: ='Valuation Output'!G11*'Scenario Engine'!E11 -> 25282.615 | I11: ='Valuation Output'!J11/'Valuation Output'!K11 -> 0.082191 | J11: ='Valuation Output'!K11-'Valuation Output'!H11 -> 2264.0913 | K11: ='Valuation Output'!G11*Assumptions!F6 -> 27546.706 | L11: ='Scenario Engine'!G11*'Scenario Engine'!E11 -> 208.09285 | M11: =SUM('Scenario Engine'!J11,'Valuation Output'!L11) -> 1661.0928 | N11: ='Valuation Output'!F11*'Scenario Engine'!E11 -> 1541.9613 | O11: =-'Valuation Output'!F11*'Scenario Engine'!E11*Assumptions!F11 -> -35.943117 | P11: =SUM('Valuation Output'!N11,'Valuation Output'!O11,'Scenario Engine'!K11) -> 1505.5421 | Q11: ='Valuation Output'!F11/'Valuation Output'!G11 -> 0.060988995 | R11: ='Valuation Output'!K11 -> 27546.706 | S11: =-'Valuation Output'!P11 -> -1505.5421 | T11: =SUM('Valuation Output'!R11,'Valuation Output'!S11,'Scenario Engine'!L11:'Scenario Engine'!Q11) -> 25098.564 | U11: ='Valuation Output'!H11 -> 25282.615 | V11: ='Valuation Output'!U11/Assumptions!J16 -> 89.241082 | W11: ='Valuation Output'!R11/Assumptions!J16 -> 97.232738 | X11: ='Valuation Output'!T11/Assumptions!J15 -> 36.362425 | Y11: ='Valuation Output'!T11/Assumptions!J14 -> 4.2435015 | Z11: =Assumptions!J16/'Valuation Output'!G11 -> 4.6901175 | AA11: ='Valuation Output'!Z11-Assumptions!J12 -> -0.45051152 | AB11: ='Valuation Output'!AA11/Assumptions!J12 -> -0.087637432 | AC11: =Assumptions!J16/'Valuation Output'!H11 -> 0.011205602 | AD11: ='Valuation Output'!U11+SUM('Valuation Output'!S11,'Scenario Engine'!L11:'Scenario Engine'!Q11) -> 22834.473 | AE11: ='Valuation Output'!AD11/Assumptions!J15 -> 33.082243 | AF11: ='Valuation Output'!AD11/Assumptions!J14 -> 3.8607037
B12: Scenario 6 | D12: ='Scenario Engine'!F12*Assumptions!F13 -> 3.1248009 | E12: ='Scenario Engine'!F12-'Valuation Output'!D12 -> 0.1673499 | F12: ='Valuation Output'!D12+'Scenario Engine'!H12 -> 3.4937158 | G12: =SUM('Scenario Engine'!I12,'Valuation Output'!F12) -> 60.214748 | H12: ='Valuation Output'!G12*'Scenario Engine'!E12 -> 26575.948 | I12: ='Valuation Output'!J12/'Valuation Output'!K12 -> 0.032191 | J12: ='Valuation Output'!K12-'Valuation Output'!H12 -> 883.96196 | K12: ='Valuation Output'!G12*Assumptions!F6 -> 27459.91 | L12: ='Scenario Engine'!G12*'Scenario Engine'!E12 -> 208.09285 | M12: =SUM('Scenario Engine'!J12,'Valuation Output'!L12) -> 1661.0928 | N12: ='Valuation Output'!F12*'Scenario Engine'!E12 -> 1541.9613 | O12: =-'Valuation Output'!F12*'Scenario Engine'!E12*Assumptions!F11 -> -35.943117 | P12: =SUM('Valuation Output'!N12,'Valuation Output'!O12,'Scenario Engine'!K12) -> 1505.5421 | Q12: ='Valuation Output'!F12/'Valuation Output'!G12 -> 0.058020932 | R12: ='Valuation Output'!K12 -> 27459.91 | S12: =-'Valuation Output'!P12 -> -1505.5421 | T12: =SUM('Valuation Output'!R12,'Valuation Output'!S12,'Scenario Engine'!L12:'Scenario Engine'!Q12) -> 25438.258 | U12: ='Valuation Output'!H12 -> 26575.948 | V12: ='Valuation Output'!U12/Assumptions!J16 -> 93.806212 | W12: ='Valuation Output'!R12/Assumptions!J16 -> 96.926369 | X12: ='Valuation Output'!T12/Assumptions!J15 -> 36.854567 | Y12: ='Valuation Output'!T12/Assumptions!J14 -> 4.3009347 | Z12: =Assumptions!J16/'Valuation Output'!G12 -> 4.7049422 | AA12: ='Valuation Output'!Z12-Assumptions!J12 -> -0.43568682 | AB12: ='Valuation Output'!AA12/Assumptions!J12 -> -0.084753601 | AC12: =Assumptions!J16/'Valuation Output'!H12 -> 0.010660275 | AD12: ='Valuation Output'!U12+SUM('Valuation Output'!S12,'Scenario Engine'!L12:'Scenario Engine'!Q12) -> 24554.296 | AE12: ='Valuation Output'!AD12/Assumptions!J15 -> 35.573897 | AF12: ='Valuation Output'!AD12/Assumptions!J14 -> 4.1514802
