Workbook

Sheet Assumptions
B2: Transaction Scenario Assumptions
B4: Capital and Ownership Inputs | H4: Fees and Forward Metrics
B6: Reference Share Price | F6: 456.03296 | H6: Regulatory Filing Fees | J6: 0.163386
B7: Diluted Shares | F7: 56.721032 | H7: Document Production Fees | J7: 0.086736
B8: Diluted Equity Value | F8: =F6*F7 -> 25866.66 | H8: Accounting and Legal Fees | J8: 0.114488
H9: Other Transaction Fees | J9: 0.111437
B10: Base Offering Proceeds | F10: 1453 | H10: Total Transaction Fees | J10: =SUM(J6:J9) -> 0.476047
B11: Underwriting Fee Rate | F11: 0.02331
H12: Pre-Transaction Forward EPS | J12: 5.140629
B13: Primary Share Mix | F13: 0.949167
B14: Secondary Share Mix | F14: =1-F13 -> 0.050833 | H14: Forward Revenue | J14: 5914.5882
H15: Forward EBITDA | J15: 690.23351
B16: Overallotment Rate | F16: 0.143216 | H16: Forward Net Income | J16: 283.30691
B17: Primary Overallotment Mix | F17: 0.782447 | H17: Debt and Convertible Costs | J17: Scenario-specific

Sheet Scenario Engine
B2: Scenario Calculation Engine
B5: Scenario | D5: Pricing Step | E5: Scenario Offer Price | F5: Base Shares in Transaction | G5: Overallotment Shares | H5: Primary Shares — Overallotment | I5: Diluted Shares Before Transaction | J5: Base Transaction Value | K5: Total Transaction Fees | L5: Less: Cash and Equivalents | M5: Less: Equity Investments | N5: Less: Non-Core Assets | O5: Less: Tax Attributes | P5: Add: Debt | Q5: Add: Noncontrolling Interests | R5: Secondary Shares — Overallotment | S5: After-Tax Debt Cost | T5: After-Tax Convertible Cost
B6: Pricing Discount | D6: % | E6: $ | F6: M shares | G6: M shares | H6: M shares | I6: M shares | J6: $M | K6: $M | L6: $M | M6: $M | N6: $M | O6: $M | P6: $M | Q6: $M | R6: M shares | S6: % | T6: %
B7: Scenario 1 | D7: -0.282191 | E7: =Assumptions!F6*(1+D7) -> 327.34456 | F7: =Assumptions!F10/E7 -> 4.4387479 | G7: =F7*Assumptions!F16 -> 0.63569972 | H7: =G7*Assumptions!F17 -> 0.49740134 | I7: =Assumptions!F7 -> 56.721032 | J7: =F7*E7 -> 1453 | K7: =-Assumptions!J10 -> -0.476047 | L7: -1641.0471 | M7: 0 | N7: 0 | O7: 0 | P7: 914.69783 | Q7: 0 | R7: =G7-H7 -> 0.13829838 | S7: 0.030909 | T7: 0.008054
B8: Scenario 2 | D8: -0.232191 | E8: =Assumptions!F6*(1+D8) -> 350.14621 | F8: =Assumptions!F10/E8 -> 4.149695 | G8: =F8*Assumptions!F16 -> 0.59430272 | H8: =G8*Assumptions!F17 -> 0.46501038 | I8: =Assumptions!F7 -> 56.721032 | J8: =F8*E8 -> 1453 | K8: =-Assumptions!J10 -> -0.476047 | L8: -1395.8204 | M8: 0 | N8: 0 | O8: 0 | P8: 821.41272 | Q8: 0 | R8: =G8-H8 -> 0.12929234 | S8: 0.041825 | T8: 0.008623
B9: Scenario 3 | D9: -0.182191 | E9: =Assumptions!F6*(1+D9) -> 372.94786 | F9: =Assumptions!F10/E9 -> 3.895987 | G9: =F9*Assumptions!F16 -> 0.55796767 | H9: =G9*Assumptions!F17 -> 0.43658013 | I9: =Assumptions!F7 -> 56.721032 | J9: =F9*E9 -> 1453 | K9: =-Assumptions!J10 -> -0.476047 | L9: -1778.0757 | M9: 0 | N9: 0 | O9: 0 | P9: 810.06477 | Q9: 0 | R9: =G9-H9 -> 0.12138754 | S9: 0.034759 | T9: 0.009477
B10: Scenario 4 | D10: -0.132191 | E10: =Assumptions!F6*(1+D10) -> 395.74951 | F10: =Assumptions!F10/E10 -> 3.6715143 | G10: =F10*Assumptions!F16 -> 0.5258196 | H10: =G10*Assumptions!F17 -> 0.41142597 | I10: =Assumptions!F7 -> 56.721032 | J10: =F10*E10 -> 1453 | K10: =-Assumptions!J10 -> -0.476047 | L10: -1633.9267 | M10: 0 | N10: 0 | O10: 0 | P10: 815.65032 | Q10: 0 | R10: =G10-H10 -> 0.11439363 | S10: 0.032319 | T10: 0.011279
B11: Scenario 5 | D11: -0.082191 | E11: =Assumptions!F6*(1+D11) -> 418.55116 | F11: =Assumptions!F10/E11 -> 3.4714992 | G11: =F11*Assumptions!F16 -> 0.49717423 | H11: =G11*Assumptions!F17 -> 0.38901248 | I11: =Assumptions!F7 -> 56.721032 | J11: =F11*E11 -> 1453 | K11: =-Assumptions!J10 -> -0.476047 | L11: -1720.5347 | M11: 0 | N11: 0 | O11: 0 | P11: 777.93471 | Q11: 0 | R11: =G11-H11 -> 0.10816174 | S11: 0.035771 | T11: 0.009761
B12: Scenario 6 | D12: -0.032191 | E12: =Assumptions!F6*(1+D12) -> 441.3528 | F12: =Assumptions!F10/E12 -> 3.2921508 | G12: =F12*Assumptions!F16 -> 0.47148867 | H12: =G12*Assumptions!F17 -> 0.3689149 | I12: =Assumptions!F7 -> 56.721032 | J12: =F12*E12 -> 1453 | K12: =-Assumptions!J10 -> -0.476047 | L12: -1388.898 | M12: 0 | N12: 0 | O12: 0 | P12: 872.78779 | Q12: 0 | R12: =G12-H12 -> 0.10257378 | S12: 0.033781 | T12: 0.008276

Sheet Valuation Output
B2: Scenario Valuation and Dilution Outputs
B5: Scenario | D5: Primary Shares — Base | E5: Secondary Shares — Base | F5: Total Primary Shares | G5: Diluted Shares After Transaction | H5: Equity Value at Offer Price | I5: Offer-Price Discount | J5: Equity Value Discount | K5: Equity Value at Market Price | L5: Overallotment Value | M5: Total Transaction Value | N5: Gross Primary Capital | O5: Underwriting Fees | P5: Net Primary Capital | Q5: Ownership Sold | R5: Equity Value at Market Price | S5: Less: Net Primary Capital | T5: Enterprise Value at Market Price | U5: Equity Value at Offer Price | V5: Forward P/E at Offer Price | W5: Forward P/E at Market Price | X5: Forward EV / EBITDA at Market Price | Y5: Forward EV / Revenue at Market Price | Z5: Forward EPS After Transaction | AA5: Forward EPS Change per Share | AB5: Forward EPS Change | AC5: Cost of Equity After Taxes | AD5: Enterprise Value at Offer Price | AE5: Forward EV / EBITDA at Offer Price | AF5: Forward EV / Revenue at Offer Price
B6: Pricing Discount | D6: M shares | E6: M shares | F6: M shares | G6: M shares | H6: $M | I6: % | J6: $M | K6: $M | L6: $M | M6: $M | N6: $M | O6: $M | P6: $M | Q6: % | R6: $M | S6: $M | T6: $M | U6: $M | V6: x | W6: x | X6: x | Y6: x | Z6: $ | AA6: $ | AB6: % | AC6: % | AD6: $M | AE6: x | AF6: x
B7: Scenario 1 | E7: ='Scenario Engine'!F7-'Valuation Output'!D7 -> 4.4387479 | F7: ='Valuation Output'!D7+'Scenario Engine'!H7 -> 0.49740134 | G7: =SUM('Scenario Engine'!I7,'Valuation Output'!F7) -> 57.218433 | H7: ='Valuation Output'!G7*'Scenario Engine'!E7 -> 18730.143 | J7: ='Valuation Output'!K7-'Valuation Output'!H7 -> 7363.3485 | K7: ='Valuation Output'!G7*Assumptions!F6 -> 26093.492 | M7: =SUM('Scenario Engine'!J7,'Valuation Output'!L7) -> 1453 | N7: ='Valuation Output'!F7*'Scenario Engine'!E7 -> 162.82162 | O7: =-'Valuation Output'!F7*'Scenario Engine'!E7*Assumptions!F11 -> -3.7953721 | P7: =SUM('Valuation Output'!N7,'Valuation Output'!O7,'Scenario Engine'!K7) -> 158.55021 | Q7: ='Valuation Output'!F7/'Valuation Output'!G7 -> 0.0086930262 | R7: ='Valuation Output'!K7 -> 26093.492 | U7: ='Valuation Output'!H7 -> 18730.143 | W7: ='Valuation Output'!R7/Assumptions!J16 -> 92.103267 | X7: ='Valuation Output'!T7/Assumptions!J15 -> 0 | Y7: ='Valuation Output'!T7/Assumptions!J14 -> 0 | Z7: =Assumptions!J16/'Valuation Output'!G7 -> 4.9513223 | AC7: =Assumptions!J16/'Valuation Output'!H7 -> 0.01512572 | AD7: 18003.794 | AE7: 26.083628 | AF7: 3.0439641
B8: Scenario 2 | E8: ='Scenario Engine'!F8-'Valuation Output'!D8 -> 4.149695 | F8: ='Valuation Output'!D8+'Scenario Engine'!H8 -> 0.46501038 | G8: =SUM('Scenario Engine'!I8,'Valuation Output'!F8) -> 57.186042 | H8: ='Valuation Output'!G8*'Scenario Engine'!E8 -> 20023.476 | J8: ='Valuation Output'!K8-'Valuation Output'!H8 -> 6055.2441 | K8: ='Valuation Output'!G8*Assumptions!F6 -> 26078.72 | M8: =SUM('Scenario Engine'!J8,'Valuation Output'!L8) -> 1453 | N8: ='Valuation Output'!F8*'Scenario Engine'!E8 -> 162.82162 | O8: =-'Valuation Output'!F8*'Scenario Engine'!E8*Assumptions!F11 -> -3.7953721 | P8: =SUM('Valuation Output'!N8,'Valuation Output'!O8,'Scenario Engine'!K8) -> 158.55021 | Q8: ='Valuation Output'!F8/'Valuation Output'!G8 -> 0.0081315364 | R8: ='Valuation Output'!K8 -> 26078.72 | U8: ='Valuation Output'!H8 -> 20023.476 | W8: ='Valuation Output'!R8/Assumptions!J16 -> 92.051128 | X8: ='Valuation Output'!T8/Assumptions!J15 -> 0 | Y8: ='Valuation Output'!T8/Assumptions!J14 -> 0 | Z8: =Assumptions!J16/'Valuation Output'!G8 -> 4.9541268 | AC8: =Assumptions!J16/'Valuation Output'!H8 -> 0.014148737 | AD8: 19449.068 | AE8: 28.17752 | AF8: 3.2883216
B9: Scenario 3 | E9: ='Scenario Engine'!F9-'Valuation Output'!D9 -> 3.895987 | F9: ='Valuation Output'!D9+'Scenario Engine'!H9 -> 0.43658013 | G9: =SUM('Scenario Engine'!I9,'Valuation Output'!F9) -> 57.157612 | H9: ='Valuation Output'!G9*'Scenario Engine'!E9 -> 21316.809 | J9: ='Valuation Output'!K9-'Valuation Output'!H9 -> 4748.946 | K9: ='Valuation Output'!G9*Assumptions!F6 -> 26065.755 | M9: =SUM('Scenario Engine'!J9,'Valuation Output'!L9) -> 1453 | N9: ='Valuation Output'!F9*'Scenario Engine'!E9 -> 162.82162 | O9: =-'Valuation Output'!F9*'Scenario Engine'!E9*Assumptions!F11 -> -3.7953721 | P9: =SUM('Valuation Output'!N9,'Valuation Output'!O9,'Scenario Engine'!K9) -> 158.55021 | Q9: ='Valuation Output'!F9/'Valuation Output'!G9 -> 0.00763818 | R9: ='Valuation Output'!K9 -> 26065.755 | U9: ='Valuation Output'!H9 -> 21316.809 | W9: ='Valuation Output'!R9/Assumptions!J16 -> 92.005364 | X9: ='Valuation Output'!T9/Assumptions!J15 -> 0 | Y9: ='Valuation Output'!T9/Assumptions!J14 -> 0 | Z9: =Assumptions!J16/'Valuation Output'!G9 -> 4.956591 | AC9: =Assumptions!J16/'Valuation Output'!H9 -> 0.013290306 | AD9: 20348.798 | AE9: 29.481035 | AF9: 3.4404421
B10: Scenario 4 | E10: ='Scenario Engine'!F10-'Valuation Output'!D10 -> 3.6715143 | F10: ='Valuation Output'!D10+'Scenario Engine'!H10 -> 0.41142597 | G10: =SUM('Scenario Engine'!I10,'Valuation Output'!F10) -> 57.132458 | H10: ='Valuation Output'!G10*'Scenario Engine'!E10 -> 22610.142 | J10: ='Valuation Output'!K10-'Valuation Output'!H10 -> 3444.1419 | K10: ='Valuation Output'!G10*Assumptions!F6 -> 26054.284 | M10: =SUM('Scenario Engine'!J10,'Valuation Output'!L10) -> 1453 | N10: ='Valuation Output'!F10*'Scenario Engine'!E10 -> 162.82162 | O10: =-'Valuation Output'!F10*'Scenario Engine'!E10*Assumptions!F11 -> -3.7953721 | P10: =SUM('Valuation Output'!N10,'Valuation Output'!O10,'Scenario Engine'!K10) -> 158.55021 | Q10: ='Valuation Output'!F10/'Valuation Output'!G10 -> 0.007201265 | R10: ='Valuation Output'!K10 -> 26054.284 | U10: ='Valuation Output'!H10 -> 22610.142 | W10: ='Valuation Output'!R10/Assumptions!J16 -> 91.964874 | X10: ='Valuation Output'!T10/Assumptions!J15 -> 0 | Y10: ='Valuation Output'!T10/Assumptions!J14 -> 0 | Z10: =Assumptions!J16/'Valuation Output'!G10 -> 4.9587733 | AC10: =Assumptions!J16/'Valuation Output'!H10 -> 0.012530081 | AD10: 21791.866 | AE10: 31.57173 | AF10: 3.6844265
B11: Scenario 5 | E11: ='Scenario Engine'!F11-'Valuation Output'!D11 -> 3.4714992 | F11: ='Valuation Output'!D11+'Scenario Engine'!H11 -> 0.38901248 | G11: =SUM('Scenario Engine'!I11,'Valuation Output'!F11) -> 57.110044 | H11: ='Valuation Output'!G11*'Scenario Engine'!E11 -> 23903.475 | J11: ='Valuation Output'!K11-'Valuation Output'!H11 -> 2140.5876 | K11: ='Valuation Output'!G11*Assumptions!F6 -> 26044.063 | M11: =SUM('Scenario Engine'!J11,'Valuation Output'!L11) -> 1453 | N11: ='Valuation Output'!F11*'Scenario Engine'!E11 -> 162.82162 | O11: =-'Valuation Output'!F11*'Scenario Engine'!E11*Assumptions!F11 -> -3.7953721 | P11: =SUM('Valuation Output'!N11,'Valuation Output'!O11,'Scenario Engine'!K11) -> 158.55021 | Q11: ='Valuation Output'!F11/'Valuation Output'!G11 -> 0.0068116298 | R11: ='Valuation Output'!K11 -> 26044.063 | U11: ='Valuation Output'!H11 -> 23903.475 | W11: ='Valuation Output'!R11/Assumptions!J16 -> 91.928796 | X11: ='Valuation Output'!T11/Assumptions!J15 -> 0 | Y11: ='Valuation Output'!T11/Assumptions!J14 -> 0 | Z11: =Assumptions!J16/'Valuation Output'!G11 -> 4.9607194 | AC11: =Assumptions!J16/'Valuation Output'!H11 -> 0.011852122 | AD11: 22960.875 | AE11: 33.265373 | AF11: 3.882075
B12: Scenario 6 | E12: ='Scenario Engine'!F12-'Valuation Output'!D12 -> 3.2921508 | F12: ='Valuation Output'!D12+'Scenario Engine'!H12 -> 0.3689149 | G12: =SUM('Scenario Engine'!I12,'Valuation Output'!F12) -> 57.089947 | H12: ='Valuation Output'!G12*'Scenario Engine'!E12 -> 25196.808 | J12: ='Valuation Output'!K12-'Valuation Output'!H12 -> 838.08939 | K12: ='Valuation Output'!G12*Assumptions!F6 -> 26034.898 | M12: =SUM('Scenario Engine'!J12,'Valuation Output'!L12) -> 1453 | N12: ='Valuation Output'!F12*'Scenario Engine'!E12 -> 162.82162 | O12: =-'Valuation Output'!F12*'Scenario Engine'!E12*Assumptions!F11 -> -3.7953721 | P12: =SUM('Valuation Output'!N12,'Valuation Output'!O12,'Scenario Engine'!K12) -> 158.55021 | Q12: ='Valuation Output'!F12/'Valuation Output'!G12 -> 0.006461994 | R12: ='Valuation Output'!K12 -> 26034.898 | U12: ='Valuation Output'!H12 -> 25196.808 | W12: ='Valuation Output'!R12/Assumptions!J16 -> 91.896445 | X12: ='Valuation Output'!T12/Assumptions!J15 -> 0 | Y12: ='Valuation Output'!T12/Assumptions!J14 -> 0 | Z12: =Assumptions!J16/'Valuation Output'!G12 -> 4.9624658 | AC12: =Assumptions!J16/'Valuation Output'!H12 -> 0.011243762 | AD12: 24680.698 | AE12: 35.757027 | AF12: 4.1728515
