Workbook

Sheet Source Data
B2: Operating Statement Export
B3: Report Run: 03/05/2025 12:09 PM
B5: Virelthorn Owner, LLC
B6: Properties: Active
B7: Date Range: 01/01/2024 to 12/31/2024
B8: Accounting Basis: Accrual
B9: Account Map: Standard chart of accounts
B10: Level of Detail: Detail View
B11: Include Zero-Balance Accounts: No
B13: Account Name | C13: Reported Period
B14: Operating Income & Expense
B15: Income | F15: Purchase Price | G15: 67015280
B16: Gross Potential Rent | C16: 4899934.7 | D16: =SUM(C16:C24) -> 4323174.4 | F16: Mortgage in place | G16: 50938905
B17: Gain/Loss to Lease | C17: -192135.32
B18: Vacancy | C18: -335370.69
B19: CONCESSIONS
B20: One-Time Concessions | C20: -8249 | F20: Analysis Scope
B21: Hometown Hero Discount | C21: -2624.96 | F21: 1. Create financial model including NOI pro-forma, rent sensitivities, value sensitivities, sales comps
B22: Employee Units | C22: -11797.28 | F22: 2. What changed between projections (See OM) and outcome.
B23: Other Concession | C23: -2213 | F23: 2. Estimate refinance options with bank, HUD and agency
B24: Total CONCESSIONS | C24: -24370.04 | F24: 3. Provide recommendation for refinance / sale
B25: Interest Income | C25: 17291.77
B26: OTHER INCOME
B27: Application Fee Income | C27: 29441
B28: CO Inspection Fee | C28: 2766
B29: Monthly Amenity Fee | C29: 106817.24
B30: Annual Amenity Fee | C30: 628
B31: Transfer Fee | C31: 2454
B32: Resident Insurance Services | C32: 5659.59
B33: Resident Insurance Admin Fees | C33: 1039
B34: One-Time Pet Fee | C34: 6302
B35: Pet Rent | C35: 9516.04
B36: Resident Parking | C36: 232901.88
B37: NSF Fees Collected | C37: 1365
B38: Late Fee | C38: 9362
... B47: Total Operating Income | C47: 6456915.2
B48: Expense
B49: PAYROLL COSTS
B50: Property Manager | C50: 20397.49
B51: Assistant Property Manager | C51: 59807.66
B52: Leasing - Salaries | C52: 8981.65
B53: Superintendent | C53: 70280.21
B54: Assistant Superintendent | C54: 46415.34
B55: Cleaning | C55: 18916.58
B56: Bonuses | C56: 3311
B57: Retirement | C57: 5949.34
B58: Payroll Tax Expense | C58: 29703.96
B59: Workers Compensation | C59: 7939.07
B60: Group Insurance | C60: 8054.38
B61: Total PAYROLL COSTS | C61: 280012.93
B62: REPAIRS & MAINTENANCE
B63: Building - Roof Repairs | C63: 152.4
B64: Building - Garbage Disposal | C64: -235
B65: Cleaning & Supplies | C65: 2911.57
B66: CAM: Common Area Maintenance | C66: 1514.89
B67: Doors Repairs/Replacement | C67: 1589.98
B68: Elevator Repairs | C68: 6288.25
B69: HVAC (Heat, Ventilation, Air) | C69: 27709.6
B70: Landscape Supplies & Maintenance | C70: 192.24
B71: Lighting Supplies/Repairs | C71: 92.586482
B72: Electrical Repairs | C72: 2447.31
B73: Maintenance Supplies | C73: 19452.62
B74: Painting Supplies/Repairs | C74: 11657.59
... B78: Total REPAIRS & MAINTENANCE | C78: 76633.3
B79: CONTRACT SERVICES
B80: Telephone/Cable/Internet | C80: 14957.18
B81: Elevator Contract | C81: 14271.68
B82: Cleaning Contract | C82: 47612.7
B83: Low Voltage Contract (Access Control, Cameras, Fire Alarm) | C83: 44257.55
B84: Fire Safety System (Alarm & Sprinkler) | C84: 8547.84
B85: Exterminator | C85: 3894.78
B86: Garbage & Recycling | C86: 29822.39
B87: Other Contract Services | C87: 2837
B88: Total CONTRACT SERVICES | C88: 179125.77
B89: MAKE & READY
B90: Appliance/Repairs | C90: 694.82
B91: Unit Move in Fee/Turn Over Reserve Fund | C91: -64739
B92: Flooring | C92: 685.71
B93: Unit Renovation Supplies | C93: 750.8
B94: Cleaning Services/Supplies | C94: 10912.59
B95: Total MAKE & READY | C95: -56662.69
B96: MARKETING
B97: Internet Marketing | C97: 84890.26
B98: Amenity Rooms Furniture & Equipment | C98: 2181.52
B99: Leasing Commissions (INT) | C99: 25421.55
B100: Resident Activities | C100: 2549.47
B101: Signage | C101: 174.1
B102: Other Marketing Expenses | C102: 494.56
B103: Total MARKETING | C103: 120758.81
B104: OFFICE EXPENSES
B105: Office Expense | C105: 820.24
B106: Office Supplies | C106: 1978.78
B107: Resident Screening | C107: 11043.1
B108: Computer & Software | C108: 2513.09
B109: Total OFFICE EXPENSES | C109: 14068.26
B110: GENERAL & ADMINISTRATIVE EXPENSE
B111: Resident Portal Fees | C111: 16837
B112: Legal Expenses | C112: 2108.91
B113: Eviction Fees | C113: -455
B114: Internet Access | C114: 3044.77
...

Sheet Assumptions
B2: Property Address | D2: 1840 Kestrel Row
B3: City | D3: Lindenfen
B4: State | D4: NC
B5: Zip Code | D5: 27604
B6: Year Built | D6: 2021
B8: Property Details
B9: # of Units | D9: =Assumptions!C36 -> 214
B10: Gross SF | D10: 0
B11: NSF | D11: =Assumptions!D36*Assumptions!C36 -> 164300
B12: # of Parking Spaces Covered | D12: 283
B13: # of Parking Spaces uncovered | D13: 0
B15: Acquisition Info
B16: Purchase Price | D16: 85493946
B17: Acquisition Date | D17: 45778
B18: T-12 NOI | D18: ='Source Data'!C150 -> 1965100.7
B19: Going In Cap Rate | D19: =D18/D16 -> 0.022985262
B20: Price/Unit | D20: =D16/D9 -> 399504.42
B21: Price/GSF | D21: =IFERROR(D16/D10,0) -> 0
B22: Price/NSF | D22: =IFERROR(D16/D11,0) -> 520.35268
B23: Closing Cost | D23: 0.008621
B25: Exit Assumptions
B26: Month | D26: 36
B27: Exit Cap Rate | D27: 0.057887
B28: Cost of Sale | D28: 0.0234
B30: Unit Mix
B31: Unit Type | C31: # of Units | D31: SF | E31: Monthly Avg Rent | F31: Annual Rent | G31: Annual $/SF | I31: Existing Loan Info
B32: 1BD | C32: 53 | D32: 650 | E32: 2050 | I32: Existing Mortgage | K32: 50736714
B33: 1 BD + Den | C33: 70 | D33: 725 | E33: 2150 | I33: Lender | K33: NYCB
B34: 2 BD | C34: 84 | D34: 850 | E34: 2450 | I34: Floating/Fixed | K34: Fixed
B35: 2BD + 2 BA | C35: 7 | D35: 1100 | E35: 2800 | I35: Term | K35: 5+5
B36: Total | C36: =SUM(C32:C35) -> 214 | D36: =SUMPRODUCT(C32:C35,D32:D35)/C36 -> 767.75701 | E36: =SUMPRODUCT(E32:E35,$C$32:$C$35)/C36 -> 2264.2523 | I36: Rate | K36: 0.0335
I37: I/O Period (MTHs) | K37: 24
I38: Amortization | K38: 30
B39: Other Income
B40: Item | C40: $/Unit/MTH | D40: Monthly Income | E40: Annual Income
B41: Pet Fees & Rent | C41: 6
B42: Application Fee | C42: 12.5
B43: Amenity Fees | C43: 45
B44: Parking | C44: 83
B45: Transfer Fee | C45: 1.15
B46: Late Fee | C46: 3.5
B47: Lockout Fee | C47: 0.5
B48: Move-Out Charges | C48: 2.5
B49: Termination Fees | C49: 14
B50: Resident Insurance & Fees | C50: 2.5
B51: Total | C51: =SUM(C41:C50) -> 170.65
B55: Annual Expenses T-12 | G55: Pro Forma Annual Expenses
B56: Item | C56: Annual Expense | D56: $/Unit | G56: Item | H56: Annual Expense | I56: $/Unit
B57: Taxes | C57: ='Source Data'!C138 -> 479096.71 | D57: =C57/Assumptions!$D$9 -> 2238.7697 | G57: Taxes | H57: =I57*Assumptions!$D$9 -> 556400 | I57: 2600
B58: Insurance | C58: ='Source Data'!C135 -> 194393.68 | D58: =C58/Assumptions!$D$9 -> 908.38168 | G58: Insurance | H58: =I58*Assumptions!$D$9 -> 192600 | I58: 900
B59: Payroll | C59: ='Source Data'!C61 -> 280012.93 | D59: =C59/Assumptions!$D$9 -> 1308.4716 | G59: Payroll | H59: =I59*Assumptions!$D$9 -> 288900 | I59: 1350
B60: Repairs & Maintenance | C60: ='Source Data'!C78 -> 76633.3 | D60: =C60/Assumptions!$D$9 -> 358.09953 | G60: Repairs & Maintenance | H60: =I60*Assumptions!$D$9 -> 96300 | I60: 450
B61: Contract Services | C61: ='Source Data'!C88 -> 179125.77 | D61: =C61/Assumptions!$D$9 -> 837.03631 | G61: Contract Services | H61: =I61*Assumptions!$D$9 -> 162640 | I61: 760
B62: Marketing | C62: ='Source Data'!C103 -> 120758.81 | D62: =C62/Assumptions!$D$9 -> 564.2935 | G62: Marketing | H62: =I62*Assumptions!$D$9 -> 107000 | I62: 500
B63: General & Administrative | C63: ='Source Data'!C120 -> 73950.49 | D63: =C63/Assumptions!$D$9 -> 345.56304 | G63: General & Administrative | H63: =I63*Assumptions!$D$9 -> 66340 | I63: 310
B64: Utilities | C64: ='Source Data'!C126 -> 109101.86 | D64: =C64/Assumptions!$D$9 -> 509.82178 | G64: Utilities | H64: =I64*Assumptions!$D$9 -> 130540 | I64: 610
B65: Management | C65: ='Source Data'!C129 -> 191408 | D65: =C65/Assumptions!$D$9 -> 894.42991 | F65: 0.04 | G65: Reserves | H65: =F65*Assumptions!$F$36 -> 0 | I65: =H65/Assumptions!$D$9 -> 0
B66: Total | C66: =SUM(C57:C65) -> 1704481.6 | D66: =C66/Assumptions!$D$9 -> 7964.8671 | F66: 0.03 | G66: Management | H66: =F66*Assumptions!$F$36 -> 0 | I66: =H66/Assumptions!$D$9 -> 0
G67: Total | H67: =SUM(H57:H66) -> 1600720 | I67: =H67/Assumptions!$D$9 -> 7480

Sheet Investment Summary
B2: Unit Mix | H2: Pro Forma
B3: =Assumptions!B31 -> Unit Type | C3: =Assumptions!C31 -> # of Units | D3: =Assumptions!D31 -> SF | E3: =Assumptions!E31 -> Monthly Avg Rent | F3: =Assumptions!F31 -> Annual Rent | G3: =Assumptions!G31 -> Annual $/SF | H3: ='Annual Forecast'!B4 -> Resi Gross Potential Rent | I3: ='Annual Forecast'!C4 -> 0
B4: =Assumptions!B32 -> 1BD | C4: =Assumptions!C32 -> 53 | D4: =Assumptions!D32 -> 650 | E4: =Assumptions!E32 -> 2050 | F4: =Assumptions!F32 -> 0 | G4: =Assumptions!G32 -> 0 | H4: ='Annual Forecast'!B5 -> Vacancy | I4: ='Annual Forecast'!C5 -> 0
B5: =Assumptions!B33 -> 1 BD + Den | C5: =Assumptions!C33 -> 70 | D5: =Assumptions!D33 -> 725 | E5: =Assumptions!E33 -> 2150 | F5: =Assumptions!F33 -> 0 | G5: =Assumptions!G33 -> 0 | H5: ='Annual Forecast'!B6 -> Bad Debt | I5: ='Annual Forecast'!C6 -> 0
B6: =Assumptions!B34 -> 2 BD | C6: =Assumptions!C34 -> 84 | D6: =Assumptions!D34 -> 850 | E6: =Assumptions!E34 -> 2450 | F6: =Assumptions!F34 -> 0 | G6: =Assumptions!G34 -> 0 | H6: ='Annual Forecast'!B7 -> Net Rental Income | I6: =SUM(I3:I5) -> 0
B7: =Assumptions!B35 -> 2BD + 2 BA | C7: =Assumptions!C35 -> 7 | D7: =Assumptions!D35 -> 1100 | E7: =Assumptions!E35 -> 2800 | F7: =Assumptions!F35 -> 0 | G7: =Assumptions!G35 -> 0 | H7: ='Annual Forecast'!B8 -> Other Income | I7: ='Annual Forecast'!C8 -> 0
B8: =Assumptions!B36 -> Total | C8: =Assumptions!C36 -> 214 | D8: =Assumptions!D36 -> 767.75701 | E8: =Assumptions!E36 -> 2264.2523 | F8: =Assumptions!F36 -> 0 | G8: =Assumptions!G36 -> 0 | H8: ='Annual Forecast'!B9 -> Net Revenue | I8: =SUM(I6:I7) -> 0
H10: ='Annual Forecast'!B10 -> Expenses
H11: ='Annual Forecast'!B11 -> Taxes | I11: ='Annual Forecast'!C11 -> 0
B12: Sources and Uses | H12: ='Annual Forecast'!B12 -> Insurance | I12: ='Annual Forecast'!C12 -> 0
B13: Sources | D13: $/Unit | E13: % of Total | H13: ='Annual Forecast'!B13 -> Payroll | I13: ='Annual Forecast'!C13 -> 0
B14: Equity | C14: =C16-C15 -> 35494275 | D14: =C14/Assumptions!$D$9 -> 165861.1 | E14: =C14/$C$16 -> 0.41161856 | H14: ='Annual Forecast'!B14 -> Repairs & Maintenance | I14: ='Annual Forecast'!C14 -> 0
B15: Debt | C15: =Assumptions!K32 -> 50736714 | D15: =C15/Assumptions!$D$9 -> 237087.45 | E15: =C15/$C$16 -> 0.58838144 | H15: ='Annual Forecast'!B15 -> Contract Services | I15: ='Annual Forecast'!C15 -> 0
B16: Total | C16: =C20 -> 86230989 | D16: =C16/Assumptions!$D$9 -> 402948.55 | E16: =C16/$C$16 -> 1 | H16: ='Annual Forecast'!B16 -> Marketing | I16: ='Annual Forecast'!C16 -> 0
B17: Uses | H17: ='Annual Forecast'!B17 -> General & Administrative | I17: ='Annual Forecast'!C17 -> 0
B18: Purchase Price | C18: =Assumptions!D16 -> 85493946 | D18: =C18/Assumptions!$D$9 -> 399504.42 | E18: =C18/$C$20 -> 0.99145269 | H18: ='Annual Forecast'!B18 -> Utilities | I18: ='Annual Forecast'!C18 -> 0
B19: Closing Cost | C19: =Assumptions!D16*Assumptions!D23 -> 737043.31 | D19: =C19/Assumptions!$D$9 -> 3444.1276 | E19: =C19/$C$20 -> 0.0085473136 | H19: ='Annual Forecast'!B19 -> Reserves | I19: ='Annual Forecast'!C19 -> 0
B20: Total | C20: =SUM(C18:C19) -> 86230989 | D20: =C20/Assumptions!$D$9 -> 402948.55 | E20: =C20/$C$20 -> 1 | H20: ='Annual Forecast'!B20 -> Management | I20: ='Annual Forecast'!C20 -> 0
H21: ='Annual Forecast'!B21 -> Total Expenses | I21: =SUM(I11:I20) -> 0
H22: ='Annual Forecast'!B22 -> Net Operating Income | I22: =I21+I8 -> 0
A24: Returns | H24: Projected Value | I24: =I22/Assumptions!D27 -> 0
A25: Unlevered IRR
A26: Levered IRR
A27: Unlevered Equity Multiple | B27: Bank Refinance Loan Info | E27: HUD Refinance Loan Info | H27: Agency Refinance Loan Info
A28: Levered Equity Multiple | B28: LTV Constraint | D28: 0.631759 | E28: LTV Constraint | G28: 0.8516 | H28: LTV Constraint | J28: 0.75
B29: DSCR Constraint | D29: 1.25 | E29: DSCR Constraint | G29: 1.15 | H29: DSCR Constraint | J29: 1.2
B30: Debt Yield Constraint | D30: 0.08 | E30: Debt Yield Constraint | H30: Debt Yield Constraint
B31: Cap Rate | D31: =Assumptions!$D$27 -> 0.057887 | E31: Cap Rate | G31: =Assumptions!$D$27 -> 0.057887 | H31: Cap Rate | J31: =Assumptions!$D$27 -> 0.057887
B32: Spread | D32: 0.02 | E32: Spread | G32: 0.0175 | H32: Spread | J32: 0.0175
B33: Rate Index | C33: SOFR | D33: 0.04321 | E33: Rate Index | F33: 10-Year Treasury | G33: 0.04245 | H33: Rate Index | I33: 10-Year Treasury | J33: 0.04245
B34: Projected Rate | D34: =D33+D32 -> 0.06321 | E34: Projected Rate | G34: =G33+G32 -> 0.05995 | H34: Projected Rate | J34: =J33+J32 -> 0.05995
B35: Amortization | D35: 25 | E35: Amortization | G35: 35 | H35: Amortization | J35: 30
B37: Existing Mortgage | D37: =ABS(SUMIF('Monthly Cash Flow'!$F$38:$BZ$38,"<0",'Monthly Cash Flow'!$F$38:$BZ$38)) -> 0 | E37: Existing Mortgage | G37: =ABS(SUMIF('Monthly Cash Flow'!$F$38:$BZ$38,"<0",'Monthly Cash Flow'!$F$38:$BZ$38)) -> 0 | H37: Existing Mortgage | J37: =ABS(SUMIF('Monthly Cash Flow'!$F$38:$BZ$38,"<0",'Monthly Cash Flow'!$F$38:$BZ$38)) -> 0
B39: Loan Sizing | E39: Loan Sizing | H39: Loan Sizing
B40: LTV Proceeds | D40: =D28*'Annual Forecast'!C22/'Investment Summary'!D31 -> 0 | E40: LTV Proceeds | G40: =G28*'Annual Forecast'!E22/'Investment Summary'!G31 -> 0 | H40: LTV Proceeds | J40: =J28*'Annual Forecast'!C22/'Investment Summary'!J31 -> 0
B41: DSCR Proceeds | D41: =PV(D34/12,D35*12,-'Annual Forecast'!C22/'Investment Summary'!D29/12,0,0) -> 0 | E41: DSCR Proceeds | G41: =PV(G34/12,G35*12,-'Annual Forecast'!C22/'Investment Summary'!G29/12,0,0) -> 0 | H41: DSCR Proceeds | J41: =PV(J34/12,J35*12,-'Annual Forecast'!C22/'Investment Summary'!J29/12,0,0) -> 0
B42: Debt Yield Proceeds | D42: ='Annual Forecast'!C22/'Investment Summary'!D30 -> 0 | E42: Debt Yield Proceeds | H42: Debt Yield Proceeds
B44: Excess Proceeds/Shortfall | D44: =MIN(D40:D42)-D37 -> 0 | G44: =MIN(G40:G42)-G37 -> 0 | J44: =MIN(J40:J42)-J37 -> 0

Sheet Annual Forecast
B2: Five-Year Operating Forecast
B3: Year | C3: 1 | D3: =C3+1 -> 2 | E3: =D3+1 -> 3 | F3: =E3+1 -> 4 | G3: =F3+1 -> 5
B4: Resi Gross Potential Rent
B5: Vacancy
B6: Bad Debt
B7: Net Rental Income
B8: Other Income
B9: Net Revenue
B10: Expenses
B11: =Assumptions!G57 -> Taxes
B12: =Assumptions!G58 -> Insurance
B13: =Assumptions!G59 -> Payroll
B14: =Assumptions!G60 -> Repairs & Maintenance
B15: =Assumptions!G61 -> Contract Services
B16: =Assumptions!G62 -> Marketing
B17: =Assumptions!G63 -> General & Administrative
B18: =Assumptions!G64 -> Utilities
B19: =Assumptions!G65 -> Reserves
B20: =Assumptions!G66 -> Management
B21: Total Expenses
B22: Net Operating Income
B24: Exp Ratio
B25: NOI/Unit
B27: Projected Value
B28: /Unit

Sheet Monthly Cash Flow
B2: Rental Growth | C2: 0.029415 | E2: Five-Year Operating Forecast | BN2: 0
B3: Other Income Growth | C3: 0 | E3: Year | G3: 1 | H3: 1 | I3: 1 | J3: 1 | K3: 1 | L3: 1 | M3: 1 | N3: 1 | O3: 1 | P3: 1 | Q3: 1 | R3: 1 | S3: =G3+1 -> 2 | T3: =H3+1 -> 2 | U3: =I3+1 -> 2 | V3: =J3+1 -> 2 | W3: =K3+1 -> 2 | X3: =L3+1 -> 2 | Y3: =M3+1 -> 2 | Z3: =N3+1 -> 2 | ... BZ3: =BN3+1 -> 6
B4: Expense Growth | C4: 0.031295 | E4: Month | F4: 0 | G4: =F4+1 -> 1 | H4: =G4+1 -> 2 | I4: =H4+1 -> 3 | J4: =I4+1 -> 4 | K4: =J4+1 -> 5 | L4: =K4+1 -> 6 | M4: =L4+1 -> 7 | N4: =M4+1 -> 8 | ... BZ4: =BY4+1 -> 72
B5: Vacancy | C5: 0.05 | E5: Month Ending | F5: =Assumptions!D17 -> 45778 | G5: =EOMONTH(F5,1) -> 45838 | H5: =EOMONTH(G5,1) -> 45869 | I5: =EOMONTH(H5,1) -> 45900 | J5: =EOMONTH(I5,1) -> 45930 | K5: =EOMONTH(J5,1) -> 45961 | L5: =EOMONTH(K5,1) -> 45991 | M5: =EOMONTH(L5,1) -> 46022 | N5: =EOMONTH(M5,1) -> 46053 | ... BZ5: =EOMONTH(BY5,1) -> 47999
B6: Bad Debt | C6: 0.06 | E6: Gross Potential Rent
B7: Capital Improvements (% of NOI) | C7: 0.015 | E7: Vacancy
E8: Bad Debt
E9: Net Rental Income
E10: Other Income
E11: Net Revenue
E12: Expenses
E13: =Assumptions!G57 -> Taxes
E14: =Assumptions!G58 -> Insurance
E15: =Assumptions!G59 -> Payroll
E16: =Assumptions!G60 -> Repairs & Maintenance
E17: =Assumptions!G61 -> Contract Services
E18: =Assumptions!G62 -> Marketing
E19: =Assumptions!G63 -> General & Administrative
E20: =Assumptions!G64 -> Utilities
E21: =Assumptions!G65 -> Reserves
E22: =Assumptions!G66 -> Management
E23: Total Expenses
E24: Exp Ratio
E25: Net Operating Income
E26: Capital Improvements
E27: Cash Flow Before Debt Service
E28: Principal Payment
E29: Interest Payments
E30: Cash Flow After Debt Service
E31: Acquisition Price
E32: Closing Cost
E33: Sale Proceeds
E34: Cost Of Sale
... E39: Total Levered Cash Flows
B41: 1
B42: =B41+1 -> 2
B43: =B42+1 -> 3
B44: =B43+1 -> 4
B45: =B44+1 -> 5
