Workbook

Sheet Google Drivers
B2: Google (Alphabet) — Operating Model Assumptions
B3: 3-Year Historical (2021-2023) | 5-Year Projections (2024-2028)
B4: Figures in $mm
B5: Case selector
B6: Chosen case: | D6: Base
B8: Actuals | G8: Forecast
D9: 2021 | E9: 2022 | F9: 2023 | G9: 2024 | H9: 2025 | I9: 2026 | J9: 2027 | K9: 2028
B11: Revenue Assumptions — 1
B13: Growth rates — Revenue (%)
C14: Case | D14: 2021 | E14: 2022 | F14: 2023 | G14: 2024 | H14: 2025 | I14: 2026 | J14: 2027 | K14: 2028
B15: Google Search | C15: Base | G15: 0.085 | H15: 0.075 | I15: 0.065 | J15: 0.055 | K15: 0.05
C16: Bull | G16: 0.105 | H16: 0.095 | I16: 0.085 | J16: 0.075 | K16: 0.07
C17: Bear | G17: 0.06 | H17: 0.05 | I17: 0.04 | J17: 0.035 | K17: 0.03
B19: YouTube Ads | C19: Base | G19: 0.15 | H19: 0.13 | I19: 0.11 | J19: 0.1 | K19: 0.09
C20: Bull | G20: 0.18 | H20: 0.16 | I20: 0.14 | J20: 0.12 | K20: 0.11
C21: Bear | G21: 0.12 | H21: 0.1 | I21: 0.08 | J21: 0.07 | K21: 0.06
B23: Google Cloud | C23: Base | G23: 0.28 | H23: 0.25 | I23: 0.22 | J23: 0.2 | K23: 0.18
C24: Bull | G24: 0.32 | H24: 0.3 | I24: 0.27 | J24: 0.24 | K24: 0.22
C25: Bear | G25: 0.24 | H25: 0.2 | I25: 0.17 | J25: 0.15 | K25: 0.14
B27: Other Revenues | C27: Base | G27: 0.05 | H27: 0.045 | I27: 0.04 | J27: 0.035 | K27: 0.03
C28: Bull | G28: 0.07 | H28: 0.06 | I28: 0.055 | J28: 0.05 | K28: 0.045
C29: Bear | G29: 0.03 | H29: 0.025 | I29: 0.02 | J29: 0.015 | K29: 0.01
B31: Operating Expense Assumptions — 2
B33: Expenses — Operating (% of Revenue)
B35: R&D | C35: Base | D35: 0.151 | E35: 0.148 | F35: 0.145 | G35: 0.143 | H35: 0.14 | I35: 0.138 | J35: 0.135 | K35: 0.133
C36: Bull | D36: 0.151 | E36: 0.148 | F36: 0.145 | G36: 0.138 | H36: 0.135 | I36: 0.132 | J36: 0.13 | K36: 0.128
C37: Bear | D37: 0.151 | E37: 0.148 | F37: 0.145 | G37: 0.148 | H37: 0.145 | I37: 0.143 | J37: 0.14 | K37: 0.138
B39: S&M | C39: Base | D39: 0.115 | E39: 0.112 | F39: 0.108 | G39: 0.105 | H39: 0.103 | I39: 0.1 | J39: 0.098 | K39: 0.095
C40: Bull | D40: 0.115 | E40: 0.112 | F40: 0.108 | G40: 0.102 | H40: 0.1 | I40: 0.097 | J40: 0.095 | K40: 0.092
C41: Bear | D41: 0.115 | E41: 0.112 | F41: 0.108 | G41: 0.108 | H41: 0.106 | I41: 0.103 | J41: 0.101 | K41: 0.098
B43: G&A | C43: Base | D43: 0.068 | E43: 0.065 | F43: 0.063 | G43: 0.062 | H43: 0.06 | I43: 0.058 | J43: 0.057 | K43: 0.055
C44: Bull | D44: 0.068 | E44: 0.065 | F44: 0.063 | G44: 0.06 | H44: 0.058 | I44: 0.056 | J44: 0.055 | K44: 0.053
C45: Bear | D45: 0.068 | E45: 0.065 | F45: 0.063 | G45: 0.064 | H45: 0.062 | I45: 0.06 | J45: 0.059 | K45: 0.057
B47: SBC | C47: Base | D47: 0.092 | E47: 0.095 | F47: 0.098 | G47: 0.095 | H47: 0.093 | I47: 0.09 | J47: 0.088 | K47: 0.085
C48: Bull | D48: 0.092 | E48: 0.095 | F48: 0.098 | G48: 0.092 | H48: 0.09 | I48: 0.087 | J48: 0.085 | K48: 0.082
C49: Bear | D49: 0.092 | E49: 0.095 | F49: 0.098 | G49: 0.098 | H49: 0.096 | I49: 0.093 | J49: 0.091 | K49: 0.088
B51: Balance Sheet & Cash Flow Assumptions — 3
B53: Working Capital Metrics
B55: Days Sales Outstanding — DSO | C55: Base | D55: 48 | E55: 47 | F55: 46 | G55: 46 | H55: 45 | I55: 45 | J55: 44 | K55: 44
C56: Bull | D56: 48 | E56: 47 | F56: 46 | G56: 45 | H56: 44 | I56: 43 | J56: 42 | K56: 42
C57: Bear | D57: 48 | E57: 47 | F57: 46 | G57: 47 | H57: 47 | I57: 46 | J57: 46 | K57: 45
B59: Days Payable Outstanding — DPO | C59: Base | D59: 32 | E59: 33 | F59: 34 | G59: 34 | H59: 35 | I59: 35 | J59: 36 | K59: 36
C60: Bull | D60: 32 | E60: 33 | F60: 34 | G60: 35 | H60: 36 | I60: 37 | J60: 38 | K60: 38
C61: Bear | D61: 32 | E61: 33 | F61: 34 | G61: 33 | H61: 33 | I61: 34 | J61: 34 | K61: 34
B63: ='Google Model'!$B$66 -> Other current assets | C63: % Increase | E63: 0.058823529 | F63: 0.055555556 | G63: 0.05 | H63: 0.05 | I63: 0.05 | J63: 0.05 | K63: 0.05
B64: ='Google Model'!$B$74 -> Other Long-term Assets | C64: % Increase | E64: 0.085714286 | F64: 0.10526316 | G64: 0.08 | H64: 0.08 | I64: 0.08 | J64: 0.08 | K64: 0.08
B65: ='Google Model'!$B$83 -> Accrued Expenses | C65: % Increase | E65: 0.083333333 | F65: 0.076923077 | G65: 0.06 | H65: 0.06 | I65: 0.06 | J65: 0.06 | K65: 0.06
B67: Capital Expenditure
B69: CapEx — % of Revenue | C69: Base | D69: 0.125 | E69: 0.132 | F69: 0.14 | G69: 0.135 | H69: 0.13 | I69: 0.125 | J69: 0.12 | K69: 0.115
C70: Bull | D70: 0.125 | E70: 0.132 | F70: 0.14 | G70: 0.13 | H70: 0.125 | I70: 0.12 | J70: 0.115 | K70: 0.11
C71: Bear | D71: 0.125 | E71: 0.132 | F71: 0.14 | G71: 0.14 | H71: 0.135 | I71: 0.13 | J71: 0.125 | K71: 0.12
B73: D&A — % of Prior Year CapEx | C73: Base | D73: 0.7 | E73: 0.7 | F73: 0.7 | G73: 0.7 | H73: 0.7 | I73: 0.7 | J73: 0.7 | K73: 0.7
C74: Bull | D74: 0.7 | E74: 0.7 | F74: 0.7 | G74: 0.68 | H74: 0.68 | I74: 0.68 | J74: 0.68 | K74: 0.68
C75: Bear | D75: 0.7 | E75: 0.7 | F75: 0.7 | G75: 0.72 | H75: 0.72 | I75: 0.72 | J75: 0.72 | K75: 0.72
B77: Other Financial Assumptions — 4
B79: Tax Rate
B81: Effective Tax Rate | C81: Base | D81: 0.162 | E81: 0.16 | F81: 0.158 | G81: 0.165 | H81: 0.17 | I81: 0.175 | J81: 0.18 | K81: 0.185
C82: Bull | D82: 0.162 | E82: 0.16 | F82: 0.158 | G82: 0.16 | H82: 0.165 | I82: 0.17 | J82: 0.175 | K82: 0.18
C83: Bear | D83: 0.162 | E83: 0.16 | F83: 0.158 | G83: 0.17 | H83: 0.175 | I83: 0.18 | J83: 0.185 | K83: 0.19
B86: Interest Rates
B88: Interest Income Rate — on cash | C88: Base | D88: 0.005 | E88: 0.015 | F88: 0.025 | G88: 0.035 | H88: 0.03 | I88: 0.025 | J88: 0.025 | K88: 0.02
C89: Bull | D89: 0.01 | E89: 0.02 | F89: 0.03 | G89: 0.04 | H89: 0.045 | I89: 0.04 | J89: 0.035 | K89: 0.035
C90: Bear | D90: 0.0025 | E90: 0.0125 | F90: 0.0225 | G90: 0.0325 | H90: 0.0375 | I90: 0.0325 | J90: 0.0275 | K90: 0.0275
B92: Interest Expense Rate — on LT debt | C92: Base | D92: 0.03 | E92: 0.035 | F92: 0.04 | G92: 0.045 | H92: 0.04 | I92: 0.035 | J92: 0.03 | K92: 0.03
C93: Bull | D93: 0.025 | E93: 0.03 | F93: 0.035 | G93: 0.04 | H93: 0.035 | I93: 0.03 | J93: 0.025 | K93: 0.025
C94: Bear | D94: 0.04 | E94: 0.045 | F94: 0.05 | G94: 0.055 | H94: 0.05 | I94: 0.045 | J94: 0.04 | K94: 0.04
B96: Share Buyback
B98: Buyback — % of FCF | C98: Base | D98: 0.75 | E98: 0.75 | F98: 0.75 | G98: 0.7 | H98: 0.7 | I98: 0.65 | J98: 0.65 | K98: 0.6
C99: Bull | D99: 0.75 | E99: 0.75 | F99: 0.75 | G99: 0.75 | H99: 0.75 | I99: 0.7 | J99: 0.7 | K99: 0.65
C100: Bear | D100: 0.75 | E100: 0.75 | F100: 0.75 | G100: 0.65 | H100: 0.65 | I100: 0.6 | J100: 0.6 | K100: 0.55
B102: International Revenue Mix
B104: US Revenue % | D104: 0.6 | E104: 0.6 | F104: 0.6 | G104: 0.6 | H104: 0.6 | I104: 0.6 | J104: 0.6 | K104: 0.6
B105: International Revenue % | D105: =1-D104 -> 0.4 | E105: =1-E104 -> 0.4 | F105: =1-F104 -> 0.4 | G105: =1-G104 -> 0.4 | H105: =1-H104 -> 0.4 | I105: =1-I104 -> 0.4 | J105: =1-J104 -> 0.4 | K105: =1-K104 -> 0.4
B107: FX Impact on Int'l Revenue
B108: Base Case | D108: 0 | E108: =D108 -> 0 | F108: =E108 -> 0 | G108: =F108 -> 0 | H108: =G108 -> 0 | I108: =H108 -> 0 | J108: =I108 -> 0 | K108: 0.02
B109: Bull Case | D109: 0.01 | E109: =D109 -> 0.01 | F109: =E109 -> 0.01 | G109: =F109 -> 0.01 | H109: =G109 -> 0.01 | I109: =H109 -> 0.01 | J109: =I109 -> 0.01 | K109: 0.03
B110: Bear Case | D110: -0.02 | E110: =D110 -> -0.02 | F110: =E110 -> -0.02 | G110: =F110 -> -0.02 | H110: =G110 -> -0.02 | I110: =H110 -> -0.02 | J110: =I110 -> -0.02 | K110: 0.01

Sheet Google Model
B2: Google (Alphabet) — Income Statement
B3: Figures in $mm
B5: Chosen case: | D5: ='Google Drivers'!$D$6 -> Base
B7: Actuals | F7: Forecast
C8: 2021 | D8: 2022 | E8: 2023 | F8: 2024 | G8: 2025 | H8: 2026 | I8: 2027 | J8: 2028
B10: P&L statement
B12: Google Search | C12: 148951 | D12: 162450 | E12: 175033 | F12: =E12*(1+INDEX('Google Drivers'!G$15:G$17,MATCH($D$5,'Google Drivers'!$C$15:$C$17,0))) -> 189910.8 | G12: =F12*(1+INDEX('Google Drivers'!H$15:H$17,MATCH($D$5,'Google Drivers'!$C$15:$C$17,0))) -> 204154.12 | H12: =G12*(1+INDEX('Google Drivers'!I$15:I$17,MATCH($D$5,'Google Drivers'!$C$15:$C$17,0))) -> 217424.13 | I12: =H12*(1+INDEX('Google Drivers'!J$15:J$17,MATCH($D$5,'Google Drivers'!$C$15:$C$17,0))) -> 229382.46 | J12: =I12*(1+INDEX('Google Drivers'!K$15:K$17,MATCH($D$5,'Google Drivers'!$C$15:$C$17,0))) -> 240851.58
B13: YouTube Ads | C13: 28845 | D13: 29243 | E13: 31865 | F13: =E13*(1+INDEX('Google Drivers'!G$19:G$21,MATCH($D$5,'Google Drivers'!$C$19:$C$21,0))) -> 36644.75 | G13: =F13*(1+INDEX('Google Drivers'!H$19:H$21,MATCH($D$5,'Google Drivers'!$C$19:$C$21,0))) -> 41408.567 | H13: =G13*(1+INDEX('Google Drivers'!I$19:I$21,MATCH($D$5,'Google Drivers'!$C$19:$C$21,0))) -> 45963.51 | I13: =H13*(1+INDEX('Google Drivers'!J$19:J$21,MATCH($D$5,'Google Drivers'!$C$19:$C$21,0))) -> 50559.861 | J13: =I13*(1+INDEX('Google Drivers'!K$19:K$21,MATCH($D$5,'Google Drivers'!$C$19:$C$21,0))) -> 55110.248
B14: Google Cloud | C14: 13059 | D14: 19206 | E14: 26280 | F14: =E14*(1+INDEX('Google Drivers'!G$23:G$25,MATCH($D$5,'Google Drivers'!$C$23:$C$25,0))) -> 33638.4 | G14: =F14*(1+INDEX('Google Drivers'!H$23:H$25,MATCH($D$5,'Google Drivers'!$C$23:$C$25,0))) -> 42048 | H14: =G14*(1+INDEX('Google Drivers'!I$23:I$25,MATCH($D$5,'Google Drivers'!$C$23:$C$25,0))) -> 51298.56 | I14: =H14*(1+INDEX('Google Drivers'!J$23:J$25,MATCH($D$5,'Google Drivers'!$C$23:$C$25,0))) -> 61558.272 | J14: =I14*(1+INDEX('Google Drivers'!K$23:K$25,MATCH($D$5,'Google Drivers'!$C$23:$C$25,0))) -> 72638.761
B15: Other Revenues | C15: 28032 | D15: 29071 | E15: 30300 | F15: =E15*(1+INDEX('Google Drivers'!G$27:G$29,MATCH($D$5,'Google Drivers'!$C$27:$C$29,0))) -> 31815 | G15: =F15*(1+INDEX('Google Drivers'!H$27:H$29,MATCH($D$5,'Google Drivers'!$C$27:$C$29,0))) -> 33246.675 | H15: =G15*(1+INDEX('Google Drivers'!I$27:I$29,MATCH($D$5,'Google Drivers'!$C$27:$C$29,0))) -> 34576.542 | I15: =H15*(1+INDEX('Google Drivers'!J$27:J$29,MATCH($D$5,'Google Drivers'!$C$27:$C$29,0))) -> 35786.721 | J15: =I15*(1+INDEX('Google Drivers'!K$27:K$29,MATCH($D$5,'Google Drivers'!$C$27:$C$29,0))) -> 36860.323
B16: Revenue — Total | C16: =SUM(C12:C15) -> 218887 | D16: =SUM(D12:D15) -> 239970 | E16: =SUM(E12:E15) -> 263478 | F16: =SUM(F12:F15) -> 292008.95 | G16: =SUM(G12:G15) -> 320857.36 | H16: =SUM(H12:H15) -> 349262.74 | I16: =SUM(I12:I15) -> 377287.31 | J16: =SUM(J12:J15) -> 405460.92
B17: YoY Growth % | D17: =D16/C16-1 -> 0.096319105 | E17: =E16/D16-1 -> 0.097962245 | F17: =F16/E16-1 -> 0.10828591 | G17: =G16/F16-1 -> 0.09879287 | H17: =H16/G16-1 -> 0.088529642 | I17: =I16/H16-1 -> 0.080239217 | J17: =J16/I16-1 -> 0.074674128
B19: Quarterly Seasonality
B20: Seasonality Factors — % of Annual
B21: Q1 Factor | F21: 0.22
B22: Q2 Factor | F22: =F21+(($F$24-$F$21)/3) -> 0.24
B23: Q3 Factor | F23: =F22+(($F$24-$F$21)/3) -> 0.26
B24: Q4 Factor | F24: 0.28
B25: 2024 Quarterly Revenue — $mm
B26: Q1 2024 | F26: =$F$16*F21 -> 64241.97
B27: Q2 2024 | F27: =$F$16*F22 -> 70082.149
B28: Q3 2024 | F28: =$F$16*F23 -> 75922.328
B29: Q4 2024 | F29: =$F$16*F24 -> 81762.507
B30: Total Check | F30: =SUM(F26:F29) -> 292008.95
B32: Cost of sales | C32: =C16*(1-C34) -> 99593.585 | D32: =D16*(1-D34) -> 108466.44 | E32: =E16*(1-E34) -> 118565.1 | F32: =F16*(1-F34) -> 130820.01 | G32: =G16*(1-G34) -> 143102.38 | H32: =H16*(1-H34) -> 155072.66 | I32: =I16*(1-I34) -> 166760.99 | J32: =J16*(1-J34) -> 178402.8
B33: Profit — Gross | C33: =C16-C32 -> 119293.41 | D33: =D16-D32 -> 131503.56 | E33: =E16-E32 -> 144912.9 | F33: =F16-F32 -> 161188.94 | G33: =G16-G32 -> 177754.98 | H33: =H16-H32 -> 194190.09 | I33: =I16-I32 -> 210526.32 | J33: =J16-J32 -> 227058.11
B34: Gross Margin (%) | C34: 0.545 | D34: 0.548 | E34: 0.55 | F34: 0.552 | G34: 0.554 | H34: 0.556 | I34: 0.558 | J34: 0.56
B36: R&D | C36: =C16*INDEX('Google Drivers'!D$35:D$37,MATCH($D$5,'Google Drivers'!$C$35:$C$37,0)) -> 33051.937 | D36: =D16*INDEX('Google Drivers'!E$35:E$37,MATCH($D$5,'Google Drivers'!$C$35:$C$37,0)) -> 35515.56 | E36: =E16*INDEX('Google Drivers'!F$35:F$37,MATCH($D$5,'Google Drivers'!$C$35:$C$37,0)) -> 38204.31 | F36: =F16*INDEX('Google Drivers'!G$35:G$37,MATCH($D$5,'Google Drivers'!$C$35:$C$37,0)) -> 41757.281 | G36: =G16*INDEX('Google Drivers'!H$35:H$37,MATCH($D$5,'Google Drivers'!$C$35:$C$37,0)) -> 44920.03 | H36: =H16*INDEX('Google Drivers'!I$35:I$37,MATCH($D$5,'Google Drivers'!$C$35:$C$37,0)) -> 48198.259 | I36: =I16*INDEX('Google Drivers'!J$35:J$37,MATCH($D$5,'Google Drivers'!$C$35:$C$37,0)) -> 50933.787 | J36: =J16*INDEX('Google Drivers'!K$35:K$37,MATCH($D$5,'Google Drivers'!$C$35:$C$37,0)) -> 53926.302
B37: S&M | C37: =C16*INDEX('Google Drivers'!D$39:D$41,MATCH($D$5,'Google Drivers'!$C$39:$C$41,0)) -> 25172.005 | D37: =D16*INDEX('Google Drivers'!E$39:E$41,MATCH($D$5,'Google Drivers'!$C$39:$C$41,0)) -> 26876.64 | E37: =E16*INDEX('Google Drivers'!F$39:F$41,MATCH($D$5,'Google Drivers'!$C$39:$C$41,0)) -> 28455.624 | F37: =F16*INDEX('Google Drivers'!G$39:G$41,MATCH($D$5,'Google Drivers'!$C$39:$C$41,0)) -> 30660.94 | G37: =G16*INDEX('Google Drivers'!H$39:H$41,MATCH($D$5,'Google Drivers'!$C$39:$C$41,0)) -> 33048.308 | H37: =H16*INDEX('Google Drivers'!I$39:I$41,MATCH($D$5,'Google Drivers'!$C$39:$C$41,0)) -> 34926.274 | I37: =I16*INDEX('Google Drivers'!J$39:J$41,MATCH($D$5,'Google Drivers'!$C$39:$C$41,0)) -> 36974.157 | J37: =J16*INDEX('Google Drivers'!K$39:K$41,MATCH($D$5,'Google Drivers'!$C$39:$C$41,0)) -> 38518.787
B38: G&A | C38: =C16*INDEX('Google Drivers'!D$43:D$45,MATCH($D$5,'Google Drivers'!$C$43:$C$45,0)) -> 14884.316 | D38: =D16*INDEX('Google Drivers'!E$43:E$45,MATCH($D$5,'Google Drivers'!$C$43:$C$45,0)) -> 15598.05 | E38: =E16*INDEX('Google Drivers'!F$43:F$45,MATCH($D$5,'Google Drivers'!$C$43:$C$45,0)) -> 16599.114 | F38: =F16*INDEX('Google Drivers'!G$43:G$45,MATCH($D$5,'Google Drivers'!$C$43:$C$45,0)) -> 18104.555 | G38: =G16*INDEX('Google Drivers'!H$43:H$45,MATCH($D$5,'Google Drivers'!$C$43:$C$45,0)) -> 19251.441 | H38: =H16*INDEX('Google Drivers'!I$43:I$45,MATCH($D$5,'Google Drivers'!$C$43:$C$45,0)) -> 20257.239 | I38: =I16*INDEX('Google Drivers'!J$43:J$45,MATCH($D$5,'Google Drivers'!$C$43:$C$45,0)) -> 21505.377 | J38: =J16*INDEX('Google Drivers'!K$43:K$45,MATCH($D$5,'Google Drivers'!$C$43:$C$45,0)) -> 22300.35
B39: SBC | C39: =C16*INDEX('Google Drivers'!D$47:D$49,MATCH($D$5,'Google Drivers'!$C$47:$C$49,0)) -> 20137.604 | D39: =D16*INDEX('Google Drivers'!E$47:E$49,MATCH($D$5,'Google Drivers'!$C$47:$C$49,0)) -> 22797.15 | E39: =E16*INDEX('Google Drivers'!F$47:F$49,MATCH($D$5,'Google Drivers'!$C$47:$C$49,0)) -> 25820.844 | F39: =F16*INDEX('Google Drivers'!G$47:G$49,MATCH($D$5,'Google Drivers'!$C$47:$C$49,0)) -> 27740.851 | G39: =G16*INDEX('Google Drivers'!H$47:H$49,MATCH($D$5,'Google Drivers'!$C$47:$C$49,0)) -> 29839.734 | H39: =H16*INDEX('Google Drivers'!I$47:I$49,MATCH($D$5,'Google Drivers'!$C$47:$C$49,0)) -> 31433.647 | I39: =I16*INDEX('Google Drivers'!J$47:J$49,MATCH($D$5,'Google Drivers'!$C$47:$C$49,0)) -> 33201.284 | J39: =J16*INDEX('Google Drivers'!K$47:K$49,MATCH($D$5,'Google Drivers'!$C$47:$C$49,0)) -> 34464.178
B40: Operating Expenses — Total | C40: =SUM(C36:C39) -> 93245.862 | D40: =SUM(D36:D39) -> 100787.4 | E40: =SUM(E36:E39) -> 109079.89 | F40: =SUM(F36:F39) -> 118263.63 | G40: =SUM(G36:G39) -> 127059.51 | H40: =SUM(H36:H39) -> 134815.42 | I40: =SUM(I36:I39) -> 142614.6 | J40: =SUM(J36:J39) -> 149209.62
B42: EBIT / Operating Income | C42: =C33-C40 -> 26047.553 | D42: =D33-D40 -> 30716.16 | E42: =E33-E40 -> 35833.008 | F42: =F33-F40 -> 42925.316 | G42: =G33-G40 -> 50695.463 | H42: =H33-H40 -> 59374.667 | I42: =I33-I40 -> 67911.717 | J42: =J33-J40 -> 77848.496
B43: Operating Margin (%) | C43: =C42/C16 -> 0.119 | D43: =D42/D16 -> 0.128 | E43: =E42/E16 -> 0.136 | F43: =F42/F16 -> 0.147 | G43: =G42/G16 -> 0.158 | H43: =H42/H16 -> 0.17 | I43: =I42/I16 -> 0.18 | J43: =J42/J16 -> 0.192
B45: Interest (Expense) / Income | C45: =(C$64*INDEX('Google Drivers'!D$88:D$90,MATCH($D$5,'Google Drivers'!$C$88:$C$90,0)))-(C86*INDEX('Google Drivers'!D$92:D$94,MATCH($D$5,'Google Drivers'!$C$92:$C$94,0))) -> 0 | D45: =(D$64*INDEX('Google Drivers'!E$88:E$90,MATCH($D$5,'Google Drivers'!$C$88:$C$90,0)))-(D86*INDEX('Google Drivers'!E$92:E$94,MATCH($D$5,'Google Drivers'!$C$92:$C$94,0))) -> 972.47681 | E45: =(E$64*INDEX('Google Drivers'!F$88:F$90,MATCH($D$5,'Google Drivers'!$C$88:$C$90,0)))-(E86*INDEX('Google Drivers'!F$92:F$94,MATCH($D$5,'Google Drivers'!$C$92:$C$94,0))) -> 2137.5582 | F45: =(F$64*INDEX('Google Drivers'!G$88:G$90,MATCH($D$5,'Google Drivers'!$C$88:$C$90,0)))-(F86*INDEX('Google Drivers'!G$92:G$94,MATCH($D$5,'Google Drivers'!$C$92:$C$94,0))) -> 3647.2704 | G45: =(G$64*INDEX('Google Drivers'!H$88:H$90,MATCH($D$5,'Google Drivers'!$C$88:$C$90,0)))-(G86*INDEX('Google Drivers'!H$92:H$94,MATCH($D$5,'Google Drivers'!$C$92:$C$94,0))) -> 3628.5766 | H45: =(H$64*INDEX('Google Drivers'!I$88:I$90,MATCH($D$5,'Google Drivers'!$C$88:$C$90,0)))-(H86*INDEX('Google Drivers'!I$92:I$94,MATCH($D$5,'Google Drivers'!$C$92:$C$94,0))) -> 3565.6401 | I45: =(I$64*INDEX('Google Drivers'!J$88:J$90,MATCH($D$5,'Google Drivers'!$C$88:$C$90,0)))-(I86*INDEX('Google Drivers'!J$92:J$94,MATCH($D$5,'Google Drivers'!$C$92:$C$94,0))) -> 4272.5338 | J45: =(J$64*INDEX('Google Drivers'!K$88:K$90,MATCH($D$5,'Google Drivers'!$C$88:$C$90,0)))-(J86*INDEX('Google Drivers'!K$92:K$94,MATCH($D$5,'Google Drivers'!$C$92:$C$94,0))) -> 4000.4265
B47: Pre-tax Income | C47: =C42+C45 -> 26047.553 | D47: =D42+D45 -> 31688.637 | E47: =E42+E45 -> 37970.566 | F47: =F42+F45 -> 46572.587 | G47: =G42+G45 -> 54324.039 | H47: =H42+H45 -> 62940.307 | I47: =I42+I45 -> 72184.25 | J47: =J42+J45 -> 81848.922
B48: Tax Expense / Provision | C48: =C47*INDEX('Google Drivers'!D$81:D$83,MATCH($D$5,'Google Drivers'!$C$81:$C$83,0)) -> 4219.7036 | D48: =D47*INDEX('Google Drivers'!E$81:E$83,MATCH($D$5,'Google Drivers'!$C$81:$C$83,0)) -> 5070.1819 | E48: =E47*INDEX('Google Drivers'!F$81:F$83,MATCH($D$5,'Google Drivers'!$C$81:$C$83,0)) -> 5999.3495 | F48: =F47*INDEX('Google Drivers'!G$81:G$83,MATCH($D$5,'Google Drivers'!$C$81:$C$83,0)) -> 7684.4768 | G48: =G47*INDEX('Google Drivers'!H$81:H$83,MATCH($D$5,'Google Drivers'!$C$81:$C$83,0)) -> 9235.0866 | H48: =H47*INDEX('Google Drivers'!I$81:I$83,MATCH($D$5,'Google Drivers'!$C$81:$C$83,0)) -> 11014.554 | I48: =I47*INDEX('Google Drivers'!J$81:J$83,MATCH($D$5,'Google Drivers'!$C$81:$C$83,0)) -> 12993.165 | J48: =J47*INDEX('Google Drivers'!K$81:K$83,MATCH($D$5,'Google Drivers'!$C$81:$C$83,0)) -> 15142.051
B50: Net income | C50: =C47-C48 -> 21827.849 | D50: =D47-D48 -> 26618.455 | E50: =E47-E48 -> 31971.217 | F50: =F47-F48 -> 38888.11 | G50: =G47-G48 -> 45088.952 | H50: =H47-H48 -> 51925.753 | I50: =I47-I48 -> 59191.085 | J50: =J47-J48 -> 66706.872
B51: Net Margin (%) | C51: =C50/C16 -> 0.099722 | D51: =D50/D16 -> 0.11092409 | E51: =E50/E16 -> 0.12134302 | F51: =F50/F16 -> 0.13317437 | G51: =G50/G16 -> 0.14052647 | H51: =H50/H16 -> 0.14867246 | I51: =I50/I16 -> 0.15688597 | J51: =J50/J16 -> 0.16452109
B53: EPS calculation
B55: Basic Shares — Outstanding | C55: 13000 | D55: 12800 | E55: 12600 | F55: 12400 | G55: 12200 | H55: 12000 | I55: 11800 | J55: 11600
B56: EPS — Basic | C56: =C50/C55 -> 1.6790653 | D56: =D50/D55 -> 2.0795668 | E56: =E50/E55 -> 2.5373982 | F56: =F50/F55 -> 3.1361379 | G56: =G50/G55 -> 3.6958158 | H56: =H50/H55 -> 4.3271461 | I56: =I50/I55 -> 5.0161937 | J56: =J50/J55 -> 5.7505924
B59: Balance sheet schedule
B61: Assets section
B63: Assets — Current
B64: Cash and equivalents | C64: 90000 | D64: =D$121 -> 97498.454 | E64: =E$121 -> 106302.33 | F64: =F$121 -> 120279.15 | G64: =G$121 -> 136952.55 | H64: =H$121 -> 158725.6 | I64: =I$121 -> 184101.35 | J64: =J$121 -> 215771.32
B65: Receivables | C65: =C$16*INDEX('Google Drivers'!D$55:D$57,MATCH($D$5,'Google Drivers'!$C$55:$C$57,0))/365 -> 28785.14 | D65: =D$16*INDEX('Google Drivers'!E$55:E$57,MATCH($D$5,'Google Drivers'!$C$55:$C$57,0))/365 -> 30900.247 | E65: =E$16*INDEX('Google Drivers'!F$55:F$57,MATCH($D$5,'Google Drivers'!$C$55:$C$57,0))/365 -> 33205.447 | F65: =F$16*INDEX('Google Drivers'!G$55:G$57,MATCH($D$5,'Google Drivers'!$C$55:$C$57,0))/365 -> 36801.129 | G65: =G$16*INDEX('Google Drivers'!H$55:H$57,MATCH($D$5,'Google Drivers'!$C$55:$C$57,0))/365 -> 39557.756 | H65: =H$16*INDEX('Google Drivers'!I$55:I$57,MATCH($D$5,'Google Drivers'!$C$55:$C$57,0))/365 -> 43059.79 | I65: =I$16*INDEX('Google Drivers'!J$55:J$57,MATCH($D$5,'Google Drivers'!$C$55:$C$57,0))/365 -> 45481.21 | J65: =J$16*INDEX('Google Drivers'!K$55:K$57,MATCH($D$5,'Google Drivers'!$C$55:$C$57,0))/365 -> 48877.48
B66: Other current assets | C66: 8500 | D66: =C66*(1+'Google Drivers'!E$63) -> 9000 | E66: =D66*(1+'Google Drivers'!F$63) -> 9500 | F66: =E66*(1+'Google Drivers'!G$63) -> 9975 | G66: =F66*(1+'Google Drivers'!H$63) -> 10473.75 | H66: =G66*(1+'Google Drivers'!I$63) -> 10997.438 | I66: =H66*(1+'Google Drivers'!J$63) -> 11547.309 | J66: =I66*(1+'Google Drivers'!K$63) -> 12124.675
B67: Current Assets — Total | C67: =SUM(C64:C66) -> 127285.14 | D67: =SUM(D64:D66) -> 137398.7 | E67: =SUM(E64:E66) -> 149007.77 | F67: =SUM(F64:F66) -> 167055.28 | G67: =SUM(G64:G66) -> 186984.06 | H67: =SUM(H64:H66) -> 212782.83 | I67: =SUM(I64:I66) -> 241129.87 | J67: =SUM(J64:J66) -> 276773.48
B69: Assets — Non-current
B70: PP&E (Gross) | C70: 80000 | D70: =C70+D110 -> 111676.04 | E70: =D70+E110 -> 148562.96 | F70: =E70+F110 -> 187984.17 | G70: =F70+G110 -> 229695.63 | H70: =G70+H110 -> 273353.47 | I70: =H70+I110 -> 318627.95 | J70: =I70+J110 -> 365255.95
B71: Less: Accumulated depreciation | C71: 25000 | D71: =C71+D102 -> 44152.613 | E71: =D71+E102 -> 66325.841 | F71: =E71+F102 -> 92146.685 | G71: =F71+G102 -> 119741.53 | H71: =G71+H102 -> 148939.55 | I71: =H71+I102 -> 179500.04 | J71: =I71+J102 -> 211192.17
B72: Net PP&E | C72: =C70-C71 -> 55000 | D72: =D70-D71 -> 67523.428 | E72: =E70-E71 -> 82237.12 | F72: =F70-F71 -> 95837.484 | G72: =G70-G71 -> 109954.09 | H72: =H70-H71 -> 124413.92 | I72: =I70-I71 -> 139127.91 | J72: =J70-J71 -> 154063.78
B74: Other Long-term Assets | C74: 35000 | D74: =C74*(1+'Google Drivers'!E$64) -> 38000 | E74: =D74*(1+'Google Drivers'!F$64) -> 42000 | F74: =E74*(1+'Google Drivers'!G$64) -> 45360 | G74: =F74*(1+'Google Drivers'!H$64) -> 48988.8 | H74: =G74*(1+'Google Drivers'!I$64) -> 52907.904 | I74: =H74*(1+'Google Drivers'!J$64) -> 57140.536 | J74: =I74*(1+'Google Drivers'!K$64) -> 61711.779
B75: Total Non-Current Assets | C75: =C72+C74 -> 90000 | D75: =D72+D74 -> 105523.43 | E75: =E72+E74 -> 124237.12 | F75: =F72+F74 -> 141197.48 | G75: =G72+G74 -> 158942.89 | H75: =H72+H74 -> 177321.82 | I75: =I72+I74 -> 196268.44 | J75: =J72+J74 -> 215775.56
B77: Total Assets | C77: =C67+C75 -> 217285.14 | D77: =D67+D75 -> 242922.13 | E77: =E67+E75 -> 273244.89 | F77: =F67+F75 -> 308252.77 | G77: =G67+G75 -> 345926.95 | H77: =H67+H75 -> 390104.65 | I77: =I67+I75 -> 437398.32 | J77: =J67+J75 -> 492549.03
B79: Liabilities and equity
B81: Liabilities — Current
B82: Payables | C82: =(C32+C36+C37+C38)*INDEX('Google Drivers'!D$59:D$61,MATCH($D$5,'Google Drivers'!$C$59:$C$61,0))/365 -> 15140.983 | D82: =(D32+D36+D37+D38)*INDEX('Google Drivers'!E$59:E$61,MATCH($D$5,'Google Drivers'!$C$59:$C$61,0))/365 -> 16857.728 | E82: =(E32+E36+E37+E38)*INDEX('Google Drivers'!F$59:F$61,MATCH($D$5,'Google Drivers'!$C$59:$C$61,0))/365 -> 18800.058 | F82: =(F32+F36+F37+F38)*INDEX('Google Drivers'!G$59:G$61,MATCH($D$5,'Google Drivers'!$C$59:$C$61,0))/365 -> 20618.232 | G82: =(G32+G36+G37+G38)*INDEX('Google Drivers'!H$59:H$61,MATCH($D$5,'Google Drivers'!$C$59:$C$61,0))/365 -> 23044.591 | H82: =(H32+H36+H37+H38)*INDEX('Google Drivers'!I$59:I$61,MATCH($D$5,'Google Drivers'!$C$59:$C$61,0))/365 -> 24783.302 | I82: =(I32+I36+I37+I38)*INDEX('Google Drivers'!J$59:J$61,MATCH($D$5,'Google Drivers'!$C$59:$C$61,0))/365 -> 27239.11 | J82: =(J32+J36+J37+J38)*INDEX('Google Drivers'!K$59:K$61,MATCH($D$5,'Google Drivers'!$C$59:$C$61,0))/365 -> 28913.251
B83: Accrued Expenses | C83: 12000 | D83: =C83*(1+'Google Drivers'!E$65) -> 13000 | E83: =D83*(1+'Google Drivers'!F$65) -> 14000 | F83: =E83*(1+'Google Drivers'!G$65) -> 14840 | G83: =F83*(1+'Google Drivers'!H$65) -> 15730.4 | H83: =G83*(1+'Google Drivers'!I$65) -> 16674.224 | I83: =H83*(1+'Google Drivers'!J$65) -> 17674.677 | J83: =I83*(1+'Google Drivers'!K$65) -> 18735.158
B84: Current Liabilities — Total | C84: =SUM(C82:C83) -> 27140.983 | D84: =SUM(D82:D83) -> 29857.728 | E84: =SUM(E82:E83) -> 32800.058 | F84: =SUM(F82:F83) -> 35458.232 | G84: =SUM(G82:G83) -> 38774.991 | H84: =SUM(H82:H83) -> 41457.526 | I84: =SUM(I82:I83) -> 44913.788 | J84: =SUM(J82:J83) -> 47648.409
B86: Long-term Debt | C86: 15000 | D86: 14000 | E86: 13000 | F86: 12500 | G86: 12000 | H86: 11500 | I86: 11000 | J86: 10500
B87: Liabilities — Total | C87: =C84+C86 -> 42140.983 | D87: =D84+D86 -> 43857.728 | E87: =E84+E86 -> 45800.058 | F87: =F84+F86 -> 47958.232 | G87: =G84+G86 -> 50774.991 | H87: =H84+H86 -> 52957.526 | I87: =I84+I86 -> 55913.788 | J87: =J84+J86 -> 58148.409
B89: Shareholders' Equity
B90: Common Stock & APIC | C90: 50000 | D90: =C90+D103 -> 72797.15 | E90: =D90+E103 -> 98617.994 | F90: =E90+F103 -> 126358.84 | G90: =F90+G103 -> 156198.58 | H90: =G90+H103 -> 187632.23 | I90: =H90+I103 -> 220833.51 | J90: =I90+J103 -> 255297.69
B91: Treasury Stock | C91: 24855.844 | D91: =C91+D115 -> 50351.205 | E91: =D91+E115 -> 79762.829 | F91: =E91+F115 -> 113542.09 | G91: =F91+G115 -> 153613.35 | H91: =G91+H115 -> 194977.59 | I91: =H91+I115 -> 243032.55 | J91: =I91+J115 -> 291287.51
B92: Retained earnings | C92: 150000 | D92: =C92+D101 -> 176618.45 | E92: =D92+E101 -> 208589.67 | F92: =E92+F101 -> 247477.78 | G92: =F92+G101 -> 292566.73 | H92: =G92+H101 -> 344492.49 | I92: =H92+I101 -> 403683.57 | J92: =I92+J101 -> 470390.44
B93: Total Shareholders' Equity | C93: =C90-C91+C92 -> 175144.16 | D93: =D90-D91+D92 -> 199064.4 | E93: =E90-E91+E92 -> 227444.84 | F93: =F90-F91+F92 -> 260294.54 | G93: =G90-G91+G92 -> 295151.96 | H93: =H90-H91+H92 -> 337147.13 | I93: =I90-I91+I92 -> 381484.53 | J93: =J90-J91+J92 -> 434400.62
B95: Total Liabilities & Equity | C95: =C87+C93 -> 217285.14 | D95: =D87+D93 -> 242922.13 | E95: =E87+E93 -> 273244.89 | F95: =F87+F93 -> 308252.77 | G95: =G87+G93 -> 345926.95 | H95: =H87+H93 -> 390104.65 | I95: =I87+I93 -> 437398.32 | J95: =J87+J93 -> 492549.03
B97: Balance Check (Assets — L&E) | C97: =C77-C95 -> 0 | D97: =D77-D95 -> 0 | E97: =E77-E95 -> 0 | F97: =F77-F95 -> 0 | G97: =G77-G95 -> 0 | H97: =H77-H95 -> 0 | I97: =I77-I95 -> 0 | J97: =J77-J95 -> 0
B99: Cash-flow statement
B100: Cash Flow from Operating Activities
B101: Net Income | D101: {=D50} -> 26618.455 | E101: {=E50} -> 31971.217 | F101: {=F50} -> 38888.11 | G101: {=G50} -> 45088.952 | H101: {=H50} -> 51925.753 | I101: {=I50} -> 59191.085 | J101: {=J50} -> 66706.872
B102: Add — Depreciation & Amortization | D102: =C$110*INDEX('Google Drivers'!E$73:E$75,MATCH($D$5,'Google Drivers'!$C$73:$C$75,0)) -> 19152.612 | E102: =D$110*INDEX('Google Drivers'!F$73:F$75,MATCH($D$5,'Google Drivers'!$C$73:$C$75,0)) -> 22173.228 | F102: =E$110*INDEX('Google Drivers'!G$73:G$75,MATCH($D$5,'Google Drivers'!$C$73:$C$75,0)) -> 25820.844 | G102: =F$110*INDEX('Google Drivers'!H$73:H$75,MATCH($D$5,'Google Drivers'!$C$73:$C$75,0)) -> 27594.846 | H102: =G$110*INDEX('Google Drivers'!I$73:I$75,MATCH($D$5,'Google Drivers'!$C$73:$C$75,0)) -> 29198.02 | I102: =H$110*INDEX('Google Drivers'!J$73:J$75,MATCH($D$5,'Google Drivers'!$C$73:$C$75,0)) -> 30560.49 | J102: =I$110*INDEX('Google Drivers'!K$73:K$75,MATCH($D$5,'Google Drivers'!$C$73:$C$75,0)) -> 31692.134
B103: Add: SBC | D103: {=D39} -> 22797.15 | E103: {=E39} -> 25820.844 | F103: {=F39} -> 27740.851 | G103: {=G39} -> 29839.734 | H103: {=H39} -> 31433.647 | I103: {=I39} -> 33201.284 | J103: {=J39} -> 34464.178
B104: Changes in Working Capital —
B105: (Increase)/Decrease in Current Assets | D105: =-(SUM(D65:D66)-SUM(C65:C66)) -> -2615.1068 | E105: =-(SUM(E65:E66)-SUM(D65:D66)) -> -2805.2 | F105: =-(SUM(F65:F66)-SUM(E65:E66)) -> -4070.682 | G105: =-(SUM(G65:G66)-SUM(F65:F66)) -> -3255.3779 | H105: =-(SUM(H65:H66)-SUM(G65:G66)) -> -4025.7215 | I105: =-(SUM(I65:I66)-SUM(H65:H66)) -> -2971.2919 | J105: =-(SUM(J65:J66)-SUM(I65:I66)) -> -3973.6352
B106: Increase/(Decrease) in Current Liabilities | D106: =SUM(D82:D83)-SUM(C82:C83) -> 2716.7446 | E106: =SUM(E82:E83)-SUM(D82:D83) -> 2942.3295 | F106: =SUM(F82:F83)-SUM(E82:E83) -> 2658.1747 | G106: =SUM(G82:G83)-SUM(F82:F83) -> 3316.7585 | H106: =SUM(H82:H83)-SUM(G82:G83) -> 2682.5348 | I106: =SUM(I82:I83)-SUM(H82:H83) -> 3456.2622 | J106: =SUM(J82:J83)-SUM(I82:I83) -> 2734.6215
B107: Net Cash from Operating Activities | D107: =SUM(D101:D106) -> 68669.855 | E107: =SUM(E101:E106) -> 80102.418 | F107: =SUM(F101:F106) -> 91037.297 | G107: =SUM(G101:G106) -> 102584.91 | H107: =SUM(H101:H106) -> 111214.23 | I107: =SUM(I101:I106) -> 123437.83 | J107: =SUM(J101:J106) -> 131624.17
B109: Cash Flow from Investing Activities
B110: CapEx | C110: =C$16*INDEX('Google Drivers'!D$69:D$71,MATCH($D$5,'Google Drivers'!$C$69:$C$71,0)) -> 27360.875 | D110: =D$16*INDEX('Google Drivers'!E$69:E$71,MATCH($D$5,'Google Drivers'!$C$69:$C$71,0)) -> 31676.04 | E110: =E$16*INDEX('Google Drivers'!F$69:F$71,MATCH($D$5,'Google Drivers'!$C$69:$C$71,0)) -> 36886.92 | F110: =F$16*INDEX('Google Drivers'!G$69:G$71,MATCH($D$5,'Google Drivers'!$C$69:$C$71,0)) -> 39421.209 | G110: =G$16*INDEX('Google Drivers'!H$69:H$71,MATCH($D$5,'Google Drivers'!$C$69:$C$71,0)) -> 41711.457 | H110: =H$16*INDEX('Google Drivers'!I$69:I$71,MATCH($D$5,'Google Drivers'!$C$69:$C$71,0)) -> 43657.843 | I110: =I$16*INDEX('Google Drivers'!J$69:J$71,MATCH($D$5,'Google Drivers'!$C$69:$C$71,0)) -> 45274.478 | J110: =J$16*INDEX('Google Drivers'!K$69:K$71,MATCH($D$5,'Google Drivers'!$C$69:$C$71,0)) -> 46628.005
B111: Long-term investments | D111: =D74-C74 -> 3000 | E111: =E74-D74 -> 4000 | F111: =F74-E74 -> 3360 | G111: =G74-F74 -> 3628.8 | H111: =H74-G74 -> 3919.104 | I111: =I74-H74 -> 4232.6323 | J111: =J74-I74 -> 4571.2429
B112: Net Cash from Investing Activities | D112: =-D110-D111 -> -34676.04 | E112: =-E110-E111 -> -40886.92 | F112: =-F110-F111 -> -42781.209 | G112: =-G110-G111 -> -45340.257 | H112: =-H110-H111 -> -47576.947 | I112: =-I110-I111 -> -49507.11 | J112: =-J110-J111 -> -51199.248
B114: Cash Flow from Financing Activities
B115: Share Repurchases | D115: =MAX(D107+D112,0)*INDEX('Google Drivers'!E$98:E$100,MATCH($D$5,'Google Drivers'!$C$98:$C$100,0)) -> 25495.361 | E115: =MAX(E107+E112,0)*INDEX('Google Drivers'!F$98:F$100,MATCH($D$5,'Google Drivers'!$C$98:$C$100,0)) -> 29411.624 | F115: =MAX(F107+F112,0)*INDEX('Google Drivers'!G$98:G$100,MATCH($D$5,'Google Drivers'!$C$98:$C$100,0)) -> 33779.262 | G115: =MAX(G107+G112,0)*INDEX('Google Drivers'!H$98:H$100,MATCH($D$5,'Google Drivers'!$C$98:$C$100,0)) -> 40071.26 | H115: =MAX(H107+H112,0)*INDEX('Google Drivers'!I$98:I$100,MATCH($D$5,'Google Drivers'!$C$98:$C$100,0)) -> 41364.236 | I115: =MAX(I107+I112,0)*INDEX('Google Drivers'!J$98:J$100,MATCH($D$5,'Google Drivers'!$C$98:$C$100,0)) -> 48054.968 | J115: =MAX(J107+J112,0)*INDEX('Google Drivers'!K$98:K$100,MATCH($D$5,'Google Drivers'!$C$98:$C$100,0)) -> 48254.953
B116: Debt Repayments | D116: =-D$86+C$86 -> 1000 | E116: =-E$86+D$86 -> 1000 | F116: =-F$86+E$86 -> 500 | G116: =-G$86+F$86 -> 500 | H116: =-H$86+G$86 -> 500 | I116: =-I$86+H$86 -> 500 | J116: =-J$86+I$86 -> 500
B117: Net Cash from Financing Activities | D117: =-D115-D116 -> -26495.361 | E117: =-E115-E116 -> -30411.624 | F117: =-F115-F116 -> -34279.262 | G117: =-G115-G116 -> -40571.26 | H117: =-H115-H116 -> -41864.236 | I117: =-I115-I116 -> -48554.968 | J117: =-J115-J116 -> -48754.953
B119: Net Change in Cash | D119: =D107+D112+D117 -> 7498.4538 | E119: =E107+E112+E117 -> 8803.8746 | F119: =F107+F112+F117 -> 13976.827 | G119: =G107+G112+G117 -> 16673.397 | H119: =H107+H112+H117 -> 21773.05 | I119: =I107+I112+I117 -> 25375.752 | J119: =J107+J112+J117 -> 31669.969
B120: Beginning Cash | D120: =C$121 -> 90000 | E120: =D$121 -> 97498.454 | F120: =E$121 -> 106302.33 | G120: =F$121 -> 120279.15 | H120: =G$121 -> 136952.55 | I120: =H$121 -> 158725.6 | J120: =I$121 -> 184101.35
B121: Cash — Ending | C121: =C64 -> 90000 | D121: =D119+D120 -> 97498.454 | E121: =E119+E120 -> 106302.33 | F121: =F119+F120 -> 120279.15 | G121: =G119+G120 -> 136952.55 | H121: =H119+H120 -> 158725.6 | I121: =I119+I120 -> 184101.35 | J121: =J119+J120 -> 215771.32
B123: Cash Balance Check | C123: =C121-C64 -> 0 | D123: =D121-D64 -> 0 | E123: =E121-E64 -> 0 | F123: =F121-F64 -> 0 | G123: =G121-G64 -> 0 | H123: =H121-H64 -> 0 | I123: =I121-I64 -> 0 | J123: =J121-J64 -> 0
B125: Valuation Multiples
F126: 2024P | G126: 2025P | H126: 2026P | I126: 2027P | J126: 2028P
B127: Market Capitalization ($B) | F127: 2980
B128: Net Debt Position ($B) | F128: =($F$86-$F$64)/1000 -> -107.77915
B129: Enterprise Value / TEV ($B) | F129: =F127+F128 -> 2872.2208
B131: Revenue Multiple (EV / Sales) | F131: =$F$129*1000/F$16 -> 9.8360711 | G131: =$F$129*1000/G$16 -> 8.9517063 | H131: =$F$129*1000/H$16 -> 8.223668 | I131: =$F$129*1000/I$16 -> 7.6128212 | J131: =$F$129*1000/J$16 -> 7.0838415
B132: EBITDA Multiple (EV / EBITDA) | F132: =$F$129*1000/(F$42+F$102) -> 41.780091 | G132: =$F$129*1000/(G$42+G$102) -> 36.686799 | H132: =$F$129*1000/(H$42+H$102) -> 32.427839 | I132: =$F$129*1000/(I$42+I$102) -> 29.167833 | J132: =$F$129*1000/(J$42+J$102) -> 26.220598
B133: P / E | F133: =$F$127*1000/F$50 -> 76.630106 | G133: =$F$127*1000/G$50 -> 66.091578 | H133: =$F$127*1000/H$50 -> 57.389635 | I133: =$F$127*1000/I$50 -> 50.345419 | J133: =$F$127*1000/J$50 -> 44.673059

Sheet Meta Drivers
B2: Meta Platforms — Operating Model Assumptions
B3: 3-Year Historical (2021-2023) | 5-Year Projections (2024-2028)
B4: Figures in $mm
B5: Case selector
B6: Chosen case: | D6: ='Google Drivers'!$D$6 -> Base
B8: Actuals | G8: Forecast
D9: 2021 | E9: 2022 | F9: 2023 | G9: 2024 | H9: 2025 | I9: 2026 | J9: 2027 | K9: 2028
B11: Revenue Assumptions — 1
B13: Growth rates — Revenue (%)
C14: Case | D14: 2021 | E14: 2022 | F14: 2023 | G14: 2024 | H14: 2025 | I14: 2026 | J14: 2027 | K14: 2028
B15: Family of Apps — FoA | C15: Base | G15: 0.12 | H15: 0.1 | I15: 0.085 | J15: 0.075 | K15: 0.07
C16: Bull | G16: 0.14 | H16: 0.12 | I16: 0.105 | J16: 0.095 | K16: 0.09
C17: Bear | G17: 0.1 | H17: 0.08 | I17: 0.065 | J17: 0.055 | K17: 0.05
B19: Reality Labs | C19: Base | G19: 0.014 | H19: =G$19+(($K$19-$G$19)/COUNT($H$14:$K$14)) -> 0.023 | I19: =H$19+(($K$19-$G$19)/COUNT($H$14:$K$14)) -> 0.032 | J19: =I$19+(($K$19-$G$19)/COUNT($H$14:$K$14)) -> 0.041 | K19: 0.05
B20: % of total revenue | C20: Bull | G20: =G19+$M$20 -> 0.019 | H20: =H19+$M$20 -> 0.028 | I20: =I19+$M$20 -> 0.037 | J20: =J19+$M$20 -> 0.046 | K20: =K19+$M$20 -> 0.055 | M20: 0.005
C21: Bear | G21: =G19-$M$21 -> 0.009 | H21: =H19-$M$21 -> 0.018 | I21: =I19-$M$21 -> 0.027 | J21: =J19-$M$21 -> 0.036 | K21: =K19-$M$21 -> 0.045 | M21: 0.005
B24: User Growth Metrics
B26: DAU Growth — % | C26: Base | G26: 0.03 | H26: 0.025 | I26: 0.02 | J26: 0.015 | K26: 0.01
C27: Bull | G27: 0.04 | H27: 0.035 | I27: 0.03 | J27: 0.025 | K27: 0.02
C28: Bear | G28: 0.02 | H28: 0.015 | I28: 0.01 | J28: 0.005 | K28: 0
B30: ARPU Growth — % | C30: Base | G30: 0.085 | H30: 0.07 | I30: 0.06 | J30: 0.055 | K30: 0.05
C31: Bull | G31: 0.1 | H31: 0.085 | I31: 0.075 | J31: 0.07 | K31: 0.065
C32: Bear | G32: 0.07 | H32: 0.055 | I32: 0.045 | J32: 0.04 | K32: 0.035
B34: Operating Expense Assumptions — 2
B36: Expenses — Operating (% of Revenue)
B38: R&D | C38: Base | D38: 0.255 | E38: 0.27 | F38: 0.29 | G38: 0.285 | H38: 0.28 | I38: 0.275 | J38: 0.27 | K38: 0.265
C39: Bull | D39: 0.255 | E39: 0.27 | F39: 0.29 | G39: 0.28 | H39: 0.275 | I39: 0.27 | J39: 0.265 | K39: 0.26
C40: Bear | D40: 0.255 | E40: 0.27 | F40: 0.29 | G40: 0.29 | H40: 0.285 | I40: 0.28 | J40: 0.275 | K40: 0.27
B42: S&M | C42: Base | D42: 0.118 | E42: 0.125 | F42: 0.13 | G42: 0.125 | H42: 0.12 | I42: 0.115 | J42: 0.11 | K42: 0.105
C43: Bull | D43: 0.118 | E43: 0.125 | F43: 0.13 | G43: 0.12 | H43: 0.115 | I43: 0.11 | J43: 0.105 | K43: 0.1
C44: Bear | D44: 0.118 | E44: 0.125 | F44: 0.13 | G44: 0.13 | H44: 0.125 | I44: 0.12 | J44: 0.115 | K44: 0.11
B46: G&A | C46: Base | D46: 0.102 | E46: 0.108 | F46: 0.115 | G46: 0.11 | H46: 0.105 | I46: 0.1 | J46: 0.095 | K46: 0.09
C47: Bull | D47: 0.102 | E47: 0.108 | F47: 0.115 | G47: 0.105 | H47: 0.1 | I47: 0.095 | J47: 0.09 | K47: 0.085
C48: Bear | D48: 0.102 | E48: 0.108 | F48: 0.115 | G48: 0.115 | H48: 0.11 | I48: 0.105 | J48: 0.1 | K48: 0.095
B50: SBC | C50: Base | D50: 0.085 | E50: 0.102 | F50: 0.118 | G50: 0.11 | H50: 0.105 | I50: 0.1 | J50: 0.095 | K50: 0.09
C51: Bull | D51: 0.085 | E51: 0.102 | F51: 0.118 | G51: 0.105 | H51: 0.1 | I51: 0.095 | J51: 0.09 | K51: 0.085
C52: Bear | D52: 0.085 | E52: 0.102 | F52: 0.118 | G52: 0.115 | H52: 0.11 | I52: 0.105 | J52: 0.1 | K52: 0.095
B54: Reality Labs Operating Margin
B56: Operating Margin — % | C56: Base | D56: -3.5 | E56: -3 | F56: -2.5 | G56: -2 | H56: -1.5 | I56: -1 | J56: -0.75 | K56: -0.5
C57: Bull | D57: -3.5 | E57: -3 | F57: -2.5 | G57: -1.75 | H57: -1.25 | I57: -0.75 | J57: -0.5 | K57: -0.25
C58: Bear | D58: -3.5 | E58: -3 | F58: -2.5 | G58: -2.25 | H58: -1.75 | I58: -1.25 | J58: -1 | K58: -0.75
B60: Balance Sheet & Cash Flow Assumptions — 3
B62: Working Capital Metrics
B64: Days Sales Outstanding — DSO | C64: Base | D64: 55 | E64: 53 | F64: 51 | G64: 50 | H64: 49 | I64: 48 | J64: 47 | K64: 46
C65: Bull | D65: 55 | E65: 53 | F65: 51 | G65: 49 | H65: 47 | I65: 46 | J65: 45 | K65: 44
C66: Bear | D66: 55 | E66: 53 | F66: 51 | G66: 52 | H66: 51 | I66: 50 | J66: 49 | K66: 48
B68: Days Payable Outstanding — DPO | C68: Base | D68: 28 | E68: 30 | F68: 32 | G68: 33 | H68: 34 | I68: 35 | J68: 36 | K68: 37
C69: Bull | D69: 28 | E69: 30 | F69: 32 | G69: 34 | H69: 36 | I69: 37 | J69: 38 | K69: 39
C70: Bear | D70: 28 | E70: 30 | F70: 32 | G70: 32 | H70: 32 | I70: 33 | J70: 34 | K70: 35
B72: ='Meta Model'!$B$51 -> Other current assets | C72: % Increase | E72: 0.04 | F72: 0.038461538 | G72: 0.04 | H72: 0.04 | I72: 0.04 | J72: 0.04 | K72: 0.04
B73: ='Meta Model'!$B$59 -> Other Long-term Assets | C73: % Increase | E73: 0.12 | F73: 0.14285714 | G73: 0.1 | H73: 0.1 | I73: 0.1 | J73: 0.1 | K73: 0.1
B74: ='Meta Model'!$B$68 -> Accrued Expenses | C74: % Increase | E74: 0.0625 | F74: 0.058823529 | G74: 0.05 | H74: 0.05 | I74: 0.05 | J74: 0.05 | K74: 0.05
B76: Capital Expenditure
B78: CapEx — % of Revenue | C78: Base | D78: 0.185 | E78: 0.22 | F78: 0.245 | G78: 0.23 | H78: 0.215 | I78: 0.2 | J78: 0.19 | K78: 0.18
C79: Bull | D79: 0.185 | E79: 0.22 | F79: 0.245 | G79: 0.22 | H79: 0.205 | I79: 0.19 | J79: 0.18 | K79: 0.17
C80: Bear | D80: 0.185 | E80: 0.22 | F80: 0.245 | G80: 0.24 | H80: 0.225 | I80: 0.21 | J80: 0.2 | K80: 0.19
B82: D&A — % of Prior Year CapEx | C82: Base | D82: 0.65 | E82: 0.65 | F82: 0.65 | G82: 0.65 | H82: 0.65 | I82: 0.65 | J82: 0.65 | K82: 0.65
C83: Bull | D83: 0.65 | E83: 0.65 | F83: 0.65 | G83: 0.63 | H83: 0.63 | I83: 0.63 | J83: 0.63 | K83: 0.63
C84: Bear | D84: 0.65 | E84: 0.65 | F84: 0.65 | G84: 0.67 | H84: 0.67 | I84: 0.67 | J84: 0.67 | K84: 0.67
B88: Other Financial Assumptions — 4
B90: Tax Rate
B92: Effective Tax Rate | C92: Base | D92: 0.175 | E92: 0.19 | F92: 0.185 | G92: 0.19 | H92: 0.195 | I92: 0.2 | J92: 0.205 | K92: 0.21
C93: Bull | D93: 0.175 | E93: 0.19 | F93: 0.185 | G93: 0.185 | H93: 0.19 | I93: 0.195 | J93: 0.2 | K93: 0.205
C94: Bear | D94: 0.175 | E94: 0.19 | F94: 0.185 | G94: 0.195 | H94: 0.2 | I94: 0.205 | J94: 0.21 | K94: 0.215
B97: Interest Rates
B99: Interest Income Rate — on cash | C99: Base | D99: 0.005 | E99: 0.015 | F99: 0.025 | G99: 0.035 | H99: 0.03 | I99: 0.025 | J99: 0.025 | K99: 0.02
C100: Bull | D100: 0.01 | E100: 0.02 | F100: 0.03 | G100: 0.04 | H100: 0.045 | I100: 0.04 | J100: 0.035 | K100: 0.035
C101: Bear | D101: 0.0025 | E101: 0.0125 | F101: 0.0225 | G101: 0.0325 | H101: 0.0375 | I101: 0.0325 | J101: 0.0275 | K101: 0.0275
B103: Interest Expense Rate — on LT debt | C103: Base | D103: 0.03 | E103: 0.035 | F103: 0.04 | G103: 0.045 | H103: 0.04 | I103: 0.035 | J103: 0.03 | K103: 0.03
C104: Bull | D104: 0.025 | E104: 0.03 | F104: 0.035 | G104: 0.04 | H104: 0.035 | I104: 0.03 | J104: 0.025 | K104: 0.025
C105: Bear | D105: 0.04 | E105: 0.045 | F105: 0.05 | G105: 0.055 | H105: 0.05 | I105: 0.045 | J105: 0.04 | K105: 0.04
B107: Share Buyback & Dividends
B109: Buyback — % of FCF | C109: Base | D109: 0.6 | E109: 0.65 | F109: 0.7 | G109: 0.65 | H109: 0.65 | I109: 0.6 | J109: 0.6 | K109: 0.55
C110: Bull | D110: 0.6 | E110: 0.65 | F110: 0.7 | G110: 0.7 | H110: 0.7 | I110: 0.65 | J110: 0.65 | K110: 0.6
C111: Bear | D111: 0.6 | E111: 0.65 | F111: 0.7 | G111: 0.6 | H111: 0.6 | I111: 0.55 | J111: 0.55 | K111: 0.5
B113: Dividend Payout Ratio | C113: Base | D113: 0 | E113: 0 | F113: 0.02 | G113: 0.03 | H113: 0.04 | I113: 0.05 | J113: 0.06 | K113: 0.07
C114: Bull | D114: 0 | E114: 0 | F114: 0.02 | G114: 0.04 | H114: 0.05 | I114: 0.06 | J114: 0.07 | K114: 0.08
C115: Bear | D115: 0 | E115: 0 | F115: 0.02 | G115: 0.02 | H115: 0.03 | I115: 0.04 | J115: 0.05 | K115: 0.06
B117: International Revenue Mix
B119: US Revenue % | D119: 0.45 | E119: 0.45 | F119: 0.45 | G119: 0.45 | H119: 0.45 | I119: 0.45 | J119: 0.45 | K119: 0.45
B120: International Revenue % | D120: =1-D119 -> 0.55 | E120: =1-E119 -> 0.55 | F120: =1-F119 -> 0.55 | G120: =1-G119 -> 0.55 | H120: =1-H119 -> 0.55 | I120: =1-I119 -> 0.55 | J120: =1-J119 -> 0.55 | K120: =1-K119 -> 0.55
B122: FX Impact on Int'l Revenue
B123: Base Case | D123: 0 | E123: =D123+(($K$123-$D$123)/(COUNTA($E$123:$J$123)+1)) -> 0.0014285714 | F123: =E123+(($K$123-$D$123)/(COUNTA($E$123:$J$123)+1)) -> 0.0028571429 | G123: =F123+(($K$123-$D$123)/(COUNTA($E$123:$J$123)+1)) -> 0.0042857143 | H123: =G123+(($K$123-$D$123)/(COUNTA($E$123:$J$123)+1)) -> 0.0057142857 | I123: =H123+(($K$123-$D$123)/(COUNTA($E$123:$J$123)+1)) -> 0.0071428571 | J123: =I123+(($K$123-$D$123)/(COUNTA($E$123:$J$123)+1)) -> 0.0085714286 | K123: 0.01
B124: Bull Case | D124: 0.01 | E124: =D124+(($K$124-$D$124)/(COUNTA($E$124:$J$124)+1)) -> 0.011428571 | F124: =E124+(($K$124-$D$124)/(COUNTA($E$124:$J$124)+1)) -> 0.012857143 | G124: =F124+(($K$124-$D$124)/(COUNTA($E$124:$J$124)+1)) -> 0.014285714 | H124: =G124+(($K$124-$D$124)/(COUNTA($E$124:$J$124)+1)) -> 0.015714286 | I124: =H124+(($K$124-$D$124)/(COUNTA($E$124:$J$124)+1)) -> 0.017142857 | J124: =I124+(($K$124-$D$124)/(COUNTA($E$124:$J$124)+1)) -> 0.018571429 | K124: 0.02
B125: Bear Case | D125: -0.02 | E125: =D125+(($K$125-$D$125)/(COUNTA($E$125:$J$125)+1)) -> -0.017142857 | F125: =E125+(($K$125-$D$125)/(COUNTA($E$125:$J$125)+1)) -> -0.014285714 | G125: =F125+(($K$125-$D$125)/(COUNTA($E$125:$J$125)+1)) -> -0.011428571 | H125: =G125+(($K$125-$D$125)/(COUNTA($E$125:$J$125)+1)) -> -0.0085714286 | I125: =H125+(($K$125-$D$125)/(COUNTA($E$125:$J$125)+1)) -> -0.0057142857 | J125: =I125+(($K$125-$D$125)/(COUNTA($E$125:$J$125)+1)) -> -0.0028571429 | K125: 0

Sheet Meta Model
B2: Meta Platforms — Income Statement
B3: Figures in $mm
B5: Chosen case: | D5: ='Google Drivers'!$D$6 -> Base
B7: Actuals | F7: Forecast
C8: 2021 | D8: 2022 | E8: 2023 | F8: 2024 | G8: 2025 | H8: 2026 | I8: 2027 | J8: 2028
B10: P&L statement
B12: Family of Apps | C12: 115655 | D12: 114450 | E12: 133008 | F12: =E12*(1+INDEX('Meta Drivers'!G$15:G$17,MATCH($D$5,'Meta Drivers'!$C$15:$C$17,0))) -> 148968.96 | G12: =F12*(1+INDEX('Meta Drivers'!H$15:H$17,MATCH($D$5,'Meta Drivers'!$C$15:$C$17,0))) -> 163865.86 | H12: =G12*(1+INDEX('Meta Drivers'!I$15:I$17,MATCH($D$5,'Meta Drivers'!$C$15:$C$17,0))) -> 177794.45 | I12: =H12*(1+INDEX('Meta Drivers'!J$15:J$17,MATCH($D$5,'Meta Drivers'!$C$15:$C$17,0))) -> 191129.04 | J12: =I12*(1+INDEX('Meta Drivers'!K$15:K$17,MATCH($D$5,'Meta Drivers'!$C$15:$C$17,0))) -> 204508.07
B13: Reality Labs | C13: 2274 | D13: 2159 | E13: 1896 | F13: =F14-F12 -> 2115.1779 | G13: =G14-G12 -> 3857.6404 | H13: =H14-H12 -> 5877.5026 | I13: =I14-I12 -> 8171.3144 | J13: =J14-J12 -> 10763.583
B14: Revenue — Total | C14: =SUM(C12:C13) -> 117929 | D14: =SUM(D12:D13) -> 116609 | E14: =SUM(E12:E13) -> 134904 | F14: =F12/(1-(INDEX('Meta Drivers'!G$19:G$21,MATCH('Meta Model'!$D$5,'Meta Drivers'!$D$6,0)))) -> 151084.14 | G14: =G12/(1-(INDEX('Meta Drivers'!H$19:H$21,MATCH('Meta Model'!$D$5,'Meta Drivers'!$D$6,0)))) -> 167723.5 | H14: =H12/(1-(INDEX('Meta Drivers'!I$19:I$21,MATCH('Meta Model'!$D$5,'Meta Drivers'!$D$6,0)))) -> 183671.96 | I14: =I12/(1-(INDEX('Meta Drivers'!J$19:J$21,MATCH('Meta Model'!$D$5,'Meta Drivers'!$D$6,0)))) -> 199300.35 | J14: =J12/(1-(INDEX('Meta Drivers'!K$19:K$21,MATCH('Meta Model'!$D$5,'Meta Drivers'!$D$6,0)))) -> 215271.65
B15: YoY Growth % | D15: =D14/C14-1 -> -0.011193176 | E15: =E14/D14-1 -> 0.15689184 | F15: =F14/E14-1 -> 0.11993816 | G15: =G14/F14-1 -> 0.11013306 | H15: =H14/G14-1 -> 0.09508781 | I15: =I14/H14-1 -> 0.085088634 | J15: =J14/I14-1 -> 0.080136842
B17: Cost of sales | C17: =C14*(1-C19) -> 23349.942 | D17: =D14*(1-D19) -> 23555.018 | E17: =E14*(1-E19) -> 27655.32 | F17: =F14*(1-F19) -> 30670.08 | G17: =G14*(1-G19) -> 33712.423 | H17: =H14*(1-H19) -> 36550.719 | I17: =I14*(1-I19) -> 39262.169 | J17: =J14*(1-J19) -> 41977.972
B18: Profit — Gross | C18: =C14-C17 -> 94579.058 | D18: =D14-D17 -> 93053.982 | E18: =E14-E17 -> 107248.68 | F18: =F14-F17 -> 120414.06 | G18: =G14-G17 -> 134011.07 | H18: =H14-H17 -> 147121.24 | I18: =I14-I17 -> 160038.18 | J18: =J14-J17 -> 173293.68
B19: Gross Margin (%) | C19: 0.802 | D19: 0.798 | E19: 0.795 | F19: 0.797 | G19: 0.799 | H19: 0.801 | I19: 0.803 | J19: 0.805
B21: R&D | C21: =C14*INDEX('Meta Drivers'!D$38:D$40,MATCH($D$5,'Meta Drivers'!$C$38:$C$40,0)) -> 30071.895 | D21: =D14*INDEX('Meta Drivers'!E$38:E$40,MATCH($D$5,'Meta Drivers'!$C$38:$C$40,0)) -> 31484.43 | E21: =E14*INDEX('Meta Drivers'!F$38:F$40,MATCH($D$5,'Meta Drivers'!$C$38:$C$40,0)) -> 39122.16 | F21: =F14*INDEX('Meta Drivers'!G$38:G$40,MATCH($D$5,'Meta Drivers'!$C$38:$C$40,0)) -> 43058.979 | G21: =G14*INDEX('Meta Drivers'!H$38:H$40,MATCH($D$5,'Meta Drivers'!$C$38:$C$40,0)) -> 46962.579 | H21: =H14*INDEX('Meta Drivers'!I$38:I$40,MATCH($D$5,'Meta Drivers'!$C$38:$C$40,0)) -> 50509.788 | I21: =I14*INDEX('Meta Drivers'!J$38:J$40,MATCH($D$5,'Meta Drivers'!$C$38:$C$40,0)) -> 53811.095 | J21: =J14*INDEX('Meta Drivers'!K$38:K$40,MATCH($D$5,'Meta Drivers'!$C$38:$C$40,0)) -> 57046.988
B22: S&M | C22: =C14*INDEX('Meta Drivers'!D$42:D$44,MATCH($D$5,'Meta Drivers'!$C$42:$C$44,0)) -> 13915.622 | D22: =D14*INDEX('Meta Drivers'!E$42:E$44,MATCH($D$5,'Meta Drivers'!$C$42:$C$44,0)) -> 14576.125 | E22: =E14*INDEX('Meta Drivers'!F$42:F$44,MATCH($D$5,'Meta Drivers'!$C$42:$C$44,0)) -> 17537.52 | F22: =F14*INDEX('Meta Drivers'!G$42:G$44,MATCH($D$5,'Meta Drivers'!$C$42:$C$44,0)) -> 18885.517 | G22: =G14*INDEX('Meta Drivers'!H$42:H$44,MATCH($D$5,'Meta Drivers'!$C$42:$C$44,0)) -> 20126.82 | H22: =H14*INDEX('Meta Drivers'!I$42:I$44,MATCH($D$5,'Meta Drivers'!$C$42:$C$44,0)) -> 21122.275 | I22: =I14*INDEX('Meta Drivers'!J$42:J$44,MATCH($D$5,'Meta Drivers'!$C$42:$C$44,0)) -> 21923.039 | J22: =J14*INDEX('Meta Drivers'!K$42:K$44,MATCH($D$5,'Meta Drivers'!$C$42:$C$44,0)) -> 22603.524
B23: G&A | C23: =C14*INDEX('Meta Drivers'!D$46:D$48,MATCH($D$5,'Meta Drivers'!$C$46:$C$48,0)) -> 12028.758 | D23: =D14*INDEX('Meta Drivers'!E$46:E$48,MATCH($D$5,'Meta Drivers'!$C$46:$C$48,0)) -> 12593.772 | E23: =E14*INDEX('Meta Drivers'!F$46:F$48,MATCH($D$5,'Meta Drivers'!$C$46:$C$48,0)) -> 15513.96 | F23: =F14*INDEX('Meta Drivers'!G$46:G$48,MATCH($D$5,'Meta Drivers'!$C$46:$C$48,0)) -> 16619.255 | G23: =G14*INDEX('Meta Drivers'!H$46:H$48,MATCH($D$5,'Meta Drivers'!$C$46:$C$48,0)) -> 17610.967 | H23: =H14*INDEX('Meta Drivers'!I$46:I$48,MATCH($D$5,'Meta Drivers'!$C$46:$C$48,0)) -> 18367.196 | I23: =I14*INDEX('Meta Drivers'!J$46:J$48,MATCH($D$5,'Meta Drivers'!$C$46:$C$48,0)) -> 18933.533 | J23: =J14*INDEX('Meta Drivers'!K$46:K$48,MATCH($D$5,'Meta Drivers'!$C$46:$C$48,0)) -> 19374.449
B24: SBC | C24: =C14*INDEX('Meta Drivers'!D$50:D$52,MATCH($D$5,'Meta Drivers'!$C$50:$C$52,0)) -> 10023.965 | D24: =D14*INDEX('Meta Drivers'!E$50:E$52,MATCH($D$5,'Meta Drivers'!$C$50:$C$52,0)) -> 11894.118 | E24: =E14*INDEX('Meta Drivers'!F$50:F$52,MATCH($D$5,'Meta Drivers'!$C$50:$C$52,0)) -> 15918.672 | F24: =F14*INDEX('Meta Drivers'!G$50:G$52,MATCH($D$5,'Meta Drivers'!$C$50:$C$52,0)) -> 16619.255 | G24: =G14*INDEX('Meta Drivers'!H$50:H$52,MATCH($D$5,'Meta Drivers'!$C$50:$C$52,0)) -> 17610.967 | H24: =H14*INDEX('Meta Drivers'!I$50:I$52,MATCH($D$5,'Meta Drivers'!$C$50:$C$52,0)) -> 18367.196 | I24: =I14*INDEX('Meta Drivers'!J$50:J$52,MATCH($D$5,'Meta Drivers'!$C$50:$C$52,0)) -> 18933.533 | J24: =J14*INDEX('Meta Drivers'!K$50:K$52,MATCH($D$5,'Meta Drivers'!$C$50:$C$52,0)) -> 19374.449
B25: Operating Expenses — Total | C25: =SUM(C21:C24) -> 66040.24 | D25: =SUM(D21:D24) -> 70548.445 | E25: =SUM(E21:E24) -> 88092.312 | F25: =SUM(F21:F24) -> 95183.007 | G25: =SUM(G21:G24) -> 102311.33 | H25: =SUM(H21:H24) -> 108366.45 | I25: =SUM(I21:I24) -> 113601.2 | J25: =SUM(J21:J24) -> 118399.41
B27: EBIT / Operating Income | C27: =C18-C25 -> 28538.818 | D27: =D18-D25 -> 22505.537 | E27: =E18-E25 -> 19156.368 | F27: =F18-F25 -> 25231.051 | G27: =G18-G25 -> 31699.741 | H27: =H18-H25 -> 38754.783 | I27: =I18-I25 -> 46436.982 | J27: =J18-J25 -> 54894.272
B28: Operating Margin (%) | C28: =C27/C14 -> 0.242 | D28: =D27/D14 -> 0.193 | E28: =E27/E14 -> 0.142 | F28: =F27/F14 -> 0.167 | G28: =G27/G14 -> 0.189 | H28: =H27/H14 -> 0.211 | I28: =I27/I14 -> 0.233 | J28: =J27/J14 -> 0.255
B30: Interest (Expense) / Income | C30: =(C$49*INDEX('Meta Drivers'!D$99:D$101,MATCH($D$5,'Meta Drivers'!$C$99:$C$101,0)))-(C71*INDEX('Meta Drivers'!D$103:D$105,MATCH($D$5,'Meta Drivers'!$C$103:$C$105,0))) -> -125 | D30: =(D$49*INDEX('Meta Drivers'!E$99:E$101,MATCH($D$5,'Meta Drivers'!$C$99:$C$101,0)))-(D71*INDEX('Meta Drivers'!E$103:E$105,MATCH($D$5,'Meta Drivers'!$C$103:$C$105,0))) -> 277.83077 | E30: =(E$49*INDEX('Meta Drivers'!F$99:F$101,MATCH($D$5,'Meta Drivers'!$C$99:$C$101,0)))-(E71*INDEX('Meta Drivers'!F$103:F$105,MATCH($D$5,'Meta Drivers'!$C$103:$C$105,0))) -> 735.70932 | F30: =(F$49*INDEX('Meta Drivers'!G$99:G$101,MATCH($D$5,'Meta Drivers'!$C$99:$C$101,0)))-(F71*INDEX('Meta Drivers'!G$103:G$105,MATCH($D$5,'Meta Drivers'!$C$103:$C$105,0))) -> 1394.0687 | G30: =(G$49*INDEX('Meta Drivers'!H$99:H$101,MATCH($D$5,'Meta Drivers'!$C$99:$C$101,0)))-(G71*INDEX('Meta Drivers'!H$103:H$105,MATCH($D$5,'Meta Drivers'!$C$103:$C$105,0))) -> 1470.2403 | H30: =(H$49*INDEX('Meta Drivers'!I$99:I$101,MATCH($D$5,'Meta Drivers'!$C$99:$C$101,0)))-(H71*INDEX('Meta Drivers'!I$103:I$105,MATCH($D$5,'Meta Drivers'!$C$103:$C$105,0))) -> 1548.5894 | I30: =(I$49*INDEX('Meta Drivers'!J$99:J$101,MATCH($D$5,'Meta Drivers'!$C$99:$C$101,0)))-(I71*INDEX('Meta Drivers'!J$103:J$105,MATCH($D$5,'Meta Drivers'!$C$103:$C$105,0))) -> 1978.7742 | J30: =(J$49*INDEX('Meta Drivers'!K$99:K$101,MATCH($D$5,'Meta Drivers'!$C$99:$C$101,0)))-(J71*INDEX('Meta Drivers'!K$103:K$105,MATCH($D$5,'Meta Drivers'!$C$103:$C$105,0))) -> 1954.4025
B32: Pre-tax Income | C32: =C27+C30 -> 28413.818 | D32: =D27+D30 -> 22783.368 | E32: =E27+E30 -> 19892.077 | F32: =F27+F30 -> 26625.12 | G32: =G27+G30 -> 33169.981 | H32: =H27+H30 -> 40303.372 | I32: =I27+I30 -> 48415.756 | J32: =J27+J30 -> 56848.674
B33: Tax Expense / Provision | C33: =C32*INDEX('Meta Drivers'!D$92:D$94,MATCH($D$5,'Meta Drivers'!$C$92:$C$94,0)) -> 4972.4181 | D33: =D32*INDEX('Meta Drivers'!E$92:E$94,MATCH($D$5,'Meta Drivers'!$C$92:$C$94,0)) -> 4328.8399 | E33: =E32*INDEX('Meta Drivers'!F$92:F$94,MATCH($D$5,'Meta Drivers'!$C$92:$C$94,0)) -> 3680.0343 | F33: =F32*INDEX('Meta Drivers'!G$92:G$94,MATCH($D$5,'Meta Drivers'!$C$92:$C$94,0)) -> 5058.7727 | G33: =G32*INDEX('Meta Drivers'!H$92:H$94,MATCH($D$5,'Meta Drivers'!$C$92:$C$94,0)) -> 6468.1463 | H33: =H32*INDEX('Meta Drivers'!I$92:I$94,MATCH($D$5,'Meta Drivers'!$C$92:$C$94,0)) -> 8060.6744 | I33: =I32*INDEX('Meta Drivers'!J$92:J$94,MATCH($D$5,'Meta Drivers'!$C$92:$C$94,0)) -> 9925.23 | J33: =J32*INDEX('Meta Drivers'!K$92:K$94,MATCH($D$5,'Meta Drivers'!$C$92:$C$94,0)) -> 11938.222
B35: Net income | C35: =C32-C33 -> 23441.4 | D35: =D32-D33 -> 18454.528 | E35: =E32-E33 -> 16212.043 | F35: =F32-F33 -> 21566.347 | G35: =G32-G33 -> 26701.835 | H35: =H32-H33 -> 32242.698 | I35: =I32-I33 -> 38490.526 | J35: =J32-J33 -> 44910.452
B36: Net Margin (%) | C36: =C35/C14 -> 0.19877553 | D36: =D35/D14 -> 0.15825989 | E36: =E35/E14 -> 0.12017467 | F36: =F35/F14 -> 0.14274395 | G36: =G35/G14 -> 0.15920152 | H36: =H35/H14 -> 0.17554502 | I36: =I35/I14 -> 0.19312824 | J36: =J35/J14 -> 0.20862223
B38: EPS calculation
B40: Basic Shares — Outstanding | C40: 2800 | D40: 2750 | E40: 2700 | F40: 2650 | G40: 2600 | H40: 2550 | I40: 2500 | J40: 2450
B41: EPS — Basic | C41: =C35/C40 -> 8.3719285 | D41: =D35/D40 -> 6.7107374 | E41: =E35/E40 -> 6.0044604 | F41: =F35/F40 -> 8.1382441 | G41: =G35/G40 -> 10.269936 | H41: =H35/H40 -> 12.644195 | I41: =I35/I40 -> 15.39621 | J41: =J35/J40 -> 18.330797
B44: Balance sheet schedule
B46: Assets section
B48: Assets — Current
B49: Cash and equivalents | C49: 35000 | D49: =D$106 -> 40688.718 | E49: =E$106 -> 43828.373 | F49: =F$106 -> 50759.105 | G49: =G$106 -> 59674.678 | H49: =H$106 -> 72443.575 | I49: =I$106 -> 87550.968 | J49: =J$106 -> 107470.12
B50: Receivables | C50: =C$14*INDEX('Meta Drivers'!D$64:D$66,MATCH($D$5,'Meta Drivers'!$C$64:$C$66,0))/365 -> 17770.123 | D50: =D$14*INDEX('Meta Drivers'!E$64:E$66,MATCH($D$5,'Meta Drivers'!$C$64:$C$66,0))/365 -> 16932.266 | E50: =E$14*INDEX('Meta Drivers'!F$64:F$66,MATCH($D$5,'Meta Drivers'!$C$64:$C$66,0))/365 -> 18849.6 | F50: =F$14*INDEX('Meta Drivers'!G$64:G$66,MATCH($D$5,'Meta Drivers'!$C$64:$C$66,0))/365 -> 20696.457 | G50: =G$14*INDEX('Meta Drivers'!H$64:H$66,MATCH($D$5,'Meta Drivers'!$C$64:$C$66,0))/365 -> 22516.305 | H50: =H$14*INDEX('Meta Drivers'!I$64:I$66,MATCH($D$5,'Meta Drivers'!$C$64:$C$66,0))/365 -> 24154.12 | I50: =I$14*INDEX('Meta Drivers'!J$64:J$66,MATCH($D$5,'Meta Drivers'!$C$64:$C$66,0))/365 -> 25663.333 | J50: =J$14*INDEX('Meta Drivers'!K$64:K$66,MATCH($D$5,'Meta Drivers'!$C$64:$C$66,0))/365 -> 27130.126
B51: Other current assets | C51: 5000 | D51: =C51*(1+'Meta Drivers'!E$72) -> 5200 | E51: =D51*(1+'Meta Drivers'!F$72) -> 5400 | F51: =E51*(1+'Meta Drivers'!G$72) -> 5616 | G51: =F51*(1+'Meta Drivers'!H$72) -> 5840.64 | H51: =G51*(1+'Meta Drivers'!I$72) -> 6074.2656 | I51: =H51*(1+'Meta Drivers'!J$72) -> 6317.2362 | J51: =I51*(1+'Meta Drivers'!K$72) -> 6569.9257
B52: Current Assets — Total | C52: =SUM(C49:C51) -> 57770.123 | D52: =SUM(D49:D51) -> 62820.984 | E52: =SUM(E49:E51) -> 68077.973 | F52: =SUM(F49:F51) -> 77071.562 | G52: =SUM(G49:G51) -> 88031.623 | H52: =SUM(H49:H51) -> 102671.96 | I52: =SUM(I49:I51) -> 119531.54 | J52: =SUM(J49:J51) -> 141170.18
B54: Assets — Non-current
B55: PP&E (Gross) | C55: 60000 | D55: =C55+D95 -> 85653.98 | E55: =D55+E95 -> 118705.46 | F55: =E55+F95 -> 153454.81 | G55: =F55+G95 -> 189515.36 | H55: =G55+H95 -> 226249.75 | I55: =H55+I95 -> 264116.82 | J55: =I55+J95 -> 302865.72
B56: Less: Accumulated depreciation | C56: 15000 | D56: =C56+D87 -> 29180.962 | E56: =D56+E87 -> 45856.049 | F56: =E56+F87 -> 67339.511 | G56: =F56+G87 -> 89926.59 | H56: =G56+H87 -> 113365.95 | I56: =H56+I87 -> 137243.3 | J56: =I56+J87 -> 161856.9
B57: Net PP&E | C57: =C55-C56 -> 45000 | D57: =D55-D56 -> 56473.018 | E57: =E55-E56 -> 72849.411 | F57: =F55-F56 -> 86115.3 | G57: =G55-G56 -> 99588.774 | H57: =H55-H56 -> 112883.81 | I57: =I55-I56 -> 126873.52 | J57: =J55-J56 -> 141008.82
B59: Other Long-term Assets | C59: 25000 | D59: =C59*(1+'Meta Drivers'!E$73) -> 28000 | E59: =D59*(1+'Meta Drivers'!F$73) -> 32000 | F59: =E59*(1+'Meta Drivers'!G$73) -> 35200 | G59: =F59*(1+'Meta Drivers'!H$73) -> 38720 | H59: =G59*(1+'Meta Drivers'!I$73) -> 42592 | I59: =H59*(1+'Meta Drivers'!J$73) -> 46851.2 | J59: =I59*(1+'Meta Drivers'!K$73) -> 51536.32
B60: Total Non-Current Assets | C60: =C57+C59 -> 70000 | D60: =D57+D59 -> 84473.018 | E60: =E57+E59 -> 104849.41 | F60: =F57+F59 -> 121315.3 | G60: =G57+G59 -> 138308.77 | H60: =H57+H59 -> 155475.81 | I60: =I57+I59 -> 173724.72 | J60: =J57+J59 -> 192545.14
B62: Total Assets | C62: =C52+C60 -> 127770.12 | D62: =D52+D60 -> 147294 | E62: =E52+E60 -> 172927.38 | F62: =F52+F60 -> 198386.86 | G62: =G52+G60 -> 226340.4 | H62: =H52+H60 -> 258147.77 | I62: =I52+I60 -> 293256.26 | J62: =J52+J60 -> 333715.32
B64: Liabilities and equity
B66: Liabilities — Current
B67: Payables | C67: =(C17+C21+C22+C23)*INDEX('Meta Drivers'!D$68:D$70,MATCH($D$5,'Meta Drivers'!$C$68:$C$70,0))/365 -> 6088.3673 | D67: =(D17+D21+D22+D23)*INDEX('Meta Drivers'!E$68:E$70,MATCH($D$5,'Meta Drivers'!$C$68:$C$70,0))/365 -> 6756.9325 | E67: =(E17+E21+E22+E23)*INDEX('Meta Drivers'!F$68:F$70,MATCH($D$5,'Meta Drivers'!$C$68:$C$70,0))/365 -> 8752.128 | F67: =(F17+F21+F22+F23)*INDEX('Meta Drivers'!G$68:G$70,MATCH($D$5,'Meta Drivers'!$C$68:$C$70,0))/365 -> 9875.9355 | G67: =(G17+G21+G22+G23)*INDEX('Meta Drivers'!H$68:H$70,MATCH($D$5,'Meta Drivers'!$C$68:$C$70,0))/365 -> 11030.232 | H67: =(H17+H21+H22+H23)*INDEX('Meta Drivers'!I$68:I$70,MATCH($D$5,'Meta Drivers'!$C$68:$C$70,0))/365 -> 12134.929 | I67: =(I17+I21+I22+I23)*INDEX('Meta Drivers'!J$68:J$70,MATCH($D$5,'Meta Drivers'!$C$68:$C$70,0))/365 -> 13209.518 | J67: =(J17+J21+J22+J23)*INDEX('Meta Drivers'!K$68:K$70,MATCH($D$5,'Meta Drivers'!$C$68:$C$70,0))/365 -> 14293.448
B68: Accrued Expenses | C68: 8000 | D68: =C68*(1+'Meta Drivers'!E$74) -> 8500 | E68: =D68*(1+'Meta Drivers'!F$74) -> 9000 | F68: =E68*(1+'Meta Drivers'!G$74) -> 9450 | G68: =F68*(1+'Meta Drivers'!H$74) -> 9922.5 | H68: =G68*(1+'Meta Drivers'!I$74) -> 10418.625 | I68: =H68*(1+'Meta Drivers'!J$74) -> 10939.556 | J68: =I68*(1+'Meta Drivers'!K$74) -> 11486.534
B69: Current Liabilities — Total | C69: =SUM(C67:C68) -> 14088.367 | D69: =SUM(D67:D68) -> 15256.932 | E69: =SUM(E67:E68) -> 17752.128 | F69: =SUM(F67:F68) -> 19325.935 | G69: =SUM(G67:G68) -> 20952.732 | H69: =SUM(H67:H68) -> 22553.554 | I69: =SUM(I67:I68) -> 24149.074 | J69: =SUM(J67:J68) -> 25779.982
B71: Long-term Debt | C71: 10000 | D71: 9500 | E71: 9000 | F71: 8500 | G71: 8000 | H71: 7500 | I71: 7000 | J71: 6500
B72: Liabilities — Total | C72: =C69+C71 -> 24088.367 | D72: =D69+D71 -> 24756.932 | E72: =E69+E71 -> 26752.128 | F72: =F69+F71 -> 27825.935 | G72: =G69+G71 -> 28952.732 | H72: =H69+H71 -> 30053.554 | I72: =I69+I71 -> 31149.074 | J72: =J69+J71 -> 32279.982
B74: Shareholders' Equity
B75: Common Stock & APIC | C75: 40000 | D75: =C75+D88 -> 51894.118 | E75: =D75+E88 -> 67812.79 | F75: =E75+F88 -> 84432.045 | G75: =F75+G88 -> 102043.01 | H75: =G75+H88 -> 120410.21 | I75: =H75+I88 -> 139343.74 | J75: =I75+J88 -> 158718.19
B76: Treasury Stock | C76: 36318.244 | D76: =C76-D100 -> 47811.577 | E76: =D76-E100 -> 56304.105 | F76: =E76-F100 -> 70104.036 | G76: =F76-G100 -> 87590.101 | H76: =G76-H100 -> 107493.45 | I76: =H76-I100 -> 130904.54 | J76: =I76-J100 -> 155861.28
B77: Retained earnings | C77: 100000 | D77: =C77+D86 -> 118454.53 | E77: =D77+E86 -> 134666.57 | F77: =E77+F86 -> 156232.92 | G77: =F77+G86 -> 182934.75 | H77: =G77+H86 -> 215177.45 | I77: =H77+I86 -> 253667.98 | J77: =I77+J86 -> 298578.43
B78: Total Shareholders' Equity | C78: =C75-C76+C77 -> 103681.76 | D78: =D75-D76+D77 -> 122537.07 | E78: =E75-E76+E77 -> 146175.26 | F78: =F75-F76+F77 -> 170560.93 | G78: =G75-G76+G77 -> 197387.66 | H78: =H75-H76+H77 -> 228094.21 | I78: =I75-I76+I77 -> 262107.18 | J78: =J75-J76+J77 -> 301435.34
B80: Total Liabilities & Equity | C80: =C72+C78 -> 127770.12 | D80: =D72+D78 -> 147294 | E80: =E72+E78 -> 172927.38 | F80: =F72+F78 -> 198386.86 | G80: =G72+G78 -> 226340.4 | H80: =H72+H78 -> 258147.77 | I80: =I72+I78 -> 293256.26 | J80: =J72+J78 -> 333715.32
B82: Balance Check (Assets — L&E) | C82: =C62-C80 -> 0 | D82: =D62-D80 -> 0 | E82: =E62-E80 -> 0 | F82: =F62-F80 -> 0 | G82: =G62-G80 -> 0 | H82: =H62-H80 -> 0 | I82: =I62-I80 -> 0 | J82: =J62-J80 -> 0
B84: Cash-flow statement
B85: Cash Flow from Operating Activities
B86: Net Income | D86: {=D35} -> 18454.528 | E86: {=E35} -> 16212.043 | F86: {=F35} -> 21566.347 | G86: {=G35} -> 26701.835 | H86: {=H35} -> 32242.698 | I86: {=I35} -> 38490.526 | J86: {=J35} -> 44910.452
B87: Add — Depreciation & Amortization | D87: =C$95*INDEX('Meta Drivers'!E$82:E$84,MATCH($D$5,'Meta Drivers'!$C$82:$C$84,0)) -> 14180.962 | E87: =D$95*INDEX('Meta Drivers'!F$82:F$84,MATCH($D$5,'Meta Drivers'!$C$82:$C$84,0)) -> 16675.087 | F87: =E$95*INDEX('Meta Drivers'!G$82:G$84,MATCH($D$5,'Meta Drivers'!$C$82:$C$84,0)) -> 21483.462 | G87: =F$95*INDEX('Meta Drivers'!H$82:H$84,MATCH($D$5,'Meta Drivers'!$C$82:$C$84,0)) -> 22587.079 | H87: =G$95*INDEX('Meta Drivers'!I$82:I$84,MATCH($D$5,'Meta Drivers'!$C$82:$C$84,0)) -> 23439.359 | I87: =H$95*INDEX('Meta Drivers'!J$82:J$84,MATCH($D$5,'Meta Drivers'!$C$82:$C$84,0)) -> 23877.354 | J87: =I$95*INDEX('Meta Drivers'!K$82:K$84,MATCH($D$5,'Meta Drivers'!$C$82:$C$84,0)) -> 24613.594
B88: Add: SBC | D88: {=D24} -> 11894.118 | E88: {=E24} -> 15918.672 | F88: {=F24} -> 16619.255 | G88: {=G24} -> 17610.967 | H88: {=H24} -> 18367.196 | I88: {=I24} -> 18933.533 | J88: {=J24} -> 19374.449
B89: Changes in Working Capital —
B90: (Increase)/Decrease in Current Assets | D90: =-(SUM(D50:D51)-SUM(C50:C51)) -> 637.85753 | E90: =-(SUM(E50:E51)-SUM(D50:D51)) -> -2117.3342 | F90: =-(SUM(F50:F51)-SUM(E50:E51)) -> -2062.8573 | G90: =-(SUM(G50:G51)-SUM(F50:F51)) -> -2044.4877 | H90: =-(SUM(H50:H51)-SUM(G50:G51)) -> -1871.4409 | I90: =-(SUM(I50:I51)-SUM(H50:H51)) -> -1752.1834 | J90: =-(SUM(J50:J51)-SUM(I50:I51)) -> -1719.4826
B91: Increase/(Decrease) in Current Liabilities | D91: =SUM(D67:D68)-SUM(C67:C68) -> 1168.5651 | E91: =SUM(E67:E68)-SUM(D67:D68) -> 2495.1955 | F91: =SUM(F67:F68)-SUM(E67:E68) -> 1573.8075 | G91: =SUM(G67:G68)-SUM(F67:F68) -> 1626.7969 | H91: =SUM(H67:H68)-SUM(G67:G68) -> 1600.822 | I91: =SUM(I67:I68)-SUM(H67:H68) -> 1595.52 | J91: =SUM(J67:J68)-SUM(I67:I68) -> 1630.9077
B92: Net Cash from Operating Activities | D92: =SUM(D86:D91) -> 46336.031 | E92: =SUM(E86:E91) -> 49183.663 | F92: =SUM(F86:F91) -> 59180.014 | G92: =SUM(G86:G91) -> 66482.19 | H92: =SUM(H86:H91) -> 73778.633 | I92: =SUM(I86:I91) -> 81144.751 | J92: =SUM(J86:J91) -> 88809.92
B94: Cash Flow from Investing Activities
B95: CapEx | C95: =C$14*INDEX('Meta Drivers'!D$78:D$80,MATCH($D$5,'Meta Drivers'!$C$78:$C$80,0)) -> 21816.865 | D95: =D$14*INDEX('Meta Drivers'!E$78:E$80,MATCH($D$5,'Meta Drivers'!$C$78:$C$80,0)) -> 25653.98 | E95: =E$14*INDEX('Meta Drivers'!F$78:F$80,MATCH($D$5,'Meta Drivers'!$C$78:$C$80,0)) -> 33051.48 | F95: =F$14*INDEX('Meta Drivers'!G$78:G$80,MATCH($D$5,'Meta Drivers'!$C$78:$C$80,0)) -> 34749.352 | G95: =G$14*INDEX('Meta Drivers'!H$78:H$80,MATCH($D$5,'Meta Drivers'!$C$78:$C$80,0)) -> 36060.552 | H95: =H$14*INDEX('Meta Drivers'!I$78:I$80,MATCH($D$5,'Meta Drivers'!$C$78:$C$80,0)) -> 36734.391 | I95: =I$14*INDEX('Meta Drivers'!J$78:J$80,MATCH($D$5,'Meta Drivers'!$C$78:$C$80,0)) -> 37867.067 | J95: =J$14*INDEX('Meta Drivers'!K$78:K$80,MATCH($D$5,'Meta Drivers'!$C$78:$C$80,0)) -> 38748.898
B96: Long-term investments | D96: =D59-C59 -> 3000 | E96: =E59-D59 -> 4000 | F96: =F59-E59 -> 3200 | G96: =G59-F59 -> 3520 | H96: =H59-G59 -> 3872 | I96: =I59-H59 -> 4259.2 | J96: =J59-I59 -> 4685.12
B97: Net Cash from Investing Activities | D97: =-SUM(D95:D96) -> -28653.98 | E97: =-SUM(E95:E96) -> -37051.48 | F97: =-SUM(F95:F96) -> -37949.352 | G97: =-SUM(G95:G96) -> -39580.552 | H97: =-SUM(H95:H96) -> -40606.391 | I97: =-SUM(I95:I96) -> -42126.267 | J97: =-SUM(J95:J96) -> -43434.018
B99: Cash Flow from Financing Activities
B100: Share Repurchases | D100: =-MAX(D92+D97,0)*INDEX('Meta Drivers'!E$109:E$111,MATCH($D$5,'Meta Drivers'!$C$109:$C$111,0)) -> -11493.333 | E100: =-MAX(E92+E97,0)*INDEX('Meta Drivers'!F$109:F$111,MATCH($D$5,'Meta Drivers'!$C$109:$C$111,0)) -> -8492.5283 | F100: =-MAX(F92+F97,0)*INDEX('Meta Drivers'!G$109:G$111,MATCH($D$5,'Meta Drivers'!$C$109:$C$111,0)) -> -13799.931 | G100: =-MAX(G92+G97,0)*INDEX('Meta Drivers'!H$109:H$111,MATCH($D$5,'Meta Drivers'!$C$109:$C$111,0)) -> -17486.065 | H100: =-MAX(H92+H97,0)*INDEX('Meta Drivers'!I$109:I$111,MATCH($D$5,'Meta Drivers'!$C$109:$C$111,0)) -> -19903.345 | I100: =-MAX(I92+I97,0)*INDEX('Meta Drivers'!J$109:J$111,MATCH($D$5,'Meta Drivers'!$C$109:$C$111,0)) -> -23411.09 | J100: =-MAX(J92+J97,0)*INDEX('Meta Drivers'!K$109:K$111,MATCH($D$5,'Meta Drivers'!$C$109:$C$111,0)) -> -24956.746
B101: Debt Repayments | D101: =D$71-C$71 -> -500 | E101: =E$71-D$71 -> -500 | F101: =F$71-E$71 -> -500 | G101: =G$71-F$71 -> -500 | H101: =H$71-G$71 -> -500 | I101: =I$71-H$71 -> -500 | J101: =J$71-I$71 -> -500
B102: Net Cash from Financing Activities | D102: =SUM(D99:D101) -> -11993.333 | E102: =SUM(E99:E101) -> -8992.5283 | F102: =SUM(F99:F101) -> -14299.931 | G102: =SUM(G99:G101) -> -17986.065 | H102: =SUM(H99:H101) -> -20403.345 | I102: =SUM(I99:I101) -> -23911.09 | J102: =SUM(J99:J101) -> -25456.746
B104: Net Change in Cash | D104: =D92+D97+D102 -> 5688.7178 | E104: =E92+E97+E102 -> 3139.655 | F104: =F92+F97+F102 -> 6930.7319 | G104: =G92+G97+G102 -> 8915.5733 | H104: =H92+H97+H102 -> 12768.897 | I104: =I92+I97+I102 -> 15107.393 | J104: =J92+J97+J102 -> 19919.156
B105: Beginning Cash | D105: =C$106 -> 35000 | E105: =D$106 -> 40688.718 | F105: =E$106 -> 43828.373 | G105: =F$106 -> 50759.105 | H105: =G$106 -> 59674.678 | I105: =H$106 -> 72443.575 | J105: =I$106 -> 87550.968
B106: Cash — Ending | C106: =C$49 -> 35000 | D106: =D104+D105 -> 40688.718 | E106: =E104+E105 -> 43828.373 | F106: =F104+F105 -> 50759.105 | G106: =G104+G105 -> 59674.678 | H106: =H104+H105 -> 72443.575 | I106: =I104+I105 -> 87550.968 | J106: =J104+J105 -> 107470.12
B108: Cash Balance Check | C108: =C106-C49 -> 0 | D108: =D106-D49 -> 0 | E108: =E106-E49 -> 0 | F108: =F106-F49 -> 0 | G108: =G106-G49 -> 0 | H108: =H106-H49 -> 0 | I108: =I106-I49 -> 0 | J108: =J106-J49 -> 0
B110: Valuation Multiples
F111: 2024P | G111: 2025P | H111: 2026P | I111: 2027P | J111: 2028P
B112: Market Capitalization ($B) | F112: 1830
B113: Net Debt Position ($B) | F113: =($F$71-$F$49)/1000 -> -42.259105
B114: Enterprise Value / TEV ($B) | F114: =F112+F113 -> 1787.7409
B116: Revenue Multiple (EV / Sales) | F116: =$F$114*1000/F$14 -> 11.83275 | G116: =$F$114*1000/G$14 -> 10.658858 | H116: =$F$114*1000/H$14 -> 9.7333362 | I116: =$F$114*1000/I$14 -> 8.970084 | J116: =$F$114*1000/J$14 -> 8.3045811
B117: EBITDA Multiple (EV / EBITDA) | F117: =$F$114*1000/(F$27+F$87) -> 38.269497 | G117: =$F$114*1000/(G$27+G$87) -> 32.931399 | H117: =$F$114*1000/(H$27+H$87) -> 28.744522 | I117: =$F$114*1000/(I$27+I$87) -> 25.424984 | J117: =$F$114*1000/(J$27+J$87) -> 22.485082
B118: P / E | F118: =$F$112*1000/F$35 -> 84.854426 | G118: =$F$112*1000/G$35 -> 68.534616 | H118: =$F$112*1000/H$35 -> 56.757037 | I118: =$F$112*1000/I$35 -> 47.544167 | J118: =$F$112*1000/J$35 -> 40.747752

Sheet Deal Inputs
B2: Deal input deck — Google / Meta combination
B3: Merger model inputs — pro forma
B4: Figures in $mm
B5: Transaction Overview — 1
B7: Deal structure
B8: Buyer | D8: Google (Alphabet)
B9: Seller / Target | D9: Meta Platforms
B10: Consideration type | D10: Stock & Cash Combination
B11: Announcement timing | D11: Q4 2023
B12: Expected close timing | D12: Q1 2024
B14: Purchase price Calculation — 2
B16: Stock Prices & Premium
B17: Meta Current Stock Price | D17: 520
B18: Premium Offered | D18: 0.3
B19: Offer Price per Share | D19: =D17*(1+D18) -> 676
B20: Meta Shares Outstanding (mm) | D20: 2700
B21: Total Purchase price ($mm) | D21: =D19*D20 -> 1825200
B23: Consideration split
B24: % Cash Consideration | D24: 0.5
B25: % Stock Consideration | D25: 0.5
B26: Cash Required — $mm | D26: =$D$21*D24 -> 912600
B27: Stock Value Required — $mm | D27: =$D$21*D25 -> 912600
B28: Google Stock Price | D28: 175
B29: New Google Shares Issued (mm) | D29: =D27/D28 -> 5214.8571
B31: Sources & Uses Of Funds — 3
B33: Funding Sources ($mm) | F33: Funding Uses ($mm)
B34: Stock Issued | D34: =$D$27 -> 912600 | F34: Purchase price | H34: {=D21} -> 1825200
B35: New Term Loan | D35: 400000 | F35: Transaction Fees | H35: =$D$21*$I$35 -> 36504 | I35: 0.02
B36: Bridge Loan | D36: 100000 | F36: Financing Fees | H36: =(D35+D36)*$I$36 -> 12500 | I36: 0.025
B37: Cash on Hand | D37: =H38-D26-D35-D36 -> 466604 | F37: Integration Costs | H37: 5000
B38: Sources — Total | D38: =SUM(D34:D37) -> 1879204 | F38: Uses — Total | H38: =SUM(H34:H37) -> 1879204
B40: Synergy Assumptions — 4
B42: Revenue Synergies — $mm
D43: Year 1 | E43: Year 2 | F43: Year 3 | G43: Year 4 | H43: Year 5
B44: Cross-Platform Advertising | D44: 2000 | E44: 4000 | F44: 6000 | G44: 7000 | H44: 8000
B45: Data & AI Integration | D45: 1000 | E45: 2500 | F45: 4000 | G45: 5000 | H45: 6000
B46: Market Expansion | D46: 500 | E46: 1500 | F46: 2500 | G46: 3000 | H46: 3500
B47: Total Revenue Synergies | D47: =SUM(D44:D46) -> 3500 | E47: =SUM(E44:E46) -> 8000 | F47: =SUM(F44:F46) -> 12500 | G47: =SUM(G44:G46) -> 15000 | H47: =SUM(H44:H46) -> 17500
B49: Cost Synergies — $mm
B50: Infrastructure & Cloud | D50: 3000 | E50: 5000 | F50: 7000 | G50: 8000 | H50: 8500
B51: R&D Efficiency | D51: 2000 | E51: 3500 | F51: 4500 | G51: 5000 | H51: 5500
B52: G&A Consolidation | D52: 1500 | E52: 2500 | F52: 3000 | G52: 3200 | H52: 3400
B53: S&M | D53: 1000 | E53: 2000 | F53: 2500 | G53: 2800 | H53: 3000
B54: Total Cost Synergies | D54: =SUM(D50:D53) -> 7500 | E54: =SUM(E50:E53) -> 13000 | F54: =SUM(F50:F53) -> 17000 | G54: =SUM(G50:G53) -> 19000 | H54: =SUM(H50:H53) -> 20400
B56: Dis-Synergies & Implementation
B57: Customer Attrition | D57: -1000 | E57: -800 | F57: -500 | G57: -300 | H57: -200
B58: Integration Costs | D58: -3000 | E58: -2000 | F58: -1000 | G58: -500 | H58: 0
B59: Retention Bonuses | D59: -2000 | E59: -1500 | F59: -1000 | G59: -500 | H59: 0
B60: Total Dis-Synergies | D60: =SUM(D57:D59) -> -6000 | E60: =SUM(E57:E59) -> -4300 | F60: =SUM(F57:F59) -> -2500 | G60: =SUM(G57:G59) -> -1300 | H60: =SUM(H57:H59) -> -200
B62: Net Synergies | D62: =D47+D54+D60 -> 5000 | E62: =E47+E54+E60 -> 16700 | F62: =F47+F54+F60 -> 27000 | G62: =G47+G54+G60 -> 32700 | H62: =H47+H54+H60 -> 37700
B64: Purchase Accounting — 5
B66: Purchase price Allocation ($mm)
B67: Purchase price | D67: {=D21} -> 1825200
B68: Less — Book Value of Equity | D68: -141740
B69: Premium Over Book | D69: =D67+D68 -> 1683460
B71: Allocation —
B72: Identifiable Intangible Assets | D72: 25000
B73: PP&E Fair Value Adjustment | D73: 0
B74: Deferred Tax Liability | D74: =-(D72+D73)*0.21 -> -5250
B75: Goodwill | D75: =D69-D72-D73-D74 -> 1663710
B77: Financing Assumptions — 6
B79: Debt Financing
B80: Term Loan Amount — $mm | D80: {=D35} -> 400000
B81: Term Loan Interest Rate | D81: 0.055
B82: Bridge Loan Amount — $mm | D82: {=D36} -> 100000
B83: Bridge Loan Interest Rate | D83: 0.065
B84: Mandatory Amortization % p.a. | D84: 0.05
B86: Pro Forma Adjustments — 7
B88: Amortization of Intangibles
B89: Intangible Asset Value — $mm | D89: =D72 -> 25000
B90: Amortization Period — years | D90: 10
B91: Annual Amortization — $mm | D91: =D89/D90 -> 2500
B93: Other Adjustments
B94: Stock-Based Comp Adjustment % | D94: 0
B95: Combined Tax Rate | D95: 0.21

Sheet Pro Forma
B2: Pro forma company — Google / Meta
B3: Figures in $mm
B5: Transaction snapshot
B7: Purchase price ($mm): | D7: ='Deal Inputs'!$D$21 -> 1825200
B8: Cash Consideration — | D8: ='Deal Inputs'!$D$26 -> 912600
B9: Stock Consideration — | D9: ='Deal Inputs'!$D$27 -> 912600
B10: Total Debt Raised — | D10: ='Deal Inputs'!$D$35+'Deal Inputs'!$D$36 -> 500000
B11: Goodwill Created — | D11: ='Deal Inputs'!$D$75 -> 1663710
B13: Pro Forma Income Statement
B15: For the Year Ending | D15: 2024 | E15: 2025 | F15: 2026 | G15: 2027 | H15: 2028
B17: Revenue — Combined
B18: Google Revenue | D18: ='Google Model'!F$16 -> 292008.95 | E18: ='Google Model'!G$16 -> 320857.36 | F18: ='Google Model'!H$16 -> 349262.74 | G18: ='Google Model'!I$16 -> 377287.31 | H18: ='Google Model'!J$16 -> 405460.92
B19: Meta Revenue | D19: ='Meta Model'!F$14 -> 151084.14 | E19: ='Meta Model'!G$14 -> 167723.5 | F19: ='Meta Model'!H$14 -> 183671.96 | G19: ='Meta Model'!I$14 -> 199300.35 | H19: ='Meta Model'!J$14 -> 215271.65
B20: Revenue synergy contribution | D20: ='Deal Inputs'!D$47 -> 3500 | E20: ='Deal Inputs'!E$47 -> 8000 | F20: ='Deal Inputs'!F$47 -> 12500 | G20: ='Deal Inputs'!G$47 -> 15000 | H20: ='Deal Inputs'!H$47 -> 17500
B21: Combined Revenue — Total | D21: =SUM(D18:D20) -> 446593.09 | E21: =SUM(E18:E20) -> 496580.85 | F21: =SUM(F18:F20) -> 545434.7 | G21: =SUM(G18:G20) -> 591587.67 | H21: =SUM(H18:H20) -> 638232.57
B23: Operating expense build
B24: Cost of sales (Combined) | D24: ='Google Model'!F$32+'Meta Model'!F$17 -> 161490.09 | E24: ='Google Model'!G$32+'Meta Model'!G$17 -> 176814.8 | F24: ='Google Model'!H$32+'Meta Model'!H$17 -> 191623.38 | G24: ='Google Model'!I$32+'Meta Model'!I$17 -> 206023.16 | H24: ='Google Model'!J$32+'Meta Model'!J$17 -> 220380.78
B25: Infrastructure synergy value | D25: =-'Deal Inputs'!D$50 -> -3000 | E25: =-'Deal Inputs'!E$50 -> -5000 | F25: =-'Deal Inputs'!F$50 -> -7000 | G25: =-'Deal Inputs'!G$50 -> -8000 | H25: =-'Deal Inputs'!H$50 -> -8500
B26: Profit — Gross | D26: =D21-D24-D25 -> 288103 | E26: =E21-E24-E25 -> 324766.05 | F26: =F21-F24-F25 -> 360811.32 | G26: =G21-G24-G25 -> 393564.5 | H26: =H21-H24-H25 -> 426351.79
B28: R&D — Combined | D28: ='Google Model'!F$36+'Meta Model'!F$21 -> 84816.26 | E28: ='Google Model'!G$36+'Meta Model'!G$21 -> 91882.609 | F28: ='Google Model'!H$36+'Meta Model'!H$21 -> 98708.047 | G28: ='Google Model'!I$36+'Meta Model'!I$21 -> 104744.88 | H28: ='Google Model'!J$36+'Meta Model'!J$21 -> 110973.29
B29: R&D synergy value | D29: =-'Deal Inputs'!D$51 -> -2000 | E29: =-'Deal Inputs'!E$51 -> -3500 | F29: =-'Deal Inputs'!F$51 -> -4500 | G29: =-'Deal Inputs'!G$51 -> -5000 | H29: =-'Deal Inputs'!H$51 -> -5500
B30: S&M — Combined | D30: ='Google Model'!F$37+'Meta Model'!F$22 -> 49546.458 | E30: ='Google Model'!G$37+'Meta Model'!G$22 -> 53175.127 | F30: ='Google Model'!H$37+'Meta Model'!H$22 -> 56048.549 | G30: ='Google Model'!I$37+'Meta Model'!I$22 -> 58897.196 | H30: ='Google Model'!J$37+'Meta Model'!J$22 -> 61122.311
B31: S&M synergy value | D31: =-'Deal Inputs'!D$53 -> -1000 | E31: =-'Deal Inputs'!E$53 -> -2000 | F31: =-'Deal Inputs'!F$53 -> -2500 | G31: =-'Deal Inputs'!G$53 -> -2800 | H31: =-'Deal Inputs'!H$53 -> -3000
B32: G&A — Combined | D32: ='Google Model'!F$38+'Meta Model'!F$23 -> 34723.81 | E32: ='Google Model'!G$38+'Meta Model'!G$23 -> 36862.409 | F32: ='Google Model'!H$38+'Meta Model'!H$23 -> 38624.435 | G32: ='Google Model'!I$38+'Meta Model'!I$23 -> 40438.91 | H32: ='Google Model'!J$38+'Meta Model'!J$23 -> 41674.799
B33: G&A synergy value | D33: =-'Deal Inputs'!D$52 -> -1500 | E33: =-'Deal Inputs'!E$52 -> -2500 | F33: =-'Deal Inputs'!F$52 -> -3000 | G33: =-'Deal Inputs'!G$52 -> -3200 | H33: =-'Deal Inputs'!H$52 -> -3400
B34: SBC (Combined) | D34: ='Google Model'!F$39+'Meta Model'!F$24 -> 44360.106 | E34: ='Google Model'!G$39+'Meta Model'!G$24 -> 47450.701 | F34: ='Google Model'!H$39+'Meta Model'!H$24 -> 49800.843 | G34: ='Google Model'!I$39+'Meta Model'!I$24 -> 52134.817 | H34: ='Google Model'!J$39+'Meta Model'!J$24 -> 53838.627
B35: Dis-synergies & Integration | D35: =-'Deal Inputs'!D$60 -> 6000 | E35: =-'Deal Inputs'!E$60 -> 4300 | F35: =-'Deal Inputs'!F$60 -> 2500 | G35: =-'Deal Inputs'!G$60 -> 1300 | H35: =-'Deal Inputs'!H$60 -> 200
B36: Amortization of new intangibles | D36: ='Deal Inputs'!$D$91 -> 2500 | E36: ='Deal Inputs'!$D$91 -> 2500 | F36: ='Deal Inputs'!$D$91 -> 2500 | G36: ='Deal Inputs'!$D$91 -> 2500 | H36: ='Deal Inputs'!$D$91 -> 2500
B38: EBIT | D38: =D26-SUM(D28:D36) -> 70656.367 | E38: =E26-SUM(E28:E36) -> 96595.203 | F38: =F26-SUM(F28:F36) -> 122629.45 | G38: =G26-SUM(G28:G36) -> 144548.7 | H38: =H26-SUM(H28:H36) -> 167942.77
B40: Existing interest expense / — income | D40: =-('Google Model'!F$45+'Meta Model'!F$30) -> -5041.3391 | E40: =-('Google Model'!G$45+'Meta Model'!G$30) -> -5098.8169 | F40: =-('Google Model'!H$45+'Meta Model'!H$30) -> -5114.2294 | G40: =-('Google Model'!I$45+'Meta Model'!I$30) -> -6251.3081 | H40: =-('Google Model'!J$45+'Meta Model'!J$30) -> -5954.8289
B41: New interest expense | D41: =(('Deal Inputs'!$D$80*((1-'Deal Inputs'!$D$84)^(D$15-$D$15)))*'Deal Inputs'!$D$81)+(('Deal Inputs'!$D$82*((1-'Deal Inputs'!$D$84)^(D$15-$D$15)))*'Deal Inputs'!$D$83) -> 28500 | E41: =(('Deal Inputs'!$D$80*((1-'Deal Inputs'!$D$84)^(E$15-$D$15)))*'Deal Inputs'!$D$81)+(('Deal Inputs'!$D$82*((1-'Deal Inputs'!$D$84)^(E$15-$D$15)))*'Deal Inputs'!$D$83) -> 27075 | F41: =(('Deal Inputs'!$D$80*((1-'Deal Inputs'!$D$84)^(F$15-$D$15)))*'Deal Inputs'!$D$81)+(('Deal Inputs'!$D$82*((1-'Deal Inputs'!$D$84)^(F$15-$D$15)))*'Deal Inputs'!$D$83) -> 25721.25 | G41: =(('Deal Inputs'!$D$80*((1-'Deal Inputs'!$D$84)^(G$15-$D$15)))*'Deal Inputs'!$D$81)+(('Deal Inputs'!$D$82*((1-'Deal Inputs'!$D$84)^(G$15-$D$15)))*'Deal Inputs'!$D$83) -> 24435.187 | H41: =(('Deal Inputs'!$D$80*((1-'Deal Inputs'!$D$84)^(H$15-$D$15)))*'Deal Inputs'!$D$81)+(('Deal Inputs'!$D$82*((1-'Deal Inputs'!$D$84)^(H$15-$D$15)))*'Deal Inputs'!$D$83) -> 23213.428
B42: EBT | D42: =D38-D40-D41 -> 47197.707 | E42: =E38-E40-E41 -> 74619.02 | F42: =F38-F40-F41 -> 102022.43 | G42: =G38-G40-G41 -> 126364.82 | H42: =H38-H40-H41 -> 150684.17
B43: Taxes | D43: =D42*'Deal Inputs'!$D$95 -> 9911.5184 | E43: =E42*'Deal Inputs'!$D$95 -> 15669.994 | F43: =F42*'Deal Inputs'!$D$95 -> 21424.71 | G43: =G42*'Deal Inputs'!$D$95 -> 26536.612 | H43: =H42*'Deal Inputs'!$D$95 -> 31643.675
B45: Net income | D45: =D42-D43 -> 37286.188 | E45: =E42-E43 -> 58949.026 | F45: =F42-F43 -> 80597.719 | G45: =G42-G43 -> 99828.207 | H45: =H42-H43 -> 119040.49
B47: Accretion / dilution workup
B49: Shares — Pro forma (mm) | D49: ='Google Model'!F$55+'Deal Inputs'!$D$29 -> 17614.857 | E49: ='Google Model'!G$55+'Deal Inputs'!$D$29 -> 17414.857 | F49: ='Google Model'!H$55+'Deal Inputs'!$D$29 -> 17214.857 | G49: ='Google Model'!I$55+'Deal Inputs'!$D$29 -> 17014.857 | H49: ='Google Model'!J$55+'Deal Inputs'!$D$29 -> 16814.857
B50: EPS — Pro forma | D50: =D45/D49 -> 2.1167466 | E50: =E45/E49 -> 3.3849848 | F50: =F45/F49 -> 4.6818697 | G50: =G45/G49 -> 5.8671199 | H50: =H45/H49 -> 7.0794828
B51: % Accretion — Dilution | D51: =D50/'Google Model'!F$56-1 -> -0.32504672 | E51: =E50/'Google Model'!G$56-1 -> -0.084103493 | F51: =F50/'Google Model'!H$56-1 -> 0.081976354 | G51: =G50/'Google Model'!I$56-1 -> 0.16963584 | H51: =H50/'Google Model'!J$56-1 -> 0.23108758

Sheet Synergy Case
B2: Synergy case — Google / Meta combination
B3: Revenue and cost synergy workup
B4: Figures in $mm
B5: Synergy case inputs
B7: Infrastructure Cost Savings — 1
B8: % of Combined CapEx Savings | D8: Conservative | E8: Base | F8: Aggressive
D9: 0.15 | E9: 0.2 | F9: 0.25
B10: Chosen case: | D10: ='Google Drivers'!$D$6 -> Base
B12: R&D Efficiency Gains — 2
B13: % Reduction in Combined R&D | D13: Conservative | E13: Base | F13: Aggressive
D14: 0.1 | E14: 0.15 | F14: 0.2
B15: Chosen case: | D15: ='Google Drivers'!$D$6 -> Base
B17: Revenue Synergies — Cross-Platform Advertising — 3
B18: % Revenue Uplift | D18: Conservative | E18: Base | F18: Aggressive
D19: 0.02 | E19: 0.035 | F19: 0.05
B20: Chosen case: | D20: ='Google Drivers'!$D$6 -> Base
B22: Synergy calculations
B24: Figures in $mm | D24: 2024 | E24: 2025 | F24: 2026 | G24: 2027 | H24: 2028
B26: Infrastructure Cost Savings
B27: Google CapEx | D27: ='Google Model'!F$110 -> 39421.209 | E27: ='Google Model'!G$110 -> 41711.457 | F27: ='Google Model'!H$110 -> 43657.843 | G27: ='Google Model'!I$110 -> 45274.478 | H27: ='Google Model'!J$110 -> 46628.005
B28: Meta CapEx | D28: ='Meta Model'!F$95 -> 34749.352 | E28: ='Meta Model'!G$95 -> 36060.552 | F28: ='Meta Model'!H$95 -> 36734.391 | G28: ='Meta Model'!I$95 -> 37867.067 | H28: ='Meta Model'!J$95 -> 38748.898
B29: Combined CapEx | D29: =D27+D28 -> 74170.561 | E29: =E27+E28 -> 77772.008 | F29: =F27+F28 -> 80392.234 | G29: =G27+G28 -> 83141.545 | H29: =H27+H28 -> 85376.903
B30: Savings % | D30: {=INDEX($D$9:$F$9,MATCH($D$10,$D$8:$F$8,0))} -> 0.2 | E30: {=INDEX($D$9:$F$9,MATCH($D$10,$D$8:$F$8,0))} -> 0.2 | F30: {=INDEX($D$9:$F$9,MATCH($D$10,$D$8:$F$8,0))} -> 0.2 | G30: {=INDEX($D$9:$F$9,MATCH($D$10,$D$8:$F$8,0))} -> 0.2 | H30: {=INDEX($D$9:$F$9,MATCH($D$10,$D$8:$F$8,0))} -> 0.2
B31: Infrastructure synergy value | D31: =D29*D30 -> 14834.112 | E31: =E29*E30 -> 15554.402 | F31: =F29*F30 -> 16078.447 | G31: =G29*G30 -> 16628.309 | H31: =H29*H30 -> 17075.381
B33: R&D Efficiency Gains
B34: Google R&D Expense | D34: ='Google Model'!F$38 -> 18104.555 | E34: ='Google Model'!G$38 -> 19251.441 | F34: ='Google Model'!H$38 -> 20257.239 | G34: ='Google Model'!I$38 -> 21505.377 | H34: ='Google Model'!J$38 -> 22300.35
B35: Meta R&D Expense | D35: ='Meta Model'!F$23 -> 16619.255 | E35: ='Meta Model'!G$23 -> 17610.967 | F35: ='Meta Model'!H$23 -> 18367.196 | G35: ='Meta Model'!I$23 -> 18933.533 | H35: ='Meta Model'!J$23 -> 19374.449
B36: Combined R&D | D36: =D34+D35 -> 34723.81 | E36: =E34+E35 -> 36862.409 | F36: =F34+F35 -> 38624.435 | G36: =G34+G35 -> 40438.91 | H36: =H34+H35 -> 41674.799
B37: Efficiency % | D37: {=INDEX($D$14:$F$14,MATCH($D$15,$D$13:$F$13,0))} -> 0.15 | E37: {=INDEX($D$14:$F$14,MATCH($D$15,$D$13:$F$13,0))} -> 0.15 | F37: {=INDEX($D$14:$F$14,MATCH($D$15,$D$13:$F$13,0))} -> 0.15 | G37: {=INDEX($D$14:$F$14,MATCH($D$15,$D$13:$F$13,0))} -> 0.15 | H37: {=INDEX($D$14:$F$14,MATCH($D$15,$D$13:$F$13,0))} -> 0.15
B38: R&D synergy value | D38: =D36*D37 -> 5208.5716 | E38: =E36*E37 -> 5529.3613 | F38: =F36*F37 -> 5793.6652 | G38: =G36*G37 -> 6065.8366 | H38: =H36*H37 -> 6251.2199
B40: Revenue synergy contribution
B41: Google Revenue | D41: ='Google Model'!F$16 -> 292008.95 | E41: ='Google Model'!G$16 -> 320857.36 | F41: ='Google Model'!H$16 -> 349262.74 | G41: ='Google Model'!I$16 -> 377287.31 | H41: ='Google Model'!J$16 -> 405460.92
B42: Meta Revenue | D42: ='Meta Model'!F$14 -> 151084.14 | E42: ='Meta Model'!G$14 -> 167723.5 | F42: ='Meta Model'!H$14 -> 183671.96 | G42: ='Meta Model'!I$14 -> 199300.35 | H42: ='Meta Model'!J$14 -> 215271.65
B43: Combined Revenue | D43: =D41+D42 -> 443093.09 | E43: =E41+E42 -> 488580.85 | F43: =F41+F42 -> 532934.7 | G43: =G41+G42 -> 576587.67 | H43: =H41+H42 -> 620732.57
B44: Revenue Uplift % | D44: {=INDEX($D$19:$F$19,MATCH($D$20,$D$18:$F$18,0))} -> 0.035 | E44: {=INDEX($D$19:$F$19,MATCH($D$20,$D$18:$F$18,0))} -> 0.035 | F44: {=INDEX($D$19:$F$19,MATCH($D$20,$D$18:$F$18,0))} -> 0.035 | G44: {=INDEX($D$19:$F$19,MATCH($D$20,$D$18:$F$18,0))} -> 0.035 | H44: {=INDEX($D$19:$F$19,MATCH($D$20,$D$18:$F$18,0))} -> 0.035
B45: Revenue Synergy | D45: =D43*D44 -> 15508.258 | E45: =E43*E44 -> 17100.33 | F45: =F43*F44 -> 18652.715 | G45: =G43*G44 -> 20180.568 | H45: =H43*H44 -> 21725.64
B47: Phase-in Schedule
B48: Year 1 Realization % | D48: 0 | E48: 0.3 | F48: 0.6 | G48: 0.85 | H48: 0.95
B50: Total Synergies Summary
B52: Gross Synergies
B53: Infrastructure Savings | D53: {=D31} -> 14834.112 | E53: {=E31} -> 15554.402 | F53: {=F31} -> 16078.447 | G53: {=G31} -> 16628.309 | H53: {=H31} -> 17075.381
B54: R&D Efficiency | D54: {=D38} -> 5208.5716 | E54: {=E38} -> 5529.3613 | F54: {=F38} -> 5793.6652 | G54: {=G38} -> 6065.8366 | H54: {=H38} -> 6251.2199
B55: Revenue Uplift | D55: {=D45} -> 15508.258 | E55: {=E45} -> 17100.33 | F55: {=F45} -> 18652.715 | G55: {=G45} -> 20180.568 | H55: {=H45} -> 21725.64
B56: Total Gross Synergies | D56: =SUM(D53:D55) -> 35550.942 | E56: =SUM(E53:E55) -> 38184.093 | F56: =SUM(F53:F55) -> 40524.827 | G56: =SUM(G53:G55) -> 42874.714 | H56: =SUM(H53:H55) -> 45052.24
B58: After Phase-in
B59: Realized Synergies | D59: =D56*D48 -> 0 | E59: =E56*E48 -> 11455.228 | F59: =F56*F48 -> 24314.896 | G59: =G56*G48 -> 36443.507 | H59: =H56*H48 -> 42799.628
B61: Implementation Costs
B62: One-time Costs | D62: 3000 | E62: 3000 | F62: 2000 | G62: 1000 | H62: 500
B64: Net Synergies | D64: =D59-D62 -> -3000 | E64: =E59-E62 -> 8455.2279 | F64: =F59-F62 -> 22314.896 | G64: =G59-G62 -> 35443.507 | H64: =H59-H62 -> 42299.628

Sheet Valuation
B2: Combined valuation — DCF
B3: Figures in $mm
B4: Case selection
B5: Chosen case: | D5: ='Meta Drivers'!D6 -> Base
B7: Free cash flow build
C8: 2023A | D8: 2024P | E8: 2025P | F8: 2026P | G8: 2027P | H8: 2028P
B10: Google FCF
B11: Cash flow from operations | C11: ='Google Model'!E$107 -> 80102.418 | D11: ='Google Model'!F$107 -> 91037.297 | E11: ='Google Model'!G$107 -> 102584.91 | F11: ='Google Model'!H$107 -> 111214.23 | G11: ='Google Model'!I$107 -> 123437.83 | H11: ='Google Model'!J$107 -> 131624.17
B12: Less — CapEx | C12: ='Google Model'!E$110 -> 36886.92 | D12: ='Google Model'!F$110 -> 39421.209 | E12: ='Google Model'!G$110 -> 41711.457 | F12: ='Google Model'!H$110 -> 43657.843 | G12: ='Google Model'!I$110 -> 45274.478 | H12: ='Google Model'!J$110 -> 46628.005
B13: Google FCF | C13: =C11-C12 -> 43215.498 | D13: =D11-D12 -> 51616.088 | E13: =E11-E12 -> 60873.457 | F13: =F11-F12 -> 67556.39 | G13: =G11-G12 -> 78163.352 | H13: =H11-H12 -> 84996.165
B15: Meta FCF
B16: Cash flow from operations | C16: ='Meta Model'!E$92 -> 49183.663 | D16: ='Meta Model'!F$92 -> 59180.014 | E16: ='Meta Model'!G$92 -> 66482.19 | F16: ='Meta Model'!H$92 -> 73778.633 | G16: ='Meta Model'!I$92 -> 81144.751 | H16: ='Meta Model'!J$92 -> 88809.92
B17: Less — CapEx | C17: ='Meta Model'!E$95 -> 33051.48 | D17: ='Meta Model'!F$95 -> 34749.352 | E17: ='Meta Model'!G$95 -> 36060.552 | F17: ='Meta Model'!H$95 -> 36734.391 | G17: ='Meta Model'!I$95 -> 37867.067 | H17: ='Meta Model'!J$95 -> 38748.898
B18: Meta FCF | C18: =C16-C17 -> 16132.183 | D18: =D16-D17 -> 24430.663 | E18: =E16-E17 -> 30421.638 | F18: =F16-F17 -> 37044.242 | G18: =G16-G17 -> 43277.684 | H18: =H16-H17 -> 50061.022
B20: Benefits from synergies
B21: Synergies — Annual | C21: 0 | D21: ='Deal Inputs'!D$62 -> 5000 | E21: ='Deal Inputs'!E$62 -> 16700 | F21: ='Deal Inputs'!F$62 -> 27000 | G21: ='Deal Inputs'!G$62 -> 32700 | H21: ='Deal Inputs'!H$62 -> 37700
B23: Free cash flow — Combined | C23: =C13+C18+C21 -> 59347.682 | D23: =D13+D18+D21 -> 81046.751 | E23: =E13+E18+E21 -> 107995.1 | F23: =F13+F18+F21 -> 131600.63 | G23: =G13+G18+G21 -> 154141.04 | H23: =H13+H18+H21 -> 172757.19
B26: DCF case inputs
B28: WACC
B29: Bear | D29: 0.07
B30: Base | D30: 0.075
B31: Bull | D31: 0.08
B33: Perpetual growth rate
B34: Bear | D34: 0.02
B35: Base | D35: 0.025
B36: Bull | D36: 0.03
B38: Selected case outputs
B39: WACC | D39: =INDEX($D$29:$D$31,MATCH($D$5,$B$29:$B$31)) -> 0.075
B40: Terminal growth selected | D40: =INDEX($D$34:$D$36,MATCH($D$5,$B$34:$B$36)) -> 0.025
B43: DCF value output
B45: Period discount index | C45: 0 | D45: 1 | E45: 2 | F45: 3 | G45: 4 | H45: 5
B46: Discount factor | C46: 1 | D46: =1/(1+$D$39)^D45 -> 0.93023256 | E46: =1/(1+$D$39)^E45 -> 0.86533261 | F46: =1/(1+$D$39)^F45 -> 0.80496057 | G46: =1/(1+$D$39)^G45 -> 0.74880053 | H46: =1/(1+$D$39)^H45 -> 0.69655863
B48: Present value of FCF | D48: =D$23*D$46 -> 75392.327 | E48: =E$23*E$46 -> 93451.678 | F48: =F$23*F$46 -> 105933.32 | G48: =G$23*G$46 -> 115420.89 | H48: =H$23*H$46 -> 120335.51
B50: Terminal value workup
B51: 2028 Fcf | D51: =$H$23 -> 172757.19
B52: Terminal FCF — 2029P | D52: =D51*(1+D40) -> 177076.12
B53: Terminal Value — 2028P | D53: =D52/(D39-D40) -> 3541522.3
B54: PV of Terminal Value | D54: =D53*H46 -> 2466878
B57: Valuation Summary
B59: Enterprise value Calculation
B60: Sum of PV of FCF — 2025-2028 | D60: =SUM(D48:H48) -> 510533.72
B61: PV of Terminal Value | D61: {=D54} -> 2466878
B62: Combined Enterprise value | D62: =D60+D61 -> 2977411.7
B64: Equity Value Calculation
B65: Combined Enterprise value | D65: {=D62} -> 2977411.7
B66: Less: Google Net debt | D66: =-'Google Model'!$F$128*1000 -> 107779.15
B67: Less: Meta Net debt | D67: =-'Meta Model'!$F$113*1000 -> 42259.105
B68: Combined Equity Value | D68: =D65+D66+D67 -> 3127449.9
B70: Implied Valuation — $B
B71: Enterprise value | D71: =D62/1000 -> 2977.4117
B72: Equity Value | D72: =D68/1000 -> 3127.4499
B74: Current Market capitalization ($B)
B75: Google | D75: ='Google Model'!$F$127 -> 2980
B76: Meta | D76: ='Meta Model'!F112 -> 1830
B77: Combined | D77: =D75+D76 -> 4810
B79: Implied Premium/ — Discount | D79: =(D72-D77)/D77 -> -0.34980251
B82: Sensitivity Analysis
B84: Implied Valuation Sensitivity | D84: Terminal Growth →
C85: =$D$79 -> -0.34980251 | D85: 0.02 | E85: 0.025 | F85: 0.03
B86: Wacc ↓ | C86: 0.07 | D86: -0.33866084 | E86: -0.27777119 | F86: -0.20165914
C87: 0.075 | D87: -0.39870089 | E87: -0.34980251 | F87: -0.29003782
C88: 0.08 | D88: -0.44869054 | E88: -0.40869126 | F88: -0.36069214

Sheet Board Summary
G1: 0 | H1: 1
B2: Board Summary: Google-Meta Combination Analysis
B3: $ in millions unless otherwise noted
B5: Summary Metrics | F5: Print? | G5: 1
B7: Deal Size — | D7: ='Deal Inputs'!$D$21/1000000 -> 1.8252
B8: Premium — | D8: ='Deal Inputs'!$D$18 -> 0.3
B9: Structure — | D9: =TEXT('Deal Inputs'!$D$24,"0%")&" Cash / "&TEXT('Deal Inputs'!$D$25,"0%")&" Stock" -> 50% Cash / 50% Stock
B11: Combined 2028P —
B12: Revenue — | D12: ='Pro Forma'!H$21 -> 638232.57
B13: EBITDA — | D13: ='Pro Forma'!$H$38+'Google Model'!$J$102+'Meta Model'!$J$87+'Pro Forma'!$H$36 -> 226748.5
B14: Fcf: | D14: =Valuation!H23 -> 172757.19
B16: Accretion / (Dilution) —
B17: 1 | D17: ='Pro Forma'!D51 -> -0.32504672
B18: =B17+1 -> 2 | D18: ='Pro Forma'!E51 -> -0.084103493
B19: =B18+1 -> 3 | D19: ='Pro Forma'!F51 -> 0.081976354
B21: Valuation Multiples —
B22: EV/Revenue — | D22: =Valuation!$D$71*1000/'Pro Forma'!H$21 -> 4.6650889
B23: Ev/EBITDA: | D23: =Valuation!$D$71*1000/D13 -> 13.130899
B24: 2025 P/E — | D24: =Valuation!$D$72*1000/'Pro Forma'!E$45 -> 53.053462
B25: Valuation Premium/Discount — base case | D25: =Valuation!D79 -> -0.34980251
