Workbook

Sheet Google Drivers
B2: Google (Alphabet) — Operating Model Assumptions
B3: 3-Year Historical (2021-2023) | 5-Year Projections (2024-2028)
B5: Case selector
B6: Chosen case: | D6: Base
B8: Actuals | G8: Forecast
D9: 2021 | E9: 2022 | F9: 2023 | G9: 2024 | H9: 2025 | I9: 2026 | J9: 2027 | K9: 2028
B11: Revenue Assumptions — 1
B13: Growth rates — Revenue (%)
C14: Case | D14: 2021 | E14: 2022 | F14: 2023 | G14: 2024 | H14: 2025 | I14: 2026 | J14: 2027 | K14: 2028
B15: Google Search | C15: Base | G15: 0.085 | H15: 0.075 | I15: 0.065 | J15: 0.055 | K15: 0.05
C16: Bull | G16: 0.105 | H16: 0.095 | I16: 0.085 | J16: 0.075 | K16: 0.07
C17: Bear | G17: 0.06 | H17: 0.05 | I17: 0.04 | J17: 0.035 | K17: 0.03
B19: YouTube Ads | C19: Base | G19: 0.15 | H19: 0.13 | I19: 0.11 | J19: 0.1 | K19: 0.09
C20: Bull | G20: 0.18 | H20: 0.16 | I20: 0.14 | J20: 0.12 | K20: 0.11
C21: Bear | G21: 0.12 | H21: 0.1 | I21: 0.08 | J21: 0.07 | K21: 0.06
B23: Google Cloud | C23: Base | G23: 0.28 | H23: 0.25 | I23: 0.22 | J23: 0.2 | K23: 0.18
C24: Bull | G24: 0.32 | H24: 0.3 | I24: 0.27 | J24: 0.24 | K24: 0.22
C25: Bear | G25: 0.24 | H25: 0.2 | I25: 0.17 | J25: 0.15 | K25: 0.14
B27: Other Revenues | C27: Base | G27: 0.05 | H27: 0.045 | I27: 0.04 | J27: 0.035 | K27: 0.03
C28: Bull | G28: 0.07 | H28: 0.06 | I28: 0.055 | J28: 0.05 | K28: 0.045
C29: Bear | G29: 0.03 | H29: 0.025 | I29: 0.02 | J29: 0.015 | K29: 0.01
B31: Operating Expense Assumptions — 2
B33: Expenses — Operating (% of Revenue)
B35: R&D | C35: Base | D35: 0.151 | E35: 0.148 | F35: 0.145 | G35: 0.143 | H35: 0.14 | I35: 0.138 | J35: 0.135 | K35: 0.133
C36: Bull | D36: 0.151 | E36: 0.148 | F36: 0.145 | G36: 0.138 | H36: 0.135 | I36: 0.132 | J36: 0.13 | K36: 0.128
C37: Bear | D37: 0.151 | E37: 0.148 | F37: 0.145 | G37: 0.148 | H37: 0.145 | I37: 0.143 | J37: 0.14 | K37: 0.138
B39: S&M | C39: Base | D39: 0.115 | E39: 0.112 | F39: 0.108 | G39: 0.105 | H39: 0.103 | I39: 0.1 | J39: 0.098 | K39: 0.095
C40: Bull | D40: 0.115 | E40: 0.112 | F40: 0.108 | G40: 0.102 | H40: 0.1 | I40: 0.097 | J40: 0.095 | K40: 0.092
C41: Bear | D41: 0.115 | E41: 0.112 | F41: 0.108 | G41: 0.108 | H41: 0.106 | I41: 0.103 | J41: 0.101 | K41: 0.098
B43: G&A | C43: Base | D43: 0.068 | E43: 0.065 | F43: 0.063 | G43: 0.062 | H43: 0.06 | I43: 0.058 | J43: 0.057 | K43: 0.055
C44: Bull | D44: 0.068 | E44: 0.065 | F44: 0.063 | G44: 0.06 | H44: 0.058 | I44: 0.056 | J44: 0.055 | K44: 0.053
C45: Bear | D45: 0.068 | E45: 0.065 | F45: 0.063 | G45: 0.064 | H45: 0.062 | I45: 0.06 | J45: 0.059 | K45: 0.057
B47: SBC | C47: Base | D47: 0.092 | E47: 0.095 | F47: 0.098 | G47: 0.095 | H47: 0.093 | I47: 0.09 | J47: 0.088 | K47: 0.085
C48: Bull | D48: 0.092 | E48: 0.095 | F48: 0.098 | G48: 0.092 | H48: 0.09 | I48: 0.087 | J48: 0.085 | K48: 0.082
C49: Bear | D49: 0.092 | E49: 0.095 | F49: 0.098 | G49: 0.098 | H49: 0.096 | I49: 0.093 | J49: 0.091 | K49: 0.088
B51: Balance Sheet & Cash Flow Assumptions — 3
B53: Working Capital Metrics
B55: Days Sales Outstanding — DSO | C55: Base | D55: 48 | E55: 47 | F55: 46 | G55: 46 | H55: 45 | I55: 45 | J55: 44 | K55: 44
C56: Bull | D56: 48 | E56: 47 | F56: 46 | G56: 45 | H56: 44 | I56: 43 | J56: 42 | K56: 42
C57: Bear | D57: 48 | E57: 47 | F57: 46 | G57: 47 | H57: 47 | I57: 46 | J57: 46 | K57: 45
B59: Days Payable Outstanding — DPO | C59: Base | D59: 32 | E59: 33 | F59: 34 | G59: 34 | H59: 35 | I59: 35 | J59: 36 | K59: 36
C60: Bull | D60: 32 | E60: 33 | F60: 34 | G60: 35 | H60: 36 | I60: 37 | J60: 38 | K60: 38
C61: Bear | D61: 32 | E61: 33 | F61: 34 | G61: 33 | H61: 33 | I61: 34 | J61: 34 | K61: 34
B63: Other current assets | C63: % Increase | E63: 0.058823529 | F63: 0.055555556 | G63: 0.05 | H63: 0.05 | I63: 0.05 | J63: 0.05 | K63: 0.05
B64: Other Long-term Assets | C64: % Increase | E64: 0.085714286 | F64: 0.10526316 | G64: 0.08 | H64: 0.08 | I64: 0.08 | J64: 0.08 | K64: 0.08
B65: ='Google Model'!$B$70 -> Accrued Expenses | C65: % Increase | E65: 0.083333333 | F65: 0.076923077 | G65: 0.06 | H65: 0.06 | I65: 0.06 | J65: 0.06 | K65: 0.06
B67: Capital Expenditure
B69: CapEx — % of Revenue | C69: Base | D69: 0.125 | E69: 0.132 | F69: 0.14 | G69: 0.135 | H69: 0.13 | I69: 0.125 | J69: 0.12 | K69: 0.115
C70: Bull | D70: 0.125 | E70: 0.132 | F70: 0.14 | G70: 0.13 | H70: 0.125 | I70: 0.12 | J70: 0.115 | K70: 0.11
C71: Bear | D71: 0.125 | E71: 0.132 | F71: 0.14 | G71: 0.14 | H71: 0.135 | I71: 0.13 | J71: 0.125 | K71: 0.12
B73: D&A — % of Prior Year CapEx | C73: Base | D73: 0.7 | E73: 0.7 | F73: 0.7 | G73: 0.7 | H73: 0.7 | I73: 0.7 | J73: 0.7 | K73: 0.7
C74: Bull | D74: 0.7 | E74: 0.7 | F74: 0.7 | G74: 0.68 | H74: 0.68 | I74: 0.68 | J74: 0.68 | K74: 0.68
C75: Bear | D75: 0.7 | E75: 0.7 | F75: 0.7 | G75: 0.72 | H75: 0.72 | I75: 0.72 | J75: 0.72 | K75: 0.72
B77: Other Financial Assumptions — 4
B79: Tax Rate
B81: Effective Tax Rate | C81: Base | D81: 0.162 | E81: 0.16 | F81: 0.158 | G81: 0.165 | H81: 0.17 | I81: 0.175 | J81: 0.18 | K81: 0.185
C82: Bull | D82: 0.162 | E82: 0.16 | F82: 0.158 | G82: 0.16 | H82: 0.165 | I82: 0.17 | J82: 0.175 | K82: 0.18
C83: Bear | D83: 0.162 | E83: 0.16 | F83: 0.158 | G83: 0.17 | H83: 0.175 | I83: 0.18 | J83: 0.185 | K83: 0.19
B86: Interest Rates
B88: Interest Income Rate — on cash | C88: Base | D88: 0.005 | E88: 0.015 | F88: 0.025 | G88: 0.035 | H88: 0.03 | I88: 0.025 | J88: 0.025 | K88: 0.02
C89: Bull | D89: 0.01 | E89: 0.02 | F89: 0.03 | G89: 0.04 | H89: 0.045 | I89: 0.04 | J89: 0.035 | K89: 0.035
C90: Bear | D90: 0.0025 | E90: 0.0125 | F90: 0.0225 | G90: 0.0325 | H90: 0.0375 | I90: 0.0325 | J90: 0.0275 | K90: 0.0275
B92: Interest Expense Rate — on LT debt | C92: Base | D92: 0.03 | E92: 0.035 | F92: 0.04 | G92: 0.045 | H92: 0.04 | I92: 0.035 | J92: 0.03 | K92: 0.03
C93: Bull | D93: 0.025 | E93: 0.03 | F93: 0.035 | G93: 0.04 | H93: 0.035 | I93: 0.03 | J93: 0.025 | K93: 0.025
C94: Bear | D94: 0.04 | E94: 0.045 | F94: 0.05 | G94: 0.055 | H94: 0.05 | I94: 0.045 | J94: 0.04 | K94: 0.04
B96: Share Buyback
B98: Buyback — % of FCF | C98: Base | D98: 0.75 | E98: 0.75 | F98: 0.75 | G98: 0.7 | H98: 0.7 | I98: 0.65 | J98: 0.65 | K98: 0.6
C99: Bull | D99: 0.75 | E99: 0.75 | F99: 0.75 | G99: 0.75 | H99: 0.75 | I99: 0.7 | J99: 0.7 | K99: 0.65
C100: Bear | D100: 0.75 | E100: 0.75 | F100: 0.75 | G100: 0.65 | H100: 0.65 | I100: 0.6 | J100: 0.6 | K100: 0.55

Sheet Google Model
B2: Google (Alphabet) — Income Statement
B3: Figures in $mm
B5: Chosen case: | D5: ='Google Drivers'!D6 -> Base
B7: Actuals | F7: Forecast
C8: 2021 | D8: 2022 | E8: 2023 | F8: 2024 | G8: 2025 | H8: 2026 | I8: 2027 | J8: 2028
B10: P&L statement
B12: Google Search | C12: 148951 | D12: 162450 | E12: 175033 | F12: =E12*(1+INDEX('Google Drivers'!G$15:G$17,MATCH($D$5,'Google Drivers'!$C$15:$C$17,0))) -> 189910.8 | G12: =F12*(1+INDEX('Google Drivers'!H$15:H$17,MATCH($D$5,'Google Drivers'!$C$15:$C$17,0))) -> 204154.12 | H12: =G12*(1+INDEX('Google Drivers'!I$15:I$17,MATCH($D$5,'Google Drivers'!$C$15:$C$17,0))) -> 217424.13 | I12: =H12*(1+INDEX('Google Drivers'!J$15:J$17,MATCH($D$5,'Google Drivers'!$C$15:$C$17,0))) -> 229382.46 | J12: =I12*(1+INDEX('Google Drivers'!K$15:K$17,MATCH($D$5,'Google Drivers'!$C$15:$C$17,0))) -> 240851.58
B13: YouTube Ads | C13: 28845 | D13: 29243 | E13: 31865 | F13: =E13*(1+INDEX('Google Drivers'!G$19:G$21,MATCH($D$5,'Google Drivers'!$C$19:$C$21,0))) -> 36644.75 | G13: =F13*(1+INDEX('Google Drivers'!H$19:H$21,MATCH($D$5,'Google Drivers'!$C$19:$C$21,0))) -> 41408.567 | H13: =G13*(1+INDEX('Google Drivers'!I$19:I$21,MATCH($D$5,'Google Drivers'!$C$19:$C$21,0))) -> 45963.51 | I13: =H13*(1+INDEX('Google Drivers'!J$19:J$21,MATCH($D$5,'Google Drivers'!$C$19:$C$21,0))) -> 50559.861 | J13: =I13*(1+INDEX('Google Drivers'!K$19:K$21,MATCH($D$5,'Google Drivers'!$C$19:$C$21,0))) -> 55110.248
B14: Google Cloud | C14: 13059 | D14: 19206 | E14: 26280 | F14: =E14*(1+INDEX('Google Drivers'!G$23:G$25,MATCH($D$5,'Google Drivers'!$C$23:$C$25,0))) -> 33638.4 | G14: =F14*(1+INDEX('Google Drivers'!H$23:H$25,MATCH($D$5,'Google Drivers'!$C$23:$C$25,0))) -> 42048 | H14: =G14*(1+INDEX('Google Drivers'!I$23:I$25,MATCH($D$5,'Google Drivers'!$C$23:$C$25,0))) -> 51298.56 | I14: =H14*(1+INDEX('Google Drivers'!J$23:J$25,MATCH($D$5,'Google Drivers'!$C$23:$C$25,0))) -> 61558.272 | J14: =I14*(1+INDEX('Google Drivers'!K$23:K$25,MATCH($D$5,'Google Drivers'!$C$23:$C$25,0))) -> 72638.761
B15: Other Revenues | C15: 28032 | D15: 29071 | E15: 30300 | F15: =E15*(1+INDEX('Google Drivers'!G$27:G$29,MATCH($D$5,'Google Drivers'!$C$27:$C$29,0))) -> 31815 | G15: =F15*(1+INDEX('Google Drivers'!H$27:H$29,MATCH($D$5,'Google Drivers'!$C$27:$C$29,0))) -> 33246.675 | H15: =G15*(1+INDEX('Google Drivers'!I$27:I$29,MATCH($D$5,'Google Drivers'!$C$27:$C$29,0))) -> 34576.542 | I15: =H15*(1+INDEX('Google Drivers'!J$27:J$29,MATCH($D$5,'Google Drivers'!$C$27:$C$29,0))) -> 35786.721 | J15: =I15*(1+INDEX('Google Drivers'!K$27:K$29,MATCH($D$5,'Google Drivers'!$C$27:$C$29,0))) -> 36860.323
B16: Revenue — Total | C16: =SUM(C12:C15) -> 218887 | D16: =SUM(D12:D15) -> 239970 | E16: =SUM(E12:E15) -> 263478 | F16: =SUM(F12:F15) -> 292008.95 | G16: =SUM(G12:G15) -> 320857.36 | H16: =SUM(H12:H15) -> 349262.74 | I16: =SUM(I12:I15) -> 377287.31 | J16: =SUM(J12:J15) -> 405460.92
B17: YoY Growth % | D17: =D16/C16-1 -> 0.096319105 | E17: =E16/D16-1 -> 0.097962245 | F17: =F16/E16-1 -> 0.10828591 | G17: =G16/F16-1 -> 0.09879287 | H17: =H16/G16-1 -> 0.088529642 | I17: =I16/H16-1 -> 0.080239217 | J17: =J16/I16-1 -> 0.074674128
B19: Cost of sales | C19: =C16*(1-C21) -> 99593.585 | D19: =D16*(1-D21) -> 108466.44 | E19: =E16*(1-E21) -> 118565.1 | F19: =F16*(1-F21) -> 130820.01 | G19: =G16*(1-G21) -> 143102.38 | H19: =H16*(1-H21) -> 155072.66 | I19: =I16*(1-I21) -> 166760.99 | J19: =J16*(1-J21) -> 178402.8
B20: Profit — Gross | C20: =C16-C19 -> 119293.41 | D20: =D16-D19 -> 131503.56 | E20: =E16-E19 -> 144912.9 | F20: =F16-F19 -> 161188.94 | G20: =G16-G19 -> 177754.98 | H20: =H16-H19 -> 194190.09 | I20: =I16-I19 -> 210526.32 | J20: =J16-J19 -> 227058.11
B21: Gross Margin (%) | C21: 0.545 | D21: 0.548 | E21: 0.55 | F21: 0.552 | G21: 0.554 | H21: 0.556 | I21: 0.558 | J21: 0.56
B23: R&D | C23: =C16*INDEX('Google Drivers'!D$35:D$37,MATCH($D$5,'Google Drivers'!$C$35:$C$37,0)) -> 33051.937 | D23: =D16*INDEX('Google Drivers'!E$35:E$37,MATCH($D$5,'Google Drivers'!$C$35:$C$37,0)) -> 35515.56 | E23: =E16*INDEX('Google Drivers'!F$35:F$37,MATCH($D$5,'Google Drivers'!$C$35:$C$37,0)) -> 38204.31 | F23: =F16*INDEX('Google Drivers'!G$35:G$37,MATCH($D$5,'Google Drivers'!$C$35:$C$37,0)) -> 41757.281 | G23: =G16*INDEX('Google Drivers'!H$35:H$37,MATCH($D$5,'Google Drivers'!$C$35:$C$37,0)) -> 44920.03 | H23: =H16*INDEX('Google Drivers'!I$35:I$37,MATCH($D$5,'Google Drivers'!$C$35:$C$37,0)) -> 48198.259 | I23: =I16*INDEX('Google Drivers'!J$35:J$37,MATCH($D$5,'Google Drivers'!$C$35:$C$37,0)) -> 50933.787 | J23: =J16*INDEX('Google Drivers'!K$35:K$37,MATCH($D$5,'Google Drivers'!$C$35:$C$37,0)) -> 53926.302
B24: S&M | C24: =C16*INDEX('Google Drivers'!D$39:D$41,MATCH($D$5,'Google Drivers'!$C$39:$C$41,0)) -> 25172.005 | D24: =D16*INDEX('Google Drivers'!E$39:E$41,MATCH($D$5,'Google Drivers'!$C$39:$C$41,0)) -> 26876.64 | E24: =E16*INDEX('Google Drivers'!F$39:F$41,MATCH($D$5,'Google Drivers'!$C$39:$C$41,0)) -> 28455.624 | F24: =F16*INDEX('Google Drivers'!G$39:G$41,MATCH($D$5,'Google Drivers'!$C$39:$C$41,0)) -> 30660.94 | G24: =G16*INDEX('Google Drivers'!H$39:H$41,MATCH($D$5,'Google Drivers'!$C$39:$C$41,0)) -> 33048.308 | H24: =H16*INDEX('Google Drivers'!I$39:I$41,MATCH($D$5,'Google Drivers'!$C$39:$C$41,0)) -> 34926.274 | I24: =I16*INDEX('Google Drivers'!J$39:J$41,MATCH($D$5,'Google Drivers'!$C$39:$C$41,0)) -> 36974.157 | J24: =J16*INDEX('Google Drivers'!K$39:K$41,MATCH($D$5,'Google Drivers'!$C$39:$C$41,0)) -> 38518.787
B25: G&A | C25: =C16*INDEX('Google Drivers'!D$43:D$45,MATCH($D$5,'Google Drivers'!$C$43:$C$45,0)) -> 14884.316 | D25: =D16*INDEX('Google Drivers'!E$43:E$45,MATCH($D$5,'Google Drivers'!$C$43:$C$45,0)) -> 15598.05 | E25: =E16*INDEX('Google Drivers'!F$43:F$45,MATCH($D$5,'Google Drivers'!$C$43:$C$45,0)) -> 16599.114 | F25: =F16*INDEX('Google Drivers'!G$43:G$45,MATCH($D$5,'Google Drivers'!$C$43:$C$45,0)) -> 18104.555 | G25: =G16*INDEX('Google Drivers'!H$43:H$45,MATCH($D$5,'Google Drivers'!$C$43:$C$45,0)) -> 19251.441 | H25: =H16*INDEX('Google Drivers'!I$43:I$45,MATCH($D$5,'Google Drivers'!$C$43:$C$45,0)) -> 20257.239 | I25: =I16*INDEX('Google Drivers'!J$43:J$45,MATCH($D$5,'Google Drivers'!$C$43:$C$45,0)) -> 21505.377 | J25: =J16*INDEX('Google Drivers'!K$43:K$45,MATCH($D$5,'Google Drivers'!$C$43:$C$45,0)) -> 22300.35
B26: SBC | C26: =C16*INDEX('Google Drivers'!D$47:D$49,MATCH($D$5,'Google Drivers'!$C$47:$C$49,0)) -> 20137.604 | D26: =D16*INDEX('Google Drivers'!E$47:E$49,MATCH($D$5,'Google Drivers'!$C$47:$C$49,0)) -> 22797.15 | E26: =E16*INDEX('Google Drivers'!F$47:F$49,MATCH($D$5,'Google Drivers'!$C$47:$C$49,0)) -> 25820.844 | F26: =F16*INDEX('Google Drivers'!G$47:G$49,MATCH($D$5,'Google Drivers'!$C$47:$C$49,0)) -> 27740.851 | G26: =G16*INDEX('Google Drivers'!H$47:H$49,MATCH($D$5,'Google Drivers'!$C$47:$C$49,0)) -> 29839.734 | H26: =H16*INDEX('Google Drivers'!I$47:I$49,MATCH($D$5,'Google Drivers'!$C$47:$C$49,0)) -> 31433.647 | I26: =I16*INDEX('Google Drivers'!J$47:J$49,MATCH($D$5,'Google Drivers'!$C$47:$C$49,0)) -> 33201.284 | J26: =J16*INDEX('Google Drivers'!K$47:K$49,MATCH($D$5,'Google Drivers'!$C$47:$C$49,0)) -> 34464.178
B27: Operating Expenses — Total | C27: =SUM(C23:C26) -> 93245.862 | D27: =SUM(D23:D26) -> 100787.4 | E27: =SUM(E23:E26) -> 109079.89 | F27: =SUM(F23:F26) -> 118263.63 | G27: =SUM(G23:G26) -> 127059.51 | H27: =SUM(H23:H26) -> 134815.42 | I27: =SUM(I23:I26) -> 142614.6 | J27: =SUM(J23:J26) -> 149209.62
B29: EBIT / Operating Income | C29: =C20-C27 -> 26047.553 | D29: =D20-D27 -> 30716.16 | E29: =E20-E27 -> 35833.008 | F29: =F20-F27 -> 42925.316 | G29: =G20-G27 -> 50695.463 | H29: =H20-H27 -> 59374.667 | I29: =I20-I27 -> 67911.717 | J29: =J20-J27 -> 77848.496
B30: Operating Margin (%) | C30: =C29/C16 -> 0.119 | D30: =D29/D16 -> 0.128 | E30: =E29/E16 -> 0.136 | F30: =F29/F16 -> 0.147 | G30: =G29/G16 -> 0.158 | H30: =H29/H16 -> 0.17 | I30: =I29/I16 -> 0.18 | J30: =J29/J16 -> 0.192
B32: Interest (Expense) / Income | C32: =(C$51*INDEX('Google Drivers'!D$88:D$90,MATCH($D$5,'Google Drivers'!$C$88:$C$90,0)))-(C73*INDEX('Google Drivers'!D$92:D$94,MATCH($D$5,'Google Drivers'!$C$92:$C$94,0))) -> 0 | D32: =(D$51*INDEX('Google Drivers'!E$88:E$90,MATCH($D$5,'Google Drivers'!$C$88:$C$90,0)))-(D73*INDEX('Google Drivers'!E$92:E$94,MATCH($D$5,'Google Drivers'!$C$92:$C$94,0))) -> 972.47681 | E32: =(E$51*INDEX('Google Drivers'!F$88:F$90,MATCH($D$5,'Google Drivers'!$C$88:$C$90,0)))-(E73*INDEX('Google Drivers'!F$92:F$94,MATCH($D$5,'Google Drivers'!$C$92:$C$94,0))) -> 2137.5582 | F32: =(F$51*INDEX('Google Drivers'!G$88:G$90,MATCH($D$5,'Google Drivers'!$C$88:$C$90,0)))-(F73*INDEX('Google Drivers'!G$92:G$94,MATCH($D$5,'Google Drivers'!$C$92:$C$94,0))) -> 3647.2704 | G32: =(G$51*INDEX('Google Drivers'!H$88:H$90,MATCH($D$5,'Google Drivers'!$C$88:$C$90,0)))-(G73*INDEX('Google Drivers'!H$92:H$94,MATCH($D$5,'Google Drivers'!$C$92:$C$94,0))) -> 3628.5766 | H32: =(H$51*INDEX('Google Drivers'!I$88:I$90,MATCH($D$5,'Google Drivers'!$C$88:$C$90,0)))-(H73*INDEX('Google Drivers'!I$92:I$94,MATCH($D$5,'Google Drivers'!$C$92:$C$94,0))) -> 3565.6401 | I32: =(I$51*INDEX('Google Drivers'!J$88:J$90,MATCH($D$5,'Google Drivers'!$C$88:$C$90,0)))-(I73*INDEX('Google Drivers'!J$92:J$94,MATCH($D$5,'Google Drivers'!$C$92:$C$94,0))) -> 4272.5338 | J32: =(J$51*INDEX('Google Drivers'!K$88:K$90,MATCH($D$5,'Google Drivers'!$C$88:$C$90,0)))-(J73*INDEX('Google Drivers'!K$92:K$94,MATCH($D$5,'Google Drivers'!$C$92:$C$94,0))) -> 4000.4265
B34: Pre-tax Income | C34: =C29+C32 -> 26047.553 | D34: =D29+D32 -> 31688.637 | E34: =E29+E32 -> 37970.566 | F34: =F29+F32 -> 46572.587 | G34: =G29+G32 -> 54324.039 | H34: =H29+H32 -> 62940.307 | I34: =I29+I32 -> 72184.25 | J34: =J29+J32 -> 81848.922
B35: Tax Expense / Provision | C35: =C34*INDEX('Google Drivers'!D$81:D$83,MATCH($D$5,'Google Drivers'!$C$81:$C$83,0)) -> 4219.7036 | D35: =D34*INDEX('Google Drivers'!E$81:E$83,MATCH($D$5,'Google Drivers'!$C$81:$C$83,0)) -> 5070.1819 | E35: =E34*INDEX('Google Drivers'!F$81:F$83,MATCH($D$5,'Google Drivers'!$C$81:$C$83,0)) -> 5999.3495 | F35: =F34*INDEX('Google Drivers'!G$81:G$83,MATCH($D$5,'Google Drivers'!$C$81:$C$83,0)) -> 7684.4768 | G35: =G34*INDEX('Google Drivers'!H$81:H$83,MATCH($D$5,'Google Drivers'!$C$81:$C$83,0)) -> 9235.0866 | H35: =H34*INDEX('Google Drivers'!I$81:I$83,MATCH($D$5,'Google Drivers'!$C$81:$C$83,0)) -> 11014.554 | I35: =I34*INDEX('Google Drivers'!J$81:J$83,MATCH($D$5,'Google Drivers'!$C$81:$C$83,0)) -> 12993.165 | J35: =J34*INDEX('Google Drivers'!K$81:K$83,MATCH($D$5,'Google Drivers'!$C$81:$C$83,0)) -> 15142.051
B37: Net income | C37: =C34-C35 -> 21827.849 | D37: =D34-D35 -> 26618.455 | E37: =E34-E35 -> 31971.217 | F37: =F34-F35 -> 38888.11 | G37: =G34-G35 -> 45088.952 | H37: =H34-H35 -> 51925.753 | I37: =I34-I35 -> 59191.085 | J37: =J34-J35 -> 66706.872
B38: Net Margin (%) | C38: =C37/C16 -> 0.099722 | D38: =D37/D16 -> 0.11092409 | E38: =E37/E16 -> 0.12134302 | F38: =F37/F16 -> 0.13317437 | G38: =G37/G16 -> 0.14052647 | H38: =H37/H16 -> 0.14867246 | I38: =I37/I16 -> 0.15688597 | J38: =J37/J16 -> 0.16452109
B40: EPS calculation
B42: Basic Shares — Outstanding | C42: 13000 | D42: 12800 | E42: 12600 | F42: 12400 | G42: 12200 | H42: 12000 | I42: 11800 | J42: 11600
B43: EPS — Basic | C43: =C37/C42 -> 1.6790653 | D43: =D37/D42 -> 2.0795668 | E43: =E37/E42 -> 2.5373982 | F43: =F37/F42 -> 3.1361379 | G43: =G37/G42 -> 3.6958158 | H43: =H37/H42 -> 4.3271461 | I43: =I37/I42 -> 5.0161937 | J43: =J37/J42 -> 5.7505924
B46: Balance sheet schedule
B48: Assets section
B50: Assets — Current
B51: Cash and equivalents | C51: 90000 | D51: =D$108 -> 97498.454 | E51: =E$108 -> 106302.33 | F51: =F$108 -> 120279.15 | G51: =G$108 -> 136952.55 | H51: =H$108 -> 158725.6 | I51: =I$108 -> 184101.35 | J51: =J$108 -> 215771.32
B52: Receivables | C52: =C$16*INDEX('Google Drivers'!D$55:D$57,MATCH($D$5,'Google Drivers'!$C$55:$C$57,0))/365 -> 28785.14 | D52: =D$16*INDEX('Google Drivers'!E$55:E$57,MATCH($D$5,'Google Drivers'!$C$55:$C$57,0))/365 -> 30900.247 | E52: =E$16*INDEX('Google Drivers'!F$55:F$57,MATCH($D$5,'Google Drivers'!$C$55:$C$57,0))/365 -> 33205.447 | F52: =F$16*INDEX('Google Drivers'!G$55:G$57,MATCH($D$5,'Google Drivers'!$C$55:$C$57,0))/365 -> 36801.129 | G52: =G$16*INDEX('Google Drivers'!H$55:H$57,MATCH($D$5,'Google Drivers'!$C$55:$C$57,0))/365 -> 39557.756 | H52: =H$16*INDEX('Google Drivers'!I$55:I$57,MATCH($D$5,'Google Drivers'!$C$55:$C$57,0))/365 -> 43059.79 | I52: =I$16*INDEX('Google Drivers'!J$55:J$57,MATCH($D$5,'Google Drivers'!$C$55:$C$57,0))/365 -> 45481.21 | J52: =J$16*INDEX('Google Drivers'!K$55:K$57,MATCH($D$5,'Google Drivers'!$C$55:$C$57,0))/365 -> 48877.48
B53: Other current assets | C53: 8500 | D53: =C53*(1+'Google Drivers'!E$63) -> 9000 | E53: =D53*(1+'Google Drivers'!F$63) -> 9500 | F53: =E53*(1+'Google Drivers'!G$63) -> 9975 | G53: =F53*(1+'Google Drivers'!H$63) -> 10473.75 | H53: =G53*(1+'Google Drivers'!I$63) -> 10997.438 | I53: =H53*(1+'Google Drivers'!J$63) -> 11547.309 | J53: =I53*(1+'Google Drivers'!K$63) -> 12124.675
B54: Current Assets — Total | C54: =SUM(C51:C53) -> 127285.14 | D54: =SUM(D51:D53) -> 137398.7 | E54: =SUM(E51:E53) -> 149007.77 | F54: =SUM(F51:F53) -> 167055.28 | G54: =SUM(G51:G53) -> 186984.06 | H54: =SUM(H51:H53) -> 212782.83 | I54: =SUM(I51:I53) -> 241129.87 | J54: =SUM(J51:J53) -> 276773.48
B56: Assets — Non-current
B57: PP&E (Gross) | C57: 80000 | D57: =C57+D97 -> 111676.04 | E57: =D57+E97 -> 148562.96 | F57: =E57+F97 -> 187984.17 | G57: =F57+G97 -> 229695.63 | H57: =G57+H97 -> 273353.47 | I57: =H57+I97 -> 318627.95 | J57: =I57+J97 -> 365255.95
B58: Less: Accumulated depreciation | C58: 25000 | D58: =C58+D89 -> 44152.613 | E58: =D58+E89 -> 66325.841 | F58: =E58+F89 -> 92146.685 | G58: =F58+G89 -> 119741.53 | H58: =G58+H89 -> 148939.55 | I58: =H58+I89 -> 179500.04 | J58: =I58+J89 -> 211192.17
B59: Net PP&E | C59: =C57-C58 -> 55000 | D59: =D57-D58 -> 67523.428 | E59: =E57-E58 -> 82237.12 | F59: =F57-F58 -> 95837.484 | G59: =G57-G58 -> 109954.09 | H59: =H57-H58 -> 124413.92 | I59: =I57-I58 -> 139127.91 | J59: =J57-J58 -> 154063.78
B61: Other Long-term Assets | C61: 35000 | D61: =C61*(1+'Google Drivers'!E$64) -> 38000 | E61: =D61*(1+'Google Drivers'!F$64) -> 42000 | F61: =E61*(1+'Google Drivers'!G$64) -> 45360 | G61: =F61*(1+'Google Drivers'!H$64) -> 48988.8 | H61: =G61*(1+'Google Drivers'!I$64) -> 52907.904 | I61: =H61*(1+'Google Drivers'!J$64) -> 57140.536 | J61: =I61*(1+'Google Drivers'!K$64) -> 61711.779
B62: Total Non-Current Assets | C62: =C59+C61 -> 90000 | D62: =D59+D61 -> 105523.43 | E62: =E59+E61 -> 124237.12 | F62: =F59+F61 -> 141197.48 | G62: =G59+G61 -> 158942.89 | H62: =H59+H61 -> 177321.82 | I62: =I59+I61 -> 196268.44 | J62: =J59+J61 -> 215775.56
B64: Total Assets | C64: =C54+C62 -> 217285.14 | D64: =D54+D62 -> 242922.13 | E64: =E54+E62 -> 273244.89 | F64: =F54+F62 -> 308252.77 | G64: =G54+G62 -> 345926.95 | H64: =H54+H62 -> 390104.65 | I64: =I54+I62 -> 437398.32 | J64: =J54+J62 -> 492549.03
B66: Liabilities and equity
B68: Liabilities — Current
B69: Payables | C69: =(C19+C23+C24+C25)*INDEX('Google Drivers'!D$59:D$61,MATCH($D$5,'Google Drivers'!$C$59:$C$61,0))/365 -> 15140.983 | D69: =(D19+D23+D24+D25)*INDEX('Google Drivers'!E$59:E$61,MATCH($D$5,'Google Drivers'!$C$59:$C$61,0))/365 -> 16857.728 | E69: =(E19+E23+E24+E25)*INDEX('Google Drivers'!F$59:F$61,MATCH($D$5,'Google Drivers'!$C$59:$C$61,0))/365 -> 18800.058 | F69: =(F19+F23+F24+F25)*INDEX('Google Drivers'!G$59:G$61,MATCH($D$5,'Google Drivers'!$C$59:$C$61,0))/365 -> 20618.232 | G69: =(G19+G23+G24+G25)*INDEX('Google Drivers'!H$59:H$61,MATCH($D$5,'Google Drivers'!$C$59:$C$61,0))/365 -> 23044.591 | H69: =(H19+H23+H24+H25)*INDEX('Google Drivers'!I$59:I$61,MATCH($D$5,'Google Drivers'!$C$59:$C$61,0))/365 -> 24783.302 | I69: =(I19+I23+I24+I25)*INDEX('Google Drivers'!J$59:J$61,MATCH($D$5,'Google Drivers'!$C$59:$C$61,0))/365 -> 27239.11 | J69: =(J19+J23+J24+J25)*INDEX('Google Drivers'!K$59:K$61,MATCH($D$5,'Google Drivers'!$C$59:$C$61,0))/365 -> 28913.251
B70: Accrued Expenses | C70: 12000 | D70: =C70*(1+'Google Drivers'!E$65) -> 13000 | E70: =D70*(1+'Google Drivers'!F$65) -> 14000 | F70: =E70*(1+'Google Drivers'!G$65) -> 14840 | G70: =F70*(1+'Google Drivers'!H$65) -> 15730.4 | H70: =G70*(1+'Google Drivers'!I$65) -> 16674.224 | I70: =H70*(1+'Google Drivers'!J$65) -> 17674.677 | J70: =I70*(1+'Google Drivers'!K$65) -> 18735.158
B71: Current Liabilities — Total | C71: =SUM(C69:C70) -> 27140.983 | D71: =SUM(D69:D70) -> 29857.728 | E71: =SUM(E69:E70) -> 32800.058 | F71: =SUM(F69:F70) -> 35458.232 | G71: =SUM(G69:G70) -> 38774.991 | H71: =SUM(H69:H70) -> 41457.526 | I71: =SUM(I69:I70) -> 44913.788 | J71: =SUM(J69:J70) -> 47648.409
B73: Long-term Debt | C73: 15000 | D73: 14000 | E73: 13000 | F73: 12500 | G73: 12000 | H73: 11500 | I73: 11000 | J73: 10500
B74: Liabilities — Total | C74: =C71+C73 -> 42140.983 | D74: =D71+D73 -> 43857.728 | E74: =E71+E73 -> 45800.058 | F74: =F71+F73 -> 47958.232 | G74: =G71+G73 -> 50774.991 | H74: =H71+H73 -> 52957.526 | I74: =I71+I73 -> 55913.788 | J74: =J71+J73 -> 58148.409
B76: Shareholders' Equity
B77: Common Stock & APIC | C77: 50000 | D77: =C77+D90 -> 72797.15 | E77: =D77+E90 -> 98617.994 | F77: =E77+F90 -> 126358.84 | G77: =F77+G90 -> 156198.58 | H77: =G77+H90 -> 187632.23 | I77: =H77+I90 -> 220833.51 | J77: =I77+J90 -> 255297.69
B78: Treasury Stock | C78: 24855.844 | D78: =C78+D102 -> 50351.205 | E78: =D78+E102 -> 79762.829 | F78: =E78+F102 -> 113542.09 | G78: =F78+G102 -> 153613.35 | H78: =G78+H102 -> 194977.59 | I78: =H78+I102 -> 243032.55 | J78: =I78+J102 -> 291287.51
B79: Retained earnings | C79: 150000 | D79: =C79+D88 -> 176618.45 | E79: =D79+E88 -> 208589.67 | F79: =E79+F88 -> 247477.78 | G79: =F79+G88 -> 292566.73 | H79: =G79+H88 -> 344492.49 | I79: =H79+I88 -> 403683.57 | J79: =I79+J88 -> 470390.44
B80: Total Shareholders' Equity | C80: =C77-C78+C79 -> 175144.16 | D80: =D77-D78+D79 -> 199064.4 | E80: =E77-E78+E79 -> 227444.84 | F80: =F77-F78+F79 -> 260294.54 | G80: =G77-G78+G79 -> 295151.96 | H80: =H77-H78+H79 -> 337147.13 | I80: =I77-I78+I79 -> 381484.53 | J80: =J77-J78+J79 -> 434400.62
B82: Total Liabilities & Equity | C82: =C74+C80 -> 217285.14 | D82: =D74+D80 -> 242922.13 | E82: =E74+E80 -> 273244.89 | F82: =F74+F80 -> 308252.77 | G82: =G74+G80 -> 345926.95 | H82: =H74+H80 -> 390104.65 | I82: =I74+I80 -> 437398.32 | J82: =J74+J80 -> 492549.03
B84: Balance Check (Assets — L&E) | C84: =C64-C82 -> 0 | D84: =D64-D82 -> 0 | E84: =E64-E82 -> 0 | F84: =F64-F82 -> 0 | G84: =G64-G82 -> 0 | H84: =H64-H82 -> 0 | I84: =I64-I82 -> 0 | J84: =J64-J82 -> 0
B86: Cash-flow statement
B87: Cash Flow from Operating Activities
B88: Net Income | D88: {=D37} -> 26618.455 | E88: {=E37} -> 31971.217 | F88: {=F37} -> 38888.11 | G88: {=G37} -> 45088.952 | H88: {=H37} -> 51925.753 | I88: {=I37} -> 59191.085 | J88: {=J37} -> 66706.872
B89: Add — Depreciation & Amortization | D89: =C$97*INDEX('Google Drivers'!E$73:E$75,MATCH($D$5,'Google Drivers'!$C$73:$C$75,0)) -> 19152.612 | E89: =D$97*INDEX('Google Drivers'!F$73:F$75,MATCH($D$5,'Google Drivers'!$C$73:$C$75,0)) -> 22173.228 | F89: =E$97*INDEX('Google Drivers'!G$73:G$75,MATCH($D$5,'Google Drivers'!$C$73:$C$75,0)) -> 25820.844 | G89: =F$97*INDEX('Google Drivers'!H$73:H$75,MATCH($D$5,'Google Drivers'!$C$73:$C$75,0)) -> 27594.846 | H89: =G$97*INDEX('Google Drivers'!I$73:I$75,MATCH($D$5,'Google Drivers'!$C$73:$C$75,0)) -> 29198.02 | I89: =H$97*INDEX('Google Drivers'!J$73:J$75,MATCH($D$5,'Google Drivers'!$C$73:$C$75,0)) -> 30560.49 | J89: =I$97*INDEX('Google Drivers'!K$73:K$75,MATCH($D$5,'Google Drivers'!$C$73:$C$75,0)) -> 31692.134
B90: Add: SBC | D90: {=D26} -> 22797.15 | E90: {=E26} -> 25820.844 | F90: {=F26} -> 27740.851 | G90: {=G26} -> 29839.734 | H90: {=H26} -> 31433.647 | I90: {=I26} -> 33201.284 | J90: {=J26} -> 34464.178
B91: Changes in Working Capital —
B92: (Increase)/Decrease in Current Assets | D92: =-(SUM(D52:D53)-SUM(C52:C53)) -> -2615.1068 | E92: =-(SUM(E52:E53)-SUM(D52:D53)) -> -2805.2 | F92: =-(SUM(F52:F53)-SUM(E52:E53)) -> -4070.682 | G92: =-(SUM(G52:G53)-SUM(F52:F53)) -> -3255.3779 | H92: =-(SUM(H52:H53)-SUM(G52:G53)) -> -4025.7215 | I92: =-(SUM(I52:I53)-SUM(H52:H53)) -> -2971.2919 | J92: =-(SUM(J52:J53)-SUM(I52:I53)) -> -3973.6352
B93: Increase/(Decrease) in Current Liabilities | D93: =SUM(D69:D70)-SUM(C69:C70) -> 2716.7446 | E93: =SUM(E69:E70)-SUM(D69:D70) -> 2942.3295 | F93: =SUM(F69:F70)-SUM(E69:E70) -> 2658.1747 | G93: =SUM(G69:G70)-SUM(F69:F70) -> 3316.7585 | H93: =SUM(H69:H70)-SUM(G69:G70) -> 2682.5348 | I93: =SUM(I69:I70)-SUM(H69:H70) -> 3456.2622 | J93: =SUM(J69:J70)-SUM(I69:I70) -> 2734.6215
B94: Net Cash from Operating Activities | D94: =SUM(D88:D93) -> 68669.855 | E94: =SUM(E88:E93) -> 80102.418 | F94: =SUM(F88:F93) -> 91037.297 | G94: =SUM(G88:G93) -> 102584.91 | H94: =SUM(H88:H93) -> 111214.23 | I94: =SUM(I88:I93) -> 123437.83 | J94: =SUM(J88:J93) -> 131624.17
B96: Cash Flow from Investing Activities
B97: CapEx | C97: =C$16*INDEX('Google Drivers'!D$69:D$71,MATCH($D$5,'Google Drivers'!$C$69:$C$71,0)) -> 27360.875 | D97: =D$16*INDEX('Google Drivers'!E$69:E$71,MATCH($D$5,'Google Drivers'!$C$69:$C$71,0)) -> 31676.04 | E97: =E$16*INDEX('Google Drivers'!F$69:F$71,MATCH($D$5,'Google Drivers'!$C$69:$C$71,0)) -> 36886.92 | F97: =F$16*INDEX('Google Drivers'!G$69:G$71,MATCH($D$5,'Google Drivers'!$C$69:$C$71,0)) -> 39421.209 | G97: =G$16*INDEX('Google Drivers'!H$69:H$71,MATCH($D$5,'Google Drivers'!$C$69:$C$71,0)) -> 41711.457 | H97: =H$16*INDEX('Google Drivers'!I$69:I$71,MATCH($D$5,'Google Drivers'!$C$69:$C$71,0)) -> 43657.843 | I97: =I$16*INDEX('Google Drivers'!J$69:J$71,MATCH($D$5,'Google Drivers'!$C$69:$C$71,0)) -> 45274.478 | J97: =J$16*INDEX('Google Drivers'!K$69:K$71,MATCH($D$5,'Google Drivers'!$C$69:$C$71,0)) -> 46628.005
B98: Long-term investments | D98: =D61-C61 -> 3000 | E98: =E61-D61 -> 4000 | F98: =F61-E61 -> 3360 | G98: =G61-F61 -> 3628.8 | H98: =H61-G61 -> 3919.104 | I98: =I61-H61 -> 4232.6323 | J98: =J61-I61 -> 4571.2429
B99: Net Cash from Investing Activities | D99: =-D97-D98 -> -34676.04 | E99: =-E97-E98 -> -40886.92 | F99: =-F97-F98 -> -42781.209 | G99: =-G97-G98 -> -45340.257 | H99: =-H97-H98 -> -47576.947 | I99: =-I97-I98 -> -49507.11 | J99: =-J97-J98 -> -51199.248
B101: Cash Flow from Financing Activities
B102: Share Repurchases | D102: =MAX(D94+D99,0)*INDEX('Google Drivers'!E$98:E$100,MATCH($D$5,'Google Drivers'!$C$98:$C$100,0)) -> 25495.361 | E102: =MAX(E94+E99,0)*INDEX('Google Drivers'!F$98:F$100,MATCH($D$5,'Google Drivers'!$C$98:$C$100,0)) -> 29411.624 | F102: =MAX(F94+F99,0)*INDEX('Google Drivers'!G$98:G$100,MATCH($D$5,'Google Drivers'!$C$98:$C$100,0)) -> 33779.262 | G102: =MAX(G94+G99,0)*INDEX('Google Drivers'!H$98:H$100,MATCH($D$5,'Google Drivers'!$C$98:$C$100,0)) -> 40071.26 | H102: =MAX(H94+H99,0)*INDEX('Google Drivers'!I$98:I$100,MATCH($D$5,'Google Drivers'!$C$98:$C$100,0)) -> 41364.236 | I102: =MAX(I94+I99,0)*INDEX('Google Drivers'!J$98:J$100,MATCH($D$5,'Google Drivers'!$C$98:$C$100,0)) -> 48054.968 | J102: =MAX(J94+J99,0)*INDEX('Google Drivers'!K$98:K$100,MATCH($D$5,'Google Drivers'!$C$98:$C$100,0)) -> 48254.953
B103: Debt Repayments | D103: =-D$73+C$73 -> 1000 | E103: =-E$73+D$73 -> 1000 | F103: =-F$73+E$73 -> 500 | G103: =-G$73+F$73 -> 500 | H103: =-H$73+G$73 -> 500 | I103: =-I$73+H$73 -> 500 | J103: =-J$73+I$73 -> 500
B104: Net Cash from Financing Activities | D104: =-D102-D103 -> -26495.361 | E104: =-E102-E103 -> -30411.624 | F104: =-F102-F103 -> -34279.262 | G104: =-G102-G103 -> -40571.26 | H104: =-H102-H103 -> -41864.236 | I104: =-I102-I103 -> -48554.968 | J104: =-J102-J103 -> -48754.953
B106: Net Change in Cash | D106: =D94+D99+D104 -> 7498.4538 | E106: =E94+E99+E104 -> 8803.8746 | F106: =F94+F99+F104 -> 13976.827 | G106: =G94+G99+G104 -> 16673.397 | H106: =H94+H99+H104 -> 21773.05 | I106: =I94+I99+I104 -> 25375.752 | J106: =J94+J99+J104 -> 31669.969
B107: Beginning Cash | D107: =C$108 -> 90000 | E107: =D$108 -> 97498.454 | F107: =E$108 -> 106302.33 | G107: =F$108 -> 120279.15 | H107: =G$108 -> 136952.55 | I107: =H$108 -> 158725.6 | J107: =I$108 -> 184101.35
B108: Cash — Ending | C108: =C51 -> 90000 | D108: =D106+D107 -> 97498.454 | E108: =E106+E107 -> 106302.33 | F108: =F106+F107 -> 120279.15 | G108: =G106+G107 -> 136952.55 | H108: =H106+H107 -> 158725.6 | I108: =I106+I107 -> 184101.35 | J108: =J106+J107 -> 215771.32
B110: Cash Balance Check | C110: =C108-C51 -> 0 | D110: =D108-D51 -> 0 | E110: =E108-E51 -> 0 | F110: =F108-F51 -> 0 | G110: =G108-G51 -> 0 | H110: =H108-H51 -> 0 | I110: =I108-I51 -> 0 | J110: =J108-J51 -> 0

Sheet Meta Drivers
B2: Meta Platforms — Operating Model Assumptions
B3: 3-Year Historical (2021-2023) | 5-Year Projections (2024-2028)
B5: Case selector
B6: Chosen case: | D6: Base
B8: Actuals | G8: Forecast
D9: 2021 | E9: 2022 | F9: 2023 | G9: 2024 | H9: 2025 | I9: 2026 | J9: 2027 | K9: 2028
B11: Revenue Assumptions — 1
B13: Growth rates — Revenue (%)
C14: Case | D14: 2021 | E14: 2022 | F14: 2023 | G14: 2024 | H14: 2025 | I14: 2026 | J14: 2027 | K14: 2028
B15: Family of Apps — FoA | C15: Base | G15: 0.12 | H15: 0.1 | I15: 0.085 | J15: 0.075 | K15: 0.07
B16: Growth rate | C16: Bull | G16: 0.14 | H16: 0.12 | I16: 0.105 | J16: 0.095 | K16: 0.09
C17: Bear | G17: 0.1 | H17: 0.08 | I17: 0.065 | J17: 0.055 | K17: 0.05
B19: Reality Labs | C19: Base | G19: 0.25 | H19: 0.35 | I19: 0.45 | J19: 0.4 | K19: 0.35
B20: % of total revenue | C20: Bull | G20: 0.3 | H20: 0.45 | I20: 0.55 | J20: 0.5 | K20: 0.45 | M20: 0.005
C21: Bear | G21: 0.2 | H21: 0.25 | I21: 0.35 | J21: 0.3 | K21: 0.25 | M21: 0.005
B24: User Growth Metrics
B26: DAU Growth — % | C26: Base | G26: 0.03 | H26: 0.025 | I26: 0.02 | J26: 0.015 | K26: 0.01
C27: Bull | G27: 0.04 | H27: 0.035 | I27: 0.03 | J27: 0.025 | K27: 0.02
C28: Bear | G28: 0.02 | H28: 0.015 | I28: 0.01 | J28: 0.005 | K28: 0
B30: ARPU Growth — % | C30: Base | G30: 0.085 | H30: 0.07 | I30: 0.06 | J30: 0.055 | K30: 0.05
C31: Bull | G31: 0.1 | H31: 0.085 | I31: 0.075 | J31: 0.07 | K31: 0.065
C32: Bear | G32: 0.07 | H32: 0.055 | I32: 0.045 | J32: 0.04 | K32: 0.035
B34: Operating Expense Assumptions — 2
B36: Expenses — Operating (% of Revenue)
B38: R&D | C38: Base | D38: 0.255 | E38: 0.27 | F38: 0.29 | G38: 0.285 | H38: 0.28 | I38: 0.275 | J38: 0.27 | K38: 0.265
C39: Bull | D39: 0.255 | E39: 0.27 | F39: 0.29 | G39: 0.28 | H39: 0.275 | I39: 0.27 | J39: 0.265 | K39: 0.26
C40: Bear | D40: 0.255 | E40: 0.27 | F40: 0.29 | G40: 0.29 | H40: 0.285 | I40: 0.28 | J40: 0.275 | K40: 0.27
B42: S&M | C42: Base | D42: 0.118 | E42: 0.125 | F42: 0.13 | G42: 0.125 | H42: 0.12 | I42: 0.115 | J42: 0.11 | K42: 0.105
C43: Bull | D43: 0.118 | E43: 0.125 | F43: 0.13 | G43: 0.12 | H43: 0.115 | I43: 0.11 | J43: 0.105 | K43: 0.1
C44: Bear | D44: 0.118 | E44: 0.125 | F44: 0.13 | G44: 0.13 | H44: 0.125 | I44: 0.12 | J44: 0.115 | K44: 0.11
B46: G&A | C46: Base | D46: 0.102 | E46: 0.108 | F46: 0.115 | G46: 0.11 | H46: 0.105 | I46: 0.1 | J46: 0.095 | K46: 0.09
C47: Bull | D47: 0.102 | E47: 0.108 | F47: 0.115 | G47: 0.105 | H47: 0.1 | I47: 0.095 | J47: 0.09 | K47: 0.085
C48: Bear | D48: 0.102 | E48: 0.108 | F48: 0.115 | G48: 0.115 | H48: 0.11 | I48: 0.105 | J48: 0.1 | K48: 0.095
B50: SBC | C50: Base | D50: 0.085 | E50: 0.102 | F50: 0.118 | G50: 0.11 | H50: 0.105 | I50: 0.1 | J50: 0.095 | K50: 0.09
C51: Bull | D51: 0.085 | E51: 0.102 | F51: 0.118 | G51: 0.105 | H51: 0.1 | I51: 0.095 | J51: 0.09 | K51: 0.085
C52: Bear | D52: 0.085 | E52: 0.102 | F52: 0.118 | G52: 0.115 | H52: 0.11 | I52: 0.105 | J52: 0.1 | K52: 0.095
B54: Reality Labs Operating Margin
B56: Operating Margin — % | C56: Base | D56: -3.5 | E56: -3 | F56: -2.5 | G56: -2 | H56: -1.5 | I56: -1 | J56: -0.75 | K56: -0.5
C57: Bull | D57: -3.5 | E57: -3 | F57: -2.5 | G57: -1.75 | H57: -1.25 | I57: -0.75 | J57: -0.5 | K57: -0.25
C58: Bear | D58: -3.5 | E58: -3 | F58: -2.5 | G58: -2.25 | H58: -1.75 | I58: -1.25 | J58: -1 | K58: -0.75
B60: Balance Sheet & Cash Flow Assumptions — 3
B62: Working Capital Metrics
B64: Days Sales Outstanding — DSO | C64: Base | D64: 55 | E64: 53 | F64: 51 | G64: 50 | H64: 49 | I64: 48 | J64: 47 | K64: 46
C65: Bull | D65: 55 | E65: 53 | F65: 51 | G65: 49 | H65: 47 | I65: 46 | J65: 45 | K65: 44
C66: Bear | D66: 55 | E66: 53 | F66: 51 | G66: 52 | H66: 51 | I66: 50 | J66: 49 | K66: 48
B68: Days Payable Outstanding — DPO | C68: Base | D68: 28 | E68: 30 | F68: 32 | G68: 33 | H68: 34 | I68: 35 | J68: 36 | K68: 37
C69: Bull | D69: 28 | E69: 30 | F69: 32 | G69: 34 | H69: 36 | I69: 37 | J69: 38 | K69: 39
C70: Bear | D70: 28 | E70: 30 | F70: 32 | G70: 32 | H70: 32 | I70: 33 | J70: 34 | K70: 35
B72: ='Meta Model'!$B$51 -> Other current assets | C72: % Increase | E72: 0.04 | F72: 0.038461538 | G72: 0.04 | H72: 0.04 | I72: 0.04 | J72: 0.04 | K72: 0.04
B73: ='Meta Model'!$B$59 -> Other Long-term Assets | C73: % Increase | E73: 0.12 | F73: 0.14285714 | G73: 0.1 | H73: 0.1 | I73: 0.1 | J73: 0.1 | K73: 0.1
B74: ='Meta Model'!$B$68 -> Accrued Expenses | C74: % Increase | E74: 0.0625 | F74: 0.058823529 | G74: 0.05 | H74: 0.05 | I74: 0.05 | J74: 0.05 | K74: 0.05
B76: Capital Expenditure
B78: CapEx — % of Revenue | C78: Base | D78: 0.185 | E78: 0.22 | F78: 0.245 | G78: 0.23 | H78: 0.215 | I78: 0.2 | J78: 0.19 | K78: 0.18
C79: Bull | D79: 0.185 | E79: 0.22 | F79: 0.245 | G79: 0.22 | H79: 0.205 | I79: 0.19 | J79: 0.18 | K79: 0.17
C80: Bear | D80: 0.185 | E80: 0.22 | F80: 0.245 | G80: 0.24 | H80: 0.225 | I80: 0.21 | J80: 0.2 | K80: 0.19
B82: D&A — % of Prior Year CapEx | C82: Base | D82: 0.65 | E82: 0.65 | F82: 0.65 | G82: 0.65 | H82: 0.65 | I82: 0.65 | J82: 0.65 | K82: 0.65
C83: Bull | D83: 0.65 | E83: 0.65 | F83: 0.65 | G83: 0.63 | H83: 0.63 | I83: 0.63 | J83: 0.63 | K83: 0.63
C84: Bear | D84: 0.65 | E84: 0.65 | F84: 0.65 | G84: 0.67 | H84: 0.67 | I84: 0.67 | J84: 0.67 | K84: 0.67
B88: Other Financial Assumptions — 4
B90: Tax Rate
B92: Effective Tax Rate | C92: Base | D92: 0.175 | E92: 0.19 | F92: 0.185 | G92: 0.19 | H92: 0.195 | I92: 0.2 | J92: 0.205 | K92: 0.21
C93: Bull | D93: 0.175 | E93: 0.19 | F93: 0.185 | G93: 0.185 | H93: 0.19 | I93: 0.195 | J93: 0.2 | K93: 0.205
C94: Bear | D94: 0.175 | E94: 0.19 | F94: 0.185 | G94: 0.195 | H94: 0.2 | I94: 0.205 | J94: 0.21 | K94: 0.215
B97: Interest Rates
B99: Interest Income Rate — on cash | C99: Base | D99: 0.005 | E99: 0.015 | F99: 0.025 | G99: 0.035 | H99: 0.03 | I99: 0.025 | J99: 0.025 | K99: 0.02
C100: Bull | D100: 0.01 | E100: 0.02 | F100: 0.03 | G100: 0.04 | H100: 0.045 | I100: 0.04 | J100: 0.035 | K100: 0.035
C101: Bear | D101: 0.0025 | E101: 0.0125 | F101: 0.0225 | G101: 0.0325 | H101: 0.0375 | I101: 0.0325 | J101: 0.0275 | K101: 0.0275
B103: Interest Expense Rate — on LT debt | C103: Base | D103: 0.03 | E103: 0.035 | F103: 0.04 | G103: 0.045 | H103: 0.04 | I103: 0.035 | J103: 0.03 | K103: 0.03
C104: Bull | D104: 0.025 | E104: 0.03 | F104: 0.035 | G104: 0.04 | H104: 0.035 | I104: 0.03 | J104: 0.025 | K104: 0.025
C105: Bear | D105: 0.04 | E105: 0.045 | F105: 0.05 | G105: 0.055 | H105: 0.05 | I105: 0.045 | J105: 0.04 | K105: 0.04
B107: Share Buyback & Dividends
B109: Buyback — % of FCF | C109: Base | D109: 0.6 | E109: 0.65 | F109: 0.7 | G109: 0.65 | H109: 0.65 | I109: 0.6 | J109: 0.6 | K109: 0.55
C110: Bull | D110: 0.6 | E110: 0.65 | F110: 0.7 | G110: 0.7 | H110: 0.7 | I110: 0.65 | J110: 0.65 | K110: 0.6
C111: Bear | D111: 0.6 | E111: 0.65 | F111: 0.7 | G111: 0.6 | H111: 0.6 | I111: 0.55 | J111: 0.55 | K111: 0.5
B113: Dividend Payout Ratio | C113: Base | D113: 0 | E113: 0 | F113: 0.02 | G113: 0.03 | H113: 0.04 | I113: 0.05 | J113: 0.06 | K113: 0.07
C114: Bull | D114: 0 | E114: 0 | F114: 0.02 | G114: 0.04 | H114: 0.05 | I114: 0.06 | J114: 0.07 | K114: 0.08
C115: Bear | D115: 0 | E115: 0 | F115: 0.02 | G115: 0.02 | H115: 0.03 | I115: 0.04 | J115: 0.05 | K115: 0.06

Sheet Meta Model
B2: Meta Platforms — Income Statement
B3: Figures in $mm
B5: Chosen case: | D5: ='Meta Drivers'!D6 -> Base
B7: Actuals | F7: Forecast
C8: 2021 | D8: 2022 | E8: 2023 | F8: 2024 | G8: 2025 | H8: 2026 | I8: 2027 | J8: 2028
B10: P&L statement
B12: Family of Apps | C12: 115655 | D12: 114450 | E12: 133008 | F12: =E12*(1+INDEX('Meta Drivers'!G$15:G$17,MATCH($D$5,'Meta Drivers'!$C$15:$C$17,0))) -> 148968.96 | G12: =F12*(1+INDEX('Meta Drivers'!H$15:H$17,MATCH($D$5,'Meta Drivers'!$C$15:$C$17,0))) -> 163865.86 | H12: =G12*(1+INDEX('Meta Drivers'!I$15:I$17,MATCH($D$5,'Meta Drivers'!$C$15:$C$17,0))) -> 177794.45 | I12: =H12*(1+INDEX('Meta Drivers'!J$15:J$17,MATCH($D$5,'Meta Drivers'!$C$15:$C$17,0))) -> 191129.04 | J12: =I12*(1+INDEX('Meta Drivers'!K$15:K$17,MATCH($D$5,'Meta Drivers'!$C$15:$C$17,0))) -> 204508.07
B13: Reality Labs | C13: 2274 | D13: 2159 | E13: 1896 | F13: =E13*(1+INDEX('Meta Drivers'!G$19:G$21,MATCH($D$5,'Meta Drivers'!$C$19:$C$21,0))) -> 2370 | G13: =F13*(1+INDEX('Meta Drivers'!H$19:H$21,MATCH($D$5,'Meta Drivers'!$C$19:$C$21,0))) -> 3199.5 | H13: =G13*(1+INDEX('Meta Drivers'!I$19:I$21,MATCH($D$5,'Meta Drivers'!$C$19:$C$21,0))) -> 4639.275 | I13: =H13*(1+INDEX('Meta Drivers'!J$19:J$21,MATCH($D$5,'Meta Drivers'!$C$19:$C$21,0))) -> 6494.985 | J13: =I13*(1+INDEX('Meta Drivers'!K$19:K$21,MATCH($D$5,'Meta Drivers'!$C$19:$C$21,0))) -> 8768.2297
B14: Revenue — Total | C14: =SUM(C12:C13) -> 117929 | D14: =SUM(D12:D13) -> 116609 | E14: =SUM(E12:E13) -> 134904 | F14: =SUM(F12:F13) -> 151338.96 | G14: =SUM(G12:G13) -> 167065.36 | H14: =SUM(H12:H13) -> 182433.73 | I14: =SUM(I12:I13) -> 197624.02 | J14: =SUM(J12:J13) -> 213276.3
B15: YoY Growth % | D15: =D14/C14-1 -> -0.011193176 | E15: =E14/D14-1 -> 0.15689184 | F15: =F14/E14-1 -> 0.12182708 | G15: =G14/F14-1 -> 0.10391505 | H15: =H14/G14-1 -> 0.091990184 | I15: =I14/H14-1 -> 0.083264724 | J15: =J14/I14-1 -> 0.079202301
B17: Cost of sales | C17: =C14*(1-C19) -> 23349.942 | D17: =D14*(1-D19) -> 23555.018 | E17: =E14*(1-E19) -> 27655.32 | F17: =F14*(1-F19) -> 30721.809 | G17: =G14*(1-G19) -> 33580.137 | H17: =H14*(1-H19) -> 36304.312 | I17: =I14*(1-I19) -> 38931.932 | J17: =J14*(1-J19) -> 41588.879
B18: Profit — Gross | C18: =C14-C17 -> 94579.058 | D18: =D14-D17 -> 93053.982 | E18: =E14-E17 -> 107248.68 | F18: =F14-F17 -> 120617.15 | G18: =G14-G17 -> 133485.22 | H18: =H14-H17 -> 146129.42 | I18: =I14-I17 -> 158692.09 | J18: =J14-J17 -> 171687.42
B19: Gross Margin (%) | C19: 0.802 | D19: 0.798 | E19: 0.795 | F19: 0.797 | G19: 0.799 | H19: 0.801 | I19: 0.803 | J19: 0.805
B21: R&D | C21: =C14*INDEX('Meta Drivers'!D$38:D$40,MATCH($D$5,'Meta Drivers'!$C$38:$C$40,0)) -> 30071.895 | D21: =D14*INDEX('Meta Drivers'!E$38:E$40,MATCH($D$5,'Meta Drivers'!$C$38:$C$40,0)) -> 31484.43 | E21: =E14*INDEX('Meta Drivers'!F$38:F$40,MATCH($D$5,'Meta Drivers'!$C$38:$C$40,0)) -> 39122.16 | F21: =F14*INDEX('Meta Drivers'!G$38:G$40,MATCH($D$5,'Meta Drivers'!$C$38:$C$40,0)) -> 43131.604 | G21: =G14*INDEX('Meta Drivers'!H$38:H$40,MATCH($D$5,'Meta Drivers'!$C$38:$C$40,0)) -> 46778.3 | H21: =H14*INDEX('Meta Drivers'!I$38:I$40,MATCH($D$5,'Meta Drivers'!$C$38:$C$40,0)) -> 50169.275 | I21: =I14*INDEX('Meta Drivers'!J$38:J$40,MATCH($D$5,'Meta Drivers'!$C$38:$C$40,0)) -> 53358.486 | J21: =J14*INDEX('Meta Drivers'!K$38:K$40,MATCH($D$5,'Meta Drivers'!$C$38:$C$40,0)) -> 56518.22
B22: S&M | C22: =C14*INDEX('Meta Drivers'!D$42:D$44,MATCH($D$5,'Meta Drivers'!$C$42:$C$44,0)) -> 13915.622 | D22: =D14*INDEX('Meta Drivers'!E$42:E$44,MATCH($D$5,'Meta Drivers'!$C$42:$C$44,0)) -> 14576.125 | E22: =E14*INDEX('Meta Drivers'!F$42:F$44,MATCH($D$5,'Meta Drivers'!$C$42:$C$44,0)) -> 17537.52 | F22: =F14*INDEX('Meta Drivers'!G$42:G$44,MATCH($D$5,'Meta Drivers'!$C$42:$C$44,0)) -> 18917.37 | G22: =G14*INDEX('Meta Drivers'!H$42:H$44,MATCH($D$5,'Meta Drivers'!$C$42:$C$44,0)) -> 20047.843 | H22: =H14*INDEX('Meta Drivers'!I$42:I$44,MATCH($D$5,'Meta Drivers'!$C$42:$C$44,0)) -> 20979.879 | I22: =I14*INDEX('Meta Drivers'!J$42:J$44,MATCH($D$5,'Meta Drivers'!$C$42:$C$44,0)) -> 21738.643 | J22: =J14*INDEX('Meta Drivers'!K$42:K$44,MATCH($D$5,'Meta Drivers'!$C$42:$C$44,0)) -> 22394.012
B23: G&A | C23: =C14*INDEX('Meta Drivers'!D$46:D$48,MATCH($D$5,'Meta Drivers'!$C$46:$C$48,0)) -> 12028.758 | D23: =D14*INDEX('Meta Drivers'!E$46:E$48,MATCH($D$5,'Meta Drivers'!$C$46:$C$48,0)) -> 12593.772 | E23: =E14*INDEX('Meta Drivers'!F$46:F$48,MATCH($D$5,'Meta Drivers'!$C$46:$C$48,0)) -> 15513.96 | F23: =F14*INDEX('Meta Drivers'!G$46:G$48,MATCH($D$5,'Meta Drivers'!$C$46:$C$48,0)) -> 16647.286 | G23: =G14*INDEX('Meta Drivers'!H$46:H$48,MATCH($D$5,'Meta Drivers'!$C$46:$C$48,0)) -> 17541.862 | H23: =H14*INDEX('Meta Drivers'!I$46:I$48,MATCH($D$5,'Meta Drivers'!$C$46:$C$48,0)) -> 18243.373 | I23: =I14*INDEX('Meta Drivers'!J$46:J$48,MATCH($D$5,'Meta Drivers'!$C$46:$C$48,0)) -> 18774.282 | J23: =J14*INDEX('Meta Drivers'!K$46:K$48,MATCH($D$5,'Meta Drivers'!$C$46:$C$48,0)) -> 19194.867
B24: SBC | C24: =C14*INDEX('Meta Drivers'!D$50:D$52,MATCH($D$5,'Meta Drivers'!$C$50:$C$52,0)) -> 10023.965 | D24: =D14*INDEX('Meta Drivers'!E$50:E$52,MATCH($D$5,'Meta Drivers'!$C$50:$C$52,0)) -> 11894.118 | E24: =E14*INDEX('Meta Drivers'!F$50:F$52,MATCH($D$5,'Meta Drivers'!$C$50:$C$52,0)) -> 15918.672 | F24: =F14*INDEX('Meta Drivers'!G$50:G$52,MATCH($D$5,'Meta Drivers'!$C$50:$C$52,0)) -> 16647.286 | G24: =G14*INDEX('Meta Drivers'!H$50:H$52,MATCH($D$5,'Meta Drivers'!$C$50:$C$52,0)) -> 17541.862 | H24: =H14*INDEX('Meta Drivers'!I$50:I$52,MATCH($D$5,'Meta Drivers'!$C$50:$C$52,0)) -> 18243.373 | I24: =I14*INDEX('Meta Drivers'!J$50:J$52,MATCH($D$5,'Meta Drivers'!$C$50:$C$52,0)) -> 18774.282 | J24: =J14*INDEX('Meta Drivers'!K$50:K$52,MATCH($D$5,'Meta Drivers'!$C$50:$C$52,0)) -> 19194.867
B25: Operating Expenses — Total | C25: =SUM(C21:C24) -> 66040.24 | D25: =SUM(D21:D24) -> 70548.445 | E25: =SUM(E21:E24) -> 88092.312 | F25: =SUM(F21:F24) -> 95343.545 | G25: =SUM(G21:G24) -> 101909.87 | H25: =SUM(H21:H24) -> 107635.9 | I25: =SUM(I21:I24) -> 112645.69 | J25: =SUM(J21:J24) -> 117301.97
B27: EBIT / Operating Income | C27: =C18-C25 -> 28538.818 | D27: =D18-D25 -> 22505.537 | E27: =E18-E25 -> 19156.368 | F27: =F18-F25 -> 25273.606 | G27: =G18-G25 -> 31575.352 | H27: =H18-H25 -> 38493.517 | I27: =I18-I25 -> 46046.397 | J27: =J18-J25 -> 54385.457
B28: Operating Margin (%) | C28: =C27/C14 -> 0.242 | D28: =D27/D14 -> 0.193 | E28: =E27/E14 -> 0.142 | F28: =F27/F14 -> 0.167 | G28: =G27/G14 -> 0.189 | H28: =H27/H14 -> 0.211 | I28: =I27/I14 -> 0.233 | J28: =J27/J14 -> 0.255
B30: Interest (Expense) / Income | C30: =(C$49*INDEX('Meta Drivers'!D$99:D$101,MATCH($D$5,'Meta Drivers'!$C$99:$C$101,0)))-(C71*INDEX('Meta Drivers'!D$103:D$105,MATCH($D$5,'Meta Drivers'!$C$103:$C$105,0))) -> -125 | D30: =(D$49*INDEX('Meta Drivers'!E$99:E$101,MATCH($D$5,'Meta Drivers'!$C$99:$C$101,0)))-(D71*INDEX('Meta Drivers'!E$103:E$105,MATCH($D$5,'Meta Drivers'!$C$103:$C$105,0))) -> 277.83077 | E30: =(E$49*INDEX('Meta Drivers'!F$99:F$101,MATCH($D$5,'Meta Drivers'!$C$99:$C$101,0)))-(E71*INDEX('Meta Drivers'!F$103:F$105,MATCH($D$5,'Meta Drivers'!$C$103:$C$105,0))) -> 735.70932 | F30: =(F$49*INDEX('Meta Drivers'!G$99:G$101,MATCH($D$5,'Meta Drivers'!$C$99:$C$101,0)))-(F71*INDEX('Meta Drivers'!G$103:G$105,MATCH($D$5,'Meta Drivers'!$C$103:$C$105,0))) -> 1393.891 | G30: =(G$49*INDEX('Meta Drivers'!H$99:H$101,MATCH($D$5,'Meta Drivers'!$C$99:$C$101,0)))-(G71*INDEX('Meta Drivers'!H$103:H$105,MATCH($D$5,'Meta Drivers'!$C$103:$C$105,0))) -> 1470.867 | H30: =(H$49*INDEX('Meta Drivers'!I$99:I$101,MATCH($D$5,'Meta Drivers'!$C$99:$C$101,0)))-(H71*INDEX('Meta Drivers'!I$103:I$105,MATCH($D$5,'Meta Drivers'!$C$103:$C$105,0))) -> 1547.6923 | I30: =(I$49*INDEX('Meta Drivers'!J$99:J$101,MATCH($D$5,'Meta Drivers'!$C$99:$C$101,0)))-(I71*INDEX('Meta Drivers'!J$103:J$105,MATCH($D$5,'Meta Drivers'!$C$103:$C$105,0))) -> 1974.9617 | J30: =(J$49*INDEX('Meta Drivers'!K$99:K$101,MATCH($D$5,'Meta Drivers'!$C$99:$C$101,0)))-(J71*INDEX('Meta Drivers'!K$103:K$105,MATCH($D$5,'Meta Drivers'!$C$103:$C$105,0))) -> 1947.5673
B32: Pre-tax Income | C32: =C27+C30 -> 28413.818 | D32: =D27+D30 -> 22783.368 | E32: =E27+E30 -> 19892.077 | F32: =F27+F30 -> 26667.497 | G32: =G27+G30 -> 33046.219 | H32: =H27+H30 -> 40041.209 | I32: =I27+I30 -> 48021.359 | J32: =J27+J30 -> 56333.024
B33: Tax Expense / Provision | C33: =C32*INDEX('Meta Drivers'!D$92:D$94,MATCH($D$5,'Meta Drivers'!$C$92:$C$94,0)) -> 4972.4181 | D33: =D32*INDEX('Meta Drivers'!E$92:E$94,MATCH($D$5,'Meta Drivers'!$C$92:$C$94,0)) -> 4328.8399 | E33: =E32*INDEX('Meta Drivers'!F$92:F$94,MATCH($D$5,'Meta Drivers'!$C$92:$C$94,0)) -> 3680.0343 | F33: =F32*INDEX('Meta Drivers'!G$92:G$94,MATCH($D$5,'Meta Drivers'!$C$92:$C$94,0)) -> 5066.8245 | G33: =G32*INDEX('Meta Drivers'!H$92:H$94,MATCH($D$5,'Meta Drivers'!$C$92:$C$94,0)) -> 6444.0128 | H33: =H32*INDEX('Meta Drivers'!I$92:I$94,MATCH($D$5,'Meta Drivers'!$C$92:$C$94,0)) -> 8008.2418 | I33: =I32*INDEX('Meta Drivers'!J$92:J$94,MATCH($D$5,'Meta Drivers'!$C$92:$C$94,0)) -> 9844.3786 | J33: =J32*INDEX('Meta Drivers'!K$92:K$94,MATCH($D$5,'Meta Drivers'!$C$92:$C$94,0)) -> 11829.935
B35: Net income | C35: =C32-C33 -> 23441.4 | D35: =D32-D33 -> 18454.528 | E35: =E32-E33 -> 16212.043 | F35: =F32-F33 -> 21600.673 | G35: =G32-G33 -> 26602.207 | H35: =H32-H33 -> 32032.967 | I35: =I32-I33 -> 38176.98 | J35: =J32-J33 -> 44503.089
B36: Net Margin (%) | C36: =C35/C14 -> 0.19877553 | D36: =D35/D14 -> 0.15825989 | E36: =E35/E14 -> 0.12017467 | F36: =F35/F14 -> 0.14273042 | G36: =G35/G14 -> 0.15923233 | H36: =H35/H14 -> 0.17558687 | I36: =I35/I14 -> 0.19317986 | J36: =J35/J14 -> 0.20866401
B38: EPS calculation
B40: Basic Shares — Outstanding | C40: 2800 | D40: 2750 | E40: 2700 | F40: 2650 | G40: 2600 | H40: 2550 | I40: 2500 | J40: 2450
B41: EPS — Basic | C41: =C35/C40 -> 8.3719285 | D41: =D35/D40 -> 6.7107374 | E41: =E35/E40 -> 6.0044604 | F41: =F35/F40 -> 8.1511973 | G41: =G35/G40 -> 10.231618 | H41: =H35/H40 -> 12.561948 | I41: =I35/I40 -> 15.270792 | J41: =J35/J40 -> 18.164526
B44: Balance sheet schedule
B46: Assets section
B48: Assets — Current
B49: Cash and equivalents | C49: 35000 | D49: =D$106 -> 40688.718 | E49: =E$106 -> 43828.373 | F49: =F$106 -> 50754.029 | G49: =G$106 -> 59695.566 | H49: =H$106 -> 72407.693 | I49: =I$106 -> 87398.469 | J49: =J$106 -> 107128.37
B50: Receivables | C50: =C$14*INDEX('Meta Drivers'!D$64:D$66,MATCH($D$5,'Meta Drivers'!$C$64:$C$66,0))/365 -> 17770.123 | D50: =D$14*INDEX('Meta Drivers'!E$64:E$66,MATCH($D$5,'Meta Drivers'!$C$64:$C$66,0))/365 -> 16932.266 | E50: =E$14*INDEX('Meta Drivers'!F$64:F$66,MATCH($D$5,'Meta Drivers'!$C$64:$C$66,0))/365 -> 18849.6 | F50: =F$14*INDEX('Meta Drivers'!G$64:G$66,MATCH($D$5,'Meta Drivers'!$C$64:$C$66,0))/365 -> 20731.364 | G50: =G$14*INDEX('Meta Drivers'!H$64:H$66,MATCH($D$5,'Meta Drivers'!$C$64:$C$66,0))/365 -> 22427.952 | H50: =H$14*INDEX('Meta Drivers'!I$64:I$66,MATCH($D$5,'Meta Drivers'!$C$64:$C$66,0))/365 -> 23991.285 | I50: =I$14*INDEX('Meta Drivers'!J$64:J$66,MATCH($D$5,'Meta Drivers'!$C$64:$C$66,0))/365 -> 25447.477 | J50: =J$14*INDEX('Meta Drivers'!K$64:K$66,MATCH($D$5,'Meta Drivers'!$C$64:$C$66,0))/365 -> 26878.657
B51: Other current assets | C51: 5000 | D51: =C51*(1+'Meta Drivers'!E$72) -> 5200 | E51: =D51*(1+'Meta Drivers'!F$72) -> 5400 | F51: =E51*(1+'Meta Drivers'!G$72) -> 5616 | G51: =F51*(1+'Meta Drivers'!H$72) -> 5840.64 | H51: =G51*(1+'Meta Drivers'!I$72) -> 6074.2656 | I51: =H51*(1+'Meta Drivers'!J$72) -> 6317.2362 | J51: =I51*(1+'Meta Drivers'!K$72) -> 6569.9257
B52: Current Assets — Total | C52: =SUM(C49:C51) -> 57770.123 | D52: =SUM(D49:D51) -> 62820.984 | E52: =SUM(E49:E51) -> 68077.973 | F52: =SUM(F49:F51) -> 77101.393 | G52: =SUM(G49:G51) -> 87964.158 | H52: =SUM(H49:H51) -> 102473.24 | I52: =SUM(I49:I51) -> 119163.18 | J52: =SUM(J49:J51) -> 140576.95
B54: Assets — Non-current
B55: PP&E (Gross) | C55: 60000 | D55: =C55+D95 -> 85653.98 | E55: =D55+E95 -> 118705.46 | F55: =E55+F95 -> 153513.42 | G55: =F55+G95 -> 189432.47 | H55: =G55+H95 -> 225919.22 | I55: =H55+I95 -> 263467.78 | J55: =I55+J95 -> 301857.52
B56: Less: Accumulated depreciation | C56: 15000 | D56: =C56+D87 -> 29180.962 | E56: =D56+E87 -> 45856.049 | F56: =E56+F87 -> 67339.511 | G56: =F56+G87 -> 89964.686 | H56: =G56+H87 -> 113312.07 | I56: =H56+I87 -> 137028.45 | J56: =I56+J87 -> 161435.02
B57: Net PP&E | C57: =C55-C56 -> 45000 | D57: =D55-D56 -> 56473.018 | E57: =E55-E56 -> 72849.411 | F57: =F55-F56 -> 86173.91 | G57: =G55-G56 -> 99467.787 | H57: =H55-H56 -> 112607.15 | I57: =I55-I56 -> 126439.33 | J57: =J55-J56 -> 140422.5
B59: Other Long-term Assets | C59: 25000 | D59: =C59*(1+'Meta Drivers'!E$73) -> 28000 | E59: =D59*(1+'Meta Drivers'!F$73) -> 32000 | F59: =E59*(1+'Meta Drivers'!G$73) -> 35200 | G59: =F59*(1+'Meta Drivers'!H$73) -> 38720 | H59: =G59*(1+'Meta Drivers'!I$73) -> 42592 | I59: =H59*(1+'Meta Drivers'!J$73) -> 46851.2 | J59: =I59*(1+'Meta Drivers'!K$73) -> 51536.32
B60: Total Non-Current Assets | C60: =C57+C59 -> 70000 | D60: =D57+D59 -> 84473.018 | E60: =E57+E59 -> 104849.41 | F60: =F57+F59 -> 121373.91 | G60: =G57+G59 -> 138187.79 | H60: =H57+H59 -> 155199.15 | I60: =I57+I59 -> 173290.53 | J60: =J57+J59 -> 191958.82
B62: Total Assets | C62: =C52+C60 -> 127770.12 | D62: =D52+D60 -> 147294 | E62: =E52+E60 -> 172927.38 | F62: =F52+F60 -> 198475.3 | G62: =G52+G60 -> 226151.94 | H62: =H52+H60 -> 257672.39 | I62: =I52+I60 -> 292453.71 | J62: =J52+J60 -> 332535.76
B64: Liabilities and equity
B66: Liabilities — Current
B67: Payables | C67: =(C17+C21+C22+C23)*INDEX('Meta Drivers'!D$68:D$70,MATCH($D$5,'Meta Drivers'!$C$68:$C$70,0))/365 -> 6088.3673 | D67: =(D17+D21+D22+D23)*INDEX('Meta Drivers'!E$68:E$70,MATCH($D$5,'Meta Drivers'!$C$68:$C$70,0))/365 -> 6756.9325 | E67: =(E17+E21+E22+E23)*INDEX('Meta Drivers'!F$68:F$70,MATCH($D$5,'Meta Drivers'!$C$68:$C$70,0))/365 -> 8752.128 | F67: =(F17+F21+F22+F23)*INDEX('Meta Drivers'!G$68:G$70,MATCH($D$5,'Meta Drivers'!$C$68:$C$70,0))/365 -> 9892.5925 | G67: =(G17+G21+G22+G23)*INDEX('Meta Drivers'!H$68:H$70,MATCH($D$5,'Meta Drivers'!$C$68:$C$70,0))/365 -> 10986.95 | H67: =(H17+H21+H22+H23)*INDEX('Meta Drivers'!I$68:I$70,MATCH($D$5,'Meta Drivers'!$C$68:$C$70,0))/365 -> 12053.122 | I67: =(I17+I21+I22+I23)*INDEX('Meta Drivers'!J$68:J$70,MATCH($D$5,'Meta Drivers'!$C$68:$C$70,0))/365 -> 13098.412 | J67: =(J17+J21+J22+J23)*INDEX('Meta Drivers'!K$68:K$70,MATCH($D$5,'Meta Drivers'!$C$68:$C$70,0))/365 -> 14160.962
B68: Accrued Expenses | C68: 8000 | D68: =C68*(1+'Meta Drivers'!E$74) -> 8500 | E68: =D68*(1+'Meta Drivers'!F$74) -> 9000 | F68: =E68*(1+'Meta Drivers'!G$74) -> 9450 | G68: =F68*(1+'Meta Drivers'!H$74) -> 9922.5 | H68: =G68*(1+'Meta Drivers'!I$74) -> 10418.625 | I68: =H68*(1+'Meta Drivers'!J$74) -> 10939.556 | J68: =I68*(1+'Meta Drivers'!K$74) -> 11486.534
B69: Current Liabilities — Total | C69: =SUM(C67:C68) -> 14088.367 | D69: =SUM(D67:D68) -> 15256.932 | E69: =SUM(E67:E68) -> 17752.128 | F69: =SUM(F67:F68) -> 19342.592 | G69: =SUM(G67:G68) -> 20909.45 | H69: =SUM(H67:H68) -> 22471.747 | I69: =SUM(I67:I68) -> 24037.968 | J69: =SUM(J67:J68) -> 25647.496
B71: Long-term Debt | C71: 10000 | D71: 9500 | E71: 9000 | F71: 8500 | G71: 8000 | H71: 7500 | I71: 7000 | J71: 6500
B72: Liabilities — Total | C72: =C69+C71 -> 24088.367 | D72: =D69+D71 -> 24756.932 | E72: =E69+E71 -> 26752.128 | F72: =F69+F71 -> 27842.592 | G72: =G69+G71 -> 28909.45 | H72: =H69+H71 -> 29971.747 | I72: =I69+I71 -> 31037.968 | J72: =J69+J71 -> 32147.496
B74: Shareholders' Equity
B75: Common Stock & APIC | C75: 40000 | D75: =C75+D88 -> 51894.118 | E75: =D75+E88 -> 67812.79 | F75: =E75+F88 -> 84460.076 | G75: =F75+G88 -> 102001.94 | H75: =G75+H88 -> 120245.31 | I75: =H75+I88 -> 139019.59 | J75: =I75+J88 -> 158214.46
B76: Treasury Stock | C76: 36318.244 | D76: =C76+D100 -> 47811.577 | E76: =D76+E100 -> 56304.105 | F76: =E76+F100 -> 70094.609 | G76: =F76+G100 -> 87628.894 | H76: =G76+H100 -> 107447.08 | I76: =H76+I100 -> 130683.25 | J76: =I76+J100 -> 155408.68
B77: Retained earnings | C77: 100000 | D77: =C77+D86 -> 118454.53 | E77: =D77+E86 -> 134666.57 | F77: =E77+F86 -> 156267.24 | G77: =F77+G86 -> 182869.45 | H77: =G77+H86 -> 214902.42 | I77: =H77+I86 -> 253079.4 | J77: =I77+J86 -> 297582.49
B78: Total Shareholders' Equity | C78: =C75-C76+C77 -> 103681.76 | D78: =D75-D76+D77 -> 122537.07 | E78: =E75-E76+E77 -> 146175.26 | F78: =F75-F76+F77 -> 170632.71 | G78: =G75-G76+G77 -> 197242.49 | H78: =H75-H76+H77 -> 227700.65 | I78: =I75-I76+I77 -> 261415.74 | J78: =J75-J76+J77 -> 300388.27
B80: Total Liabilities & Equity | C80: =C72+C78 -> 127770.12 | D80: =D72+D78 -> 147294 | E80: =E72+E78 -> 172927.38 | F80: =F72+F78 -> 198475.3 | G80: =G72+G78 -> 226151.94 | H80: =H72+H78 -> 257672.39 | I80: =I72+I78 -> 292453.71 | J80: =J72+J78 -> 332535.76
B82: Balance Check (Assets — L&E) | C82: =C62-C80 -> 0 | D82: =D62-D80 -> 0 | E82: =E62-E80 -> 0 | F82: =F62-F80 -> 0 | G82: =G62-G80 -> 0 | H82: =H62-H80 -> 0 | I82: =I62-I80 -> 0 | J82: =J62-J80 -> 0
B84: Cash-flow statement
B85: Cash Flow from Operating Activities
B86: Net Income | D86: {=D35} -> 18454.528 | E86: {=E35} -> 16212.043 | F86: {=F35} -> 21600.673 | G86: {=G35} -> 26602.207 | H86: {=H35} -> 32032.967 | I86: {=I35} -> 38176.98 | J86: {=J35} -> 44503.089
B87: Add — Depreciation & Amortization | D87: =C$95*INDEX('Meta Drivers'!E$82:E$84,MATCH($D$5,'Meta Drivers'!$C$82:$C$84,0)) -> 14180.962 | E87: =D$95*INDEX('Meta Drivers'!F$82:F$84,MATCH($D$5,'Meta Drivers'!$C$82:$C$84,0)) -> 16675.087 | F87: =E$95*INDEX('Meta Drivers'!G$82:G$84,MATCH($D$5,'Meta Drivers'!$C$82:$C$84,0)) -> 21483.462 | G87: =F$95*INDEX('Meta Drivers'!H$82:H$84,MATCH($D$5,'Meta Drivers'!$C$82:$C$84,0)) -> 22625.175 | H87: =G$95*INDEX('Meta Drivers'!I$82:I$84,MATCH($D$5,'Meta Drivers'!$C$82:$C$84,0)) -> 23347.384 | I87: =H$95*INDEX('Meta Drivers'!J$82:J$84,MATCH($D$5,'Meta Drivers'!$C$82:$C$84,0)) -> 23716.385 | J87: =I$95*INDEX('Meta Drivers'!K$82:K$84,MATCH($D$5,'Meta Drivers'!$C$82:$C$84,0)) -> 24406.567
B88: Add: SBC | D88: {=D24} -> 11894.118 | E88: {=E24} -> 15918.672 | F88: {=F24} -> 16647.286 | G88: {=G24} -> 17541.862 | H88: {=H24} -> 18243.373 | I88: {=I24} -> 18774.282 | J88: {=J24} -> 19194.867
B89: Changes in Working Capital —
B90: (Increase)/Decrease in Current Assets | D90: =-(SUM(D50:D51)-SUM(C50:C51)) -> 637.85753 | E90: =-(SUM(E50:E51)-SUM(D50:D51)) -> -2117.3342 | F90: =-(SUM(F50:F51)-SUM(E50:E51)) -> -2097.7644 | G90: =-(SUM(G50:G51)-SUM(F50:F51)) -> -1921.2275 | H90: =-(SUM(H50:H51)-SUM(G50:G51)) -> -1796.9586 | I90: =-(SUM(I50:I51)-SUM(H50:H51)) -> -1699.1627 | J90: =-(SUM(J50:J51)-SUM(I50:I51)) -> -1683.8696
B91: Increase/(Decrease) in Current Liabilities | D91: =SUM(D67:D68)-SUM(C67:C68) -> 1168.5651 | E91: =SUM(E67:E68)-SUM(D67:D68) -> 2495.1955 | F91: =SUM(F67:F68)-SUM(E67:E68) -> 1590.4645 | G91: =SUM(G67:G68)-SUM(F67:F68) -> 1566.8577 | H91: =SUM(H67:H68)-SUM(G67:G68) -> 1562.2964 | I91: =SUM(I67:I68)-SUM(H67:H68) -> 1566.2216 | J91: =SUM(J67:J68)-SUM(I67:I68) -> 1609.5279
B92: Net Cash from Operating Activities | D92: =SUM(D86:D91) -> 46336.031 | E92: =SUM(E86:E91) -> 49183.663 | F92: =SUM(F86:F91) -> 59224.121 | G92: =SUM(G86:G91) -> 66414.874 | H92: =SUM(H86:H91) -> 73389.061 | I92: =SUM(I86:I91) -> 80534.706 | J92: =SUM(J86:J91) -> 88030.181
B94: Cash Flow from Investing Activities
B95: CapEx | C95: =C$14*INDEX('Meta Drivers'!D$78:D$80,MATCH($D$5,'Meta Drivers'!$C$78:$C$80,0)) -> 21816.865 | D95: =D$14*INDEX('Meta Drivers'!E$78:E$80,MATCH($D$5,'Meta Drivers'!$C$78:$C$80,0)) -> 25653.98 | E95: =E$14*INDEX('Meta Drivers'!F$78:F$80,MATCH($D$5,'Meta Drivers'!$C$78:$C$80,0)) -> 33051.48 | F95: =F$14*INDEX('Meta Drivers'!G$78:G$80,MATCH($D$5,'Meta Drivers'!$C$78:$C$80,0)) -> 34807.961 | G95: =G$14*INDEX('Meta Drivers'!H$78:H$80,MATCH($D$5,'Meta Drivers'!$C$78:$C$80,0)) -> 35919.052 | H95: =H$14*INDEX('Meta Drivers'!I$78:I$80,MATCH($D$5,'Meta Drivers'!$C$78:$C$80,0)) -> 36486.746 | I95: =I$14*INDEX('Meta Drivers'!J$78:J$80,MATCH($D$5,'Meta Drivers'!$C$78:$C$80,0)) -> 37548.564 | J95: =J$14*INDEX('Meta Drivers'!K$78:K$80,MATCH($D$5,'Meta Drivers'!$C$78:$C$80,0)) -> 38389.734
B96: Long-term investments | D96: =D59-C59 -> 3000 | E96: =E59-D59 -> 4000 | F96: =F59-E59 -> 3200 | G96: =G59-F59 -> 3520 | H96: =H59-G59 -> 3872 | I96: =I59-H59 -> 4259.2 | J96: =J59-I59 -> 4685.12
B97: Net Cash from Investing Activities | D97: =-SUM(D95:D96) -> -28653.98 | E97: =-SUM(E95:E96) -> -37051.48 | F97: =-SUM(F95:F96) -> -38007.961 | G97: =-SUM(G95:G96) -> -39439.052 | H97: =-SUM(H95:H96) -> -40358.746 | I97: =-SUM(I95:I96) -> -41807.764 | J97: =-SUM(J95:J96) -> -43074.854
B99: Cash Flow from Financing Activities
B100: Share Repurchases | D100: =MAX(D92+D97,0)*INDEX('Meta Drivers'!E$109:E$111,MATCH($D$5,'Meta Drivers'!$C$109:$C$111,0)) -> 11493.333 | E100: =MAX(E92+E97,0)*INDEX('Meta Drivers'!F$109:F$111,MATCH($D$5,'Meta Drivers'!$C$109:$C$111,0)) -> 8492.5283 | F100: =MAX(F92+F97,0)*INDEX('Meta Drivers'!G$109:G$111,MATCH($D$5,'Meta Drivers'!$C$109:$C$111,0)) -> 13790.504 | G100: =MAX(G92+G97,0)*INDEX('Meta Drivers'!H$109:H$111,MATCH($D$5,'Meta Drivers'!$C$109:$C$111,0)) -> 17534.284 | H100: =MAX(H92+H97,0)*INDEX('Meta Drivers'!I$109:I$111,MATCH($D$5,'Meta Drivers'!$C$109:$C$111,0)) -> 19818.189 | I100: =MAX(I92+I97,0)*INDEX('Meta Drivers'!J$109:J$111,MATCH($D$5,'Meta Drivers'!$C$109:$C$111,0)) -> 23236.165 | J100: =MAX(J92+J97,0)*INDEX('Meta Drivers'!K$109:K$111,MATCH($D$5,'Meta Drivers'!$C$109:$C$111,0)) -> 24725.43
B101: Debt Repayments | D101: =C$71-D$71 -> 500 | E101: =D$71-E$71 -> 500 | F101: =E$71-F$71 -> 500 | G101: =F$71-G$71 -> 500 | H101: =G$71-H$71 -> 500 | I101: =H$71-I$71 -> 500 | J101: =I$71-J$71 -> 500
B102: Net Cash from Financing Activities | D102: =D99-D100-D101 -> -11993.333 | E102: =E99-E100-E101 -> -8992.5283 | F102: =F99-F100-F101 -> -14290.504 | G102: =G99-G100-G101 -> -18034.284 | H102: =H99-H100-H101 -> -20318.189 | I102: =I99-I100-I101 -> -23736.165 | J102: =J99-J100-J101 -> -25225.43
B104: Net Change in Cash | D104: =D92+D97+D102 -> 5688.7178 | E104: =E92+E97+E102 -> 3139.655 | F104: =F92+F97+F102 -> 6925.6559 | G104: =G92+G97+G102 -> 8941.5377 | H104: =H92+H97+H102 -> 12712.126 | I104: =I92+I97+I102 -> 14990.777 | J104: =J92+J97+J102 -> 19729.897
B105: Beginning Cash | D105: =C$106 -> 35000 | E105: =D$106 -> 40688.718 | F105: =E$106 -> 43828.373 | G105: =F$106 -> 50754.029 | H105: =G$106 -> 59695.566 | I105: =H$106 -> 72407.693 | J105: =I$106 -> 87398.469
B106: Cash — Ending | C106: =C$49 -> 35000 | D106: =D104+D105 -> 40688.718 | E106: =E104+E105 -> 43828.373 | F106: =F104+F105 -> 50754.029 | G106: =G104+G105 -> 59695.566 | H106: =H104+H105 -> 72407.693 | I106: =I104+I105 -> 87398.469 | J106: =J104+J105 -> 107128.37
B108: Cash Balance Check | C108: =C106-C49 -> 0 | D108: =D106-D49 -> 0 | E108: =E106-E49 -> 0 | F108: =F106-F49 -> 0 | G108: =G106-G49 -> 0 | H108: =H106-H49 -> 0 | I108: =I106-I49 -> 0 | J108: =J106-J49 -> 0

Sheet Deal Inputs
B2: Deal input deck — Google / Meta combination
B3: Merger model inputs — pro forma
B5: Transaction Overview — 1
B7: Deal structure
B8: Buyer | D8: Google (Alphabet)
B9: Seller / Target | D9: Meta Platforms
B10: Consideration type | D10: Stock & Cash Combination
B11: Announcement timing | D11: Q4 2023
B12: Expected close timing | D12: Q1 2024
B14: Purchase price Calculation — 2
B16: Stock Prices & Premium
B17: Meta Current Stock Price | D17: 520
B18: Premium Offered | D18: 0.3
B19: Offer Price per Share | D19: =D17*(1+D18) -> 676
B20: Meta Shares Outstanding (mm) | D20: 2700
B21: Total Purchase price ($mm) | D21: =D19*D20 -> 1825200
B23: Consideration split
B24: % Cash Consideration | D24: 0.5
B25: % Stock Consideration | D25: 0.5
B26: Cash Required — $mm | D26: =$D$21*D24 -> 912600
B27: Stock Value Required — $mm | D27: =$D$21*D25 -> 912600
B28: Google Stock Price | D28: 175
B29: New Google Shares Issued (mm) | D29: =D27/D28 -> 5214.8571
B31: Sources & Uses Of Funds — 3
B33: Funding Sources ($mm) | F33: Funding Uses ($mm)
B34: Stock Issued | D34: =$D$27 -> 912600 | F34: Purchase price | H34: {=D21} -> 1825200
B35: New Term Loan | D35: 400000 | F35: Transaction Fees | H35: =$D$21*$I$35 -> 36504 | I35: 0.02
B36: Bridge Loan | D36: 100000 | F36: Financing Fees | H36: =(D35+D36)*$I$36 -> 12500 | I36: 0.025
B37: Cash on Hand | D37: =H38-D34-D35-D36 -> 466604 | F37: Integration Costs | H37: 5000
B38: Sources — Total | D38: =SUM(D34:D37) -> 1879204 | F38: Uses — Total | H38: =SUM(H34:H37) -> 1879204
B40: Synergy Assumptions — 4
B42: Revenue Synergies — $mm
D43: Year 1 | E43: Year 2 | F43: Year 3 | G43: Year 4 | H43: Year 5
B44: Cross-Platform Advertising | D44: 2000 | E44: 4000 | F44: 6000 | G44: 7000 | H44: 8000
B45: Data & AI Integration | D45: 1000 | E45: 2500 | F45: 4000 | G45: 5000 | H45: 6000
B46: Market Expansion | D46: 500 | E46: 1500 | F46: 2500 | G46: 3000 | H46: 3500
B47: Total Revenue Synergies | D47: =SUM(D44:D46) -> 3500 | E47: =SUM(E44:E46) -> 8000 | F47: =SUM(F44:F46) -> 12500 | G47: =SUM(G44:G46) -> 15000 | H47: =SUM(H44:H46) -> 17500
B49: Cost Synergies — $mm
B50: Infrastructure & Cloud | D50: 3000 | E50: 5000 | F50: 7000 | G50: 8000 | H50: 8500
B51: R&D Efficiency | D51: 2000 | E51: 3500 | F51: 4500 | G51: 5000 | H51: 5500
B52: G&A Consolidation | D52: 1500 | E52: 2500 | F52: 3000 | G52: 3200 | H52: 3400
B53: S&M | D53: 1000 | E53: 2000 | F53: 2500 | G53: 2800 | H53: 3000
B54: Total Cost Synergies | D54: =SUM(D50:D53) -> 7500 | E54: =SUM(E50:E53) -> 13000 | F54: =SUM(F50:F53) -> 17000 | G54: =SUM(G50:G53) -> 19000 | H54: =SUM(H50:H53) -> 20400
B56: Dis-Synergies & Implementation
B57: Customer Attrition | D57: -1000 | E57: -800 | F57: -500 | G57: -300 | H57: -200
B58: Integration Costs | D58: -3000 | E58: -2000 | F58: -1000 | G58: -500 | H58: 0
B59: Retention Bonuses | D59: -2000 | E59: -1500 | F59: -1000 | G59: -500 | H59: 0
B60: Total Dis-Synergies | D60: =SUM(D57:D59) -> -6000 | E60: =SUM(E57:E59) -> -4300 | F60: =SUM(F57:F59) -> -2500 | G60: =SUM(G57:G59) -> -1300 | H60: =SUM(H57:H59) -> -200
B62: Net Synergies | D62: =D47+D54+D60 -> 5000 | E62: =E47+E54+E60 -> 16700 | F62: =F47+F54+F60 -> 27000 | G62: =G47+G54+G60 -> 32700 | H62: =H47+H54+H60 -> 37700
B64: Purchase Accounting — 5
B66: Purchase price Allocation ($mm)
B67: Purchase price | D67: {=D21} -> 1825200
B68: Less — Book Value of Equity | D68: -141740
B69: Premium Over Book | D69: =D67+D68 -> 1683460
B71: Allocation —
B72: Identifiable Intangible Assets | D72: 25000
B73: PP&E Fair Value Adjustment | D73: 0
B74: Deferred Tax Liability | D74: =-(D72+D73)*0.21 -> -5250
B75: Goodwill | D75: =D69-D72-D73-D74 -> 1663710
B77: Financing Assumptions — 6
B79: Debt Financing
B80: Term Loan Amount — $mm | D80: {=D35} -> 400000
B81: Term Loan Interest Rate | D81: 0.055
B82: Bridge Loan Amount — $mm | D82: {=D36} -> 100000
B83: Bridge Loan Interest Rate | D83: 0.065
B84: Mandatory Amortization % p.a. | D84: 0.05
B86: Pro Forma Adjustments — 7
B88: Amortization of Intangibles
B89: Intangible Asset Value — $mm | D89: =D72 -> 25000
B90: Amortization Period — years | D90: 10
B91: Annual Amortization — $mm | D91: =D89/D90 -> 2500
B93: Other Adjustments
B94: Stock-Based Comp Adjustment % | D94: 0
B95: Combined Tax Rate | D95: 0.21

Sheet Pro Forma
B2: Pro forma company — Google / Meta
B3: Figures in $mm
B5: Transaction snapshot
B7: Purchase price ($mm): | D7: ='Deal Inputs'!$D$21 -> 1825200
B8: Cash Consideration — | D8: ='Deal Inputs'!$D$26 -> 912600
B9: Stock Consideration — | D9: ='Deal Inputs'!$D$27 -> 912600
B10: Total Debt Raised — | D10: ='Deal Inputs'!$D$35+'Deal Inputs'!$D$36 -> 500000
B11: Goodwill Created — | D11: ='Deal Inputs'!$D$75 -> 1663710
B13: Pro Forma Income Statement
B15: For the Year Ending | D15: 2024 | E15: 2025 | F15: 2026 | G15: 2027 | H15: 2028
B17: Revenue — Combined
B18: Google Revenue | D18: ='Google Model'!F$16 -> 292008.95 | E18: ='Google Model'!G$16 -> 320857.36 | F18: ='Google Model'!H$16 -> 349262.74 | G18: ='Google Model'!I$16 -> 377287.31 | H18: ='Google Model'!J$16 -> 405460.92
B19: Meta Revenue | D19: ='Meta Model'!F$14 -> 151338.96 | E19: ='Meta Model'!G$14 -> 167065.36 | F19: ='Meta Model'!H$14 -> 182433.73 | G19: ='Meta Model'!I$14 -> 197624.02 | H19: ='Meta Model'!J$14 -> 213276.3
B20: Revenue synergy contribution | D20: ='Deal Inputs'!D$47 -> 3500 | E20: ='Deal Inputs'!E$47 -> 8000 | F20: ='Deal Inputs'!F$47 -> 12500 | G20: ='Deal Inputs'!G$47 -> 15000 | H20: ='Deal Inputs'!H$47 -> 17500
B21: Combined Revenue — Total | D21: =SUM(D18:D20) -> 446847.91 | E21: =SUM(E18:E20) -> 495922.71 | F21: =SUM(F18:F20) -> 544196.47 | G21: =SUM(G18:G20) -> 589911.34 | H21: =SUM(H18:H20) -> 636237.22
B23: Operating expense build
B24: Cost of sales (Combined) | D24: ='Google Model'!F$19+'Meta Model'!F$17 -> 161541.82 | E24: ='Google Model'!G$19+'Meta Model'!G$17 -> 176682.52 | F24: ='Google Model'!H$19+'Meta Model'!H$17 -> 191376.97 | G24: ='Google Model'!I$19+'Meta Model'!I$17 -> 205692.93 | H24: ='Google Model'!J$19+'Meta Model'!J$17 -> 219991.68
B25: Infrastructure synergy value | D25: =-'Deal Inputs'!D$50 -> -3000 | E25: =-'Deal Inputs'!E$50 -> -5000 | F25: =-'Deal Inputs'!F$50 -> -7000 | G25: =-'Deal Inputs'!G$50 -> -8000 | H25: =-'Deal Inputs'!H$50 -> -8500
B26: Profit — Gross | D26: =D21-D24-D25 -> 288306.09 | E26: =E21-E24-E25 -> 324240.2 | F26: =F21-F24-F25 -> 359819.5 | G26: =G21-G24-G25 -> 392218.41 | H26: =H21-H24-H25 -> 424745.53
B28: R&D — Combined | D28: ='Google Model'!F$23+'Meta Model'!F$21 -> 84888.884 | E28: ='Google Model'!G$23+'Meta Model'!G$21 -> 91698.33 | F28: ='Google Model'!H$23+'Meta Model'!H$21 -> 98367.534 | G28: ='Google Model'!I$23+'Meta Model'!I$21 -> 104292.27 | H28: ='Google Model'!J$23+'Meta Model'!J$21 -> 110444.52
B29: R&D synergy value | D29: =-'Deal Inputs'!D$51 -> -2000 | E29: =-'Deal Inputs'!E$51 -> -3500 | F29: =-'Deal Inputs'!F$51 -> -4500 | G29: =-'Deal Inputs'!G$51 -> -5000 | H29: =-'Deal Inputs'!H$51 -> -5500
B30: S&M — Combined | D30: ='Google Model'!F$24+'Meta Model'!F$22 -> 49578.31 | E30: ='Google Model'!G$24+'Meta Model'!G$22 -> 53096.151 | F30: ='Google Model'!H$24+'Meta Model'!H$22 -> 55906.153 | G30: ='Google Model'!I$24+'Meta Model'!I$22 -> 58712.799 | H30: ='Google Model'!J$24+'Meta Model'!J$22 -> 60912.798
B31: S&M synergy value | D31: =-'Deal Inputs'!D$53 -> -1000 | E31: =-'Deal Inputs'!E$53 -> -2000 | F31: =-'Deal Inputs'!F$53 -> -2500 | G31: =-'Deal Inputs'!G$53 -> -2800 | H31: =-'Deal Inputs'!H$53 -> -3000
B32: G&A — Combined | D32: ='Google Model'!F$25+'Meta Model'!F$23 -> 34751.841 | E32: ='Google Model'!G$25+'Meta Model'!G$23 -> 36793.304 | F32: ='Google Model'!H$25+'Meta Model'!H$23 -> 38500.612 | G32: ='Google Model'!I$25+'Meta Model'!I$23 -> 40279.659 | H32: ='Google Model'!J$25+'Meta Model'!J$23 -> 41495.217
B33: G&A synergy value | D33: =-'Deal Inputs'!D$52 -> -1500 | E33: =-'Deal Inputs'!E$52 -> -2500 | F33: =-'Deal Inputs'!F$52 -> -3000 | G33: =-'Deal Inputs'!G$52 -> -3200 | H33: =-'Deal Inputs'!H$52 -> -3400
B34: SBC (Combined) | D34: ='Google Model'!F$26+'Meta Model'!F$24 -> 44388.136 | E34: ='Google Model'!G$26+'Meta Model'!G$24 -> 47381.597 | F34: ='Google Model'!H$26+'Meta Model'!H$24 -> 49677.02 | G34: ='Google Model'!I$26+'Meta Model'!I$24 -> 51975.566 | H34: ='Google Model'!J$26+'Meta Model'!J$24 -> 53659.045
B35: Dis-synergies & Integration | D35: =-'Deal Inputs'!D$60 -> 6000 | E35: =-'Deal Inputs'!E$60 -> 4300 | F35: =-'Deal Inputs'!F$60 -> 2500 | G35: =-'Deal Inputs'!G$60 -> 1300 | H35: =-'Deal Inputs'!H$60 -> 200
B36: Amortization of new intangibles | D36: ='Deal Inputs'!$D$91 -> 2500 | E36: ='Deal Inputs'!$D$91 -> 2500 | F36: ='Deal Inputs'!$D$91 -> 2500 | G36: ='Deal Inputs'!$D$91 -> 2500 | H36: ='Deal Inputs'!$D$91 -> 2500
B37: EBIT | D37: =D26-SUM(D28:D36) -> 70698.923 | E37: =E26-SUM(E28:E36) -> 96470.815 | F37: =F26-SUM(F28:F36) -> 122368.18 | G37: =G26-SUM(G28:G36) -> 144158.11 | H37: =H26-SUM(H28:H36) -> 167433.95
B39: Existing interest expense / — income | D39: =-('Google Model'!F$32+'Meta Model'!F$30) -> -5041.1614 | E39: =-('Google Model'!G$32+'Meta Model'!G$30) -> -5099.4436 | F39: =-('Google Model'!H$32+'Meta Model'!H$30) -> -5113.3324 | G39: =-('Google Model'!I$32+'Meta Model'!I$30) -> -6247.4956 | H39: =-('Google Model'!J$32+'Meta Model'!J$30) -> -5947.9938
B40: New interest expense | D40: =(('Deal Inputs'!$D$80*((1-'Deal Inputs'!$D$84)^(D$15-$D$15)))*'Deal Inputs'!$D$81)+(('Deal Inputs'!$D$82*((1-'Deal Inputs'!$D$84)^(D$15-$D$15)))*'Deal Inputs'!$D$83) -> 28500 | E40: =(('Deal Inputs'!$D$80*((1-'Deal Inputs'!$D$84)^(E$15-$D$15)))*'Deal Inputs'!$D$81)+(('Deal Inputs'!$D$82*((1-'Deal Inputs'!$D$84)^(E$15-$D$15)))*'Deal Inputs'!$D$83) -> 27075 | F40: =(('Deal Inputs'!$D$80*((1-'Deal Inputs'!$D$84)^(F$15-$D$15)))*'Deal Inputs'!$D$81)+(('Deal Inputs'!$D$82*((1-'Deal Inputs'!$D$84)^(F$15-$D$15)))*'Deal Inputs'!$D$83) -> 25721.25 | G40: =(('Deal Inputs'!$D$80*((1-'Deal Inputs'!$D$84)^(G$15-$D$15)))*'Deal Inputs'!$D$81)+(('Deal Inputs'!$D$82*((1-'Deal Inputs'!$D$84)^(G$15-$D$15)))*'Deal Inputs'!$D$83) -> 24435.187 | H40: =(('Deal Inputs'!$D$80*((1-'Deal Inputs'!$D$84)^(H$15-$D$15)))*'Deal Inputs'!$D$81)+(('Deal Inputs'!$D$82*((1-'Deal Inputs'!$D$84)^(H$15-$D$15)))*'Deal Inputs'!$D$83) -> 23213.428
B41: EBT | D41: =D37-D39-D40 -> 47240.084 | E41: =E37-E39-E40 -> 74495.258 | F41: =F37-F39-F40 -> 101760.27 | G41: =G37-G39-G40 -> 125970.42 | H41: =H37-H39-H40 -> 150168.52
B42: Taxes | D42: =D41*'Deal Inputs'!$D$95 -> 9920.4177 | E42: =E41*'Deal Inputs'!$D$95 -> 15644.004 | F42: =F41*'Deal Inputs'!$D$95 -> 21369.656 | G42: =G41*'Deal Inputs'!$D$95 -> 26453.789 | H42: =H41*'Deal Inputs'!$D$95 -> 31535.389
B44: Net income | D44: =D41-D42 -> 37319.666 | E44: =E41-E42 -> 58851.254 | F44: =F41-F42 -> 80390.61 | G44: =G41-G42 -> 99516.633 | H44: =H41-H42 -> 118633.13
B46: Accretion / dilution workup
B48: Shares — Pro forma (mm) | D48: ='Google Model'!F$42+'Deal Inputs'!$D$29 -> 17614.857 | E48: ='Google Model'!G$42+'Deal Inputs'!$D$29 -> 17414.857 | F48: ='Google Model'!H$42+'Deal Inputs'!$D$29 -> 17214.857 | G48: ='Google Model'!I$42+'Deal Inputs'!$D$29 -> 17014.857 | H48: ='Google Model'!J$42+'Deal Inputs'!$D$29 -> 16814.857
B49: EPS — Pro forma | D49: =D44/D48 -> 2.1186471 | E49: =E44/E48 -> 3.3793705 | F49: =F44/F48 -> 4.6698389 | G49: =G44/G48 -> 5.848808 | H49: =H44/H48 -> 7.0552564
B50: % Accretion — Dilution | D50: =D49/'Google Model'!F$43-1 -> -0.3244407 | E50: =E49/'Google Model'!G$43-1 -> -0.085622584 | F50: =F49/'Google Model'!H$43-1 -> 0.079196041 | G50: =G49/'Google Model'!I$43-1 -> 0.16598529 | H50: =H49/'Google Model'!J$43-1 -> 0.22687473
