Workbook
Name Scenarios: 'Formula Audit'!$C$4:$C$6

Sheet Control Center
A2: NAVIGATION | B2: Integrated Operating Model & Analysis
C3: This operating model provides a multi-year projection framework for strategic planning. It includes: - A scenario-driven approach - A first-year 3-statement build - A multi-year forecast - Budget-versus-actual variance - Breakeven analysis - Ratio analysis and valuation - Chart-based presentation
C4: Contents | E4: Overview
C5: Summary Overview | E5: Business Category | F5: Financials
C6: Valuation Detail | E6: Entity Name
C7: Performance Dashboard | E7: Jurisdiction | F7: United Kingdom
C8: Revenue by Business Unit | E8: Fiscal Year | F8: 2025
C9: Scenario Planning | E9: Reporting Periods | F9: 10
C10: Trailing 12-Month Actuals | E10: Reporting Currency | F10: USD
C11: Forward 12-Month Projection
C12: Budget vs. Actual Variance
C13: Multi-Year Forecast
C14: Breakeven Detail | E14: Notes:
C15: Ratio Detail | E15: figures | F15: enter inputs only in the blue-shaded cells
A21: NAVIGATION | B21: ='Control Center'!F6
C23: Scenario Planning
C24: ='Formula Audit'!A3 -> Figures in USD
D25: Planning Case | E25: Central Case | G25: Key Assumptions
C26: Selected Case | G26: ='Formula Audit'!C9 -> 2025 | H26: ='Formula Audit'!D9 -> 2026 | I26: ='Formula Audit'!E9 -> 2027 | J26: ='Formula Audit'!F9 -> 2028 | K26: ='Formula Audit'!G9 -> 2029 | L26: ='Formula Audit'!H9 -> 2030 | M26: ='Formula Audit'!I9 -> 2031 | N26: ='Formula Audit'!J9 -> 2032 | ... P26: ='Formula Audit'!L9 -> 2034
C27: Statement of Operations
D28: Revenue Growth Rate | E28: % Chg | G28: ='Formula Audit'!C45 -> 0 | H28: ='Formula Audit'!D45 -> 0.067019 | I28: ='Formula Audit'!E45 -> 0.055849 | J28: ='Formula Audit'!F45 -> 0.044679 | K28: ='Formula Audit'!G45 -> 0.03351 | L28: ='Formula Audit'!H45 -> 0.03351 | M28: ='Formula Audit'!I45 -> 0.02234 | N28: ='Formula Audit'!J45 -> 0.02234 | ... P28: ='Formula Audit'!L45 -> 0.02234
D29: Service Costs | E29: share of service revenue | H29: ='Formula Audit'!D49 -> 0.265943 | I29: ='Formula Audit'!E49 -> 0.265943 | J29: ='Formula Audit'!F49 -> 0.255305 | K29: ='Formula Audit'!G49 -> 0.255305 | L29: ='Formula Audit'!H49 -> 0.244668 | M29: ='Formula Audit'!I49 -> 0.244668 | N29: ='Formula Audit'!J49 -> 0.23403 | O29: ='Formula Audit'!K49 -> 0.23403 | P29: ='Formula Audit'!L49 -> 0.223392
D30: Product Costs | E30: share of product revenue | H30: ='Formula Audit'!D53 -> 0.33648 | I30: ='Formula Audit'!E53 -> 0.319656 | J30: ='Formula Audit'!F53 -> 0.311244 | K30: ='Formula Audit'!G53 -> 0.302832 | L30: ='Formula Audit'!H53 -> 0.29442 | M30: ='Formula Audit'!I53 -> 0.29442 | N30: ='Formula Audit'!J53 -> 0.286008 | O30: ='Formula Audit'!K53 -> 0.286008 | P30: ='Formula Audit'!L53 -> 0.286008
D31: Direct Labour Costs | E31: share of total revenue | G31: ='Formula Audit'!C57 -> 0.190469 | H31: ='Formula Audit'!D57 -> 0.190469 | I31: ='Formula Audit'!E57 -> 0.190469 | J31: ='Formula Audit'!F57 -> 0.190469 | K31: ='Formula Audit'!G57 -> 0.190469 | L31: ='Formula Audit'!H57 -> 0.190469 | M31: ='Formula Audit'!I57 -> 0.190469 | N31: ='Formula Audit'!J57 -> 0.190469 | ... P31: ='Formula Audit'!L57 -> 0.190469
D32: Discounts & Promotions | E32: share of total revenue | G32: ='Formula Audit'!C61 -> 0.137193 | H32: ='Formula Audit'!D61 -> 0.12576 | I32: ='Formula Audit'!E61 -> 0.114327 | J32: ='Formula Audit'!F61 -> 0.102895 | K32: ='Formula Audit'!G61 -> 0.102895 | L32: ='Formula Audit'!H61 -> 0.091462 | M32: ='Formula Audit'!I61 -> 0.091462 | N32: ='Formula Audit'!J61 -> 0.080029 | ... P32: ='Formula Audit'!L61 -> 0.080029
D33: Salaries & Benefits | E33: ='Control Center'!$F$10 -> USD | G33: ='Formula Audit'!C65 -> 58749 | H33: ='Formula Audit'!D65 -> 58749 | I33: ='Formula Audit'!E65 -> 58749 | J33: ='Formula Audit'!F65 -> 58749 | K33: ='Formula Audit'!G65 -> 58749 | L33: ='Formula Audit'!H65 -> 58749 | M33: ='Formula Audit'!I65 -> 58749 | N33: ='Formula Audit'!J65 -> 58749 | ... P33: ='Formula Audit'!L65 -> 58749
D34: Sales & Marketing | E34: share of total revenue | G34: ='Formula Audit'!C69 -> 0.045594 | H34: ='Formula Audit'!D69 -> 0.045594 | I34: ='Formula Audit'!E69 -> 0.039895 | J34: ='Formula Audit'!F69 -> 0.039895 | K34: ='Formula Audit'!G69 -> 0.039895 | L34: ='Formula Audit'!H69 -> 0.039895 | M34: ='Formula Audit'!I69 -> 0.034195 | N34: ='Formula Audit'!J69 -> 0.034195 | ... P34: ='Formula Audit'!L69 -> 0.034195
D35: General & Administrative | E35: ='Control Center'!$F$10 -> USD | G35: ='Formula Audit'!C73 -> 34135 | H35: ='Formula Audit'!D73 -> 34135 | I35: ='Formula Audit'!E73 -> 34135 | J35: ='Formula Audit'!F73 -> 34135 | K35: ='Formula Audit'!G73 -> 34135 | L35: ='Formula Audit'!H73 -> 34135 | M35: ='Formula Audit'!I73 -> 34135 | N35: ='Formula Audit'!J73 -> 34135 | ... P35: ='Formula Audit'!L73 -> 34135
D36: Card Processing Fees | E36: share of total revenue | G36: ='Formula Audit'!C77 -> 0.007054 | H36: ='Formula Audit'!D77 -> 0.007054 | I36: ='Formula Audit'!E77 -> 0.007054 | J36: ='Formula Audit'!F77 -> 0.007054 | K36: ='Formula Audit'!G77 -> 0.007054 | L36: ='Formula Audit'!H77 -> 0.007054 | M36: ='Formula Audit'!I77 -> 0.007054 | N36: ='Formula Audit'!J77 -> 0.007054 | ... P36: ='Formula Audit'!L77 -> 0.007054
D37: Depreciation & Amortization | E37: share of PP&E | G37: ='Formula Audit'!C81 -> 0.414517 | H37: ='Formula Audit'!D81 -> 0.414517 | I37: ='Formula Audit'!E81 -> 0.414517 | J37: ='Formula Audit'!F81 -> 0.414517 | K37: ='Formula Audit'!G81 -> 0.414517 | L37: ='Formula Audit'!H81 -> 0.414517 | M37: ='Formula Audit'!I81 -> 0.414517 | N37: ='Formula Audit'!J81 -> 0.414517 | ... P37: ='Formula Audit'!L81 -> 0.414517
D38: Effective Tax Rate | E38: share of EBT | G38: ='Formula Audit'!C85 -> 0.264834 | H38: ='Formula Audit'!D85 -> 0.264834 | I38: ='Formula Audit'!E85 -> 0.264834 | J38: ='Formula Audit'!F85 -> 0.264834 | K38: ='Formula Audit'!G85 -> 0.264834 | L38: ='Formula Audit'!H85 -> 0.264834 | M38: ='Formula Audit'!I85 -> 0.264834 | N38: ='Formula Audit'!J85 -> 0.264834 | ... P38: ='Formula Audit'!L85 -> 0.264834
C40: Statement of Financial Position
D41: Trade Receivables | E41: days | G41: ='Formula Audit'!C89 -> 37 | H41: ='Formula Audit'!D89 -> 37 | I41: ='Formula Audit'!E89 -> 37 | J41: ='Formula Audit'!F89 -> 37 | K41: ='Formula Audit'!G89 -> 37 | L41: ='Formula Audit'!H89 -> 32 | M41: ='Formula Audit'!I89 -> 32 | N41: ='Formula Audit'!J89 -> 32 | ... P41: ='Formula Audit'!L89 -> 32
D42: Inventories | E42: days | G42: ='Formula Audit'!C93 -> 66 | H42: ='Formula Audit'!D93 -> 66 | I42: ='Formula Audit'!E93 -> 66 | J42: ='Formula Audit'!F93 -> 71 | K42: ='Formula Audit'!G93 -> 71 | L42: ='Formula Audit'!H93 -> 71 | M42: ='Formula Audit'!I93 -> 76 | N42: ='Formula Audit'!J93 -> 76 | ... P42: ='Formula Audit'!L93 -> 81
D43: Property, Plant & Equipment | E43: USD (opening) | G43: ='Formula Audit'!C97 -> 13917
D44: Trade Payables | E44: days | G44: ='Formula Audit'!C101 -> 53 | H44: ='Formula Audit'!D101 -> 53 | I44: ='Formula Audit'!E101 -> 53 | J44: ='Formula Audit'!F101 -> 53 | K44: ='Formula Audit'!G101 -> 53 | L44: ='Formula Audit'!H101 -> 48 | M44: ='Formula Audit'!I101 -> 48 | N44: ='Formula Audit'!J101 -> 48 | ... P44: ='Formula Audit'!L101 -> 48
D45: Accrued & Other Liabilities | E45: share of total revenue | G45: ='Formula Audit'!C105 -> 0.050563 | H45: ='Formula Audit'!D105 -> 0.050563 | I45: ='Formula Audit'!E105 -> 0.050563 | J45: ='Formula Audit'!F105 -> 0.050563 | K45: ='Formula Audit'!G105 -> 0.050563 | L45: ='Formula Audit'!H105 -> 0.050563 | M45: ='Formula Audit'!I105 -> 0.050563 | N45: ='Formula Audit'!J105 -> 0.050563 | ... P45: ='Formula Audit'!L105 -> 0.050563
D46: Capex Outlays | E46: ='Control Center'!$F$10 -> USD | G46: ='Formula Audit'!C109 -> 6975 | H46: ='Formula Audit'!D109 -> 8719 | I46: ='Formula Audit'!E109 -> 10463 | J46: ='Formula Audit'!F109 -> 10463 | K46: ='Formula Audit'!G109 -> 13078 | L46: ='Formula Audit'!H109 -> 15694 | M46: ='Formula Audit'!I109 -> 13078 | N46: ='Formula Audit'!J109 -> 10463 | ... P46: ='Formula Audit'!L109 -> 6975
C48: Financing Activities
D49: Interest Rate (% of Borrowings) | E49: % | G49: ='Formula Audit'!C113 -> 0.06294 | H49: ='Formula Audit'!D113 -> 0.06294 | I49: ='Formula Audit'!E113 -> 0.06294 | J49: ='Formula Audit'!F113 -> 0.06294 | K49: ='Formula Audit'!G113 -> 0.06294 | L49: ='Formula Audit'!H113 -> 0.06294 | M49: ='Formula Audit'!I113 -> 0.06294 | N49: ='Formula Audit'!J113 -> 0.06294 | ... P49: ='Formula Audit'!L113 -> 0.06294
D50: Long-Term Borrowings | E50: USD (Opening) | G50: ='Formula Audit'!C117 -> 70860
D51: Equity Funding | E51: USD | G51: ='Formula Audit'!C121 -> 92803 | H51: ='Formula Audit'!D121 -> 92803 | I51: ='Formula Audit'!E121 -> 92803 | J51: ='Formula Audit'!F121 -> 92803 | K51: ='Formula Audit'!G121 -> 92803 | L51: ='Formula Audit'!H121 -> 92803 | M51: ='Formula Audit'!I121 -> 92803 | N51: ='Formula Audit'!J121 -> 92803 | ... P51: ='Formula Audit'!L121 -> 92803
D52: Borrowings Drawn/(Repaid) | E52: ='Control Center'!$F$10 -> USD | G52: ='Formula Audit'!C125 -> -5497 | H52: ='Formula Audit'!D125 -> -5497 | I52: ='Formula Audit'!E125 -> -5497 | J52: ='Formula Audit'!F125 -> -5497 | K52: ='Formula Audit'!G125 -> -5497 | L52: ='Formula Audit'!H125 -> -5497 | M52: ='Formula Audit'!I125 -> -5497 | N52: ='Formula Audit'!J125 -> -5497 | ... P52: ='Formula Audit'!L125 -> -5497
D53: Equity Raised/(Returned) | E53: ='Control Center'!$F$10 -> USD | G53: ='Formula Audit'!C129 -> 0 | H53: ='Formula Audit'!D129 -> 0 | I53: ='Formula Audit'!E129 -> 0 | J53: ='Formula Audit'!F129 -> 0 | K53: ='Formula Audit'!G129 -> 0 | L53: ='Formula Audit'!H129 -> 0 | M53: ='Formula Audit'!I129 -> 0 | N53: ='Formula Audit'!J129 -> 0 | ... P53: ='Formula Audit'!L129 -> 0
D54: Dividend Distributions | E54: share of net income | G54: ='Formula Audit'!C133 -> 0.149393 | H54: ='Formula Audit'!D133 -> 0.149393 | I54: ='Formula Audit'!E133 -> 0.149393 | J54: ='Formula Audit'!F133 -> 0.149393 | K54: ='Formula Audit'!G133 -> 0.149393 | L54: ='Formula Audit'!H133 -> 0.149393 | M54: ='Formula Audit'!I133 -> 0.149393 | N54: ='Formula Audit'!J133 -> 0.149393 | ... P54: ='Formula Audit'!L133 -> 0.149393
C56: Central Scenario
C57: Statement of Operations
D58: Revenue Growth Rate | E58: % Chg | H58: 0.067019 | I58: 0.055849 | J58: 0.044679 | K58: 0.03351 | L58: 0.03351 | M58: 0.02234 | N58: 0.02234 | O58: 0.02234 | P58: 0.02234
D59: Service Costs | E59: share of service revenue | H59: 0.265943 | I59: 0.265943 | J59: 0.255305 | K59: 0.255305 | L59: 0.244668 | M59: 0.244668 | N59: 0.23403 | O59: 0.23403 | P59: 0.223392
D60: Product Costs | E60: share of product revenue | H60: 0.33648 | I60: 0.319656 | J60: 0.311244 | K60: 0.302832 | L60: 0.29442 | M60: 0.29442 | N60: 0.286008 | O60: 0.286008 | P60: 0.286008
D61: Direct Labour Costs | E61: share of total revenue | G61: 0.190469 | H61: 0.190469 | I61: 0.190469 | J61: 0.190469 | K61: 0.190469 | L61: 0.190469 | M61: 0.190469 | N61: 0.190469 | O61: 0.190469 | P61: 0.190469
D62: Discounts & Promotions | E62: share of total revenue | G62: 0.137193 | H62: 0.12576 | I62: 0.114327 | J62: 0.102895 | K62: 0.102895 | L62: 0.091462 | M62: 0.091462 | N62: 0.080029 | O62: 0.080029 | P62: 0.080029
D63: Salaries & Benefits | E63: ='Control Center'!$F$10 -> USD | G63: 58749 | H63: 58749 | I63: 58749 | J63: 58749 | K63: 58749 | L63: 58749 | M63: 58749 | N63: 58749 | O63: 58749 | P63: 58749
D64: Sales & Marketing | E64: share of total revenue | G64: 0.045594 | H64: 0.045594 | I64: 0.039895 | J64: 0.039895 | K64: 0.039895 | L64: 0.039895 | M64: 0.034195 | N64: 0.034195 | O64: 0.034195 | P64: 0.034195
D65: General & Administrative | E65: ='Control Center'!$F$10 -> USD | G65: 34135 | H65: 34135 | I65: 34135 | J65: 34135 | K65: 34135 | L65: 34135 | M65: 34135 | N65: 34135 | O65: 34135 | P65: 34135
D66: Card Processing Fees | E66: share of total revenue | G66: 0.007054 | H66: 0.007054 | I66: 0.007054 | J66: 0.007054 | K66: 0.007054 | L66: 0.007054 | M66: 0.007054 | N66: 0.007054 | O66: 0.007054 | P66: 0.007054
D67: Depreciation & Amortization | E67: share of PP&E | G67: 0.414517 | H67: 0.414517 | I67: 0.414517 | J67: 0.414517 | K67: 0.414517 | L67: 0.414517 | M67: 0.414517 | N67: 0.414517 | O67: 0.414517 | P67: 0.414517
D68: Effective Tax Rate | E68: share of EBT | G68: 0.264834 | H68: 0.264834 | I68: 0.264834 | J68: 0.264834 | K68: 0.264834 | L68: 0.264834 | M68: 0.264834 | N68: 0.264834 | O68: 0.264834 | P68: 0.264834
C70: Statement of Financial Position
D71: Trade Receivables | E71: days | G71: 37 | H71: 37 | I71: 37 | J71: 37 | K71: 37 | L71: 32 | M71: 32 | N71: 32 | O71: 32 | P71: 32
D72: Inventories | E72: days | G72: 66 | H72: 66 | I72: 66 | J72: 71 | K72: 71 | L72: 71 | M72: 76 | N72: 76 | O72: 81 | P72: 81
D73: Property, Plant & Equipment | E73: USD (opening) | G73: 13917
D74: Trade Payables | E74: days | G74: 53 | H74: 53 | I74: 53 | J74: 53 | K74: 53 | L74: 48 | M74: 48 | N74: 48 | O74: 48 | P74: 48
D75: Accrued & Other Liabilities | E75: share of total revenue | G75: 0.050563 | H75: 0.050563 | I75: 0.050563 | J75: 0.050563 | K75: 0.050563 | L75: 0.050563 | M75: 0.050563 | N75: 0.050563 | O75: 0.050563 | P75: 0.050563
D76: Capex Outlays | E76: ='Control Center'!$F$10 -> USD | G76: 6975 | H76: 8719 | I76: 10463 | J76: 10463 | K76: 13078 | L76: 15694 | M76: 13078 | N76: 10463 | O76: 8719 | P76: 6975
C78: Financing Activities
D79: Interest Rate (% of Borrowings) | E79: % | G79: 0.06294 | H79: 0.06294 | I79: 0.06294 | J79: 0.06294 | K79: 0.06294 | L79: 0.06294 | M79: 0.06294 | N79: 0.06294 | O79: 0.06294 | P79: 0.06294
D80: Long-Term Borrowings | E80: USD (Opening) | G80: 70860
D81: Equity Funding | E81: USD | G81: 92803 | H81: 92803 | I81: 92803 | J81: 92803 | K81: 92803 | L81: 92803 | M81: 92803 | N81: 92803 | O81: 92803 | P81: 92803
D82: Borrowings Drawn/(Repaid) | E82: ='Control Center'!$F$10 -> USD | G82: -5497 | H82: -5497 | I82: -5497 | J82: -5497 | K82: -5497 | L82: -5497 | M82: -5497 | N82: -5497 | O82: -5497 | P82: -5497
D83: Equity Raised/(Returned) | E83: ='Control Center'!$F$10 -> USD | H83: 0
D84: Dividend Distributions | E84: share of net income | G84: 0.149393 | H84: 0.149393 | I84: 0.149393 | J84: 0.149393 | K84: 0.149393 | L84: 0.149393 | M84: 0.149393 | N84: 0.149393 | O84: 0.149393 | P84: 0.149393
C86: Upside Scenario
C87: Statement of Operations
D88: Revenue Growth Rate | E88: % Chg | H88: 0.082932 | I88: 0.072566 | J88: 0.062199 | K88: 0.051833 | L88: 0.051833 | M88: 0.041466 | N88: 0.041466 | O88: 0.0311 | P88: 0.0311
D89: Service Costs | E89: share of service revenue | H89: 0.170966 | I89: 0.170966 | J89: 0.161468 | K89: 0.161468 | L89: 0.161468 | M89: 0.151969 | N89: 0.151969 | O89: 0.151969 | P89: 0.142471
D90: Product Costs | E90: share of product revenue | H90: 0.442336 | I90: 0.420219 | J90: 0.409161 | K90: 0.398103 | L90: 0.387044 | M90: 0.387044 | N90: 0.375986 | O90: 0.375986 | P90: 0.364927
D91: Direct Labour Costs | E91: share of total revenue | G91: 0.158474 | H91: 0.158474 | I91: 0.158474 | J91: 0.158474 | K91: 0.158474 | L91: 0.158474 | M91: 0.158474 | N91: 0.158474 | O91: 0.158474 | P91: 0.158474
D92: Discounts & Promotions | E92: share of total revenue | G92: 0.098443 | H92: 0.090239 | I92: 0.082036 | J92: 0.082036 | K92: 0.073832 | L92: 0.073832 | M92: 0.065629 | N92: 0.065629 | O92: 0.065629 | P92: 0.057425
D93: Salaries & Benefits | E93: ='Control Center'!$F$10 -> USD | G93: 41113 | H93: 41113 | I93: 41113 | J93: 41113 | K93: 41113 | L93: 41113 | M93: 41113 | N93: 41113 | O93: 41113 | P93: 41113
D94: Sales & Marketing | E94: share of total revenue | G94: 0.043169 | H94: 0.043169 | I94: 0.037773 | J94: 0.037773 | K94: 0.037773 | L94: 0.032377 | M94: 0.032377 | N94: 0.032377 | O94: 0.032377 | P94: 0.026981
D95: General & Administrative | E95: ='Control Center'!$F$10 -> USD | G95: 31054 | H95: 31054 | I95: 31054 | J95: 31054 | K95: 31054 | L95: 31054 | M95: 31054 | N95: 31054 | O95: 31054 | P95: 31054
D96: Card Processing Fees | E96: share of total revenue | G96: 0.009061 | H96: 0.009061 | I96: 0.009061 | J96: 0.009061 | K96: 0.009061 | L96: 0.009061 | M96: 0.009061 | N96: 0.009061 | O96: 0.009061 | P96: 0.009061
D97: Depreciation & Amortization | E97: share of PP&E | G97: 0.37587 | H97: 0.37587 | I97: 0.37587 | J97: 0.37587 | K97: 0.37587 | L97: 0.37587 | M97: 0.37587 | N97: 0.37587 | O97: 0.37587 | P97: 0.37587
D98: Effective Tax Rate | E98: share of EBT | G98: 0.22962 | H98: 0.22962 | I98: 0.22962 | J98: 0.22962 | K98: 0.22962 | L98: 0.22962 | M98: 0.22962 | N98: 0.22962 | O98: 0.22962 | P98: 0.22962
C100: Statement of Financial Position
D101: Trade Receivables | E101: days | G101: 45 | H101: 45 | I101: 45 | J101: 45 | K101: 45 | L101: 40 | M101: 40 | N101: 40 | O101: 40 | P101: 40
D102: Inventories | E102: days | G102: 63 | H102: 63 | I102: 63 | J102: 68 | K102: 68 | L102: 68 | M102: 73 | N102: 73 | O102: 78 | P102: 78
D103: Property, Plant & Equipment | E103: USD (opening) | G103: 15666
D104: Trade Payables | E104: days | G104: 56 | H104: 56 | I104: 56 | J104: 56 | K104: 56 | L104: 50 | M104: 50 | N104: 50 | O104: 50 | P104: 50
D105: Accrued & Other Liabilities | E105: share of total revenue | G105: 0.039674 | H105: 0.039674 | I105: 0.039674 | J105: 0.039674 | K105: 0.039674 | L105: 0.039674 | M105: 0.039674 | N105: 0.039674 | O105: 0.039674 | P105: 0.039674
D106: Capex Outlays | E106: ='Control Center'!$F$10 -> USD | G106: 13398 | H106: 16747 | I106: 22330 | J106: 22330 | K106: 27912 | L106: 27912 | M106: 22330 | N106: 16747 | O106: 11165 | P106: 5582
C108: Financing Activities
D109: Interest Rate (% of Borrowings) | E109: % | G109: 0.046243 | H109: 0.046243 | I109: 0.046243 | J109: 0.046243 | K109: 0.046243 | L109: 0.046243 | M109: 0.046243 | N109: 0.046243 | O109: 0.046243 | P109: 0.046243
D110: Long-Term Borrowings | E110: USD (Opening) | G110: 60220
D111: Equity Funding | E111: USD | G111: 126895 | H111: 126895 | I111: 126895 | J111: 126895 | K111: 126895 | L111: 126895 | M111: 126895 | N111: 126895 | O111: 126895 | P111: 126895
D112: Borrowings Drawn/(Repaid) | E112: ='Control Center'!$F$10 -> USD | G112: -5589 | H112: -5589 | I112: -5589 | J112: -5589 | K112: -5589 | L112: -5589 | M112: -5589 | N112: -5589 | O112: -5589 | P112: -5589
D113: Equity Raised/(Returned) | E113: ='Control Center'!$F$10 -> USD | G113: 0
D114: Dividend Distributions | E114: share of net income | G114: 0.127679 | H114: 0.127679 | I114: 0.127679 | J114: 0.127679 | K114: 0.127679 | L114: 0.127679 | M114: 0.127679 | N114: 0.127679 | O114: 0.127679 | P114: 0.127679
C116: Downside Scenario
...

Sheet Forecast Model
A2: NAVIGATION | B2: ='Control Center'!F6
C4: Trailing 12-Month Actuals
C5: ='Formula Audit'!A3 -> Figures in USD
H6: ='Control Center'!F8 -> 2025
C7: Statement of Operations | H7: ='Formula Audit'!C41 -> January | I7: ='Formula Audit'!D41 -> February | J7: ='Formula Audit'!E41 -> March | K7: ='Formula Audit'!F41 -> April | L7: ='Formula Audit'!G41 -> May | M7: ='Formula Audit'!H41 -> June | N7: ='Formula Audit'!I41 -> July | O7: ='Formula Audit'!J41 -> August | ... S7: ='Formula Audit'!N41 -> December | T7: FY
D8: Service Revenue | H8: 31629 | I8: 31629 | J8: 31629 | K8: 31629 | L8: 31629 | M8: 31629 | N8: 31629 | O8: 31629 | P8: 31629 | Q8: 31629 | R8: 31629 | S8: 31629 | T8: =SUM(H8:S8) -> 379548
D9: Product Revenue | H9: 8537 | I9: 8537 | J9: 8537 | K9: 8537 | L9: 8537 | M9: 8537 | N9: 8537 | O9: 8537 | P9: 8537 | Q9: 8537 | R9: 8537 | S9: 8537 | T9: =SUM(H9:S9) -> 102444
C10: Sales — Total | H10: =SUM(H8:H9) -> 40166 | I10: =SUM(I8:I9) -> 40166 | J10: =SUM(J8:J9) -> 40166 | K10: =SUM(K8:K9) -> 40166 | L10: =SUM(L8:L9) -> 40166 | M10: =SUM(M8:M9) -> 40166 | N10: =SUM(N8:N9) -> 40166 | O10: =SUM(O8:O9) -> 40166 | ... T10: =SUM(T8:T9) -> 481992
D12: Service Costs | H12: 7381 | I12: 7381 | J12: 7381 | K12: 7381 | L12: 7381 | M12: 7381 | N12: 7381 | O12: 7381 | P12: 7381 | Q12: 7381 | R12: 7381 | S12: 7381 | T12: =SUM(H12:S12) -> 88572
D13: Product Costs | H13: 4129 | I13: 4129 | J13: 4129 | K13: 4129 | L13: 4129 | M13: 4129 | N13: 4129 | O13: 4129 | P13: 4129 | Q13: 4129 | R13: 4129 | S13: 4129 | T13: =SUM(H13:S13) -> 49548
D14: Direct Labour Costs | H14: 9051 | I14: 9051 | J14: 9051 | K14: 9051 | L14: 9051 | M14: 9051 | N14: 9051 | O14: 9051 | P14: 9051 | Q14: 9051 | R14: 9051 | S14: 9051 | T14: =SUM(H14:S14) -> 108612
D15: Discounts & Promotions | H15: 6076 | I15: 6076 | J15: 6076 | K15: 6076 | L15: 6076 | M15: 6076 | N15: 6076 | O15: 6076 | P15: 6076 | Q15: 6076 | R15: 6076 | S15: 6076 | T15: =SUM(H15:S15) -> 72912
C16: Total Sales Costs | H16: =SUM(H12:H15) -> 26637 | I16: =SUM(I12:I15) -> 26637 | J16: =SUM(J12:J15) -> 26637 | K16: =SUM(K12:K15) -> 26637 | L16: =SUM(L12:L15) -> 26637 | M16: =SUM(M12:M15) -> 26637 | N16: =SUM(N12:N15) -> 26637 | O16: =SUM(O12:O15) -> 26637 | ... T16: =SUM(T12:T15) -> 319644
C18: Gross Income | H18: =H10-H16 -> 13529 | I18: =I10-I16 -> 13529 | J18: =J10-J16 -> 13529 | K18: =K10-K16 -> 13529 | L18: =L10-L16 -> 13529 | M18: =M10-M16 -> 13529 | N18: =N10-N16 -> 13529 | O18: =O10-O16 -> 13529 | ... T18: =T10-T16 -> 162348
C19: Gross Margin Rate | H19: =IFERROR(H18/H10,0) -> 0.33682717 | I19: =IFERROR(I18/I10,0) -> 0.33682717 | J19: =IFERROR(J18/J10,0) -> 0.33682717 | K19: =IFERROR(K18/K10,0) -> 0.33682717 | L19: =IFERROR(L18/L10,0) -> 0.33682717 | M19: =IFERROR(M18/M10,0) -> 0.33682717 | N19: =IFERROR(N18/N10,0) -> 0.33682717 | O19: =IFERROR(O18/O10,0) -> 0.33682717 | ... T19: =IFERROR(T18/T10,0) -> 0.33682717
D21: Salaries & Benefits | H21: 3648 | I21: 3648 | J21: 3648 | K21: 3648 | L21: 3648 | M21: 3648 | N21: 3648 | O21: 3648 | P21: 3648 | Q21: 3648 | R21: 3648 | S21: 3648 | T21: =SUM(H21:S21) -> 43776
D22: Sales & Marketing | H22: 2019 | I22: 2019 | J22: 2019 | K22: 2019 | L22: 2019 | M22: 2019 | N22: 2019 | O22: 2019 | P22: 2019 | Q22: 2019 | R22: 2019 | S22: 2019 | T22: =SUM(H22:S22) -> 24228
D23: General & Administrative | H23: 3647 | I23: 3647 | J23: 3647 | K23: 3647 | L23: 3647 | M23: 3647 | N23: 3647 | O23: 3647 | P23: 3647 | Q23: 3647 | R23: 3647 | S23: 3647 | T23: =SUM(H23:S23) -> 43764
D24: Card Processing Fees | H24: 440 | I24: 440 | J24: 440 | K24: 440 | L24: 440 | M24: 440 | N24: 440 | O24: 440 | P24: 440 | Q24: 440 | R24: 440 | S24: 440 | T24: =SUM(H24:S24) -> 5280
D25: Depreciation & Amortization | H25: 871 | I25: 871 | J25: 871 | K25: 871 | L25: 871 | M25: 871 | N25: 871 | O25: 871 | P25: 871 | Q25: 871 | R25: 871 | S25: 871 | T25: =SUM(H25:S25) -> 10452
C26: Operating Expenses — Total | H26: =SUM(H21:H25) -> 10625 | I26: =SUM(I21:I25) -> 10625 | J26: =SUM(J21:J25) -> 10625 | K26: =SUM(K21:K25) -> 10625 | L26: =SUM(L21:L25) -> 10625 | M26: =SUM(M21:M25) -> 10625 | N26: =SUM(N21:N25) -> 10625 | O26: =SUM(O21:O25) -> 10625 | ... T26: =SUM(T21:T25) -> 127500
C28: Operating Income (EBIT) | H28: =H18-H26 -> 2904 | I28: =I18-I26 -> 2904 | J28: =J18-J26 -> 2904 | K28: =K18-K26 -> 2904 | L28: =L18-L26 -> 2904 | M28: =M18-M26 -> 2904 | N28: =N18-N26 -> 2904 | O28: =O18-O26 -> 2904 | ... T28: =T18-T26 -> 34848
C29: Operating Margin Rate | H29: =IFERROR(H28/H10,0) -> 0.072299955 | I29: =IFERROR(I28/I10,0) -> 0.072299955 | J29: =IFERROR(J28/J10,0) -> 0.072299955 | K29: =IFERROR(K28/K10,0) -> 0.072299955 | L29: =IFERROR(L28/L10,0) -> 0.072299955 | M29: =IFERROR(M28/M10,0) -> 0.072299955 | N29: =IFERROR(N28/N10,0) -> 0.072299955 | O29: =IFERROR(O28/O10,0) -> 0.072299955 | ... T29: =IFERROR(T28/T10,0) -> 0.072299955
D31: Interest Expense | H31: 383 | I31: 383 | J31: 383 | K31: 383 | L31: 383 | M31: 383 | N31: 383 | O31: 383 | P31: 383 | Q31: 383 | R31: 383 | S31: 383 | T31: =SUM(H31:S31) -> 4596
C32: Pre-Tax Earnings (EBT) | H32: =H28-H31 -> 2521 | I32: =I28-I31 -> 2521 | J32: =J28-J31 -> 2521 | K32: =K28-K31 -> 2521 | L32: =L28-L31 -> 2521 | M32: =M28-M31 -> 2521 | N32: =N28-N31 -> 2521 | O32: =O28-O31 -> 2521 | ... T32: =T28-T31 -> 30252
D34: Income Tax Expense | H34: 1717 | I34: 1717 | J34: 1717 | K34: 1717 | L34: 1717 | M34: 1717 | N34: 1717 | O34: 1717 | P34: 1717 | Q34: 1717 | R34: 1717 | S34: 1717 | T34: =SUM(H34:S34) -> 20604
C35: Net Earnings | H35: =H32-H34 -> 804 | I35: =I32-I34 -> 804 | J35: =J32-J34 -> 804 | K35: =K32-K34 -> 804 | L35: =L32-L34 -> 804 | M35: =M32-M34 -> 804 | N35: =N32-N34 -> 804 | O35: =O32-O34 -> 804 | ... T35: =T32-T34 -> 9648
C36: Net Margin Rate | H36: =IFERROR(H35/H10,0) -> 0.02001693 | I36: =IFERROR(I35/I10,0) -> 0.02001693 | J36: =IFERROR(J35/J10,0) -> 0.02001693 | K36: =IFERROR(K35/K10,0) -> 0.02001693 | L36: =IFERROR(L35/L10,0) -> 0.02001693 | M36: =IFERROR(M35/M10,0) -> 0.02001693 | N36: =IFERROR(N35/N10,0) -> 0.02001693 | O36: =IFERROR(O35/O10,0) -> 0.02001693 | ... T36: =IFERROR(T35/T10,0) -> 0.02001693
C38: Statement of Financial Position
C39: Short-Term Assets
D40: Cash & Equivalents | H40: =H91 -> 155456 | I40: =I91 -> 150020 | J40: =J91 -> 144585 | K40: =K91 -> 139151 | L40: =L91 -> 133716 | M40: =M91 -> 128281 | N40: =N91 -> 122846 | O40: =O91 -> 117411 | ... S40: =S91 -> 95671 | T40: =S40 -> 95671
D41: Trade Receivables | H41: 5865 | I41: 11729 | J41: 17594 | K41: 23458 | L41: 29323 | M41: 35187 | N41: 41052 | O41: 46916 | P41: 52781 | Q41: 58645 | R41: 64510 | S41: 70374 | T41: =S41 -> 70374
D42: Inventories | H42: 4935 | I42: 9871 | J42: 14806 | K42: 19741 | L42: 24676 | M42: 29612 | N42: 34547 | O42: 39482 | P42: 44418 | Q42: 49353 | R42: 54288 | S42: 59223 | T42: =S42 -> 59223
D43: Current Assets — Total | H43: =SUM(H40:H42) -> 166256 | I43: =SUM(I40:I42) -> 171620 | J43: =SUM(J40:J42) -> 176985 | K43: =SUM(K40:K42) -> 182350 | L43: =SUM(L40:L42) -> 187715 | M43: =SUM(M40:M42) -> 193080 | N43: =SUM(N40:N42) -> 198445 | O43: =SUM(O40:O42) -> 203809 | ... T43: =SUM(T40:T42) -> 225268
C45: Long-Term Assets
D46: Property, Plant & Equipment | H46: 1659 | I46: 3317 | J46: 4976 | K46: 6634 | L46: 8293 | M46: 9952 | N46: 11610 | O46: 13269 | P46: 14927 | Q46: 16586 | R46: 18244 | S46: 19903 | T46: =S46 -> 19903
D47: Long-Term Assets — Total | H47: =SUM(H46) -> 1659 | I47: =SUM(I46) -> 3317 | J47: =SUM(J46) -> 4976 | K47: =SUM(K46) -> 6634 | L47: =SUM(L46) -> 8293 | M47: =SUM(M46) -> 9952 | N47: =SUM(N46) -> 11610 | O47: =SUM(O46) -> 13269 | ... T47: =SUM(T46) -> 19903
C48: Total Asset Base | H48: =H43+H47 -> 167915 | I48: =I43+I47 -> 174937 | J48: =J43+J47 -> 181961 | K48: =K43+K47 -> 188984 | L48: =L43+L47 -> 196008 | M48: =M43+M47 -> 203032 | N48: =N43+N47 -> 210055 | O48: =O43+O47 -> 217078 | ... T48: =T43+T47 -> 245171
C50: Short-Term Liabilities
D51: Trade Payable | H51: 4205 | I51: 8410 | J51: 12615 | K51: 16820 | L51: 21026 | M51: 25231 | N51: 29436 | O51: 33641 | P51: 37846 | Q51: 42051 | R51: 46256 | S51: 50461 | T51: =S51 -> 50461
D52: Accrued & Other Liabilities | H52: 2077 | I52: 4153 | J52: 6230 | K52: 8307 | L52: 10383 | M52: 12460 | N52: 14537 | O52: 16613 | P52: 18690 | Q52: 20767 | R52: 22843 | S52: 24920 | T52: =S52 -> 24920
D53: Current Liabilities — Total | H53: =SUM(H51:H52) -> 6282 | I53: =SUM(I51:I52) -> 12563 | J53: =SUM(J51:J52) -> 18845 | K53: =SUM(K51:K52) -> 25127 | L53: =SUM(L51:L52) -> 31409 | M53: =SUM(M51:M52) -> 37691 | N53: =SUM(N51:N52) -> 43973 | O53: =SUM(O51:O52) -> 50254 | ... T53: =SUM(T51:T52) -> 75381
C55: Long-Term Liabilities
D56: Long-Term Borrowings | H56: 70645 | I56: 70645 | J56: 70645 | K56: 70645 | L56: 70645 | M56: 70645 | N56: 70645 | O56: 70645 | P56: 70645 | Q56: 70645 | R56: 70645 | S56: 70645 | T56: =S56 -> 70645
D57: Long-Term Liabilities — Total | H57: =SUM(H56) -> 70645 | I57: =SUM(I56) -> 70645 | J57: =SUM(J56) -> 70645 | K57: =SUM(K56) -> 70645 | L57: =SUM(L56) -> 70645 | M57: =SUM(M56) -> 70645 | N57: =SUM(N56) -> 70645 | O57: =SUM(O56) -> 70645 | ... T57: =SUM(T56) -> 70645
C58: Liabilities — Total | H58: =H53+H57 -> 76927 | I58: =I53+I57 -> 83208 | J58: =J53+J57 -> 89490 | K58: =K53+K57 -> 95772 | L58: =L53+L57 -> 102054 | M58: =M53+M57 -> 108336 | N58: =N53+N57 -> 114618 | O58: =O53+O57 -> 120899 | ... T58: =T53+T57 -> 146026
C60: Shareholders' Equity
D61: Equity Funding | H61: 130094 | I61: 130094 | J61: 130094 | K61: 130094 | L61: 130094 | M61: 130094 | N61: 130094 | O61: 130094 | P61: 130094 | Q61: 130094 | R61: 130094 | S61: 130094 | T61: =S61 -> 130094
D62: Retained Earnings | H62: =H35+H86 -> 804 | I62: =H62+I35+I86 -> 1608 | J62: =I62+J35+J86 -> 2412 | K62: =J62+K35+K86 -> 3216 | L62: =K62+L35+L86 -> 4020 | M62: =L62+M35+M86 -> 4824 | N62: =M62+N35+N86 -> 5628 | O62: =N62+O35+O86 -> 6432 | P62: =O62+P35+P86 -> 7236 | ... S62: =R62+S35+S86 -> 9648 | T62: =S62 -> 9648
D63: Shareholder Equity — Total | H63: =SUM(H61:H62) -> 130898 | I63: =SUM(I61:I62) -> 131702 | J63: =SUM(J61:J62) -> 132506 | K63: =SUM(K61:K62) -> 133310 | L63: =SUM(L61:L62) -> 134114 | M63: =SUM(M61:M62) -> 134918 | N63: =SUM(N61:N62) -> 135722 | O63: =SUM(O61:O62) -> 136526 | ... T63: =SUM(T61:T62) -> 139742
C64: Total Liabilities & Shareholder Equity | H64: =H58+H63 -> 207825 | I64: =I58+I63 -> 214910 | J64: =J58+J63 -> 221996 | K64: =K58+K63 -> 229082 | L64: =L58+L63 -> 236168 | M64: =M58+M63 -> 243254 | N64: =N58+N63 -> 250340 | O64: =O58+O63 -> 257425 | ... T64: =T58+T63 -> 285768
D66: Reconciliation | H66: =H48-H64 -> -39910 | I66: =I48-I64 -> -39973 | J66: =J48-J64 -> -40035 | K66: =K48-K64 -> -40098 | L66: =L48-L64 -> -40160 | M66: =M48-M64 -> -40222 | N66: =N48-N64 -> -40285 | O66: =O48-O64 -> -40347 | ... T66: =T48-T64 -> -40597
C68: Statement of Cash Flows
C69: Cash Flow from Operations
D70: Net Earnings | H70: =H35 -> 804 | I70: =I35 -> 804 | J70: =J35 -> 804 | K70: =K35 -> 804 | L70: =L35 -> 804 | M70: =M35 -> 804 | N70: =N35 -> 804 | O70: =O35 -> 804 | ... S70: =S35 -> 804 | T70: =SUM(H70:S70) -> 9648
D71: (+) Depreciation & Amortization | H71: =H25 -> 871 | I71: =I25 -> 871 | J71: =J25 -> 871 | K71: =K25 -> 871 | L71: =L25 -> 871 | M71: =M25 -> 871 | N71: =N25 -> 871 | O71: =O25 -> 871 | ... S71: =S25 -> 871 | T71: =SUM(H71:S71) -> 10452
D72: (-) Working Capital Movement
E73: Trade Receivables | H73: =0-H41 -> -5865 | I73: =H41-I41 -> -5864 | J73: =I41-J41 -> -5865 | K73: =J41-K41 -> -5864 | L73: =K41-L41 -> -5865 | M73: =L41-M41 -> -5864 | N73: =M41-N41 -> -5865 | O73: =N41-O41 -> -5864 | P73: =O41-P41 -> -5865 | ... S73: =R41-S41 -> -5864 | T73: =-T41 -> -70374
E74: Inventories | H74: =0-H42 -> -4935 | I74: =H42-I42 -> -4936 | J74: =I42-J42 -> -4935 | K74: =J42-K42 -> -4935 | L74: =K42-L42 -> -4935 | M74: =L42-M42 -> -4936 | N74: =M42-N42 -> -4935 | O74: =N42-O42 -> -4935 | P74: =O42-P42 -> -4936 | ... S74: =R42-S42 -> -4935 | T74: =-T42 -> -59223
E75: Trade Payables | H75: =H51-0 -> 4205 | I75: =I51-H51 -> 4205 | J75: =J51-I51 -> 4205 | K75: =K51-J51 -> 4205 | L75: =L51-K51 -> 4206 | M75: =M51-L51 -> 4205 | N75: =N51-M51 -> 4205 | O75: =O51-N51 -> 4205 | P75: =P51-O51 -> 4205 | ... S75: =S51-R51 -> 4205 | T75: =T51 -> 50461
E76: Accrued & Other Liabilities | H76: =H52-0 -> 2077 | I76: =I52-H52 -> 2076 | J76: =J52-I52 -> 2077 | K76: =K52-J52 -> 2077 | L76: =L52-K52 -> 2076 | M76: =M52-L52 -> 2077 | N76: =N52-M52 -> 2077 | O76: =O52-N52 -> 2076 | P76: =P52-O52 -> 2077 | ... S76: =S52-R52 -> 2077 | T76: =T52 -> 24920
C77: Operating Cash Flows | H77: =SUM(H70:H76) -> -2843 | I77: =SUM(I70:I76) -> -2844 | J77: =SUM(J70:J76) -> -2843 | K77: =SUM(K70:K76) -> -2842 | L77: =SUM(L70:L76) -> -2843 | M77: =SUM(M70:M76) -> -2843 | N77: =SUM(N70:N76) -> -2843 | O77: =SUM(O70:O76) -> -2843 | ... T77: =SUM(T70:T76) -> -34116
C79: Cash Flow from Investing
D80: Purchases of property, plant & equipment | H80: -2592 | I80: -2592 | J80: -2592 | K80: -2592 | L80: -2592 | M80: -2592 | N80: -2592 | O80: -2592 | P80: -2592 | Q80: -2592 | R80: -2592 | S80: -2592 | T80: =SUM(H80:S80) -> -31104
C81: Investing Cash Flows | H81: =SUM(H80) -> -2592 | I81: =SUM(I80) -> -2592 | J81: =SUM(J80) -> -2592 | K81: =SUM(K80) -> -2592 | L81: =SUM(L80) -> -2592 | M81: =SUM(M80) -> -2592 | N81: =SUM(N80) -> -2592 | O81: =SUM(O80) -> -2592 | ... T81: =SUM(T80) -> -31104
C83: Cash Flow from Financing
D84: Long-Term Borrowings Proceeds (Repayments) and Other | H84: 69097 | T84: =SUM(H84:S84) -> 69097
D85: Equity Proceeds (Repayments) | H85: 91794 | T85: =SUM(H85:S85) -> 91794
D86: Dividend Distributions
C87: Financing Cash Flows | H87: =SUM(H84:H86) -> 160891 | I87: =SUM(I84:I86) -> 0 | J87: =SUM(J84:J86) -> 0 | K87: =SUM(K84:K86) -> 0 | L87: =SUM(L84:L86) -> 0 | M87: =SUM(M84:M86) -> 0 | N87: =SUM(N84:N86) -> 0 | O87: =SUM(O84:O86) -> 0 | ... S87: =SUM(S84:S86) -> 0 | T87: =SUM(T84:T85) -> 160891
D89: Net Change in Cash | H89: =H77+H81+H87 -> 155456 | I89: =I77+I81+I87 -> -5436 | J89: =J77+J81+J87 -> -5435 | K89: =K77+K81+K87 -> -5434 | L89: =L77+L81+L87 -> -5435 | M89: =M77+M81+M87 -> -5435 | N89: =N77+N81+N87 -> -5435 | O89: =O77+O81+O87 -> -5435 | ... T89: =T77+T81+T87 -> 95671
D90: Beginning Cash Balance | H90: 0 | I90: =H91 -> 155456 | J90: =I91 -> 150020 | K90: =J91 -> 144585 | L90: =K91 -> 139151 | M90: =L91 -> 133716 | N90: =M91 -> 128281 | O90: =N91 -> 122846 | P90: =O91 -> 117411 | ... S90: =R91 -> 101105 | T90: =H90 -> 0
C91: Ending Cash Balance | H91: =SUM(H89:H90) -> 155456 | I91: =SUM(I89:I90) -> 150020 | J91: =SUM(J89:J90) -> 144585 | K91: =SUM(K89:K90) -> 139151 | L91: =SUM(L89:L90) -> 133716 | M91: =SUM(M89:M90) -> 128281 | N91: =SUM(N89:N90) -> 122846 | O91: =SUM(O89:O90) -> 117411 | ... T91: =SUM(T89:T90) -> 95671
A101: NAVIGATION | B101: ='Control Center'!F6
C103: Forward 12-Month Projection
C104: ='Formula Audit'!A3 -> Figures in USD
E105: Planning Case | F105: ='Control Center'!E25 -> Central Case
E106: Period Days | F106: 365 | H106: ='Control Center'!F8 -> 2025
C107: Statement of Operations | H107: ='Formula Audit'!C41 -> January | I107: ='Formula Audit'!D41 -> February | J107: ='Formula Audit'!E41 -> March | K107: ='Formula Audit'!F41 -> April | L107: ='Formula Audit'!G41 -> May | M107: ='Formula Audit'!H41 -> June | N107: ='Formula Audit'!I41 -> July | O107: ='Formula Audit'!J41 -> August | ... S107: ='Formula Audit'!N41 -> December | T107: FY
D108: Service Revenue | H108: ='Control Center'!G167 -> 15549.2 | I108: ='Control Center'!H167 -> 15690.807 | J108: ='Control Center'!I167 -> 15832.414 | K108: ='Control Center'!J167 -> 15974.007 | L108: ='Control Center'!K167 -> 16682.028 | M108: ='Control Center'!L167 -> 16965.228 | N108: ='Control Center'!M167 -> 16398.814 | O108: ='Control Center'!N167 -> 15974.007 | ... S108: ='Control Center'!R167 -> 16965.228 | T108: =SUM(H108:S108) -> 193104.15
D109: Product Revenue | H109: ='Control Center'!G179 -> 16824.425 | I109: ='Control Center'!H179 -> 16977.646 | J109: ='Control Center'!I179 -> 17130.867 | K109: ='Control Center'!J179 -> 17284.072 | L109: ='Control Center'!K179 -> 18050.16 | M109: ='Control Center'!L179 -> 18356.586 | N109: ='Control Center'!M179 -> 17743.718 | O109: ='Control Center'!N179 -> 17284.072 | ... S109: ='Control Center'!R179 -> 18356.586 | T109: =SUM(H109:S109) -> 208941.07
C110: Sales — Total | H110: =SUM(H108:H109) -> 32373.625 | I110: =SUM(I108:I109) -> 32668.453 | J110: =SUM(J108:J109) -> 32963.282 | K110: =SUM(K108:K109) -> 33258.078 | L110: =SUM(L108:L109) -> 34732.188 | M110: =SUM(M108:M109) -> 35321.813 | N110: =SUM(N108:N109) -> 34142.532 | O110: =SUM(O108:O109) -> 33258.078 | ... T110: =SUM(T108:T109) -> 402045.22
D112: Service Costs | H112: ='Control Center'!G196 -> 2382.6684 | I112: ='Control Center'!H196 -> 2404.3675 | J112: ='Control Center'!I196 -> 2426.0666 | K112: ='Control Center'!J196 -> 2447.7634 | L112: ='Control Center'!K196 -> 2556.2565 | M112: ='Control Center'!L196 -> 2599.6523 | N112: ='Control Center'!M196 -> 2512.8583 | O112: ='Control Center'!N196 -> 2447.7634 | ... S112: ='Control Center'!R196 -> 2599.6523 | T112: =SUM(H112:S112) -> 29590.151
D113: Product Costs | H113: ='Control Center'!G208 -> 4953.0105 | I113: ='Control Center'!H208 -> 4998.1179 | J113: ='Control Center'!I208 -> 5043.2252 | K113: ='Control Center'!J208 -> 5088.3277 | L113: ='Control Center'!K208 -> 5313.8595 | M113: ='Control Center'!L208 -> 5404.0693 | N113: ='Control Center'!M208 -> 5223.6448 | O113: ='Control Center'!N208 -> 5088.3277 | ... S113: ='Control Center'!R208 -> 5404.0693 | T113: =SUM(H113:S113) -> 61511.006
D114: Direct Labour Costs | H114: ='Control Center'!$G$31*H110 -> 6166.172 | I114: ='Control Center'!$G$31*I110 -> 6222.3276 | J114: ='Control Center'!$G$31*J110 -> 6278.4833 | K114: ='Control Center'!$G$31*K110 -> 6334.6329 | L114: ='Control Center'!$G$31*L110 -> 6615.4052 | M114: ='Control Center'!$G$31*M110 -> 6727.7105 | N114: ='Control Center'!$G$31*N110 -> 6503.0939 | O114: ='Control Center'!$G$31*O110 -> 6334.6329 | ... S114: ='Control Center'!$G$31*S110 -> 6727.7105 | T114: =SUM(H114:S114) -> 76577.152
D115: Discounts & Promotions | H115: ='Control Center'!$G$32*H110 -> 4441.4347 | I115: ='Control Center'!$G$32*I110 -> 4481.8831 | J115: ='Control Center'!$G$32*J110 -> 4522.3315 | K115: ='Control Center'!$G$32*K110 -> 4562.7755 | L115: ='Control Center'!$G$32*L110 -> 4765.0131 | M115: ='Control Center'!$G$32*M110 -> 4845.9056 | N115: ='Control Center'!$G$32*N110 -> 4684.1164 | O115: ='Control Center'!$G$32*O110 -> 4562.7755 | ... S115: ='Control Center'!$G$32*S110 -> 4845.9056 | T115: =SUM(H115:S115) -> 55157.79
C116: Total Sales Costs | H116: =SUM(H112:H115) -> 17943.286 | I116: =SUM(I112:I115) -> 18106.696 | J116: =SUM(J112:J115) -> 18270.107 | K116: =SUM(K112:K115) -> 18433.5 | L116: =SUM(L112:L115) -> 19250.534 | M116: =SUM(M112:M115) -> 19577.338 | N116: =SUM(N112:N115) -> 18923.713 | O116: =SUM(O112:O115) -> 18433.5 | ... T116: =SUM(T112:T115) -> 222836.1
C118: Gross Income | H118: =H110-H116 -> 14430.339 | I118: =I110-I116 -> 14561.757 | J118: =J110-J116 -> 14693.175 | K118: =K110-K116 -> 14824.579 | L118: =L110-L116 -> 15481.654 | M118: =M110-M116 -> 15744.476 | N118: =N110-N116 -> 15218.818 | O118: =O110-O116 -> 14824.579 | ... T118: =T110-T116 -> 179209.12
C119: Gross Margin Rate | H119: =IFERROR(H118/H110,0) -> 0.4457437 | I119: =IFERROR(I118/I110,0) -> 0.4457437 | J119: =IFERROR(J118/J110,0) -> 0.4457437 | K119: =IFERROR(K118/K110,0) -> 0.4457437 | L119: =IFERROR(L118/L110,0) -> 0.4457437 | M119: =IFERROR(M118/M110,0) -> 0.4457437 | N119: =IFERROR(N118/N110,0) -> 0.4457437 | O119: =IFERROR(O118/O110,0) -> 0.4457437 | ... T119: =IFERROR(T118/T110,0) -> 0.4457437
D121: Salaries & Benefits | H121: ='Control Center'!$G$33/12 -> 4895.75 | I121: ='Control Center'!$G$33/12 -> 4895.75 | J121: ='Control Center'!$G$33/12 -> 4895.75 | K121: ='Control Center'!$G$33/12 -> 4895.75 | L121: ='Control Center'!$G$33/12 -> 4895.75 | M121: ='Control Center'!$G$33/12 -> 4895.75 | N121: ='Control Center'!$G$33/12 -> 4895.75 | O121: ='Control Center'!$G$33/12 -> 4895.75 | ... S121: ='Control Center'!$G$33/12 -> 4895.75 | T121: =SUM(H121:S121) -> 58749
D122: Sales & Marketing | H122: ='Control Center'!$G$34*H110 -> 1476.0431 | I122: ='Control Center'!$G$34*I110 -> 1489.4855 | J122: ='Control Center'!$G$34*J110 -> 1502.9279 | K122: ='Control Center'!$G$34*K110 -> 1516.3688 | L122: ='Control Center'!$G$34*L110 -> 1583.5794 | M122: ='Control Center'!$G$34*M110 -> 1610.4628 | N122: ='Control Center'!$G$34*N110 -> 1556.6946 | O122: ='Control Center'!$G$34*O110 -> 1516.3688 | ... S122: ='Control Center'!$G$34*S110 -> 1610.4628 | T122: =SUM(H122:S122) -> 18330.85
D123: General & Administrative | H123: ='Control Center'!$G$35/12 -> 2844.5833 | I123: ='Control Center'!$G$35/12 -> 2844.5833 | J123: ='Control Center'!$G$35/12 -> 2844.5833 | K123: ='Control Center'!$G$35/12 -> 2844.5833 | L123: ='Control Center'!$G$35/12 -> 2844.5833 | M123: ='Control Center'!$G$35/12 -> 2844.5833 | N123: ='Control Center'!$G$35/12 -> 2844.5833 | O123: ='Control Center'!$G$35/12 -> 2844.5833 | ... S123: ='Control Center'!$G$35/12 -> 2844.5833 | T123: =SUM(H123:S123) -> 34135
D124: Card Processing Fees | H124: ='Control Center'!$G$36*H110 -> 228.36355 | I124: ='Control Center'!$G$36*I110 -> 230.44327 | J124: ='Control Center'!$G$36*J110 -> 232.52299 | K124: ='Control Center'!$G$36*K110 -> 234.60248 | L124: ='Control Center'!$G$36*L110 -> 245.00086 | M124: ='Control Center'!$G$36*M110 -> 249.16007 | N124: ='Control Center'!$G$36*N110 -> 240.84142 | O124: ='Control Center'!$G$36*O110 -> 234.60248 | ... S124: ='Control Center'!$G$36*S110 -> 249.16007 | T124: =SUM(H124:S124) -> 2836.027
D125: Depreciation & Amortization | H125: ='Control Center'!$G$37*(('Control Center'!$G$43+'Control Center'!$G$46)/12) -> 721.6741 | I125: =H125 -> 721.6741 | J125: =I125 -> 721.6741 | K125: =J125 -> 721.6741 | L125: =K125 -> 721.6741 | M125: =L125 -> 721.6741 | N125: =M125 -> 721.6741 | O125: =N125 -> 721.6741 | P125: =O125 -> 721.6741 | ... S125: =R125 -> 721.6741 | T125: =SUM(H125:S125) -> 8660.0892
C126: Operating Expenses — Total | H126: =SUM(H121:H125) -> 10166.414 | I126: =SUM(I121:I125) -> 10181.936 | J126: =SUM(J121:J125) -> 10197.458 | K126: =SUM(K121:K125) -> 10212.979 | L126: =SUM(L121:L125) -> 10290.588 | M126: =SUM(M121:M125) -> 10321.63 | N126: =SUM(N121:N125) -> 10259.543 | O126: =SUM(O121:O125) -> 10212.979 | ... T126: =SUM(T121:T125) -> 122710.97
C128: Operating Income (EBIT) | H128: =H118-H126 -> 4263.9253 | I128: =I118-I126 -> 4379.821 | J128: =J118-J126 -> 4495.7168 | K128: =K118-K126 -> 4611.6001 | L128: =L118-L126 -> 5191.0664 | M128: =M118-M126 -> 5422.8455 | N128: =N118-N126 -> 4959.2749 | O128: =O118-O126 -> 4611.6001 | ... T128: =T118-T126 -> 56498.159
C129: Operating Margin Rate | H129: =IFERROR(H128/H110,0) -> 0.13170985 | I129: =IFERROR(I128/I110,0) -> 0.13406882 | J129: =IFERROR(J128/J110,0) -> 0.1363856 | K129: =IFERROR(K128/K110,0) -> 0.13866105 | L129: =IFERROR(L128/L110,0) -> 0.14945981 | M129: =IFERROR(M128/M110,0) -> 0.15352681 | N129: =IFERROR(N128/N110,0) -> 0.14525211 | O129: =IFERROR(O128/O110,0) -> 0.13866105 | ... T129: =IFERROR(T128/T110,0) -> 0.14052687
D131: Interest Expense | H131: ='Control Center'!$G$49*(('Control Center'!$G$49*(('Control Center'!$G$50)/12)+H156)/12) -> 371.20741 | I131: ='Control Center'!$G$49*((H131+I156)/12) -> 368.80239 | J131: ='Control Center'!$G$49*((I131+J156)/12) -> 366.38713 | K131: ='Control Center'!$G$49*((J131+K156)/12) -> 363.97181 | L131: ='Control Center'!$G$49*((K131+L156)/12) -> 361.5565 | M131: ='Control Center'!$G$49*((L131+M156)/12) -> 359.14118 | N131: ='Control Center'!$G$49*((M131+N156)/12) -> 356.72587 | O131: ='Control Center'!$G$49*((N131+O156)/12) -> 354.31055 | P131: ='Control Center'!$G$49*((O131+P156)/12) -> 351.89524 | ... S131: ='Control Center'!$G$49*((R131+S156)/12) -> 344.64929 | T131: =SUM(H131:S131) -> 4295.1919
C132: Pre-Tax Earnings (EBT) | H132: =H128-H131 -> 3892.7178 | I132: =I128-I131 -> 4011.0186 | J132: =J128-J131 -> 4129.3297 | K132: =K128-K131 -> 4247.6283 | L132: =L128-L131 -> 4829.5099 | M132: =M128-M131 -> 5063.7043 | N132: =N128-N131 -> 4602.549 | O132: =O128-O131 -> 4257.2895 | ... T132: =T128-T131 -> 52202.967
D134: Income Tax Expense | H134: =IF(H132>0,'Control Center'!$G$38*H132,0) -> 1030.924 | I134: =IF(I132>0,'Control Center'!$G$38*I132,0) -> 1062.2541 | J134: =IF(J132>0,'Control Center'!$G$38*J132,0) -> 1093.5869 | K134: =IF(K132>0,'Control Center'!$G$38*K132,0) -> 1124.9164 | L134: =IF(L132>0,'Control Center'!$G$38*L132,0) -> 1279.0184 | M134: =IF(M132>0,'Control Center'!$G$38*M132,0) -> 1341.0411 | N134: =IF(N132>0,'Control Center'!$G$38*N132,0) -> 1218.9115 | O134: =IF(O132>0,'Control Center'!$G$38*O132,0) -> 1127.475 | ... T134: =IF(T132>0,'Control Center'!$G$38*T132,0) -> 13825.12
...

Sheet Outputs
A2: NAVIGATION | B2: ='Control Center'!F6
C4: Summary Overview
C5: ='Formula Audit'!A3 -> Figures in USD
C6: Planning Case | D6: ='Control Center'!E25 -> Central Case
C7: Headline Financials | E7: ='Control Center'!F8 -> 2025 | F7: ='Formula Audit'!D9 -> 2026 | G7: ='Formula Audit'!E9 -> 2027 | H7: ='Formula Audit'!F9 -> 2028 | I7: ='Formula Audit'!G9 -> 2029 | J7: ='Formula Audit'!H9 -> 2030 | K7: ='Formula Audit'!I9 -> 2031 | L7: ='Formula Audit'!J9 -> 2032 | M7: ='Formula Audit'!K9 -> 2033 | N7: ='Formula Audit'!L9 -> 2034
C9: Revenue (Net) | E9: ='Forecast Model'!H219 -> 402045.22 | F9: ='Forecast Model'!I219 -> 428989.89 | G9: ='Forecast Model'!J219 -> 452948.55 | H9: ='Forecast Model'!K219 -> 473185.84 | I9: ='Forecast Model'!L219 -> 489042.3 | J9: ='Forecast Model'!M219 -> 505430.1 | K9: ='Forecast Model'!N219 -> 516721.41 | L9: ='Forecast Model'!O219 -> 528264.97 | ... N9: ='Forecast Model'!Q219 -> 552131.49
C10: Gross Income | E10: ='Forecast Model'!H227 -> 179209.12 | F10: ='Forecast Model'!I227 -> 163518.18 | G10: ='Forecast Model'!J227 -> 181789.36 | H10: ='Forecast Model'!K227 -> 199807.34 | I10: ='Forecast Model'!L227 -> 208640.82 | J10: ='Forecast Model'!M227 -> 226202.77 | K10: ='Forecast Model'!N227 -> 231256.14 | L10: ='Forecast Model'!O227 -> 247470.62 | ... N10: ='Forecast Model'!Q227 -> 261472.22
C11: Gross Income Margin | E11: =IFERROR('Forecast Model'!H228, "") -> 0.4457437 | F11: =IFERROR('Forecast Model'!I228, "") -> 0.38117024 | G11: =IFERROR('Forecast Model'!J228, "") -> 0.4013466 | H11: =IFERROR('Forecast Model'!K228, "") -> 0.42225976 | I11: =IFERROR('Forecast Model'!L228, "") -> 0.42663143 | J11: =IFERROR('Forecast Model'!M228, "") -> 0.44754511 | K11: =IFERROR('Forecast Model'!N228, "") -> 0.44754511 | L11: =IFERROR('Forecast Model'!O228, "") -> 0.46845927 | ... N11: =IFERROR('Forecast Model'!Q228, "") -> 0.47356875
C12: EBITDA (Operating) | E12: ='Forecast Model'!H238+'Forecast Model'!H234 -> 65158.248 | F12: ='Forecast Model'!I238+'Forecast Model'!I234 -> 48048.722 | G12: ='Forecast Model'!J238+'Forecast Model'!J234 -> 67639.878 | H12: ='Forecast Model'!K238+'Forecast Model'!K234 -> 84707.735 | I12: ='Forecast Model'!L238+'Forecast Model'!L234 -> 92796.769 | J12: ='Forecast Model'!M238+'Forecast Model'!M234 -> 109589.33 | K12: ='Forecast Model'!N238+'Forecast Model'!N234 -> 117057.9 | L12: ='Forecast Model'!O238+'Forecast Model'!O234 -> 132796.22 | ... N12: ='Forecast Model'!Q238+'Forecast Model'!Q234 -> 145813.35
C13: Net Earnings | E13: ='Forecast Model'!H245 -> 38377.846 | F13: ='Forecast Model'!I245 -> 25914.797 | G13: ='Forecast Model'!J245 -> 40029.927 | H13: ='Forecast Model'!K245 -> 52514.671 | I13: ='Forecast Model'!L245 -> 57733.132 | J13: ='Forecast Model'!M245 -> 68960.272 | K13: ='Forecast Model'!N245 -> 74698.861 | L13: ='Forecast Model'!O245 -> 87316.637 | ... N13: ='Forecast Model'!Q245 -> 99505.442
C14: Net Profit Margin Rate | E14: =IFERROR('Forecast Model'!H228,"") -> 0.4457437 | F14: =IFERROR('Forecast Model'!I228,"") -> 0.38117024 | G14: =IFERROR('Forecast Model'!J228,"") -> 0.4013466 | H14: =IFERROR('Forecast Model'!K228,"") -> 0.42225976 | I14: =IFERROR('Forecast Model'!L228,"") -> 0.42663143 | J14: =IFERROR('Forecast Model'!M228,"") -> 0.44754511 | K14: =IFERROR('Forecast Model'!N228,"") -> 0.44754511 | L14: =IFERROR('Forecast Model'!O228,"") -> 0.46845927 | ... N14: =IFERROR('Forecast Model'!Q228,"") -> 0.47356875
C16: Running Cash Flow | E16: ='Forecast Model'!H301 -> 178578.55 | F16: ='Forecast Model'!I301 -> 163839.58 | G16: ='Forecast Model'!J301 -> 189931.21 | H16: ='Forecast Model'!K301 -> 223641.76 | I16: ='Forecast Model'!L301 -> 264213.03 | J16: ='Forecast Model'!M301 -> 317061.08 | K16: ='Forecast Model'!N301 -> 370368.6 | L16: ='Forecast Model'!O301 -> 440597.54 | ... N16: ='Forecast Model'!Q301 -> 591162.38
C17: Free Cash Flows | E17: ='Valuation & Breakeven'!K17 -> 30441.127 | F17: ='Valuation & Breakeven'!L17 -> -1256.5348 | G17: ='Valuation & Breakeven'!M17 -> 41336.785 | H17: ='Valuation & Breakeven'!N17 -> 50474.859 | I17: ='Valuation & Breakeven'!O17 -> 57769.203 | J17: ='Valuation & Breakeven'!P17 -> 71377.25 | K17: ='Valuation & Breakeven'!Q17 -> 72348.047 | L17: ='Valuation & Breakeven'!R17 -> 90808.492 | ... N17: ='Valuation & Breakeven'!T17 -> 102220.34
C18: EV / Revenue | E18: =IFERROR('Valuation & Breakeven'!$K$40/E9,0) -> 0.72698649 | F18: =IFERROR('Valuation & Breakeven'!$K$40/F9,0) -> 0.68132478 | G18: =IFERROR('Valuation & Breakeven'!$K$40/G9,0) -> 0.6452862 | H18: =IFERROR('Valuation & Breakeven'!$K$40/H9,0) -> 0.61768849 | I18: =IFERROR('Valuation & Breakeven'!$K$40/I9,0) -> 0.59766088 | J18: =IFERROR('Valuation & Breakeven'!$K$40/J9,0) -> 0.57828262 | K18: =IFERROR('Valuation & Breakeven'!$K$40/K9,0) -> 0.56564609 | L18: =IFERROR('Valuation & Breakeven'!$K$40/L9,0) -> 0.55328569 | ... N18: =IFERROR('Valuation & Breakeven'!$K$40/N9,0) -> 0.52936927
C19: EV / EBITDA | E19: =IFERROR('Valuation & Breakeven'!$K$40/E12,0) -> 4.4857168 | F19: =IFERROR('Valuation & Breakeven'!$K$40/F12,0) -> 6.0830223 | G19: =IFERROR('Valuation & Breakeven'!$K$40/G12,0) -> 4.3211409 | H19: =IFERROR('Valuation & Breakeven'!$K$40/H12,0) -> 3.4504694 | I19: =IFERROR('Valuation & Breakeven'!$K$40/I12,0) -> 3.1496942 | J19: =IFERROR('Valuation & Breakeven'!$K$40/J12,0) -> 2.6670611 | K19: =IFERROR('Valuation & Breakeven'!$K$40/K12,0) -> 2.4968964 | L19: =IFERROR('Valuation & Breakeven'!$K$40/L12,0) -> 2.2009772 | ... N19: =IFERROR('Valuation & Breakeven'!$K$40/N12,0) -> 2.0044903
C21: Return on Shareholder Equity (ROE) | E21: =IFERROR('Formula Audit'!C213,"") -> 0.30592764 | F21: =IFERROR('Formula Audit'!D213,"") -> 0.17570453 | G21: =IFERROR('Formula Audit'!E213,"") -> 0.22050135 | H21: =IFERROR('Formula Audit'!F213,"") -> 0.23215024 | I21: =IFERROR('Formula Audit'!G213,"") -> 0.20969613 | J21: =IFERROR('Formula Audit'!H213,"") -> 0.20648262 | K21: =IFERROR('Formula Audit'!I213,"") -> 0.18791432 | L21: =IFERROR('Formula Audit'!J213,"") -> 0.18507613 | ... N21: =IFERROR('Formula Audit'!L213,"") -> 0.15672221
C22: Return on Capital (ROCE) | E22: =IFERROR('Formula Audit'!C215,"") -> 0.21767949 | F22: =IFERROR('Formula Audit'!D215,"") -> 0.13956251 | G22: =IFERROR('Formula Audit'!E215,"") -> 0.18142553 | H22: =IFERROR('Formula Audit'!F215,"") -> 0.20005099 | I22: =IFERROR('Formula Audit'!G215,"") -> 0.18825168 | J22: =IFERROR('Formula Audit'!H215,"") -> 0.19084711 | K22: =IFERROR('Formula Audit'!I215,"") -> 0.17783704 | L22: =IFERROR('Formula Audit'!J215,"") -> 0.17810306 | ... N22: =IFERROR('Formula Audit'!L215,"") -> 0.15441628
A27: NAVIGATION | B27: ='Control Center'!F6
C29: Performance Dashboard
C30: ='Formula Audit'!A3 -> Figures in USD
E31: Fiscal Year (Yr) | F31: 2025
D33: Revenue — Total | F33: Total Operating Costs | L33: Ending Cash Balance | N33: Long-Term Borrowings
D34: ='Formula Audit'!C238 -> 402045.22 | F34: ='Formula Audit'!C242 -> 0 | L34: ='Formula Audit'!C254 -> 178578.55 | N34: ='Formula Audit'!C258 -> 65363
D35: ='Formula Audit'!C240 -> 0 | F35: ='Formula Audit'!C244 -> 0 | J35: Net Margin Rate | L35: ='Formula Audit'!C256 -> 0 | N35: ='Formula Audit'!C260 -> 0
D36: vs. Preceding Year | F36: vs. Preceding Year | J36: ='Formula Audit'!C270 -> 0.09545654 | L36: vs. Preceding Year | N36: vs. Preceding Year
D38: Net Profit for Period | F38: EBITDA (Operating) | J38: ='Formula Audit'!C272 -> 0 | L38: Working Capital Ratio | N38: Acid-Test Ratio
D39: ='Formula Audit'!C246 -> 38377.846 | F39: ='Formula Audit'!C250 -> 0 | J39: vs. Preceding Year | L39: ='Formula Audit'!C262 | N39: ='Formula Audit'!C266
D40: ='Formula Audit'!C248 -> 0 | F40: ='Formula Audit'!C252 -> 0 | L40: ='Formula Audit'!C264 -> 0 | N40: ='Formula Audit'!C268 -> 0
D41: vs. Preceding Year | F41: vs. Preceding Year | L41: vs. Preceding Year | N41: vs. Preceding Year
M71: Statement of Operations | O71: ='Formula Audit'!C305 -> 2025
M72: Sales — Total | O72: ='Formula Audit'!C306 -> 402045.22
M73: Total Sales Costs | O73: ='Formula Audit'!C307 -> 222836.1
M74: Gross Income | O74: ='Formula Audit'!C308 -> 179209.12
M75: Operating Expenses — Total | O75: ='Formula Audit'!C309 -> 122710.97
M76: Operating Income (EBIT) | O76: ='Formula Audit'!C310 -> 56498.159
M77: Interest Expense | O77: ='Formula Audit'!C311 -> 4295.1919
M78: Pre-Tax Earnings (EBT) | O78: ='Formula Audit'!C312 -> 52202.967
M79: Income Tax Expense | O79: ='Formula Audit'!C313 -> 13825.12
M80: Net Earnings | O80: ='Formula Audit'!C314 -> 38377.846
M81: Statement of Cash Flows
M82: Operating Cash Flows | O82: ='Formula Audit'!C316 -> 47037.935
M83: Investing Cash Flows | O83: ='Formula Audit'!C317 -> -20892
M84: Financing Cash Flows | O84: ='Formula Audit'!C318 -> 152432.62
M85: Beginning Cash Balance | O85: ='Formula Audit'!C319 -> 0
M86: Ending Cash Balance | O86: ='Formula Audit'!C320 -> 178578.55
A91: NAVIGATION | B91: ='Control Center'!F6
C93: Budget vs. Actual Variance
C94: ='Formula Audit'!A3 -> Figures in USD
F95: Year-to-Date | L95: This Month | M95: February
C96: Statement of Operations | F96: Actuals | G96: Plan | H96: Δ P&L | I96: Δ P&L (%) | K96: Actuals | L96: Plan | M96: Δ P&L | N96: Δ P&L (%)
D97: Service Revenue | F97: ='Formula Audit'!$O145 -> 63258 | G97: ='Formula Audit'!$O164 -> 31240.007 | H97: =F97-G97 -> 32017.993 | I97: =H97/G97 -> 1.0249035 | K97: ='Formula Audit'!$P145 -> 31629 | L97: ='Formula Audit'!$P164 -> 15690.807 | M97: =K97-L97 -> 15938.193 | N97: =M97/L97 -> 1.0157663
D98: Product Revenue | F98: ='Formula Audit'!$O146 -> 17074 | G98: ='Formula Audit'!$O165 -> 33802.072 | H98: =F98-G98 -> -16728.072 | I98: =H98/G98 -> -0.49488303 | K98: ='Formula Audit'!$P146 -> 8537 | L98: ='Formula Audit'!$P165 -> 16977.646 | M98: =K98-L98 -> -8440.6464 | N98: =M98/L98 -> -0.49716234
C99: Revenue (Net) | F99: =SUM(F97:F98) -> 80332 | G99: =SUM(G97:G98) -> 65042.078 | H99: =F99-G99 -> 15289.922 | I99: =H99/G99 -> 0.23507738 | K99: =SUM(K97:K98) -> 40166 | L99: =SUM(L97:L98) -> 32668.453 | M99: =K99-L99 -> 7497.5466 | N99: =M99/L99 -> 0.22950418
D100: Sales Costs | F100: ='Formula Audit'!$O147 -> 53274 | G100: ='Formula Audit'!$O166 -> 36049.982 | H100: =F100-G100 -> 17224.018 | I100: =H100/G100 -> 0.4777816 | K100: ='Formula Audit'!$P147 -> 26637 | L100: ='Formula Audit'!$P166 -> 18106.696 | M100: =K100-L100 -> 8530.3038 | N100: =M100/L100 -> 0.47111321
C101: Gross Income | F101: =F99-F100 -> 27058 | G101: =G99-G100 -> 28992.096 | H101: =F101-G101 -> -1934.0965 | I101: =H101/G101 -> -0.066711164 | K101: =SUM(K97:K98)-K100 -> 13529 | L101: =L99-L100 -> 14561.757 | M101: =K101-L101 -> -1032.7572 | N101: =M101/L101 -> -0.070922566
C102: Gross Margin Rate | F102: =IFERROR(F101/SUM($F$97:$F$98),"") -> 0.33682717 | G102: =IFERROR(G101/SUM($G$97:$G$98),"") -> 0.4457437 | K102: =IFERROR(K101/SUM($K$97:$K$98),"") -> 0.33682717 | L102: =IFERROR(L101/SUM($L$97:$L$98),"") -> 0.4457437
D104: Salaries & Benefits | F104: ='Formula Audit'!$O148 -> 7296 | G104: ='Formula Audit'!$O167 -> 9791.5 | H104: =F104-G104 -> -2495.5 | I104: =H104/G104 -> -0.25486391 | K104: ='Formula Audit'!$P148 -> 3648 | L104: ='Formula Audit'!$P167 -> 4895.75 | M104: =K104-L104 -> -1247.75 | N104: =M104/L104 -> -0.25486391
D105: Sales & Marketing | F105: ='Formula Audit'!$O149 -> 4038 | G105: ='Formula Audit'!$O168 -> 2965.5285 | H105: =F105-G105 -> 1072.4715 | I105: =H105/G105 -> 0.36164598 | K105: ='Formula Audit'!$P149 -> 2019 | L105: ='Formula Audit'!$P168 -> 1489.4855 | M105: =K105-L105 -> 529.51454 | N105: =M105/L105 -> 0.35550165
D106: General & Administrative | F106: ='Formula Audit'!$O150 -> 7294 | G106: ='Formula Audit'!$O169 -> 5689.1667 | H106: =F106-G106 -> 1604.8333 | I106: =H106/G106 -> 0.28208584 | K106: ='Formula Audit'!$P150 -> 3647 | L106: ='Formula Audit'!$P169 -> 2844.5833 | M106: =K106-L106 -> 802.41667 | N106: =M106/L106 -> 0.28208584
D107: Card Processing Fees | F107: ='Formula Audit'!$O151 -> 880 | G107: ='Formula Audit'!$O170 -> 458.80682 | H107: =F107-G107 -> 421.19318 | I107: =H107/G107 -> 0.91801857 | K107: ='Formula Audit'!$P151 -> 440 | L107: ='Formula Audit'!$P170 -> 230.44327 | M107: =K107-L107 -> 209.55673 | N107: =M107/L107 -> 0.90936364
D108: Depreciation & Amortization | F108: ='Formula Audit'!$O152 -> 1742 | G108: ='Formula Audit'!$O171 -> 1443.3482 | H108: =F108-G108 -> 298.65181 | I108: =H108/G108 -> 0.20691598 | K108: ='Formula Audit'!$P152 -> 871 | L108: ='Formula Audit'!P171 -> 721.6741 | M108: =K108-L108 -> 149.3259 | N108: =M108/L108 -> 0.20691598
C109: Operating Expenses — Total | F109: =SUM(F104:F108) -> 21250 | G109: =SUM(G104:G108) -> 20348.35 | H109: =F109-G109 -> 901.6498 | I109: =H109/G109 -> 0.044310708 | K109: =SUM(K104:K108) -> 10625 | L109: =SUM(L104:L108) -> 10181.936 | M109: =K109-L109 -> 443.06384 | N109: =M109/L109 -> 0.043514694
C111: Operating Income (EBIT) | F111: =F101-F109 -> 5808 | G111: =G101-G109 -> 8643.7463 | H111: =F111-G111 -> -2835.7463 | I111: =H111/G111 -> -0.32806913 | K111: =K101-K109 -> 2904 | L111: =L101-L109 -> 4379.821 | M111: =K111-L111 -> -1475.821 | N111: =M111/L111 -> -0.33695921
C112: Operating Margin Rate | F112: =IFERROR(F111/SUM($F$97:$F$98),"") -> 0.072299955 | G112: =IFERROR(G111/SUM($G$97:$G$98),"") -> 0.13289468 | K112: =IFERROR(K111/SUM($K$97:$K$98),"") -> 0.072299955 | L112: =IFERROR(L111/SUM($L$97:$L$98),"") -> 0.13406882
D114: Interest Expense | F114: ='Formula Audit'!$O153 -> 766 | G114: ='Formula Audit'!$O172 -> 740.0098 | H114: =F114-G114 -> 25.990198 | I114: =IFERROR(H114/G114,0) -> 0.035121424 | K114: ='Formula Audit'!$P153 -> 383 | L114: ='Formula Audit'!P172 -> 368.80239 | M114: =K114-L114 -> 14.197611 | N114: =IFERROR(M114/L114,0) -> 0.038496527
C115: Pre-Tax Earnings (EBT) | F115: =F111-F114 -> 5042 | G115: =G111-G114 -> 7903.7365 | H115: =F115-G115 -> -2861.7365 | I115: =H115/G115 -> -0.36207387 | K115: =K111-K114 -> 2521 | L115: =L111-L114 -> 4011.0186 | M115: =K115-L115 -> -1490.0186 | N115: =M115/L115 -> -0.37148136
D117: Income Tax Expense | F117: ='Formula Audit'!$O154 -> 3434 | G117: ='Formula Audit'!$O173 -> 2093.1781 | H117: =F117-G117 -> 1340.8219 | I117: =H117/G117 -> 0.64056748 | K117: ='Formula Audit'!$P154 -> 1717 | L117: ='Formula Audit'!$P173 -> 1062.2541 | M117: =K117-L117 -> 654.74589 | N117: =M117/L117 -> 0.61637407
C118: Net Earnings | F118: =F115-F117 -> 1608 | G118: =G115-G117 -> 5810.5583 | H118: =SUM(H117) -> 1340.8219 | I118: =H118/G118 -> 0.23075611 | K118: =K115-K117 -> 804 | L118: =L115-L117 -> 2948.7645 | M118: =K118-L118 -> -2144.7645 | N118: =M118/L118 -> -0.72734344
C119: Net Margin Rate | F119: =IFERROR(F118/SUM($F$97:$F$98),"") -> 0.02001693 | G119: =IFERROR(G118/SUM($G$97:$G$98),"") -> 0.089335373 | K119: =IFERROR(K118/SUM($K$97:$K$98),"") -> 0.02001693 | L119: =IFERROR(L118/SUM($L$97:$L$98),"") -> 0.090263365
E122: =M95 -> February
C123: Statement of Operations | E123: Actuals | F123: Plan
D124: Revenue (Net) | E124: =SUM(K97:K98) -> 40166 | F124: =SUM(L97:L98) -> 32668.453
D125: Cost of Goods | E125: =K100 -> 26637 | F125: =L100 -> 18106.696
D126: Operating Expenditure | E126: =K109 -> 10625 | F126: =L109 -> 10181.936
D127: Interest & Tax | E127: =K114+K117 -> 2100 | F127: =L114+L117 -> 1431.0565
A132: NAVIGATION | B132: ='Control Center'!F6
C134: Ratio Detail
C135: ='Formula Audit'!A3 -> Figures in USD
E136: Planning Case | F136: ='Control Center'!E25 -> Central Case
C137: Margin Ratios | H137: ='Formula Audit'!C212 -> 2025 | I137: ='Formula Audit'!D212 -> 2026 | J137: ='Formula Audit'!E212 -> 2027 | K137: ='Formula Audit'!F212 -> 2028 | L137: ='Formula Audit'!G212 -> 2029 | M137: ='Formula Audit'!H212 -> 2030 | N137: ='Formula Audit'!I212 -> 2031 | O137: ='Formula Audit'!J212 -> 2032 | ... Q137: ='Formula Audit'!L212 -> 2034
C138: Return on Shareholder Equity (ROE) | H138: ='Formula Audit'!C213 -> 0.30592764 | I138: ='Formula Audit'!D213 -> 0.17570453 | J138: ='Formula Audit'!E213 -> 0.22050135 | K138: ='Formula Audit'!F213 -> 0.23215024 | L138: ='Formula Audit'!G213 -> 0.20969613 | M138: ='Formula Audit'!H213 -> 0.20648262 | N138: ='Formula Audit'!I213 -> 0.18791432 | O138: ='Formula Audit'!J213 -> 0.18507613 | ... Q138: ='Formula Audit'!L213 -> 0.15672221
C139: Return on Total Assets (ROA) | H139: ='Formula Audit'!C214 -> 0.20113072 | I139: ='Formula Audit'!D214 -> 0.096843086 | J139: ='Formula Audit'!E214 -> 0.13424494 | K139: ='Formula Audit'!F214 -> 0.15504609 | L139: ='Formula Audit'!G214 -> 0.15029334 | M139: ='Formula Audit'!H214 -> 0.15884686 | N139: ='Formula Audit'!I214 -> 0.1513458 | O139: ='Formula Audit'!J214 -> 0.15528238 | ... Q139: ='Formula Audit'!L214 -> 0.13879049
C140: Return on Capital (ROCE) | H140: ='Formula Audit'!C215 -> 0.21767949 | I140: ='Formula Audit'!D215 -> 0.13956251 | J140: ='Formula Audit'!E215 -> 0.18142553 | K140: ='Formula Audit'!F215 -> 0.20005099 | L140: ='Formula Audit'!G215 -> 0.18825168 | M140: ='Formula Audit'!H215 -> 0.19084711 | N140: ='Formula Audit'!I215 -> 0.17783704 | O140: ='Formula Audit'!J215 -> 0.17810306 | ... Q140: ='Formula Audit'!L215 -> 0.15441628
C141: Gross Income Margin | H141: ='Formula Audit'!C216 -> 0.4457437 | I141: ='Formula Audit'!D216 -> 0.38117024 | J141: ='Formula Audit'!E216 -> 0.4013466 | K141: ='Formula Audit'!F216 -> 0.42225976 | L141: ='Formula Audit'!G216 -> 0.42663143 | M141: ='Formula Audit'!H216 -> 0.44754511 | N141: ='Formula Audit'!I216 -> 0.44754511 | O141: ='Formula Audit'!J216 -> 0.46845927 | ... Q141: ='Formula Audit'!L216 -> 0.47356875
C142: Operating Income Margin | H142: ='Formula Audit'!C217 -> 0.14052687 | I142: ='Formula Audit'!D217 -> 0.091760234 | J142: ='Formula Audit'!E217 -> 0.1285315 | K142: ='Formula Audit'!F217 -> 0.15819236 | L142: ='Formula Audit'!G217 -> 0.16687053 | M142: ='Formula Audit'!H217 -> 0.19099048 | N142: ='Formula Audit'!I217 -> 0.2012539 | O142: ='Formula Audit'!J217 -> 0.22869088 | ... Q142: ='Formula Audit'!L217 -> 0.24758067
C143: EBITDA Margin Rate | H143: ='Formula Audit'!C218 -> 0.12767998 | I143: ='Formula Audit'!D218 -> 0.090242808 | J143: ='Formula Audit'!E218 -> 0.11749594 | K143: ='Formula Audit'!F218 -> 0.1390363 | L143: ='Formula Audit'!G218 -> 0.14722481 | M143: ='Formula Audit'!H218 -> 0.16767361 | N143: ='Formula Audit'!I218 -> 0.17446269 | O143: ='Formula Audit'!J218 -> 0.19183846 | ... Q143: ='Formula Audit'!L218 -> 0.1991696
C144: Net Profit Margin Rate | H144: ='Formula Audit'!C219 -> 0.09545654 | I144: ='Formula Audit'!D219 -> 0.060408875 | J144: ='Formula Audit'!E219 -> 0.088376323 | K144: ='Formula Audit'!F219 -> 0.11098107 | L144: ='Formula Audit'!G219 -> 0.11805345 | M144: ='Formula Audit'!H219 -> 0.13643879 | N144: ='Formula Audit'!I219 -> 0.14456312 | O144: ='Formula Audit'!J219 -> 0.16528947 | ... Q144: ='Formula Audit'!L219 -> 0.18022055
C146: Short-Term Solvency Ratios
C147: Working Capital Ratio | H147: ='Formula Audit'!C222 | I147: ='Formula Audit'!D222 -> 4.2386077 | J147: ='Formula Audit'!E222 -> 4.5744264 | K147: ='Formula Audit'!F222 -> 5.1049566 | L147: ='Formula Audit'!G222 -> 5.6282486 | M147: ='Formula Audit'!H222 -> 6.6748948 | N147: ='Formula Audit'!I222 -> 7.4623415 | O147: ='Formula Audit'!J222 -> 8.5701336 | ... Q147: ='Formula Audit'!L222 -> 10.644982
C148: Acid-Test Ratio | H148: ='Formula Audit'!C223 | I148: ='Formula Audit'!D223 -> 3.4417297 | J148: ='Formula Audit'!E223 -> 3.7871033 | K148: ='Formula Audit'!F223 -> 4.2691145 | L148: ='Formula Audit'!G223 -> 4.7947963 | M148: ='Formula Audit'!H223 -> 5.8027269 | N148: ='Formula Audit'!I223 -> 6.5287533 | O148: ='Formula Audit'!J223 -> 7.6513799 | ... Q148: ='Formula Audit'!L223 -> 9.6697565
C149: Operating Cash Ratio | H149: ='Formula Audit'!C224 | I149: ='Formula Audit'!D224 -> 0.055587244 | J149: ='Formula Audit'!E224 -> 0.7712704 | K149: ='Formula Audit'!F224 -> 0.90402845 | L149: ='Formula Audit'!G224 -> 1.0355716 | M149: ='Formula Audit'!H224 -> 1.3543055 | N149: ='Formula Audit'!I224 -> 1.3043051 | O149: ='Formula Audit'!J224 -> 1.5593659 | ... Q149: ='Formula Audit'!L224 -> 1.6305931
C151: Activity Ratios
C152: Receivable Days (DSO) | H152: ='Formula Audit'!C227 -> 0 | I152: ='Formula Audit'!D227 -> 37 | J152: ='Formula Audit'!E227 -> 37 | K152: ='Formula Audit'!F227 -> 37 | L152: ='Formula Audit'!G227 -> 37 | M152: ='Formula Audit'!H227 -> 32 | N152: ='Formula Audit'!I227 -> 32 | O152: ='Formula Audit'!J227 -> 32 | ... Q152: ='Formula Audit'!L227 -> 32
C153: Payable Days (DPO) | H153: ='Formula Audit'!C228 -> 0 | I153: ='Formula Audit'!D228 -> 53 | J153: ='Formula Audit'!E228 -> 53 | K153: ='Formula Audit'!F228 -> 53 | L153: ='Formula Audit'!G228 -> 53 | M153: ='Formula Audit'!H228 -> 48 | N153: ='Formula Audit'!I228 -> 48 | O153: ='Formula Audit'!J228 -> 48 | ... Q153: ='Formula Audit'!L228 -> 48
C154: Inventory Days (DIO) | H154: ='Formula Audit'!C229 -> 0 | I154: ='Formula Audit'!D229 -> 66 | J154: ='Formula Audit'!E229 -> 66 | K154: ='Formula Audit'!F229 -> 71 | L154: ='Formula Audit'!G229 -> 71 | M154: ='Formula Audit'!H229 -> 71 | N154: ='Formula Audit'!I229 -> 76 | O154: ='Formula Audit'!J229 -> 76 | ... Q154: ='Formula Audit'!L229 -> 81
C155: Cash-to-Cash Cycle | H155: ='Formula Audit'!C230 -> 0 | I155: ='Formula Audit'!D230 -> 50 | J155: ='Formula Audit'!E230 -> 50 | K155: ='Formula Audit'!F230 -> 55 | L155: ='Formula Audit'!G230 -> 55 | M155: ='Formula Audit'!H230 -> 55 | N155: ='Formula Audit'!I230 -> 60 | O155: ='Formula Audit'!J230 -> 60 | ... Q155: ='Formula Audit'!L230 -> 65
C157: Solvency Ratios
C158: Gearing Ratio | H158: ='Formula Audit'!C233 -> 0.52103883 | I158: ='Formula Audit'!D233 -> 0.40589658 | J158: ='Formula Audit'!E233 -> 0.29948688 | K158: ='Formula Audit'!F233 -> 0.21604717 | L158: ='Formula Audit'!G233 -> 0.15754506 | M158: ='Formula Audit'!H233 -> 0.11341528 | N158: ='Formula Audit'!I233 -> 0.081458453 | O158: ='Formula Audit'!J233 -> 0.056983261 | ... Q158: ='Formula Audit'!L233 -> 0.025026932
C159: Equity Ratio | H159: ='Formula Audit'!C234 -> 0.65744541 | I159: ='Formula Audit'!D234 -> 0.55117012 | J159: ='Formula Audit'!E234 -> 0.60881686 | K159: ='Formula Audit'!F234 -> 0.66786964 | L159: ='Formula Audit'!G234 -> 0.71671965 | M159: ='Formula Audit'!H234 -> 0.76929895 | N159: ='Formula Audit'!I234 -> 0.80539789 | O159: ='Formula Audit'!J234 -> 0.83901896 | ... Q159: ='Formula Audit'!L234 -> 0.88558276
C160: Borrowings-to-Assets Ratio | H160: ='Formula Audit'!C235 -> 0.34255459 | I160: ='Formula Audit'!D235 -> 0.22371806 | J160: ='Formula Audit'!E235 -> 0.18233266 | K160: ='Formula Audit'!F235 -> 0.14429135 | L160: ='Formula Audit'!G235 -> 0.11291564 | M160: ='Formula Audit'!H235 -> 0.087250258 | N160: ='Formula Audit'!I235 -> 0.065606467 | O160: ='Formula Audit'!J235 -> 0.047810037 | ... Q160: ='Formula Audit'!L235 -> 0.02216342
...

Sheet Valuation & Breakeven
A2: NAVIGATION | B2: ='Control Center'!F6
C4: Valuation Detail
C5: ='Formula Audit'!A3 -> Figures in USD
D6: Planning Case | E6: ='Control Center'!E25 -> Central Case
C7: DCF Valuation | K7: ='Control Center'!F8 -> 2025 | L7: ='Formula Audit'!D9 -> 2026 | M7: ='Formula Audit'!E9 -> 2027 | N7: ='Formula Audit'!F9 -> 2028 | O7: ='Formula Audit'!G9 -> 2029 | P7: ='Formula Audit'!H9 -> 2030 | Q7: ='Formula Audit'!I9 -> 2031 | R7: ='Formula Audit'!J9 -> 2032 | S7: ='Formula Audit'!K9 -> 2033 | T7: ='Formula Audit'!L9 -> 2034
D9: Pre-Tax Income (EBT) | K9: ='Forecast Model'!H242 -> 52202.967 | L9: ='Forecast Model'!I242 -> 35250.266 | M9: ='Forecast Model'!J242 -> 54450.189 | N9: ='Forecast Model'!K242 -> 71432.4 | O9: ='Forecast Model'!L242 -> 78530.743 | P9: ='Forecast Model'!M242 -> 93802.314 | Q9: ='Forecast Model'!N242 -> 101608.16 | R9: ='Forecast Model'!O242 -> 118771.32 | ... T9: ='Forecast Model'!Q242 -> 135350.98
D10: Interest Expense | K10: ='Forecast Model'!H241 -> 4295.1919 | L10: ='Forecast Model'!I241 -> 4113.9472 | M10: ='Forecast Model'!J241 -> 3767.966 | N10: ='Forecast Model'!K241 -> 3421.9849 | O10: ='Forecast Model'!L241 -> 3076.0037 | P10: ='Forecast Model'!M241 -> 2730.0225 | Q10: ='Forecast Model'!N241 -> 2384.0413 | R10: ='Forecast Model'!O241 -> 2038.0601 | ... T10: ='Forecast Model'!Q241 -> 1346.0978
C11: EBIT (Operating Income) | K11: =SUM(K9+K10) -> 56498.159 | L11: =SUM(L9+L10) -> 39364.213 | M11: =SUM(M9+M10) -> 58218.155 | N11: =SUM(N9+N10) -> 74854.384 | O11: =SUM(O9+O10) -> 81606.747 | P11: =SUM(P9+P10) -> 96532.336 | Q11: =SUM(Q9+Q10) -> 103992.2 | R11: =SUM(R9+R10) -> 120809.38 | ... T11: =SUM(T9+T10) -> 136697.08
D12: Less: Cash Tax | K12: ='Forecast Model'!H244 -> 13825.12 | L12: ='Forecast Model'!I244 -> 9335.4689 | M12: ='Forecast Model'!J244 -> 14420.261 | N12: ='Forecast Model'!K244 -> 18917.728 | O12: ='Forecast Model'!L244 -> 20797.611 | P12: ='Forecast Model'!M244 -> 24842.042 | Q12: ='Forecast Model'!N244 -> 26909.294 | R12: ='Forecast Model'!O244 -> 31454.684 | ... T12: ='Forecast Model'!Q244 -> 35845.543
D13: Plus: Depreciation & Amortization | K13: ='Forecast Model'!H234 -> 8660.0892 | L13: ='Forecast Model'!I234 -> 8684.5087 | M13: ='Forecast Model'!J234 -> 9421.7236 | N13: ='Forecast Model'!K234 -> 9853.3504 | O13: ='Forecast Model'!L234 -> 11190.022 | P13: ='Forecast Model'!M234 -> 13056.998 | Q13: ='Forecast Model'!N234 -> 13065.704 | R13: ='Forecast Model'!O234 -> 11986.839 | ... T13: ='Forecast Model'!Q234 -> 9116.2659
C14: EBITDA (Operating) | K14: =K11-K12+K13 -> 51333.127 | L14: =L11-L12+L13 -> 38713.253 | M14: =M11-M12+M13 -> 53219.617 | N14: =N11-N12+N13 -> 65790.007 | O14: =O11-O12+O13 -> 71999.158 | P14: =P11-P12+P13 -> 84747.292 | Q14: =Q11-Q12+Q13 -> 90148.606 | R14: =R11-R12+R13 -> 101341.54 | ... T14: =T11-T12+T13 -> 109967.81
D15: Less: Capital Expenditure | K15: =-'Forecast Model'!H290 -> 20892 | L15: =-'Forecast Model'!I290 -> 8719 | M15: =-'Forecast Model'!J290 -> 10463 | N15: =-'Forecast Model'!K290 -> 10463 | O15: =-'Forecast Model'!L290 -> 13078 | P15: =-'Forecast Model'!M290 -> 15694 | Q15: =-'Forecast Model'!N290 -> 13078 | R15: =-'Forecast Model'!O290 -> 10463 | ... T15: =-'Forecast Model'!Q290 -> 6975
D16: Less: Working Capital Movement | K16: =-SUM('Forecast Model'!H283:H286) -> 0 | L16: =-SUM('Forecast Model'!I283:I286) -> 31250.788 | M16: =-SUM('Forecast Model'!J283:J286) -> 1419.8319 | N16: =-SUM('Forecast Model'!K283:K286) -> 4852.1481 | O16: =-SUM('Forecast Model'!L283:L286) -> 1151.9555 | P16: =-SUM('Forecast Model'!M283:M286) -> -2323.9582 | Q16: =-SUM('Forecast Model'!N283:N286) -> 4722.5592 | R16: =-SUM('Forecast Model'!O283:O286) -> 70.043607 | ... T16: =-SUM('Forecast Model'!Q283:Q286) -> 772.46816
C17: Firm Free Cash Flow (FCFF) | K17: =K14-K15-K16 -> 30441.127 | L17: =L14-L15-L16 -> -1256.5348 | M17: =M14-M15-M16 -> 41336.785 | N17: =N14-N15-N16 -> 50474.859 | O17: =O14-O15-O16 -> 57769.203 | P17: =P14-P15-P16 -> 71377.25 | Q17: =Q14-Q15-Q16 -> 72348.047 | R17: =R14-R15-R16 -> 90808.492 | ... T17: =T14-T15-T16 -> 102220.34
D18: Terminal Worth (EBITDA Multiple Approach) | K18: =K14*$K$26*'Formula Audit'!C12 -> 0 | L18: =L14*$K$26*'Formula Audit'!D12 -> 0 | M18: =M14*$K$26*'Formula Audit'!E12 -> 0 | N18: =N14*$K$26*'Formula Audit'!F12 -> 0 | O18: =O14*$K$26*'Formula Audit'!G12 -> 0 | P18: =P14*$K$26*'Formula Audit'!H12 -> 0 | Q18: =Q14*$K$26*'Formula Audit'!I12 -> 0 | R18: =R14*$K$26*'Formula Audit'!J12 -> 0 | ... T18: =T14*$K$26*'Formula Audit'!L12 -> 351392.99
C19: Net Free Cash Flow | J19: =-K40 -> -292281.45 | K19: =K17+K18 -> 30441.127 | L19: =L17+L18 -> -1256.5348 | M19: =M17+M18 -> 41336.785 | N19: =N17+N18 -> 50474.859 | O19: =O17+O18 -> 57769.203 | P19: =P17+P18 -> 71377.25 | Q19: =Q17+Q18 -> 72348.047 | R19: =R17+R18 -> 90808.492 | ... T19: =T17+T18 -> 453613.33
D21: PV of Terminal Worth | K21: =K18/(1+$E$40)^'Formula Audit'!C13 -> 0 | L21: =L18/(1+$E$40)^'Formula Audit'!D13 -> 0 | M21: =M18/(1+$E$40)^'Formula Audit'!E13 -> 0 | N21: =N18/(1+$E$40)^'Formula Audit'!F13 -> 0 | O21: =O18/(1+$E$40)^'Formula Audit'!G13 -> 0 | P21: =P18/(1+$E$40)^'Formula Audit'!H13 -> 0 | Q21: =Q18/(1+$E$40)^'Formula Audit'!I13 -> 0 | R21: =R18/(1+$E$40)^'Formula Audit'!J13 -> 0 | ... T21: =T18/(1+$E$40)^'Formula Audit'!L13 -> 169548.04
D22: PV of Net Free Cash Flow | K22: =K19/(1+$E$40)^'Formula Audit'!C13 -> 30441.127 | L22: =L19/(1+$E$40)^'Formula Audit'!D13 -> -1158.7982 | M22: =M19/(1+$E$40)^'Formula Audit'!E13 -> 35156.311 | N22: =N19/(1+$E$40)^'Formula Audit'!F13 -> 39589.043 | O22: =O19/(1+$E$40)^'Formula Audit'!G13 -> 41785.882 | P22: =P19/(1+$E$40)^'Formula Audit'!H13 -> 47613.083 | Q22: =Q19/(1+$E$40)^'Formula Audit'!I13 -> 44506.824 | R22: =R19/(1+$E$40)^'Formula Audit'!J13 -> 51518.066 | ... T22: =T19/(1+$E$40)^'Formula Audit'!L13 -> 218869.63
C24: Valuation Detail
C25: WACC Build-Up | G25: Valuation Inputs | M25: Equity Worth Sensitivity
G26: EV / EBITDA Multiple | K26: 3.195417 | O26: Cost of Capital, Weighted Avg. (WACC)
D27: Borrowings to Total Capital | E27: =E43/E45 -> 0.43296286 | G27: Prevailing Price | K27: 10 | M27: EV / EBITDA Multiple
D28: Equity Share of Capital | E28: =E44/E45 -> 0.56703714 | G28: Outstanding Shares | K28: 40000 | P28: =R28-2% -> 0.064343054 | Q28: =R28-1% -> 0.074343054 | R28: =E40 -> 0.084343054 | S28: =R28+1% -> 0.094343054 | T28: =R28+2% -> 0.10434305
C29: Borrowings / Equity | E29: =E27/E28 -> 0.7635529 | N29: =K26-2 -> 1.195417 | O29: x | P29: ='Formula Audit'!N19 -> -679429.15 | Q29: ='Formula Audit'!O19 -> -636892.3 | R29: ='Formula Audit'!P19 -> -597375.89 | S29: ='Formula Audit'!Q19 -> -560622.81 | T29: ='Formula Audit'!R19 -> -526400.69
G30: Fundamental Value | N30: =K26-1 -> 2.195417 | O30: x | P30: ='Formula Audit'!N20 -> -627809.17 | Q30: ='Formula Audit'!O20 -> -585272.32 | R30: ='Formula Audit'!P20 -> -545755.91 | S30: ='Formula Audit'!Q20 -> -509002.83 | T30: ='Formula Audit'!R20 -> -474780.71
D31: Pre-Tax Debt Cost | E31: ='Control Center'!G49 -> 0.06294 | H31: Sum of PV of Free Cash Flows | K31: =SUM(K22:T22) -> 555946.38 | N31: =K26 -> 3.195417 | O31: x | P31: ='Formula Audit'!N21 -> -584879.21 | Q31: ='Formula Audit'!O21 -> -542342.36 | R31: ='Formula Audit'!P21 -> -502825.96 | S31: ='Formula Audit'!Q21 -> -466072.87 | T31: ='Formula Audit'!R21 -> -431850.75
D32: Effective Tax Rate | E32: ='Control Center'!G38 -> 0.264834 | H32: Plus: PV of Terminal Worth | K32: =SUM(K21:T21) -> 169548.04 | N32: =K26+1 -> 4.195417 | O32: x | P32: ='Formula Audit'!N22 -> -549471.88 | Q32: ='Formula Audit'!O22 -> -506935.03 | R32: ='Formula Audit'!P22 -> -467418.62 | S32: ='Formula Audit'!Q22 -> -430665.54 | T32: ='Formula Audit'!R22 -> -396443.42
C33: Post-Tax Debt Cost | E33: =E31*(1-E32) -> 0.046271348 | H33: Less: Net Borrowings | K33: =K38-K39 -> -107718.55 | N33: =K26+2 -> 5.195417 | O33: x | P33: ='Formula Audit'!N23 -> -520570.49 | Q33: ='Formula Audit'!O23 -> -478033.65 | R33: ='Formula Audit'!P23 -> -438517.24 | S33: ='Formula Audit'!Q23 -> -401764.15 | T33: ='Formula Audit'!R23 -> -367542.03
G34: Equity Worth | K34: =K31+K32-K33 -> 833212.98
D35: Risk-Free Rate | E35: 0.024138
D36: Market Risk Premium | E36: 0.073205 | G36: Market Worth
D37: Equity Beta | E37: 1.219518 | H37: Market Capitalization | K37: =K27*K28 -> 400000
C38: Equity Cost | E38: =E35+(E36*E37) -> 0.11341282 | H38: Plus: Borrowings | K38: =E43 -> 70860
H39: Less: Cash Balance | K39: ='Forecast Model'!T191 -> 178578.55
C40: WACC (Discounting Rate) | E40: =(E27*E33)+(E28*E38) -> 0.084343054 | G40: Enterprise Value | K40: =K37+K38-K39 -> 292281.45
C42: Capital Structure (Initial Outlay) | G42: Return Rate
D43: Borrowings | E43: ='Control Center'!G50 -> 70860 | H43: Prevailing Share Price | K43: =K27 -> 10
D44: Shareholder Equity | E44: ='Control Center'!G51 -> 92803 | H44: Upside Potential | K44: =K45-K43 -> 10.830325
C45: Total Amount | E45: =SUM(E43:E44) -> 163663 | H45: Implied Share Price | K45: =K34/K28 -> 20.830325
H46: Target Price Upside Rate | K46: =K44/K43 -> 1.0830325
C47: ='Formula Audit'!C39 -> Attractive Investment | G47: Internal Rate of Return | K47: =IFERROR(IRR(J19:T19),0) -> 0.17364782
A56: NAVIGATION | B56: ='Control Center'!F6
C58: Breakeven Detail
C59: ='Formula Audit'!A3 -> Figures in USD
E60: Planning Case | F60: ='Control Center'!E25 -> Central Case
C61: Breakeven Detail | H61: ='Formula Audit'!C9 -> 2025 | I61: ='Formula Audit'!D9 -> 2026 | J61: ='Formula Audit'!E9 -> 2027 | K61: ='Formula Audit'!F9 -> 2028 | L61: ='Formula Audit'!G9 -> 2029 | M61: ='Formula Audit'!H9 -> 2030 | N61: ='Formula Audit'!I9 -> 2031 | O61: ='Formula Audit'!J9 -> 2032 | ... Q61: ='Formula Audit'!L9 -> 2034
D62: Sales — Total | H62: ='Forecast Model'!H219 -> 402045.22 | I62: ='Forecast Model'!I219 -> 428989.89 | J62: ='Forecast Model'!J219 -> 452948.55 | K62: ='Forecast Model'!K219 -> 473185.84 | L62: ='Forecast Model'!L219 -> 489042.3 | M62: ='Forecast Model'!M219 -> 505430.1 | N62: ='Forecast Model'!N219 -> 516721.41 | O62: ='Forecast Model'!O219 -> 528264.97 | ... Q62: ='Forecast Model'!Q219 -> 552131.49
D63: Contribution | H63: =H62-H70 -> 149382.16 | I63: =I62-I70 -> 132248.21 | J63: =J62-J70 -> 151102.15 | K63: =K62-K70 -> 167738.38 | L63: =L62-L70 -> 174490.75 | M63: =M62-M70 -> 189416.34 | N63: =N62-N70 -> 196876.2 | O63: =O62-O70 -> 213693.38 | ... Q63: =Q62-Q70 -> 229581.08
C64: Contribution Margin Rate | H64: =IFERROR(H63/H62,"") -> 0.37155561 | I64: =IFERROR(I63/I62,"") -> 0.30827816 | J64: =IFERROR(J63/J62,"") -> 0.33359673 | K64: =IFERROR(K63/K62,"") -> 0.35448733 | L64: =IFERROR(L63/L62,"") -> 0.35680093 | M64: =IFERROR(M63/M62,"") -> 0.37476267 | N64: =IFERROR(N63/N62,"") -> 0.38101033 | O64: =IFERROR(O63/O62,"") -> 0.40451931 | ... Q64: =IFERROR(Q63/Q62,"") -> 0.41580871
D66: Sales Costs | H66: ='Forecast Model'!H225 -> 222836.1 | I66: ='Forecast Model'!I225 -> 265471.71 | J66: ='Forecast Model'!J225 -> 271159.19 | K66: ='Forecast Model'!K225 -> 273378.5 | L66: ='Forecast Model'!L225 -> 280401.48 | M66: ='Forecast Model'!M225 -> 279227.33 | N66: ='Forecast Model'!N225 -> 285465.27 | O66: ='Forecast Model'!O225 -> 280794.35 | ... Q66: ='Forecast Model'!Q225 -> 290659.27
D67: Sales & Marketing | H67: ='Forecast Model'!H231 -> 18330.85 | I67: ='Forecast Model'!I231 -> 19559.365 | J67: ='Forecast Model'!J231 -> 18070.382 | K67: ='Forecast Model'!K231 -> 18877.749 | L67: ='Forecast Model'!L231 -> 19510.342 | M67: ='Forecast Model'!M231 -> 20164.134 | N67: ='Forecast Model'!N231 -> 17669.289 | O67: ='Forecast Model'!O231 -> 18064.021 | ... Q67: ='Forecast Model'!Q231 -> 18880.136
D68: Card Processing Fees | H68: ='Forecast Model'!H233 -> 2836.027 | I68: ='Forecast Model'!I233 -> 3026.0947 | J68: ='Forecast Model'!J233 -> 3195.0991 | K68: ='Forecast Model'!K233 -> 3337.8529 | L68: ='Forecast Model'!L233 -> 3449.7043 | M68: ='Forecast Model'!M233 -> 3565.3039 | N68: ='Forecast Model'!N233 -> 3644.9528 | O68: ='Forecast Model'!O233 -> 3726.3811 | ... Q68: ='Forecast Model'!Q233 -> 3894.7355
D69: Depreciation & Amortization | H69: ='Forecast Model'!H234 -> 8660.0892 | I69: ='Forecast Model'!I234 -> 8684.5087 | J69: ='Forecast Model'!J234 -> 9421.7236 | K69: ='Forecast Model'!K234 -> 9853.3504 | L69: ='Forecast Model'!L234 -> 11190.022 | M69: ='Forecast Model'!M234 -> 13056.998 | N69: ='Forecast Model'!N234 -> 13065.704 | O69: ='Forecast Model'!O234 -> 11986.839 | ... Q69: ='Forecast Model'!Q234 -> 9116.2659
C70: Variable Cost Base | H70: =SUM(H66:H69) -> 252663.07 | I70: =SUM(I66:I69) -> 296741.68 | J70: =SUM(J66:J69) -> 301846.39 | K70: =SUM(K66:K69) -> 305447.45 | L70: =SUM(L66:L69) -> 314551.55 | M70: =SUM(M66:M69) -> 316013.77 | N70: =SUM(N66:N69) -> 319845.21 | O70: =SUM(O66:O69) -> 314571.59 | ... Q70: =SUM(Q66:Q69) -> 322550.41
D72: Salaries & Benefits | H72: ='Forecast Model'!H230 -> 58749 | I72: ='Forecast Model'!I230 -> 58749 | J72: ='Forecast Model'!J230 -> 58749 | K72: ='Forecast Model'!K230 -> 58749 | L72: ='Forecast Model'!L230 -> 58749 | M72: ='Forecast Model'!M230 -> 58749 | N72: ='Forecast Model'!N230 -> 58749 | O72: ='Forecast Model'!O230 -> 58749 | ... Q72: ='Forecast Model'!Q230 -> 58749
D73: General & Administrative | H73: ='Forecast Model'!H232 -> 34135 | I73: ='Forecast Model'!I232 -> 34135 | J73: ='Forecast Model'!J232 -> 34135 | K73: ='Forecast Model'!K232 -> 34135 | L73: ='Forecast Model'!L232 -> 34135 | M73: ='Forecast Model'!M232 -> 34135 | N73: ='Forecast Model'!N232 -> 34135 | O73: ='Forecast Model'!O232 -> 34135 | ... Q73: ='Forecast Model'!Q232 -> 34135
C74: Fixed Cost Base | H74: =SUM(H72:H73) -> 92884 | I74: =SUM(I72:I73) -> 92884 | J74: =SUM(J72:J73) -> 92884 | K74: =SUM(K72:K73) -> 92884 | L74: =SUM(L72:L73) -> 92884 | M74: =SUM(M72:M73) -> 92884 | N74: =SUM(N72:N73) -> 92884 | O74: =SUM(O72:O73) -> 92884 | ... Q74: =SUM(Q72:Q73) -> 92884
D76: Annual Break-Even | H76: =H74/H64 -> 249986.81 | I76: =IFERROR(I74/I64,"") -> 301299.32 | J76: =IFERROR(J74/J64,"") -> 278431.99 | K76: =IFERROR(K74/K64,"") -> 262023.47 | L76: =IFERROR(L74/L64,"") -> 260324.43 | M76: =IFERROR(M74/M64,"") -> 247847.52 | N76: =IFERROR(N74/N64,"") -> 243783.41 | O76: =IFERROR(O74/O64,"") -> 229615.74 | P76: =IFERROR(P74/P64,"") -> 227923.16 | Q76: =IFERROR(Q74/Q64,"") -> 223381.56
D77: Monthly Break-Even | H77: =IFERROR(H76/12,"") -> 20832.234 | I77: =IFERROR(I76/12,"") -> 25108.277 | J77: =IFERROR(J76/12,"") -> 23202.666 | K77: =IFERROR(K76/12,"") -> 21835.289 | L77: =IFERROR(L76/12,"") -> 21693.703 | M77: =IFERROR(M76/12,"") -> 20653.96 | N77: =IFERROR(N76/12,"") -> 20315.285 | O77: =IFERROR(O76/12,"") -> 19134.645 | ... Q77: =IFERROR(Q76/12,"") -> 18615.13
E80: Fiscal Year (Yr) | F80: 2027
D81: Units Sold | F81: ='Formula Audit'!M176 -> 1553.5965
D82: Fixed Cost Base | F82: ='Formula Audit'!M177 -> 92884
D83: Variable Cost Base | F83: ='Formula Audit'!M178 -> 194.2888
D84: Selling Price | F84: ='Formula Audit'!M179 -> 291.54839
D85: Contribution Profit Margin | F85: ='Formula Audit'!M180 -> 97.259588
D86: Contribution Margin Rate | F86: ='Formula Audit'!M181 -> 0.33359673
D87: Breakeven Volume (Units) | F87: ='Formula Audit'!M182 -> 955.01124
D88: ="Breakeven Point"&" "&"("&'Control Center'!F10&")" -> Breakeven Point (USD) | F88: ='Formula Audit'!M183 -> 278431.99

Sheet Formula Audit
A3: ="Figures in"&" "&'Control Center'!F10 -> Figures in USD | T3: WACC Rate | U3: EV / EBITDA Multiple | V3: Equity Worth
A4: Planning Cases | C4: Central Case | T4: =$A$19 -> 0.064343054 | U4: =$A$14 -> 1.195417 | V4: =N19 -> -679429.15
C5: Upside Case | T5: =$A$19 -> 0.064343054 | U5: =$A$15 -> 2.195417 | V5: =N20 -> -627809.17
C6: Downside Case | T6: =$A$19 -> 0.064343054 | U6: =$A$16 -> 3.195417 | V6: =N21 -> -584879.21
A7: Summary Overview | T7: =$A$19 -> 0.064343054 | U7: =$A$17 -> 4.195417 | V7: =N22 -> -549471.88
A8: Headline Financial | C8: =IF(('Control Center'!$F$9-COUNTBLANK($B2:B2))>=0,1,0) -> 1 | D8: =IF(('Control Center'!$F$9-COUNTBLANK($B2:C2))>=0,1,0) -> 1 | E8: =IF(('Control Center'!$F$9-COUNTBLANK($B2:D2))>=0,1,0) -> 1 | F8: =IF(('Control Center'!$F$9-COUNTBLANK($B2:E2))>=0,1,0) -> 1 | G8: =IF(('Control Center'!$F$9-COUNTBLANK($B2:F2))>=0,1,0) -> 1 | H8: =IF(('Control Center'!$F$9-COUNTBLANK($B2:G2))>=0,1,0) -> 1 | I8: =IF(('Control Center'!$F$9-COUNTBLANK($B2:H2))>=0,1,0) -> 1 | J8: =IF(('Control Center'!$F$9-COUNTBLANK($B2:I2))>=0,1,0) -> 1 | ... L8: =IF(('Control Center'!$F$9-COUNTBLANK($B2:K2))>=0,1,0) -> 1 | T8: =$A$19 -> 0.064343054 | U8: =$A$18 -> 5.195417 | V8: =N23 -> -520570.49
A9: Fiscal Years | C9: ='Control Center'!$F$8 -> 2025 | D9: =(C9+1)*D$8 -> 2026 | E9: =(D9+1)*E$8 -> 2027 | F9: =(E9+1)*F$8 -> 2028 | G9: =(F9+1)*G$8 -> 2029 | H9: =(G9+1)*H$8 -> 2030 | I9: =(H9+1)*I$8 -> 2031 | J9: =(I9+1)*J$8 -> 2032 | K9: =(J9+1)*K$8 -> 2033 | L9: =(K9+1)*L$8 -> 2034 | T9: =$A$20 -> 0.074343054 | U9: =$A$14 -> 1.195417 | V9: =O19 -> -636892.3
T10: =$A$20 -> 0.074343054 | U10: =$A$15 -> 2.195417 | V10: =O20 -> -585272.32
A11: Valuation Analysis | T11: =$A$20 -> 0.074343054 | U11: =$A$16 -> 3.195417 | V11: =O21 -> -542342.36
A12: Terminal Worth | C12: =IF(COUNT($C8:C8)='Control Center'!$F$9,1,0) -> 0 | D12: =IF(COUNT($C8:D8)='Control Center'!$F$9,1,0) -> 0 | E12: =IF(COUNT($C8:E8)='Control Center'!$F$9,1,0) -> 0 | F12: =IF(COUNT($C8:F8)='Control Center'!$F$9,1,0) -> 0 | G12: =IF(COUNT($C8:G8)='Control Center'!$F$9,1,0) -> 0 | H12: =IF(COUNT($C8:H8)='Control Center'!$F$9,1,0) -> 0 | I12: =IF(COUNT($C8:I8)='Control Center'!$F$9,1,0) -> 0 | J12: =IF(COUNT($C8:J8)='Control Center'!$F$9,1,0) -> 0 | ... L12: =IF(COUNT($C8:L8)='Control Center'!$F$9,1,0) -> 1 | T12: =$A$20 -> 0.074343054 | U12: =$A$17 -> 4.195417 | V12: =O22 -> -506935.03
A13: Reporting Period | C13: 0 | D13: =COUNT($C$8:C8)*C8 -> 1 | E13: =COUNT($C$8:D8)*D8 -> 2 | F13: =COUNT($C$8:E8)*E8 -> 3 | G13: =COUNT($C$8:F8)*F8 -> 4 | H13: =COUNT($C$8:G8)*G8 -> 5 | I13: =COUNT($C$8:H8)*H8 -> 6 | J13: =COUNT($C$8:I8)*I8 -> 7 | K13: =COUNT($C$8:J8)*J8 -> 8 | L13: =COUNT($C$8:K8)*K8 -> 9 | T13: =$A$20 -> 0.074343054 | U13: =$A$18 -> 5.195417 | V13: =O23 -> -478033.65
A14: ='Valuation & Breakeven'!N29 -> 1.195417 | B14: Terminal Worth | C14: ='Valuation & Breakeven'!K$14*$A14*'Formula Audit'!C$12 -> 0 | D14: ='Valuation & Breakeven'!L$14*$A14*'Formula Audit'!D$12 -> 0 | E14: ='Valuation & Breakeven'!M$14*$A14*'Formula Audit'!E$12 -> 0 | F14: ='Valuation & Breakeven'!N$14*$A14*'Formula Audit'!F$12 -> 0 | G14: ='Valuation & Breakeven'!O$14*$A14*'Formula Audit'!G$12 -> 0 | H14: ='Valuation & Breakeven'!P$14*$A14*'Formula Audit'!H$12 -> 0 | I14: ='Valuation & Breakeven'!Q$14*$A14*'Formula Audit'!I$12 -> 0 | J14: ='Valuation & Breakeven'!R$14*$A14*'Formula Audit'!J$12 -> 0 | ... L14: ='Valuation & Breakeven'!T$14*$A14*'Formula Audit'!L$12 -> 131457.38 | T14: =$A$21 -> 0.084343054 | U14: =$A$14 -> 1.195417 | V14: =P19 -> -597375.89
A15: ='Valuation & Breakeven'!N30 -> 2.195417 | B15: Terminal Worth | C15: ='Valuation & Breakeven'!K$14*$A15*'Formula Audit'!C$12 -> 0 | D15: ='Valuation & Breakeven'!L$14*$A15*'Formula Audit'!D$12 -> 0 | E15: ='Valuation & Breakeven'!M$14*$A15*'Formula Audit'!E$12 -> 0 | F15: ='Valuation & Breakeven'!N$14*$A15*'Formula Audit'!F$12 -> 0 | G15: ='Valuation & Breakeven'!O$14*$A15*'Formula Audit'!G$12 -> 0 | H15: ='Valuation & Breakeven'!P$14*$A15*'Formula Audit'!H$12 -> 0 | I15: ='Valuation & Breakeven'!Q$14*$A15*'Formula Audit'!I$12 -> 0 | J15: ='Valuation & Breakeven'!R$14*$A15*'Formula Audit'!J$12 -> 0 | ... L15: ='Valuation & Breakeven'!T$14*$A15*'Formula Audit'!L$12 -> 241425.19 | T15: =$A$21 -> 0.084343054 | U15: =$A$15 -> 2.195417 | V15: =P20 -> -545755.91
A16: ='Valuation & Breakeven'!N31 -> 3.195417 | B16: Terminal Worth | C16: ='Valuation & Breakeven'!K$14*$A16*'Formula Audit'!C$12 -> 0 | D16: ='Valuation & Breakeven'!L$14*$A16*'Formula Audit'!D$12 -> 0 | E16: ='Valuation & Breakeven'!M$14*$A16*'Formula Audit'!E$12 -> 0 | F16: ='Valuation & Breakeven'!N$14*$A16*'Formula Audit'!F$12 -> 0 | G16: ='Valuation & Breakeven'!O$14*$A16*'Formula Audit'!G$12 -> 0 | H16: ='Valuation & Breakeven'!P$14*$A16*'Formula Audit'!H$12 -> 0 | I16: ='Valuation & Breakeven'!Q$14*$A16*'Formula Audit'!I$12 -> 0 | J16: ='Valuation & Breakeven'!R$14*$A16*'Formula Audit'!J$12 -> 0 | ... L16: ='Valuation & Breakeven'!T$14*$A16*'Formula Audit'!L$12 -> 351392.99 | T16: =$A$21 -> 0.084343054 | U16: =$A$16 -> 3.195417 | V16: =P21 -> -502825.96
A17: ='Valuation & Breakeven'!N32 -> 4.195417 | B17: Terminal Worth | C17: ='Valuation & Breakeven'!K$14*$A17*'Formula Audit'!C$12 -> 0 | D17: ='Valuation & Breakeven'!L$14*$A17*'Formula Audit'!D$12 -> 0 | E17: ='Valuation & Breakeven'!M$14*$A17*'Formula Audit'!E$12 -> 0 | F17: ='Valuation & Breakeven'!N$14*$A17*'Formula Audit'!F$12 -> 0 | G17: ='Valuation & Breakeven'!O$14*$A17*'Formula Audit'!G$12 -> 0 | H17: ='Valuation & Breakeven'!P$14*$A17*'Formula Audit'!H$12 -> 0 | I17: ='Valuation & Breakeven'!Q$14*$A17*'Formula Audit'!I$12 -> 0 | J17: ='Valuation & Breakeven'!R$14*$A17*'Formula Audit'!J$12 -> 0 | ... L17: ='Valuation & Breakeven'!T$14*$A17*'Formula Audit'!L$12 -> 461360.8 | T17: =$A$21 -> 0.084343054 | U17: =$A$17 -> 4.195417 | V17: =P22 -> -467418.62
A18: ='Valuation & Breakeven'!N33 -> 5.195417 | B18: Terminal Worth | C18: ='Valuation & Breakeven'!K$14*$A18*'Formula Audit'!C$12 -> 0 | D18: ='Valuation & Breakeven'!L$14*$A18*'Formula Audit'!D$12 -> 0 | E18: ='Valuation & Breakeven'!M$14*$A18*'Formula Audit'!E$12 -> 0 | F18: ='Valuation & Breakeven'!N$14*$A18*'Formula Audit'!F$12 -> 0 | G18: ='Valuation & Breakeven'!O$14*$A18*'Formula Audit'!G$12 -> 0 | H18: ='Valuation & Breakeven'!P$14*$A18*'Formula Audit'!H$12 -> 0 | I18: ='Valuation & Breakeven'!Q$14*$A18*'Formula Audit'!I$12 -> 0 | J18: ='Valuation & Breakeven'!R$14*$A18*'Formula Audit'!J$12 -> 0 | ... L18: ='Valuation & Breakeven'!T$14*$A18*'Formula Audit'!L$12 -> 571328.61 | M18: ='Valuation & Breakeven'!$K$33 -> -107718.55 | N18: -862145.81 | O18: -819608.96 | P18: -780092.56 | Q18: -743339.47 | R18: -709117.35 | T18: =$A$21 -> 0.084343054 | U18: =$A$18 -> 5.195417 | V18: =P23 -> -438517.24
A19: ='Valuation & Breakeven'!P28 -> 0.064343054 | B19: PV of Terminal Worth | C19: =C14/(1+$A19)^'Formula Audit'!C$13 -> 0 | D19: =D14/(1+$A19)^'Formula Audit'!D$13 -> 0 | E19: =E14/(1+$A19)^'Formula Audit'!E$13 -> 0 | F19: =F14/(1+$A19)^'Formula Audit'!F$13 -> 0 | G19: =G14/(1+$A19)^'Formula Audit'!G$13 -> 0 | H19: =H14/(1+$A19)^'Formula Audit'!H$13 -> 0 | I19: =I14/(1+$A19)^'Formula Audit'!I$13 -> 0 | J19: =J14/(1+$A19)^'Formula Audit'!J$13 -> 0 | ... L19: =L14/(1+$A19)^'Formula Audit'!L$13 -> 74998.109 | M19: =SUM(C19:L19) -> 74998.109 | N19: =N$18+$M19-$M$18 -> -679429.15 | O19: =O$18+$M19-$M$18 -> -636892.3 | P19: =P$18+$M19-$M$18 -> -597375.89 | Q19: =Q$18+$M19-$M$18 -> -560622.81 | R19: =R$18+$M19-$M$18 -> -526400.69 | T19: =$A$22 -> 0.094343054 | U19: =$A$14 -> 1.195417 | V19: =Q19 -> -560622.81
A20: ='Valuation & Breakeven'!Q28 -> 0.074343054 | B20: PV of Terminal Worth | C20: =C15/(1+$A20)^'Formula Audit'!C$13 -> 0 | D20: =D15/(1+$A20)^'Formula Audit'!D$13 -> 0 | E20: =E15/(1+$A20)^'Formula Audit'!E$13 -> 0 | F20: =F15/(1+$A20)^'Formula Audit'!F$13 -> 0 | G20: =G15/(1+$A20)^'Formula Audit'!G$13 -> 0 | H20: =H15/(1+$A20)^'Formula Audit'!H$13 -> 0 | I20: =I15/(1+$A20)^'Formula Audit'!I$13 -> 0 | J20: =J15/(1+$A20)^'Formula Audit'!J$13 -> 0 | ... L20: =L15/(1+$A20)^'Formula Audit'!L$13 -> 126618.09 | M20: =SUM(C20:L20) -> 126618.09 | N20: =N$18+$M20-$M$18 -> -627809.17 | O20: =O$18+$M20-$M$18 -> -585272.32 | P20: =P$18+$M20-$M$18 -> -545755.91 | Q20: =Q$18+$M20-$M$18 -> -509002.83 | R20: =R$18+$M20-$M$18 -> -474780.71 | T20: =$A$22 -> 0.094343054 | U20: =$A$15 -> 2.195417 | V20: =Q20 -> -509002.83
A21: ='Valuation & Breakeven'!R28 -> 0.084343054 | B21: PV of Terminal Worth | C21: =C16/(1+$A21)^'Formula Audit'!C$13 -> 0 | D21: =D16/(1+$A21)^'Formula Audit'!D$13 -> 0 | E21: =E16/(1+$A21)^'Formula Audit'!E$13 -> 0 | F21: =F16/(1+$A21)^'Formula Audit'!F$13 -> 0 | G21: =G16/(1+$A21)^'Formula Audit'!G$13 -> 0 | H21: =H16/(1+$A21)^'Formula Audit'!H$13 -> 0 | I21: =I16/(1+$A21)^'Formula Audit'!I$13 -> 0 | J21: =J16/(1+$A21)^'Formula Audit'!J$13 -> 0 | ... L21: =L16/(1+$A21)^'Formula Audit'!L$13 -> 169548.04 | M21: =SUM(C21:L21) -> 169548.04 | N21: =N$18+$M21-$M$18 -> -584879.21 | O21: =O$18+$M21-$M$18 -> -542342.36 | P21: =P$18+$M21-$M$18 -> -502825.96 | Q21: =Q$18+$M21-$M$18 -> -466072.87 | R21: =R$18+$M21-$M$18 -> -431850.75 | T21: =$A$22 -> 0.094343054 | U21: =$A$16 -> 3.195417 | V21: =Q21 -> -466072.87
A22: ='Valuation & Breakeven'!S28 -> 0.094343054 | B22: PV of Terminal Worth | C22: =C17/(1+$A22)^'Formula Audit'!C$13 -> 0 | D22: =D17/(1+$A22)^'Formula Audit'!D$13 -> 0 | E22: =E17/(1+$A22)^'Formula Audit'!E$13 -> 0 | F22: =F17/(1+$A22)^'Formula Audit'!F$13 -> 0 | G22: =G17/(1+$A22)^'Formula Audit'!G$13 -> 0 | H22: =H17/(1+$A22)^'Formula Audit'!H$13 -> 0 | I22: =I17/(1+$A22)^'Formula Audit'!I$13 -> 0 | J22: =J17/(1+$A22)^'Formula Audit'!J$13 -> 0 | ... L22: =L17/(1+$A22)^'Formula Audit'!L$13 -> 204955.38 | M22: =SUM(C22:L22) -> 204955.38 | N22: =N$18+$M22-$M$18 -> -549471.88 | O22: =O$18+$M22-$M$18 -> -506935.03 | P22: =P$18+$M22-$M$18 -> -467418.62 | Q22: =Q$18+$M22-$M$18 -> -430665.54 | R22: =R$18+$M22-$M$18 -> -396443.42 | T22: =$A$22 -> 0.094343054 | U22: =$A$17 -> 4.195417 | V22: =Q22 -> -430665.54
A23: ='Valuation & Breakeven'!T28 -> 0.10434305 | B23: PV of Terminal Worth | C23: =C18/(1+$A23)^'Formula Audit'!C$13 -> 0 | D23: =D18/(1+$A23)^'Formula Audit'!D$13 -> 0 | E23: =E18/(1+$A23)^'Formula Audit'!E$13 -> 0 | F23: =F18/(1+$A23)^'Formula Audit'!F$13 -> 0 | G23: =G18/(1+$A23)^'Formula Audit'!G$13 -> 0 | H23: =H18/(1+$A23)^'Formula Audit'!H$13 -> 0 | I23: =I18/(1+$A23)^'Formula Audit'!I$13 -> 0 | J23: =J18/(1+$A23)^'Formula Audit'!J$13 -> 0 | ... L23: =L18/(1+$A23)^'Formula Audit'!L$13 -> 233856.76 | M23: =SUM(C23:L23) -> 233856.76 | N23: =N$18+$M23-$M$18 -> -520570.49 | O23: =O$18+$M23-$M$18 -> -478033.65 | P23: =P$18+$M23-$M$18 -> -438517.24 | Q23: =Q$18+$M23-$M$18 -> -401764.15 | R23: =R$18+$M23-$M$18 -> -367542.03 | T23: =$A$22 -> 0.094343054 | U23: =$A$18 -> 5.195417 | V23: =Q23 -> -401764.15
A24: ='Valuation & Breakeven'!P28 -> 0.064343054 | B24: PV of Net Free Cash Flow | C24: ='Valuation & Breakeven'!K$19/(1+'Formula Audit'!$A24)^'Formula Audit'!C$13 -> 30441.127 | D24: ='Valuation & Breakeven'!L$19/(1+'Formula Audit'!$A24)^'Formula Audit'!D$13 -> -1180.5731 | E24: ='Valuation & Breakeven'!M$19/(1+'Formula Audit'!$A24)^'Formula Audit'!E$13 -> 36489.964 | F24: ='Valuation & Breakeven'!N$19/(1+'Formula Audit'!$A24)^'Formula Audit'!F$13 -> 41862.988 | G24: ='Valuation & Breakeven'!O$19/(1+'Formula Audit'!$A24)^'Formula Audit'!G$13 -> 45016.306 | H24: ='Valuation & Breakeven'!P$19/(1+'Formula Audit'!$A24)^'Formula Audit'!H$13 -> 52257.865 | I24: ='Valuation & Breakeven'!Q$19/(1+'Formula Audit'!$A24)^'Formula Audit'!I$13 -> 49766.492 | J24: ='Valuation & Breakeven'!R$19/(1+'Formula Audit'!$A24)^'Formula Audit'!J$13 -> 58688.776 | ... L24: ='Valuation & Breakeven'!T$19/(1+'Formula Audit'!$A24)^'Formula Audit'!L$13 -> 258792.17 | M24: =SUM(C24:L24) -> 627408.7 | T24: =$A$23 -> 0.10434305 | U24: =$A$14 -> 1.195417 | V24: =R19 -> -526400.69
A25: ='Valuation & Breakeven'!Q28 -> 0.074343054 | B25: PV of Net Free Cash Flow | C25: ='Valuation & Breakeven'!K$19/(1+'Formula Audit'!$A25)^'Formula Audit'!C$13 -> 30441.127 | D25: ='Valuation & Breakeven'!L$19/(1+'Formula Audit'!$A25)^'Formula Audit'!D$13 -> -1169.5843 | E25: ='Valuation & Breakeven'!M$19/(1+'Formula Audit'!$A25)^'Formula Audit'!E$13 -> 35813.827 | F25: ='Valuation & Breakeven'!N$19/(1+'Formula Audit'!$A25)^'Formula Audit'!F$13 -> 40704.851 | G25: ='Valuation & Breakeven'!O$19/(1+'Formula Audit'!$A25)^'Formula Audit'!G$13 -> 43363.513 | H25: ='Valuation & Breakeven'!P$19/(1+'Formula Audit'!$A25)^'Formula Audit'!H$13 -> 49870.637 | I25: ='Valuation & Breakeven'!Q$19/(1+'Formula Audit'!$A25)^'Formula Audit'!I$13 -> 47051.008 | J25: ='Valuation & Breakeven'!R$19/(1+'Formula Audit'!$A25)^'Formula Audit'!J$13 -> 54969.983 | ... L25: ='Valuation & Breakeven'!T$19/(1+'Formula Audit'!$A25)^'Formula Audit'!L$13 -> 237902.49 | M25: =SUM(C25:L25) -> 590237.15 | T25: =$A$23 -> 0.10434305 | U25: =$A$15 -> 2.195417 | V25: =R20 -> -474780.71
A26: ='Valuation & Breakeven'!R28 -> 0.084343054 | B26: PV of Net Free Cash Flow | C26: ='Valuation & Breakeven'!K$19/(1+'Formula Audit'!$A26)^'Formula Audit'!C$13 -> 30441.127 | D26: ='Valuation & Breakeven'!L$19/(1+'Formula Audit'!$A26)^'Formula Audit'!D$13 -> -1158.7982 | E26: ='Valuation & Breakeven'!M$19/(1+'Formula Audit'!$A26)^'Formula Audit'!E$13 -> 35156.311 | F26: ='Valuation & Breakeven'!N$19/(1+'Formula Audit'!$A26)^'Formula Audit'!F$13 -> 39589.043 | G26: ='Valuation & Breakeven'!O$19/(1+'Formula Audit'!$A26)^'Formula Audit'!G$13 -> 41785.882 | H26: ='Valuation & Breakeven'!P$19/(1+'Formula Audit'!$A26)^'Formula Audit'!H$13 -> 47613.083 | I26: ='Valuation & Breakeven'!Q$19/(1+'Formula Audit'!$A26)^'Formula Audit'!I$13 -> 44506.824 | J26: ='Valuation & Breakeven'!R$19/(1+'Formula Audit'!$A26)^'Formula Audit'!J$13 -> 51518.066 | ... L26: ='Valuation & Breakeven'!T$19/(1+'Formula Audit'!$A26)^'Formula Audit'!L$13 -> 218869.63 | M26: =SUM(C26:L26) -> 555946.38 | T26: =$A$23 -> 0.10434305 | U26: =$A$16 -> 3.195417 | V26: =R21 -> -431850.75
A27: ='Valuation & Breakeven'!S28 -> 0.094343054 | B27: PV of Net Free Cash Flow | C27: ='Valuation & Breakeven'!K$19/(1+'Formula Audit'!$A27)^'Formula Audit'!C$13 -> 30441.127 | D27: ='Valuation & Breakeven'!L$19/(1+'Formula Audit'!$A27)^'Formula Audit'!D$13 -> -1148.2093 | E27: ='Valuation & Breakeven'!M$19/(1+'Formula Audit'!$A27)^'Formula Audit'!E$13 -> 34516.736 | F27: ='Valuation & Breakeven'!N$19/(1+'Formula Audit'!$A27)^'Formula Audit'!F$13 -> 38513.648 | G27: ='Valuation & Breakeven'!O$19/(1+'Formula Audit'!$A27)^'Formula Audit'!G$13 -> 40279.348 | H27: ='Valuation & Breakeven'!P$19/(1+'Formula Audit'!$A27)^'Formula Audit'!H$13 -> 45477.06 | I27: ='Valuation & Breakeven'!Q$19/(1+'Formula Audit'!$A27)^'Formula Audit'!I$13 -> 42121.701 | J27: ='Valuation & Breakeven'!R$19/(1+'Formula Audit'!$A27)^'Formula Audit'!J$13 -> 48311.672 | ... L27: ='Valuation & Breakeven'!T$19/(1+'Formula Audit'!$A27)^'Formula Audit'!L$13 -> 201513.64 | M27: =SUM(C27:L27) -> 524279.72 | T27: =$A$23 -> 0.10434305 | U27: =$A$17 -> 4.195417 | V27: =R22 -> -396443.42
A28: ='Valuation & Breakeven'!T28 -> 0.10434305 | B28: PV of Net Free Cash Flow | C28: ='Valuation & Breakeven'!K$19/(1+'Formula Audit'!$A28)^'Formula Audit'!C$13 -> 30441.127 | D28: ='Valuation & Breakeven'!L$19/(1+'Formula Audit'!$A28)^'Formula Audit'!D$13 -> -1137.812 | E28: ='Valuation & Breakeven'!M$19/(1+'Formula Audit'!$A28)^'Formula Audit'!E$13 -> 33894.458 | F28: ='Valuation & Breakeven'!N$19/(1+'Formula Audit'!$A28)^'Formula Audit'!F$13 -> 37476.852 | G28: ='Valuation & Breakeven'!O$19/(1+'Formula Audit'!$A28)^'Formula Audit'!G$13 -> 38840.102 | H28: ='Valuation & Breakeven'!P$19/(1+'Formula Audit'!$A28)^'Formula Audit'!H$13 -> 43455.004 | I28: ='Valuation & Breakeven'!Q$19/(1+'Formula Audit'!$A28)^'Formula Audit'!I$13 -> 39884.375 | J28: ='Valuation & Breakeven'!R$19/(1+'Formula Audit'!$A28)^'Formula Audit'!J$13 -> 45331.327 | ... L28: ='Valuation & Breakeven'!T$19/(1+'Formula Audit'!$A28)^'Formula Audit'!L$13 -> 185673.44 | M28: =SUM(C28:L28) -> 495005.91 | T28: =$A$23 -> 0.10434305 | U28: =$A$18 -> 5.195417 | V28: =R23 -> -367542.03
C30: x | D30: x | E30: x | F30: x | G30: x | H30: x | I30: x | J30: x | K30: x | L30: x
B31: Reporting Period | C31: =C9 -> 2025 | D31: =D9 -> 2026 | E31: =E9 -> 2027 | F31: =F9 -> 2028 | G31: =G9 -> 2029 | H31: =H9 -> 2030 | I31: =I9 -> 2031 | J31: =J9 -> 2032 | ... L31: =L9 -> 2034
B32: Cumulative Cash Position | C32: =Outputs!E16 -> 178578.55 | D32: =Outputs!F16 -> 163839.58 | E32: =Outputs!G16 -> 189931.21 | F32: =Outputs!H16 -> 223641.76 | G32: =Outputs!I16 -> 264213.03 | H32: =Outputs!J16 -> 317061.08 | I32: =Outputs!K16 -> 370368.6 | J32: =Outputs!L16 -> 440597.54 | ... L32: =Outputs!N16 -> 591162.38
B33: delta | C33: =C32 -> 178578.55 | D33: =D32-C32 -> -14738.971 | E33: =E32-D32 -> 26091.628 | F33: =F32-E32 -> 33710.549 | G33: =G32-F32 -> 40571.273 | H33: =H32-G32 -> 52848.046 | I33: =I32-H32 -> 53307.519 | J33: =J32-I32 -> 70228.937 | K33: =K32-J32 -> 70053.017 | L33: =L32-K32 -> 80511.823
B34: Revenue (Net) | C34: =Outputs!E9 -> 402045.22 | D34: =Outputs!F9 -> 428989.89 | E34: =Outputs!G9 -> 452948.55 | F34: =Outputs!H9 -> 473185.84 | G34: =Outputs!I9 -> 489042.3 | H34: =Outputs!J9 -> 505430.1 | I34: =Outputs!K9 -> 516721.41 | J34: =Outputs!L9 -> 528264.97 | ... L34: =Outputs!N9 -> 552131.49
B35: EBITDA (Operating) | C35: 0 | D35: -92884 | E35: -92884 | F35: -92884 | G35: -92884 | H35: -92884 | I35: -92884 | J35: -92884 | K35: -92884 | L35: -92884
B36: EV / Revenue | C36: =Outputs!E18 -> 0.72698649 | D36: =Outputs!F18 -> 0.68132478 | E36: =Outputs!G18 -> 0.6452862 | F36: =Outputs!H18 -> 0.61768849 | G36: =Outputs!I18 -> 0.59766088 | H36: =Outputs!J18 -> 0.57828262 | I36: =Outputs!K18 -> 0.56564609 | J36: =Outputs!L18 -> 0.55328569 | ... L36: =Outputs!N18 -> 0.52936927
B37: EV / EBITDA | C37: =Outputs!E19 -> 4.4857168 | D37: =Outputs!F19 -> 6.0830223 | E37: =Outputs!G19 -> 4.3211409 | F37: =Outputs!H19 -> 3.4504694 | G37: =Outputs!I19 -> 3.1496942 | H37: =Outputs!J19 -> 2.6670611 | I37: =Outputs!K19 -> 2.4968964 | J37: =Outputs!L19 -> 2.2009772 | ... L37: =Outputs!N19 -> 2.0044903
B39: IRR-Based Valuation | C39: =IF('Valuation & Breakeven'!$K$47 >= 15%, "Attractive Investment", IF('Valuation & Breakeven'!$K$47 >= 10%, "Adequate Investment", IF('Valuation & Breakeven'!$K$47 >= 5%, "Modest Return", "Not Advised"))) -> Attractive Investment
A41: Revenue (Net) | C41: January | D41: February | E41: March | F41: April | G41: May | H41: June | I41: July | J41: August | K41: September | L41: October | M41: November | N41: December
A42: Service & Products | C42: =1+'Control Center'!G155 -> 1.018551 | D42: =1+'Control Center'!H155 -> 1.027827 | E42: =1+'Control Center'!I155 -> 1.037103 | F42: =1+'Control Center'!J155 -> 1.046378 | G42: =1+'Control Center'!K155 -> 1.092757 | H42: =1+'Control Center'!L155 -> 1.111308 | I42: =1+'Control Center'!M155 -> 1.074205 | J42: =1+'Control Center'!N155 -> 1.046378 | ... N42: =1+'Control Center'!R155 -> 1.111308
A44: Planning Case | C44: ='Control Center'!F8 -> 2025 | D44: =(C44+1)*D$8 -> 2026 | E44: =(D44+1)*E$8 -> 2027 | F44: =(E44+1)*F$8 -> 2028 | G44: =(F44+1)*G$8 -> 2029 | H44: =(G44+1)*H$8 -> 2030 | I44: =(H44+1)*I$8 -> 2031 | J44: =(I44+1)*J$8 -> 2032 | K44: =(J44+1)*K$8 -> 2033 | L44: =(K44+1)*L$8 -> 2034
A45: Revenue Growth Rate | C45: =INDEX(C46:C48, MATCH('Control Center'!$E$25, 'Formula Audit'!$C$4:$C$6, 0))*C$8 -> 0 | D45: =INDEX(D46:D48, MATCH('Control Center'!$E$25, 'Formula Audit'!$C$4:$C$6, 0))*D$8 -> 0.067019 | E45: =INDEX(E46:E48, MATCH('Control Center'!$E$25, 'Formula Audit'!$C$4:$C$6, 0))*E$8 -> 0.055849 | F45: =INDEX(F46:F48, MATCH('Control Center'!$E$25, 'Formula Audit'!$C$4:$C$6, 0))*F$8 -> 0.044679 | G45: =INDEX(G46:G48, MATCH('Control Center'!$E$25, 'Formula Audit'!$C$4:$C$6, 0))*G$8 -> 0.03351 | H45: =INDEX(H46:H48, MATCH('Control Center'!$E$25, 'Formula Audit'!$C$4:$C$6, 0))*H$8 -> 0.03351 | I45: =INDEX(I46:I48, MATCH('Control Center'!$E$25, 'Formula Audit'!$C$4:$C$6, 0))*I$8 -> 0.02234 | J45: =INDEX(J46:J48, MATCH('Control Center'!$E$25, 'Formula Audit'!$C$4:$C$6, 0))*J$8 -> 0.02234 | ... L45: =INDEX(L46:L48, MATCH('Control Center'!$E$25, 'Formula Audit'!$C$4:$C$6, 0))*L$8 -> 0.02234
B46: Central Case | C46: ='Control Center'!G58 -> 0 | D46: ='Control Center'!H58 -> 0.067019 | E46: ='Control Center'!I58 -> 0.055849 | F46: ='Control Center'!J58 -> 0.044679 | G46: ='Control Center'!K58 -> 0.03351 | H46: ='Control Center'!L58 -> 0.03351 | I46: ='Control Center'!M58 -> 0.02234 | J46: ='Control Center'!N58 -> 0.02234 | ... L46: ='Control Center'!P58 -> 0.02234
B47: Upside Case | C47: ='Control Center'!G88 -> 0 | D47: ='Control Center'!H88 -> 0.082932 | E47: ='Control Center'!I88 -> 0.072566 | F47: ='Control Center'!J88 -> 0.062199 | G47: ='Control Center'!K88 -> 0.051833 | H47: ='Control Center'!L88 -> 0.051833 | I47: ='Control Center'!M88 -> 0.041466 | J47: ='Control Center'!N88 -> 0.041466 | ... L47: ='Control Center'!P88 -> 0.0311
B48: Downside Case | C48: ='Control Center'!G118 -> 0 | D48: ='Control Center'!H118 -> 0.02179 | E48: ='Control Center'!I118 -> 0.02179 | F48: ='Control Center'!J118 -> 0.010895 | G48: ='Control Center'!K118 -> 0.010895 | H48: ='Control Center'!L118 -> 0.010895 | I48: ='Control Center'!M118 -> 0 | J48: ='Control Center'!N118 -> 0 | ... L48: ='Control Center'!P118 -> -0.010895
A49: Service Costs | C49: =INDEX(C50:C52, MATCH('Control Center'!$E$25, 'Formula Audit'!$C$4:$C$6, 0))*C$8 -> 0 | D49: =INDEX(D50:D52, MATCH('Control Center'!$E$25, 'Formula Audit'!$C$4:$C$6, 0))*D$8 -> 0.265943 | E49: =INDEX(E50:E52, MATCH('Control Center'!$E$25, 'Formula Audit'!$C$4:$C$6, 0))*E$8 -> 0.265943 | F49: =INDEX(F50:F52, MATCH('Control Center'!$E$25, 'Formula Audit'!$C$4:$C$6, 0))*F$8 -> 0.255305 | G49: =INDEX(G50:G52, MATCH('Control Center'!$E$25, 'Formula Audit'!$C$4:$C$6, 0))*G$8 -> 0.255305 | H49: =INDEX(H50:H52, MATCH('Control Center'!$E$25, 'Formula Audit'!$C$4:$C$6, 0))*H$8 -> 0.244668 | I49: =INDEX(I50:I52, MATCH('Control Center'!$E$25, 'Formula Audit'!$C$4:$C$6, 0))*I$8 -> 0.244668 | J49: =INDEX(J50:J52, MATCH('Control Center'!$E$25, 'Formula Audit'!$C$4:$C$6, 0))*J$8 -> 0.23403 | ... L49: =INDEX(L50:L52, MATCH('Control Center'!$E$25, 'Formula Audit'!$C$4:$C$6, 0))*L$8 -> 0.223392
B50: Central Case | C50: ='Control Center'!G59 -> 0 | D50: ='Control Center'!H59 -> 0.265943 | E50: ='Control Center'!I59 -> 0.265943 | F50: ='Control Center'!J59 -> 0.255305 | G50: ='Control Center'!K59 -> 0.255305 | H50: ='Control Center'!L59 -> 0.244668 | I50: ='Control Center'!M59 -> 0.244668 | J50: ='Control Center'!N59 -> 0.23403 | ... L50: ='Control Center'!P59 -> 0.223392
B51: Upside Case | C51: ='Control Center'!G89 -> 0 | D51: ='Control Center'!H89 -> 0.170966 | E51: ='Control Center'!I89 -> 0.170966 | F51: ='Control Center'!J89 -> 0.161468 | G51: ='Control Center'!K89 -> 0.161468 | H51: ='Control Center'!L89 -> 0.161468 | I51: ='Control Center'!M89 -> 0.151969 | J51: ='Control Center'!N89 -> 0.151969 | ... L51: ='Control Center'!P89 -> 0.142471
B52: Downside Case | C52: ='Control Center'!G119 -> 0 | D52: ='Control Center'!H119 -> 0.291436 | E52: ='Control Center'!I119 -> 0.291436 | F52: ='Control Center'!J119 -> 0.310865 | G52: ='Control Center'!K119 -> 0.310865 | H52: ='Control Center'!L119 -> 0.320579 | I52: ='Control Center'!M119 -> 0.330294 | J52: ='Control Center'!N119 -> 0.330294 | ... L52: ='Control Center'!P119 -> 0.349723
A53: Product Costs | C53: =INDEX(C54:C56, MATCH('Control Center'!$E$25, 'Formula Audit'!$C$4:$C$6, 0))*C$8 -> 0 | D53: =INDEX(D54:D56, MATCH('Control Center'!$E$25, 'Formula Audit'!$C$4:$C$6, 0))*D$8 -> 0.33648 | E53: =INDEX(E54:E56, MATCH('Control Center'!$E$25, 'Formula Audit'!$C$4:$C$6, 0))*E$8 -> 0.319656 | F53: =INDEX(F54:F56, MATCH('Control Center'!$E$25, 'Formula Audit'!$C$4:$C$6, 0))*F$8 -> 0.311244 | G53: =INDEX(G54:G56, MATCH('Control Center'!$E$25, 'Formula Audit'!$C$4:$C$6, 0))*G$8 -> 0.302832 | H53: =INDEX(H54:H56, MATCH('Control Center'!$E$25, 'Formula Audit'!$C$4:$C$6, 0))*H$8 -> 0.29442 | I53: =INDEX(I54:I56, MATCH('Control Center'!$E$25, 'Formula Audit'!$C$4:$C$6, 0))*I$8 -> 0.29442 | J53: =INDEX(J54:J56, MATCH('Control Center'!$E$25, 'Formula Audit'!$C$4:$C$6, 0))*J$8 -> 0.286008 | ... L53: =INDEX(L54:L56, MATCH('Control Center'!$E$25, 'Formula Audit'!$C$4:$C$6, 0))*L$8 -> 0.286008
B54: Central Case | C54: ='Control Center'!G60 -> 0 | D54: ='Control Center'!H60 -> 0.33648 | E54: ='Control Center'!I60 -> 0.319656 | F54: ='Control Center'!J60 -> 0.311244 | G54: ='Control Center'!K60 -> 0.302832 | H54: ='Control Center'!L60 -> 0.29442 | I54: ='Control Center'!M60 -> 0.29442 | J54: ='Control Center'!N60 -> 0.286008 | ... L54: ='Control Center'!P60 -> 0.286008
B55: Upside Case | C55: ='Control Center'!G90 -> 0 | D55: ='Control Center'!H90 -> 0.442336 | E55: ='Control Center'!I90 -> 0.420219 | F55: ='Control Center'!J90 -> 0.409161 | G55: ='Control Center'!K90 -> 0.398103 | H55: ='Control Center'!L90 -> 0.387044 | I55: ='Control Center'!M90 -> 0.387044 | J55: ='Control Center'!N90 -> 0.375986 | ... L55: ='Control Center'!P90 -> 0.364927
B56: Downside Case | C56: ='Control Center'!G120 -> 0 | D56: ='Control Center'!H120 -> 0.631404 | E56: ='Control Center'!I120 -> 0.642884 | F56: ='Control Center'!J120 -> 0.654364 | G56: ='Control Center'!K120 -> 0.665844 | H56: ='Control Center'!L120 -> 0.665844 | I56: ='Control Center'!M120 -> 0.677324 | J56: ='Control Center'!N120 -> 0.688804 | ... L56: ='Control Center'!P120 -> 0.688804
A57: Direct Labour Costs | C57: =INDEX(C58:C60, MATCH('Control Center'!$E$25, 'Formula Audit'!$C$4:$C$6, 0))*C$8 -> 0.190469 | D57: =INDEX(D58:D60, MATCH('Control Center'!$E$25, 'Formula Audit'!$C$4:$C$6, 0))*D$8 -> 0.190469 | E57: =INDEX(E58:E60, MATCH('Control Center'!$E$25, 'Formula Audit'!$C$4:$C$6, 0))*E$8 -> 0.190469 | F57: =INDEX(F58:F60, MATCH('Control Center'!$E$25, 'Formula Audit'!$C$4:$C$6, 0))*F$8 -> 0.190469 | G57: =INDEX(G58:G60, MATCH('Control Center'!$E$25, 'Formula Audit'!$C$4:$C$6, 0))*G$8 -> 0.190469 | H57: =INDEX(H58:H60, MATCH('Control Center'!$E$25, 'Formula Audit'!$C$4:$C$6, 0))*H$8 -> 0.190469 | I57: =INDEX(I58:I60, MATCH('Control Center'!$E$25, 'Formula Audit'!$C$4:$C$6, 0))*I$8 -> 0.190469 | J57: =INDEX(J58:J60, MATCH('Control Center'!$E$25, 'Formula Audit'!$C$4:$C$6, 0))*J$8 -> 0.190469 | ... L57: =INDEX(L58:L60, MATCH('Control Center'!$E$25, 'Formula Audit'!$C$4:$C$6, 0))*L$8 -> 0.190469
B58: Central Case | C58: ='Control Center'!G61 -> 0.190469 | D58: ='Control Center'!H61 -> 0.190469 | E58: ='Control Center'!I61 -> 0.190469 | F58: ='Control Center'!J61 -> 0.190469 | G58: ='Control Center'!K61 -> 0.190469 | H58: ='Control Center'!L61 -> 0.190469 | I58: ='Control Center'!M61 -> 0.190469 | J58: ='Control Center'!N61 -> 0.190469 | ... L58: ='Control Center'!P61 -> 0.190469
B59: Upside Case | C59: ='Control Center'!G91 -> 0.158474 | D59: ='Control Center'!H91 -> 0.158474 | E59: ='Control Center'!I91 -> 0.158474 | F59: ='Control Center'!J91 -> 0.158474 | G59: ='Control Center'!K91 -> 0.158474 | H59: ='Control Center'!L91 -> 0.158474 | I59: ='Control Center'!M91 -> 0.158474 | J59: ='Control Center'!N91 -> 0.158474 | ... L59: ='Control Center'!P91 -> 0.158474
B60: Downside Case | C60: ='Control Center'!G121 -> 0.251431 | D60: ='Control Center'!H121 -> 0.251431 | E60: ='Control Center'!I121 -> 0.251431 | F60: ='Control Center'!J121 -> 0.251431 | G60: ='Control Center'!K121 -> 0.251431 | H60: ='Control Center'!L121 -> 0.251431 | I60: ='Control Center'!M121 -> 0.251431 | J60: ='Control Center'!N121 -> 0.251431 | ... L60: ='Control Center'!P121 -> 0.251431
A61: Discounts & Promotions | C61: =INDEX(C62:C64, MATCH('Control Center'!$E$25, 'Formula Audit'!$C$4:$C$6, 0))*C$8 -> 0.137193 | D61: =INDEX(D62:D64, MATCH('Control Center'!$E$25, 'Formula Audit'!$C$4:$C$6, 0))*D$8 -> 0.12576 | E61: =INDEX(E62:E64, MATCH('Control Center'!$E$25, 'Formula Audit'!$C$4:$C$6, 0))*E$8 -> 0.114327 | F61: =INDEX(F62:F64, MATCH('Control Center'!$E$25, 'Formula Audit'!$C$4:$C$6, 0))*F$8 -> 0.102895 | G61: =INDEX(G62:G64, MATCH('Control Center'!$E$25, 'Formula Audit'!$C$4:$C$6, 0))*G$8 -> 0.102895 | H61: =INDEX(H62:H64, MATCH('Control Center'!$E$25, 'Formula Audit'!$C$4:$C$6, 0))*H$8 -> 0.091462 | I61: =INDEX(I62:I64, MATCH('Control Center'!$E$25, 'Formula Audit'!$C$4:$C$6, 0))*I$8 -> 0.091462 | J61: =INDEX(J62:J64, MATCH('Control Center'!$E$25, 'Formula Audit'!$C$4:$C$6, 0))*J$8 -> 0.080029 | ... L61: =INDEX(L62:L64, MATCH('Control Center'!$E$25, 'Formula Audit'!$C$4:$C$6, 0))*L$8 -> 0.080029
B62: Central Case | C62: ='Control Center'!G62 -> 0.137193 | D62: ='Control Center'!H62 -> 0.12576 | E62: ='Control Center'!I62 -> 0.114327 | F62: ='Control Center'!J62 -> 0.102895 | G62: ='Control Center'!K62 -> 0.102895 | H62: ='Control Center'!L62 -> 0.091462 | I62: ='Control Center'!M62 -> 0.091462 | J62: ='Control Center'!N62 -> 0.080029 | ... L62: ='Control Center'!P62 -> 0.080029
B63: Upside Case | C63: ='Control Center'!G92 -> 0.098443 | D63: ='Control Center'!H92 -> 0.090239 | E63: ='Control Center'!I92 -> 0.082036 | F63: ='Control Center'!J92 -> 0.082036 | G63: ='Control Center'!K92 -> 0.073832 | H63: ='Control Center'!L92 -> 0.073832 | I63: ='Control Center'!M92 -> 0.065629 | J63: ='Control Center'!N92 -> 0.065629 | ... L63: ='Control Center'!P92 -> 0.057425
B64: Downside Case | C64: ='Control Center'!G122 -> 0.193025 | D64: ='Control Center'!H120 -> 0.631404 | E64: ='Control Center'!I120 -> 0.642884 | F64: ='Control Center'!J120 -> 0.654364 | G64: ='Control Center'!K120 -> 0.665844 | H64: ='Control Center'!L120 -> 0.665844 | I64: ='Control Center'!M120 -> 0.677324 | J64: ='Control Center'!N120 -> 0.688804 | K64: ='Control Center'!O120 -> 0.688804 | L64: ='Control Center'!P120 -> 0.688804
A65: Salaries & Benefits | C65: =INDEX(C66:C68, MATCH('Control Center'!$E$25, 'Formula Audit'!$C$4:$C$6, 0))*C$8 -> 58749 | D65: =INDEX(D66:D68, MATCH('Control Center'!$E$25, 'Formula Audit'!$C$4:$C$6, 0))*D$8 -> 58749 | E65: =INDEX(E66:E68, MATCH('Control Center'!$E$25, 'Formula Audit'!$C$4:$C$6, 0))*E$8 -> 58749 | F65: =INDEX(F66:F68, MATCH('Control Center'!$E$25, 'Formula Audit'!$C$4:$C$6, 0))*F$8 -> 58749 | G65: =INDEX(G66:G68, MATCH('Control Center'!$E$25, 'Formula Audit'!$C$4:$C$6, 0))*G$8 -> 58749 | H65: =INDEX(H66:H68, MATCH('Control Center'!$E$25, 'Formula Audit'!$C$4:$C$6, 0))*H$8 -> 58749 | I65: =INDEX(I66:I68, MATCH('Control Center'!$E$25, 'Formula Audit'!$C$4:$C$6, 0))*I$8 -> 58749 | J65: =INDEX(J66:J68, MATCH('Control Center'!$E$25, 'Formula Audit'!$C$4:$C$6, 0))*J$8 -> 58749 | ... L65: =INDEX(L66:L68, MATCH('Control Center'!$E$25, 'Formula Audit'!$C$4:$C$6, 0))*L$8 -> 58749
B66: Central Case | C66: ='Control Center'!G63 -> 58749 | D66: ='Control Center'!H63 -> 58749 | E66: ='Control Center'!I63 -> 58749 | F66: ='Control Center'!J63 -> 58749 | G66: ='Control Center'!K63 -> 58749 | H66: ='Control Center'!L63 -> 58749 | I66: ='Control Center'!M63 -> 58749 | J66: ='Control Center'!N63 -> 58749 | ... L66: ='Control Center'!P63 -> 58749
B67: Upside Case | C67: ='Control Center'!G93 -> 41113 | D67: ='Control Center'!H93 -> 41113 | E67: ='Control Center'!I93 -> 41113 | F67: ='Control Center'!J93 -> 41113 | G67: ='Control Center'!K93 -> 41113 | H67: ='Control Center'!L93 -> 41113 | I67: ='Control Center'!M93 -> 41113 | J67: ='Control Center'!N93 -> 41113 | ... L67: ='Control Center'!P93 -> 41113
B68: Downside Case | C68: ='Control Center'!G123 -> 39103 | D68: ='Control Center'!H123 -> 39103 | E68: ='Control Center'!I123 -> 39103 | F68: ='Control Center'!J123 -> 39103 | G68: ='Control Center'!K123 -> 39103 | H68: ='Control Center'!L123 -> 39103 | I68: ='Control Center'!M123 -> 39103 | J68: ='Control Center'!N123 -> 39103 | ... L68: ='Control Center'!P123 -> 39103
A69: Sales & Marketing | C69: =INDEX(C70:C72, MATCH('Control Center'!$E$25, 'Formula Audit'!$C$4:$C$6, 0))*C$8 -> 0.045594 | D69: =INDEX(D70:D72, MATCH('Control Center'!$E$25, 'Formula Audit'!$C$4:$C$6, 0))*D$8 -> 0.045594 | E69: =INDEX(E70:E72, MATCH('Control Center'!$E$25, 'Formula Audit'!$C$4:$C$6, 0))*E$8 -> 0.039895 | F69: =INDEX(F70:F72, MATCH('Control Center'!$E$25, 'Formula Audit'!$C$4:$C$6, 0))*F$8 -> 0.039895 | G69: =INDEX(G70:G72, MATCH('Control Center'!$E$25, 'Formula Audit'!$C$4:$C$6, 0))*G$8 -> 0.039895 | H69: =INDEX(H70:H72, MATCH('Control Center'!$E$25, 'Formula Audit'!$C$4:$C$6, 0))*H$8 -> 0.039895 | I69: =INDEX(I70:I72, MATCH('Control Center'!$E$25, 'Formula Audit'!$C$4:$C$6, 0))*I$8 -> 0.034195 | J69: =INDEX(J70:J72, MATCH('Control Center'!$E$25, 'Formula Audit'!$C$4:$C$6, 0))*J$8 -> 0.034195 | ... L69: =INDEX(L70:L72, MATCH('Control Center'!$E$25, 'Formula Audit'!$C$4:$C$6, 0))*L$8 -> 0.034195
B70: Central Case | C70: ='Control Center'!G64 -> 0.045594 | D70: ='Control Center'!H64 -> 0.045594 | E70: ='Control Center'!I64 -> 0.039895 | F70: ='Control Center'!J64 -> 0.039895 | G70: ='Control Center'!K64 -> 0.039895 | H70: ='Control Center'!L64 -> 0.039895 | I70: ='Control Center'!M64 -> 0.034195 | J70: ='Control Center'!N64 -> 0.034195 | ... L70: ='Control Center'!P64 -> 0.034195
B71: Upside Case | C71: ='Control Center'!G94 -> 0.043169 | D71: ='Control Center'!H94 -> 0.043169 | E71: ='Control Center'!I94 -> 0.037773 | F71: ='Control Center'!J94 -> 0.037773 | G71: ='Control Center'!K94 -> 0.037773 | H71: ='Control Center'!L94 -> 0.032377 | I71: ='Control Center'!M94 -> 0.032377 | J71: ='Control Center'!N94 -> 0.032377 | ... L71: ='Control Center'!P94 -> 0.026981
B72: Downside Case | C72: ='Control Center'!G124 -> 0.057921 | D72: ='Control Center'!H124 -> 0.057921 | E72: ='Control Center'!I124 -> 0.057921 | F72: ='Control Center'!J124 -> 0.052129 | G72: ='Control Center'!K124 -> 0.052129 | H72: ='Control Center'!L124 -> 0.046337 | I72: ='Control Center'!M124 -> 0.046337 | J72: ='Control Center'!N124 -> 0.046337 | ... L72: ='Control Center'!P124 -> 0.040545
A73: General & Administrative | C73: =INDEX(C74:C76, MATCH('Control Center'!$E$25, 'Formula Audit'!$C$4:$C$6, 0))*C$8 -> 34135 | D73: =INDEX(D74:D76, MATCH('Control Center'!$E$25, 'Formula Audit'!$C$4:$C$6, 0))*D$8 -> 34135 | E73: =INDEX(E74:E76, MATCH('Control Center'!$E$25, 'Formula Audit'!$C$4:$C$6, 0))*E$8 -> 34135 | F73: =INDEX(F74:F76, MATCH('Control Center'!$E$25, 'Formula Audit'!$C$4:$C$6, 0))*F$8 -> 34135 | G73: =INDEX(G74:G76, MATCH('Control Center'!$E$25, 'Formula Audit'!$C$4:$C$6, 0))*G$8 -> 34135 | H73: =INDEX(H74:H76, MATCH('Control Center'!$E$25, 'Formula Audit'!$C$4:$C$6, 0))*H$8 -> 34135 | I73: =INDEX(I74:I76, MATCH('Control Center'!$E$25, 'Formula Audit'!$C$4:$C$6, 0))*I$8 -> 34135 | J73: =INDEX(J74:J76, MATCH('Control Center'!$E$25, 'Formula Audit'!$C$4:$C$6, 0))*J$8 -> 34135 | ... L73: =INDEX(L74:L76, MATCH('Control Center'!$E$25, 'Formula Audit'!$C$4:$C$6, 0))*L$8 -> 34135
B74: Central Case | C74: ='Control Center'!G65 -> 34135 | D74: ='Control Center'!H65 -> 34135 | E74: ='Control Center'!I65 -> 34135 | F74: ='Control Center'!J65 -> 34135 | G74: ='Control Center'!K65 -> 34135 | H74: ='Control Center'!L65 -> 34135 | I74: ='Control Center'!M65 -> 34135 | J74: ='Control Center'!N65 -> 34135 | ... L74: ='Control Center'!P65 -> 34135
B75: Upside Case | C75: ='Control Center'!G95 -> 31054 | D75: ='Control Center'!H95 -> 31054 | E75: ='Control Center'!I95 -> 31054 | F75: ='Control Center'!J95 -> 31054 | G75: ='Control Center'!K95 -> 31054 | H75: ='Control Center'!L95 -> 31054 | I75: ='Control Center'!M95 -> 31054 | J75: ='Control Center'!N95 -> 31054 | ... L75: ='Control Center'!P95 -> 31054
B76: Downside Case | C76: ='Control Center'!G125 -> 53958 | D76: ='Control Center'!H125 -> 53958 | E76: ='Control Center'!I125 -> 53958 | F76: ='Control Center'!J125 -> 53958 | G76: ='Control Center'!K125 -> 53958 | H76: ='Control Center'!L125 -> 53958 | I76: ='Control Center'!M125 -> 53958 | J76: ='Control Center'!N125 -> 53958 | ... L76: ='Control Center'!P125 -> 53958
A77: Card Processing Fees | C77: =INDEX(C78:C80, MATCH('Control Center'!$E$25, 'Formula Audit'!$C$4:$C$6, 0))*C$8 -> 0.007054 | D77: =INDEX(D78:D80, MATCH('Control Center'!$E$25, 'Formula Audit'!$C$4:$C$6, 0))*D$8 -> 0.007054 | E77: =INDEX(E78:E80, MATCH('Control Center'!$E$25, 'Formula Audit'!$C$4:$C$6, 0))*E$8 -> 0.007054 | F77: =INDEX(F78:F80, MATCH('Control Center'!$E$25, 'Formula Audit'!$C$4:$C$6, 0))*F$8 -> 0.007054 | G77: =INDEX(G78:G80, MATCH('Control Center'!$E$25, 'Formula Audit'!$C$4:$C$6, 0))*G$8 -> 0.007054 | H77: =INDEX(H78:H80, MATCH('Control Center'!$E$25, 'Formula Audit'!$C$4:$C$6, 0))*H$8 -> 0.007054 | I77: =INDEX(I78:I80, MATCH('Control Center'!$E$25, 'Formula Audit'!$C$4:$C$6, 0))*I$8 -> 0.007054 | J77: =INDEX(J78:J80, MATCH('Control Center'!$E$25, 'Formula Audit'!$C$4:$C$6, 0))*J$8 -> 0.007054 | ... L77: =INDEX(L78:L80, MATCH('Control Center'!$E$25, 'Formula Audit'!$C$4:$C$6, 0))*L$8 -> 0.007054
B78: Central Case | C78: ='Control Center'!G66 -> 0.007054 | D78: ='Control Center'!H66 -> 0.007054 | E78: ='Control Center'!I66 -> 0.007054 | F78: ='Control Center'!J66 -> 0.007054 | G78: ='Control Center'!K66 -> 0.007054 | H78: ='Control Center'!L66 -> 0.007054 | I78: ='Control Center'!M66 -> 0.007054 | J78: ='Control Center'!N66 -> 0.007054 | ... L78: ='Control Center'!P66 -> 0.007054
B79: Upside Case | C79: ='Control Center'!G96 -> 0.009061 | D79: ='Control Center'!H96 -> 0.009061 | E79: ='Control Center'!I96 -> 0.009061 | F79: ='Control Center'!J96 -> 0.009061 | G79: ='Control Center'!K96 -> 0.009061 | H79: ='Control Center'!L96 -> 0.009061 | I79: ='Control Center'!M96 -> 0.009061 | J79: ='Control Center'!N96 -> 0.009061 | ... L79: ='Control Center'!P96 -> 0.009061
B80: Downside Case | C80: ='Control Center'!G126 -> 0.009962 | D80: ='Control Center'!H126 -> 0.009962 | E80: ='Control Center'!I126 -> 0.009962 | F80: ='Control Center'!J126 -> 0.009962 | G80: ='Control Center'!K126 -> 0.009962 | H80: ='Control Center'!L126 -> 0.009962 | I80: ='Control Center'!M126 -> 0.009962 | J80: ='Control Center'!N126 -> 0.009962 | ... L80: ='Control Center'!P126 -> 0.009962
A81: Depreciation Charge | C81: =INDEX(C82:C84, MATCH('Control Center'!$E$25, 'Formula Audit'!$C$4:$C$6, 0))*C$8 -> 0.414517 | D81: =INDEX(D82:D84, MATCH('Control Center'!$E$25, 'Formula Audit'!$C$4:$C$6, 0))*D$8 -> 0.414517 | E81: =INDEX(E82:E84, MATCH('Control Center'!$E$25, 'Formula Audit'!$C$4:$C$6, 0))*E$8 -> 0.414517 | F81: =INDEX(F82:F84, MATCH('Control Center'!$E$25, 'Formula Audit'!$C$4:$C$6, 0))*F$8 -> 0.414517 | G81: =INDEX(G82:G84, MATCH('Control Center'!$E$25, 'Formula Audit'!$C$4:$C$6, 0))*G$8 -> 0.414517 | H81: =INDEX(H82:H84, MATCH('Control Center'!$E$25, 'Formula Audit'!$C$4:$C$6, 0))*H$8 -> 0.414517 | I81: =INDEX(I82:I84, MATCH('Control Center'!$E$25, 'Formula Audit'!$C$4:$C$6, 0))*I$8 -> 0.414517 | J81: =INDEX(J82:J84, MATCH('Control Center'!$E$25, 'Formula Audit'!$C$4:$C$6, 0))*J$8 -> 0.414517 | ... L81: =INDEX(L82:L84, MATCH('Control Center'!$E$25, 'Formula Audit'!$C$4:$C$6, 0))*L$8 -> 0.414517
B82: Central Case | C82: ='Control Center'!G67 -> 0.414517 | D82: ='Control Center'!H67 -> 0.414517 | E82: ='Control Center'!I67 -> 0.414517 | F82: ='Control Center'!J67 -> 0.414517 | G82: ='Control Center'!K67 -> 0.414517 | H82: ='Control Center'!L67 -> 0.414517 | I82: ='Control Center'!M67 -> 0.414517 | J82: ='Control Center'!N67 -> 0.414517 | ... L82: ='Control Center'!P67 -> 0.414517
B83: Upside Case | C83: ='Control Center'!G97 -> 0.37587 | D83: ='Control Center'!H97 -> 0.37587 | E83: ='Control Center'!I97 -> 0.37587 | F83: ='Control Center'!J97 -> 0.37587 | G83: ='Control Center'!K97 -> 0.37587 | H83: ='Control Center'!L97 -> 0.37587 | I83: ='Control Center'!M97 -> 0.37587 | J83: ='Control Center'!N97 -> 0.37587 | ... L83: ='Control Center'!P97 -> 0.37587
B84: Downside Case | C84: ='Control Center'!G127 -> 0.478358 | D84: ='Control Center'!H127 -> 0.478358 | E84: ='Control Center'!I127 -> 0.478358 | F84: ='Control Center'!J127 -> 0.478358 | G84: ='Control Center'!K127 -> 0.478358 | H84: ='Control Center'!L127 -> 0.478358 | I84: ='Control Center'!M127 -> 0.478358 | J84: ='Control Center'!N127 -> 0.478358 | ... L84: ='Control Center'!P127 -> 0.478358
A85: Effective Tax Rate | C85: =INDEX(C86:C88, MATCH('Control Center'!$E$25, 'Formula Audit'!$C$4:$C$6, 0))*C$8 -> 0.264834 | D85: =INDEX(D86:D88, MATCH('Control Center'!$E$25, 'Formula Audit'!$C$4:$C$6, 0))*D$8 -> 0.264834 | E85: =INDEX(E86:E88, MATCH('Control Center'!$E$25, 'Formula Audit'!$C$4:$C$6, 0))*E$8 -> 0.264834 | F85: =INDEX(F86:F88, MATCH('Control Center'!$E$25, 'Formula Audit'!$C$4:$C$6, 0))*F$8 -> 0.264834 | G85: =INDEX(G86:G88, MATCH('Control Center'!$E$25, 'Formula Audit'!$C$4:$C$6, 0))*G$8 -> 0.264834 | H85: =INDEX(H86:H88, MATCH('Control Center'!$E$25, 'Formula Audit'!$C$4:$C$6, 0))*H$8 -> 0.264834 | I85: =INDEX(I86:I88, MATCH('Control Center'!$E$25, 'Formula Audit'!$C$4:$C$6, 0))*I$8 -> 0.264834 | J85: =INDEX(J86:J88, MATCH('Control Center'!$E$25, 'Formula Audit'!$C$4:$C$6, 0))*J$8 -> 0.264834 | ... L85: =INDEX(L86:L88, MATCH('Control Center'!$E$25, 'Formula Audit'!$C$4:$C$6, 0))*L$8 -> 0.264834
B86: Central Case | C86: ='Control Center'!G68 -> 0.264834 | D86: ='Control Center'!H68 -> 0.264834 | E86: ='Control Center'!I68 -> 0.264834 | F86: ='Control Center'!J68 -> 0.264834 | G86: ='Control Center'!K68 -> 0.264834 | H86: ='Control Center'!L68 -> 0.264834 | I86: ='Control Center'!M68 -> 0.264834 | J86: ='Control Center'!N68 -> 0.264834 | ... L86: ='Control Center'!P68 -> 0.264834
B87: Upside Case | C87: ='Control Center'!G98 -> 0.22962 | D87: ='Control Center'!H98 -> 0.22962 | E87: ='Control Center'!I98 -> 0.22962 | F87: ='Control Center'!J98 -> 0.22962 | G87: ='Control Center'!K98 -> 0.22962 | H87: ='Control Center'!L98 -> 0.22962 | I87: ='Control Center'!M98 -> 0.22962 | J87: ='Control Center'!N98 -> 0.22962 | ... L87: ='Control Center'!P98 -> 0.22962
B88: Downside Case | C88: ='Control Center'!G128 -> 0.282756 | D88: ='Control Center'!H128 -> 0.282756 | E88: ='Control Center'!I128 -> 0.282756 | F88: ='Control Center'!J128 -> 0.282756 | G88: ='Control Center'!K128 -> 0.282756 | H88: ='Control Center'!L128 -> 0.282756 | I88: ='Control Center'!M128 -> 0.282756 | J88: ='Control Center'!N128 -> 0.282756 | ... L88: ='Control Center'!P128 -> 0.282756
A89: Trade Receivables | C89: =INDEX(C90:C92, MATCH('Control Center'!$E$25, 'Formula Audit'!$C$4:$C$6, 0))*C$8 -> 37 | D89: =INDEX(D90:D92, MATCH('Control Center'!$E$25, 'Formula Audit'!$C$4:$C$6, 0))*D$8 -> 37 | E89: =INDEX(E90:E92, MATCH('Control Center'!$E$25, 'Formula Audit'!$C$4:$C$6, 0))*E$8 -> 37 | F89: =INDEX(F90:F92, MATCH('Control Center'!$E$25, 'Formula Audit'!$C$4:$C$6, 0))*F$8 -> 37 | G89: =INDEX(G90:G92, MATCH('Control Center'!$E$25, 'Formula Audit'!$C$4:$C$6, 0))*G$8 -> 37 | H89: =INDEX(H90:H92, MATCH('Control Center'!$E$25, 'Formula Audit'!$C$4:$C$6, 0))*H$8 -> 32 | I89: =INDEX(I90:I92, MATCH('Control Center'!$E$25, 'Formula Audit'!$C$4:$C$6, 0))*I$8 -> 32 | J89: =INDEX(J90:J92, MATCH('Control Center'!$E$25, 'Formula Audit'!$C$4:$C$6, 0))*J$8 -> 32 | ... L89: =INDEX(L90:L92, MATCH('Control Center'!$E$25, 'Formula Audit'!$C$4:$C$6, 0))*L$8 -> 32
B90: Central Case | C90: ='Control Center'!G71 -> 37 | D90: ='Control Center'!H71 -> 37 | E90: ='Control Center'!I71 -> 37 | F90: ='Control Center'!J71 -> 37 | G90: ='Control Center'!K71 -> 37 | H90: ='Control Center'!L71 -> 32 | I90: ='Control Center'!M71 -> 32 | J90: ='Control Center'!N71 -> 32 | ... L90: ='Control Center'!P71 -> 32
B91: Upside Case | C91: ='Control Center'!G101 -> 45 | D91: ='Control Center'!H101 -> 45 | E91: ='Control Center'!I101 -> 45 | F91: ='Control Center'!J101 -> 45 | G91: ='Control Center'!K101 -> 45 | H91: ='Control Center'!L101 -> 40 | I91: ='Control Center'!M101 -> 40 | J91: ='Control Center'!N101 -> 40 | ... L91: ='Control Center'!P101 -> 40
B92: Downside Case | C92: ='Control Center'!G131 -> 55 | D92: ='Control Center'!H131 -> 55 | E92: ='Control Center'!I131 -> 55 | F92: ='Control Center'!J131 -> 55 | G92: ='Control Center'!K131 -> 55 | H92: ='Control Center'!L131 -> 61 | I92: ='Control Center'!M131 -> 61 | J92: ='Control Center'!N131 -> 61 | ... L92: ='Control Center'!P131 -> 61
A93: Inventories | C93: =INDEX(C94:C96, MATCH('Control Center'!$E$25, 'Formula Audit'!$C$4:$C$6, 0))*C$8 -> 66 | D93: =INDEX(D94:D96, MATCH('Control Center'!$E$25, 'Formula Audit'!$C$4:$C$6, 0))*D$8 -> 66 | E93: =INDEX(E94:E96, MATCH('Control Center'!$E$25, 'Formula Audit'!$C$4:$C$6, 0))*E$8 -> 66 | F93: =INDEX(F94:F96, MATCH('Control Center'!$E$25, 'Formula Audit'!$C$4:$C$6, 0))*F$8 -> 71 | G93: =INDEX(G94:G96, MATCH('Control Center'!$E$25, 'Formula Audit'!$C$4:$C$6, 0))*G$8 -> 71 | H93: =INDEX(H94:H96, MATCH('Control Center'!$E$25, 'Formula Audit'!$C$4:$C$6, 0))*H$8 -> 71 | I93: =INDEX(I94:I96, MATCH('Control Center'!$E$25, 'Formula Audit'!$C$4:$C$6, 0))*I$8 -> 76 | J93: =INDEX(J94:J96, MATCH('Control Center'!$E$25, 'Formula Audit'!$C$4:$C$6, 0))*J$8 -> 76 | ... L93: =INDEX(L94:L96, MATCH('Control Center'!$E$25, 'Formula Audit'!$C$4:$C$6, 0))*L$8 -> 81
B94: Central Case | C94: ='Control Center'!G72 -> 66 | D94: ='Control Center'!H72 -> 66 | E94: ='Control Center'!I72 -> 66 | F94: ='Control Center'!J72 -> 71 | G94: ='Control Center'!K72 -> 71 | H94: ='Control Center'!L72 -> 71 | I94: ='Control Center'!M72 -> 76 | J94: ='Control Center'!N72 -> 76 | ... L94: ='Control Center'!P72 -> 81
B95: Upside Case | C95: ='Control Center'!G102 -> 63 | D95: ='Control Center'!H102 -> 63 | E95: ='Control Center'!I102 -> 63 | F95: ='Control Center'!J102 -> 68 | G95: ='Control Center'!K102 -> 68 | H95: ='Control Center'!L102 -> 68 | I95: ='Control Center'!M102 -> 73 | J95: ='Control Center'!N102 -> 73 | ... L95: ='Control Center'!P102 -> 78
B96: Downside Case | C96: ='Control Center'!G132 -> 82 | D96: ='Control Center'!H132 -> 82 | E96: ='Control Center'!I132 -> 87 | F96: ='Control Center'!J132 -> 92 | G96: ='Control Center'!K132 -> 92 | H96: ='Control Center'!L132 -> 97 | I96: ='Control Center'!M132 -> 100 | J96: ='Control Center'!N132 -> 100 | ... L96: ='Control Center'!P132 -> 112
A97: Property, Plant & Equipment | C97: =INDEX(C98:C100, MATCH('Control Center'!$E$25, 'Formula Audit'!$C$4:$C$6, 0))*C$8 -> 13917
B98: Central Case | C98: ='Control Center'!G73 -> 13917
B99: Upside Case | C99: ='Control Center'!G103 -> 15666
B100: Downside Case | C100: ='Control Center'!G133 -> 13646
A101: Trade Payables | C101: =INDEX(C102:C104, MATCH('Control Center'!$E$25, 'Formula Audit'!$C$4:$C$6, 0))*C$8 -> 53 | D101: =INDEX(D102:D104, MATCH('Control Center'!$E$25, 'Formula Audit'!$C$4:$C$6, 0))*D$8 -> 53 | E101: =INDEX(E102:E104, MATCH('Control Center'!$E$25, 'Formula Audit'!$C$4:$C$6, 0))*E$8 -> 53 | F101: =INDEX(F102:F104, MATCH('Control Center'!$E$25, 'Formula Audit'!$C$4:$C$6, 0))*F$8 -> 53 | G101: =INDEX(G102:G104, MATCH('Control Center'!$E$25, 'Formula Audit'!$C$4:$C$6, 0))*G$8 -> 53 | H101: =INDEX(H102:H104, MATCH('Control Center'!$E$25, 'Formula Audit'!$C$4:$C$6, 0))*H$8 -> 48 | I101: =INDEX(I102:I104, MATCH('Control Center'!$E$25, 'Formula Audit'!$C$4:$C$6, 0))*I$8 -> 48 | J101: =INDEX(J102:J104, MATCH('Control Center'!$E$25, 'Formula Audit'!$C$4:$C$6, 0))*J$8 -> 48 | ... L101: =INDEX(L102:L104, MATCH('Control Center'!$E$25, 'Formula Audit'!$C$4:$C$6, 0))*L$8 -> 48
B102: Central Case | C102: ='Control Center'!G74 -> 53 | D102: ='Control Center'!H74 -> 53 | E102: ='Control Center'!I74 -> 53 | F102: ='Control Center'!J74 -> 53 | G102: ='Control Center'!K74 -> 53 | H102: ='Control Center'!L74 -> 48 | I102: ='Control Center'!M74 -> 48 | J102: ='Control Center'!N74 -> 48 | ... L102: ='Control Center'!P74 -> 48
B103: Upside Case | C103: ='Control Center'!G104 -> 56 | D103: ='Control Center'!H104 -> 56 | E103: ='Control Center'!I104 -> 56 | F103: ='Control Center'!J104 -> 56 | G103: ='Control Center'!K104 -> 56 | H103: ='Control Center'!L104 -> 50 | I103: ='Control Center'!M104 -> 50 | J103: ='Control Center'!N104 -> 50 | ... L103: ='Control Center'!P104 -> 50
B104: Downside Case | C104: ='Control Center'!G134 -> 58 | D104: ='Control Center'!H134 -> 58 | E104: ='Control Center'!I134 -> 58 | F104: ='Control Center'!J134 -> 58 | G104: ='Control Center'!K134 -> 58 | H104: ='Control Center'!L134 -> 62 | I104: ='Control Center'!M134 -> 62 | J104: ='Control Center'!N134 -> 62 | ... L104: ='Control Center'!P134 -> 62
A105: Accrued & Other Liabilities | C105: =INDEX(C106:C108, MATCH('Control Center'!$E$25, 'Formula Audit'!$C$4:$C$6, 0))*C$8 -> 0.050563 | D105: =INDEX(D106:D108, MATCH('Control Center'!$E$25, 'Formula Audit'!$C$4:$C$6, 0))*D$8 -> 0.050563 | E105: =INDEX(E106:E108, MATCH('Control Center'!$E$25, 'Formula Audit'!$C$4:$C$6, 0))*E$8 -> 0.050563 | F105: =INDEX(F106:F108, MATCH('Control Center'!$E$25, 'Formula Audit'!$C$4:$C$6, 0))*F$8 -> 0.050563 | G105: =INDEX(G106:G108, MATCH('Control Center'!$E$25, 'Formula Audit'!$C$4:$C$6, 0))*G$8 -> 0.050563 | H105: =INDEX(H106:H108, MATCH('Control Center'!$E$25, 'Formula Audit'!$C$4:$C$6, 0))*H$8 -> 0.050563 | I105: =INDEX(I106:I108, MATCH('Control Center'!$E$25, 'Formula Audit'!$C$4:$C$6, 0))*I$8 -> 0.050563 | J105: =INDEX(J106:J108, MATCH('Control Center'!$E$25, 'Formula Audit'!$C$4:$C$6, 0))*J$8 -> 0.050563 | ... L105: =INDEX(L106:L108, MATCH('Control Center'!$E$25, 'Formula Audit'!$C$4:$C$6, 0))*L$8 -> 0.050563
B106: Central Case | C106: ='Control Center'!G75 -> 0.050563 | D106: ='Control Center'!H75 -> 0.050563 | E106: ='Control Center'!I75 -> 0.050563 | F106: ='Control Center'!J75 -> 0.050563 | G106: ='Control Center'!K75 -> 0.050563 | H106: ='Control Center'!L75 -> 0.050563 | I106: ='Control Center'!M75 -> 0.050563 | J106: ='Control Center'!N75 -> 0.050563 | ... L106: ='Control Center'!P75 -> 0.050563
...
